Workbook

Sheet Cover
A1: Investment-Grade Company Analysis Engine
A2: All figures in USD millions unless stated. · v1.0
A4: Company | B4: ='Inputs'!$B$6
A5: Ticker / type | B5: ='Inputs'!$B$7&" · "&'Inputs'!$B$8
A7: Headline
A8: DCF value per share | B8: ='DCF'!$B$36 | C8: Current share price | D8: ='DCF'!$B$39 | E8: Valuation read | F8: ='DCF'!$B$41
A9: Upside / (downside) | B9: ='DCF'!$B$40 | C9: WACC | D9: ='WACC'!$B$24 | E9: Data health | F9: ='Checks'!$B$6
A11: Contents
A12: Inputs | B12: Data-entry layer — paste income statement, balance sheet, cash flow & market data
A13: Historical | B13: Ratios, margins, growth, returns & cash flow, each with a plain-English read
A14: Assumptions | B14: Driver-based DCF assumption engine + Base/Bull/Bear/Downside scenario selector
A15: WACC | B15: Discount rate built up step by step (CAPM cost of equity, after-tax cost of debt)
A16: Forecast | B16: Driver-based operating forecast & unlevered free cash flow (active scenario)
A17: DCF | B17: Discounted cash flow: discounting, terminal value, EV→equity bridge, value per share
A18: Sensitivity | B18: Two-way heat-maps: WACC×growth, WACC×exit multiple, growth×margin
A19: Scenario | B19: Four full DCF runs side by side — base, bull, bear and downside stress
A20: Checks | B20: Automated integrity, sanity and data-gap diagnostics (PASS / REVIEW / FAIL)
A21: Dashboard | B21: One-page investment tearsheet — the summary view
A22: Conclusion | B22: Written investment thesis: drivers, risks, swing assumptions and stance
A24: LEGEND
A25: 1,234 | B25: Input — type your data here (yellow fill, blue font)
A26: a / b | B26: Calculated on this sheet (black formula)
A27: → link | B27: Linked from another sheet (green font)
A28: 12.3x | B28: Key output (shaded)
A29: Strong | B29: Caution | C29: Weak / flag | D29: n/a = data missing · n/m = not meaningful
A31: How to Use
A32: 1. Go to the Inputs sheet and replace the yellow cells with the company's figures (at least revenue and equity; the more you fill, the deeper the analysis).
A33: 2. Enter market data (price, shares, beta, rates) for the WACC and per-share value — or leave blank to use clearly-labelled fallback defaults.
A34: 3. Review the Assumptions sheet; the base case is derived from history. Adjust if you have a different view, and pick a scenario (1–4) with the selector.
A35: 4. Read the Dashboard and Conclusion. Use Sensitivity and Scenario to stress the call. Check the Checks sheet for any data flags.
A37: Generated by Investment-Grade Company Analysis Engine v1.0 on 22 Jun 2026. Illustrative analytical tool — not investment advice.

Sheet Inputs
A1: INPUTS
A2: Standardised financial-statement input layer
A3: Investment-Grade Company Analysis Engine · v1.0
A5: Company & Reporting Profile
A6: Company name | B6: <Company name>
A7: Ticker / identifier | B7: <TICKER>
A8: Business type | B8: Industrial / Manufacturing
A9: Reporting currency | B9: USD
A10: Units | B10: millions
A11: Fiscal year end | B11: 31 December
A12: Business description | B12: <One-paragraph business description>
A15: Industry note | B15: <How revenue & margins are driven in this industry>
A18: LEGEND
A19: 1,234 | B19: Input — type your data here (yellow fill, blue font)
A20: a / b | B20: Calculated on this sheet (black formula)
A21: → link | B21: Linked from another sheet (green font)
A22: 12.3x | B22: Key output (shaded)
A23: Strong | B23: Caution | C23: Weak / flag | D23: n/a = data missing · n/m = not meaningful
A25: Conventions
A26: • COGS and SG&A are entered AS REPORTED (they already include their share of depreciation). Total D&A is entered ONCE in the Cash Flow block; EBITDA is built as EBIT + D&A so depreciation is never double-counted.
A27: • Capex, acquisitions, dividends paid and buybacks are entered as POSITIVE amounts (cash spent); the model applies the sign automatically.
A28: • Signed cash-flow lines (change in working capital, net debt issued/repaid, other lines) are entered as net cash impact: positive = inflow.
A29: • Leave any cell blank if the figure is unavailable — the model marks it missing and continues with the best partial output (it will not invent data).
A31: Income Statement
B32: FY—4 | C32: FY—3 | D32: FY—2 | E32: FY—1 | F32: FY—0 | G32: Source / note
A33: Revenue / Net sales
A34: Cost of goods sold (incl. D&A)
A35: Gross profit | B35: =$B$33-$B$34 | C35: =$C$33-$C$34 | D35: =$D$33-$D$34 | E35: =$E$33-$E$34 | F35: =$F$33-$F$34
A36: Selling, general & admin (SG&A)
A37: Research & development
A38: Other operating expense / (income)
A39: EBIT (operating income) | B39: =$B$35-$B$36-$B$37-$B$38 | C39: =$C$35-$C$36-$C$37-$C$38 | D39: =$D$35-$D$36-$D$37-$D$38 | E39: =$E$35-$E$36-$E$37-$E$38 | F39: =$F$35-$F$36-$F$37-$F$38
A40: (+) Depreciation & amortisation | B40: =$B$78 | C40: =$C$78 | D40: =$D$78 | E40: =$E$78 | F40: =$F$78 | G40: Linked from cash-flow block; added back to reach EBITDA.
A41: EBITDA | B41: =$B$39+$B$40 | C41: =$C$39+$C$40 | D41: =$D$39+$D$40 | E41: =$E$39+$E$40 | F41: =$F$39+$F$40
A42: Interest expense
A43: Interest & investment income
A44: Other non-operating income / (expense)
A45: Pre-tax income | B45: =$B$39-$B$42+$B$43+$B$44 | C45: =$C$39-$C$42+$C$43+$C$44 | D45: =$D$39-$D$42+$D$43+$D$44 | E45: =$E$39-$E$42+$E$43+$E$44 | F45: =$F$39-$F$42+$F$43+$F$44
A46: Income tax expense
A47: Minority interest / (income)
A48: Net income to shareholders | B48: =$B$45-$B$46-$B$47 | C48: =$C$45-$C$46-$C$47 | D48: =$D$45-$D$46-$D$47 | E48: =$E$45-$E$46-$E$47 | F48: =$F$45-$F$46-$F$47
A50: Balance Sheet
B51: FY—4 | C51: FY—3 | D51: FY—2 | E51: FY—1 | F51: FY—0 | G51: Source / note
A52: Cash & equivalents
A53: Short-term investments
A54: Accounts receivable
A55: Inventory
A56: Other current assets
A57: Total current assets | B57: =SUM($B$52,$B$53,$B$54,$B$55,$B$56) | C57: =SUM($C$52,$C$53,$C$54,$C$55,$C$56) | D57: =SUM($D$52,$D$53,$D$54,$D$55,$D$56) | E57: =SUM($E$52,$E$53,$E$54,$E$55,$E$56) | F57: =SUM($F$52,$F$53,$F$54,$F$55,$F$56)
A58: Property, plant & equipment (net)
A59: Goodwill & intangibles
A60: Other non-current assets
A61: Total non-current assets | B61: =SUM($B$58,$B$59,$B$60) | C61: =SUM($C$58,$C$59,$C$60) | D61: =SUM($D$58,$D$59,$D$60) | E61: =SUM($E$58,$E$59,$E$60) | F61: =SUM($F$58,$F$59,$F$60)
A62: TOTAL ASSETS | B62: =$B$57+$B$61 | C62: =$C$57+$C$61 | D62: =$D$57+$D$61 | E62: =$E$57+$E$61 | F62: =$F$57+$F$61
A63: Accounts payable
A64: Short-term debt & current portion LTD
A65: Other current liabilities
A66: Total current liabilities | B66: =SUM($B$63,$B$64,$B$65) | C66: =SUM($C$63,$C$64,$C$65) | D66: =SUM($D$63,$D$64,$D$65) | E66: =SUM($E$63,$E$64,$E$65) | F66: =SUM($F$63,$F$64,$F$65)
A67: Long-term debt
A68: Other non-current liabilities
A69: Total non-current liabilities | B69: =SUM($B$67,$B$68) | C69: =SUM($C$67,$C$68) | D69: =SUM($D$67,$D$68) | E69: =SUM($E$67,$E$68) | F69: =SUM($F$67,$F$68)
A70: TOTAL LIABILITIES | B70: =$B$66+$B$69 | C70: =$C$66+$C$69 | D70: =$D$66+$D$69 | E70: =$E$66+$E$69 | F70: =$F$66+$F$69
A71: Total shareholders' equity
A72: Minority interest (equity)
A73: TOTAL LIABILITIES & EQUITY | B73: =$B$70+$B$71+$B$72 | C73: =$C$70+$C$71+$C$72 | D73: =$D$70+$D$71+$D$72 | E73: =$E$70+$E$71+$E$72 | F73: =$F$70+$F$71+$F$72
A75: Cash Flow Statement
B76: FY—4 | C76: FY—3 | D76: FY—2 | E76: FY—1 | F76: FY—0 | G76: Source / note
A77: Net income (per cash-flow statement)
A78: Depreciation & amortisation | G78: The single D&A figure; feeds EBITDA in the income statement.
A79: Change in working capital (cash impact) | G79: Positive = cash released; negative = cash invested in WC.
A80: Other non-cash / operating items
A81: Cash flow from operations (CFO) | B81: =SUM($B$77,$B$78,$B$79,$B$80) | C81: =SUM($C$77,$C$78,$C$79,$C$80) | D81: =SUM($D$77,$D$78,$D$79,$D$80) | E81: =SUM($E$77,$E$78,$E$79,$E$80) | F81: =SUM($F$77,$F$78,$F$79,$F$80)
A82: Capital expenditure | G82: Enter as a positive amount; the model subtracts it.
A83: Acquisitions / (disposals), net | G83: Positive = cash spent on acquisitions.
A84: Other investing (cash impact)
A85: Cash flow from investing (CFI) | B85: =-$B$82-$B$83+$B$84 | C85: =-$C$82-$C$83+$C$84 | D85: =-$D$82-$D$83+$D$84 | E85: =-$E$82-$E$83+$E$84 | F85: =-$F$82-$F$83+$F$84
A86: Net debt issued / (repaid) | G86: Signed: positive = net borrowing.
A87: Dividends paid | G87: Enter as a positive amount returned to shareholders.
A88: Share buybacks (net) | G88: Enter as a positive amount; net of issuance.
A89: Other financing (cash impact)
A90: Cash flow from financing (CFF) | B90: =$B$86-$B$87-$B$88+$B$89 | C90: =$C$86-$C$87-$C$88+$C$89 | D90: =$D$86-$D$87-$D$88+$D$89 | E90: =$E$86-$E$87-$E$88+$E$89 | F90: =$F$86-$F$87-$F$88+$F$89
A91: Net change in cash | B91: =$B$81+$B$85+$B$90 | C91: =$C$81+$C$85+$C$90 | D91: =$D$81+$D$85+$D$90 | E91: =$E$81+$E$85+$E$90 | F91: =$F$81+$F$85+$F$90
A93: Shares & Per-Share Data
B94: FY—4 | C94: FY—3 | D94: FY—2 | E94: FY—1 | F94: FY—0 | G94: Source / note
A95: Weighted avg shares (basic, m)
A96: Weighted avg shares (diluted, m)
A97: EPS (basic) | B97: =IF(AND(ISNUMBER($B$48),ISNUMBER($B$95),$B$95<>0),$B$48/$B$95,"n/m") | C97: =IF(AND(ISNUMBER($C$48),ISNUMBER($C$95),$C$95<>0),$C$48/$C$95,"n/m") | D97: =IF(AND(ISNUMBER($D$48),ISNUMBER($D$95),$D$95<>0),$D$48/$D$95,"n/m") | E97: =IF(AND(ISNUMBER($E$48),ISNUMBER($E$95),$E$95<>0),$E$48/$E$95,"n/m") | F97: =IF(AND(ISNUMBER($F$48),ISNUMBER($F$95),$F$95<>0),$F$48/$F$95,"n/m")
A98: EPS (diluted) | B98: =IF(AND(ISNUMBER($B$48),ISNUMBER($B$96),$B$96<>0),$B$48/$B$96,"n/m") | C98: =IF(AND(ISNUMBER($C$48),ISNUMBER($C$96),$C$96<>0),$C$48/$C$96,"n/m") | D98: =IF(AND(ISNUMBER($D$48),ISNUMBER($D$96),$D$96<>0),$D$48/$D$96,"n/m") | E98: =IF(AND(ISNUMBER($E$48),ISNUMBER($E$96),$E$96<>0),$E$48/$E$96,"n/m") | F98: =IF(AND(ISNUMBER($F$48),ISNUMBER($F$96),$F$96<>0),$F$48/$F$96,"n/m")
A99: Dividend per share | B99: =IF(AND(ISNUMBER($B$87),ISNUMBER($B$95),$B$95<>0),$B$87/$B$95,"n/m") | C99: =IF(AND(ISNUMBER($C$87),ISNUMBER($C$95),$C$95<>0),$C$87/$C$95,"n/m") | D99: =IF(AND(ISNUMBER($D$87),ISNUMBER($D$95),$D$95<>0),$D$87/$D$95,"n/m") | E99: =IF(AND(ISNUMBER($E$87),ISNUMBER($E$95),$E$95<>0),$E$87/$E$95,"n/m") | F99: =IF(AND(ISNUMBER($F$87),ISNUMBER($F$95),$F$95<>0),$F$87/$F$95,"n/m")
A100: Dividend payout ratio | B100: =IF(AND(ISNUMBER($B$87),ISNUMBER($B$48),$B$48<>0),$B$87/$B$48,"n/m") | C100: =IF(AND(ISNUMBER($C$87),ISNUMBER($C$48),$C$48<>0),$C$87/$C$48,"n/m") | D100: =IF(AND(ISNUMBER($D$87),ISNUMBER($D$48),$D$48<>0),$D$87/$D$48,"n/m") | E100: =IF(AND(ISNUMBER($E$87),ISNUMBER($E$48),$E$48<>0),$E$87/$E$48,"n/m") | F100: =IF(AND(ISNUMBER($F$87),ISNUMBER($F$48),$F$48<>0),$F$87/$F$48,"n/m")
A102: Optional Drivers (volume / price)
B103: FY—4 | C103: FY—3 | D103: FY—2 | E103: FY—1 | F103: FY—0 | G103: Source / note
A104: Volume (units, m) | G104: Optional. Units sold / delivered.
A105: Average selling price | G105: Optional. Revenue per unit; volume x price should ~ revenue.
A106: Implied revenue (volume x price) | B106: =$B$104*$B$105 | C106: =$C$104*$C$105 | D106: =$D$104*$D$105 | E106: =$E$104*$E$105 | F106: =$F$104*$F$105 | G106: Cross-check: should approximate reported revenue.
A109: Market & Valuation Reference Inputs
A110: Used by the WACC build-up and the equity-value bridge. Fallback defaults are applied (and labelled) where left blank.
A111: Reference | B111: Value | C111: Type | D111: Note
A112: Current share price | C112: input | D112: Latest market price; leave blank if private/unknown.
A113: Shares outstanding (current, m) | C113: input | D113: Current shares for market cap & per-share value.
...

Sheet Historical
A1: HISTORICAL ANALYSIS
A2: Ratios, margins, growth, returns & cash flow — with plain-English read
A3: Investment-Grade Company Analysis Engine · v1.0
A4: All figures in USD millions unless stated. Balance-sheet ratios use period-end balances.
A6: Growth (year-on-year)
B7: FY—4 | C7: FY—3 | D7: FY—2 | E7: FY—1 | F7: FY—0 | G7: Latest read
A8: Revenue growth | C8: =IF(AND(ISNUMBER('Inputs'!$C$33),ISNUMBER('Inputs'!$B$33),'Inputs'!$B$33>0),'Inputs'!$C$33/'Inputs'!$B$33-1,"n/m") | D8: =IF(AND(ISNUMBER('Inputs'!$D$33),ISNUMBER('Inputs'!$C$33),'Inputs'!$C$33>0),'Inputs'!$D$33/'Inputs'!$C$33-1,"n/m") | E8: =IF(AND(ISNUMBER('Inputs'!$E$33),ISNUMBER('Inputs'!$D$33),'Inputs'!$D$33>0),'Inputs'!$E$33/'Inputs'!$D$33-1,"n/m") | F8: =IF(AND(ISNUMBER('Inputs'!$F$33),ISNUMBER('Inputs'!$E$33),'Inputs'!$E$33>0),'Inputs'!$F$33/'Inputs'!$E$33-1,"n/m") | G8: =IF(NOT(AND(ISNUMBER($F$8),ISNUMBER($E$8))),"n/a",IF($F$8>$E$8+0.02,"Accelerating",IF($F$8<$E$8-0.02,"Decelerating","Stable")))
A9: Gross profit growth | C9: =IF(AND(ISNUMBER('Inputs'!$C$35),ISNUMBER('Inputs'!$B$35),'Inputs'!$B$35>0),'Inputs'!$C$35/'Inputs'!$B$35-1,"n/m") | D9: =IF(AND(ISNUMBER('Inputs'!$D$35),ISNUMBER('Inputs'!$C$35),'Inputs'!$C$35>0),'Inputs'!$D$35/'Inputs'!$C$35-1,"n/m") | E9: =IF(AND(ISNUMBER('Inputs'!$E$35),ISNUMBER('Inputs'!$D$35),'Inputs'!$D$35>0),'Inputs'!$E$35/'Inputs'!$D$35-1,"n/m") | F9: =IF(AND(ISNUMBER('Inputs'!$F$35),ISNUMBER('Inputs'!$E$35),'Inputs'!$E$35>0),'Inputs'!$F$35/'Inputs'!$E$35-1,"n/m") | G9: =IF(NOT(AND(ISNUMBER($F$9),ISNUMBER($E$9))),"n/a",IF($F$9>$E$9+0.02,"Accelerating",IF($F$9<$E$9-0.02,"Decelerating","Stable")))
A10: EBITDA growth | C10: =IF(AND(ISNUMBER('Inputs'!$C$41),ISNUMBER('Inputs'!$B$41),'Inputs'!$B$41>0),'Inputs'!$C$41/'Inputs'!$B$41-1,"n/m") | D10: =IF(AND(ISNUMBER('Inputs'!$D$41),ISNUMBER('Inputs'!$C$41),'Inputs'!$C$41>0),'Inputs'!$D$41/'Inputs'!$C$41-1,"n/m") | E10: =IF(AND(ISNUMBER('Inputs'!$E$41),ISNUMBER('Inputs'!$D$41),'Inputs'!$D$41>0),'Inputs'!$E$41/'Inputs'!$D$41-1,"n/m") | F10: =IF(AND(ISNUMBER('Inputs'!$F$41),ISNUMBER('Inputs'!$E$41),'Inputs'!$E$41>0),'Inputs'!$F$41/'Inputs'!$E$41-1,"n/m") | G10: =IF(NOT(AND(ISNUMBER($F$10),ISNUMBER($E$10))),"n/a",IF($F$10>$E$10+0.02,"Accelerating",IF($F$10<$E$10-0.02,"Decelerating","Stable")))
A11: EBIT growth | C11: =IF(AND(ISNUMBER('Inputs'!$C$39),ISNUMBER('Inputs'!$B$39),'Inputs'!$B$39>0),'Inputs'!$C$39/'Inputs'!$B$39-1,"n/m") | D11: =IF(AND(ISNUMBER('Inputs'!$D$39),ISNUMBER('Inputs'!$C$39),'Inputs'!$C$39>0),'Inputs'!$D$39/'Inputs'!$C$39-1,"n/m") | E11: =IF(AND(ISNUMBER('Inputs'!$E$39),ISNUMBER('Inputs'!$D$39),'Inputs'!$D$39>0),'Inputs'!$E$39/'Inputs'!$D$39-1,"n/m") | F11: =IF(AND(ISNUMBER('Inputs'!$F$39),ISNUMBER('Inputs'!$E$39),'Inputs'!$E$39>0),'Inputs'!$F$39/'Inputs'!$E$39-1,"n/m") | G11: =IF(NOT(AND(ISNUMBER($F$11),ISNUMBER($E$11))),"n/a",IF($F$11>$E$11+0.02,"Accelerating",IF($F$11<$E$11-0.02,"Decelerating","Stable")))
A12: Net income growth | C12: =IF(AND(ISNUMBER('Inputs'!$C$48),ISNUMBER('Inputs'!$B$48),'Inputs'!$B$48>0),'Inputs'!$C$48/'Inputs'!$B$48-1,"n/m") | D12: =IF(AND(ISNUMBER('Inputs'!$D$48),ISNUMBER('Inputs'!$C$48),'Inputs'!$C$48>0),'Inputs'!$D$48/'Inputs'!$C$48-1,"n/m") | E12: =IF(AND(ISNUMBER('Inputs'!$E$48),ISNUMBER('Inputs'!$D$48),'Inputs'!$D$48>0),'Inputs'!$E$48/'Inputs'!$D$48-1,"n/m") | F12: =IF(AND(ISNUMBER('Inputs'!$F$48),ISNUMBER('Inputs'!$E$48),'Inputs'!$E$48>0),'Inputs'!$F$48/'Inputs'!$E$48-1,"n/m") | G12: =IF(NOT(AND(ISNUMBER($F$12),ISNUMBER($E$12))),"n/a",IF($F$12>$E$12+0.02,"Accelerating",IF($F$12<$E$12-0.02,"Decelerating","Stable")))
A13: Diluted EPS growth | C13: =IF(AND(ISNUMBER('Inputs'!$C$98),ISNUMBER('Inputs'!$B$98),'Inputs'!$B$98>0),'Inputs'!$C$98/'Inputs'!$B$98-1,"n/m") | D13: =IF(AND(ISNUMBER('Inputs'!$D$98),ISNUMBER('Inputs'!$C$98),'Inputs'!$C$98>0),'Inputs'!$D$98/'Inputs'!$C$98-1,"n/m") | E13: =IF(AND(ISNUMBER('Inputs'!$E$98),ISNUMBER('Inputs'!$D$98),'Inputs'!$D$98>0),'Inputs'!$E$98/'Inputs'!$D$98-1,"n/m") | F13: =IF(AND(ISNUMBER('Inputs'!$F$98),ISNUMBER('Inputs'!$E$98),'Inputs'!$E$98>0),'Inputs'!$F$98/'Inputs'!$E$98-1,"n/m") | G13: =IF(NOT(AND(ISNUMBER($F$13),ISNUMBER($E$13))),"n/a",IF($F$13>$E$13+0.02,"Accelerating",IF($F$13<$E$13-0.02,"Decelerating","Stable")))
A15: Profitability & Margins
B16: FY—4 | C16: FY—3 | D16: FY—2 | E16: FY—1 | F16: FY—0 | G16: Latest read
A17: Gross margin | B17: =IF(AND(ISNUMBER('Inputs'!$B$35),ISNUMBER('Inputs'!$B$33),'Inputs'!$B$33<>0),'Inputs'!$B$35/'Inputs'!$B$33,"n/m") | C17: =IF(AND(ISNUMBER('Inputs'!$C$35),ISNUMBER('Inputs'!$C$33),'Inputs'!$C$33<>0),'Inputs'!$C$35/'Inputs'!$C$33,"n/m") | D17: =IF(AND(ISNUMBER('Inputs'!$D$35),ISNUMBER('Inputs'!$D$33),'Inputs'!$D$33<>0),'Inputs'!$D$35/'Inputs'!$D$33,"n/m") | E17: =IF(AND(ISNUMBER('Inputs'!$E$35),ISNUMBER('Inputs'!$E$33),'Inputs'!$E$33<>0),'Inputs'!$E$35/'Inputs'!$E$33,"n/m") | F17: =IF(AND(ISNUMBER('Inputs'!$F$35),ISNUMBER('Inputs'!$F$33),'Inputs'!$F$33<>0),'Inputs'!$F$35/'Inputs'!$F$33,"n/m") | G17: =IF(NOT(AND(ISNUMBER($F$17),ISNUMBER(AVERAGE($B$17:$E$17)))),"n/a",IF($F$17>AVERAGE($B$17:$E$17)*(1+0.05),"Expanding",IF($F$17<AVERAGE($B$17:$E$17)*(1-0.05),"Compressing","Stable")))
A18: EBITDA margin | B18: =IF(AND(ISNUMBER('Inputs'!$B$41),ISNUMBER('Inputs'!$B$33),'Inputs'!$B$33<>0),'Inputs'!$B$41/'Inputs'!$B$33,"n/m") | C18: =IF(AND(ISNUMBER('Inputs'!$C$41),ISNUMBER('Inputs'!$C$33),'Inputs'!$C$33<>0),'Inputs'!$C$41/'Inputs'!$C$33,"n/m") | D18: =IF(AND(ISNUMBER('Inputs'!$D$41),ISNUMBER('Inputs'!$D$33),'Inputs'!$D$33<>0),'Inputs'!$D$41/'Inputs'!$D$33,"n/m") | E18: =IF(AND(ISNUMBER('Inputs'!$E$41),ISNUMBER('Inputs'!$E$33),'Inputs'!$E$33<>0),'Inputs'!$E$41/'Inputs'!$E$33,"n/m") | F18: =IF(AND(ISNUMBER('Inputs'!$F$41),ISNUMBER('Inputs'!$F$33),'Inputs'!$F$33<>0),'Inputs'!$F$41/'Inputs'!$F$33,"n/m") | G18: =IF(NOT(AND(ISNUMBER($F$18),ISNUMBER(AVERAGE($B$18:$E$18)))),"n/a",IF($F$18>AVERAGE($B$18:$E$18)*(1+0.05),"Expanding",IF($F$18<AVERAGE($B$18:$E$18)*(1-0.05),"Compressing","Stable")))
A19: EBIT (operating) margin | B19: =IF(AND(ISNUMBER('Inputs'!$B$39),ISNUMBER('Inputs'!$B$33),'Inputs'!$B$33<>0),'Inputs'!$B$39/'Inputs'!$B$33,"n/m") | C19: =IF(AND(ISNUMBER('Inputs'!$C$39),ISNUMBER('Inputs'!$C$33),'Inputs'!$C$33<>0),'Inputs'!$C$39/'Inputs'!$C$33,"n/m") | D19: =IF(AND(ISNUMBER('Inputs'!$D$39),ISNUMBER('Inputs'!$D$33),'Inputs'!$D$33<>0),'Inputs'!$D$39/'Inputs'!$D$33,"n/m") | E19: =IF(AND(ISNUMBER('Inputs'!$E$39),ISNUMBER('Inputs'!$E$33),'Inputs'!$E$33<>0),'Inputs'!$E$39/'Inputs'!$E$33,"n/m") | F19: =IF(AND(ISNUMBER('Inputs'!$F$39),ISNUMBER('Inputs'!$F$33),'Inputs'!$F$33<>0),'Inputs'!$F$39/'Inputs'!$F$33,"n/m") | G19: =IF(NOT(AND(ISNUMBER($F$19),ISNUMBER(AVERAGE($B$19:$E$19)))),"n/a",IF($F$19>AVERAGE($B$19:$E$19)*(1+0.05),"Expanding",IF($F$19<AVERAGE($B$19:$E$19)*(1-0.05),"Compressing","Stable")))
A20: Net margin | B20: =IF(AND(ISNUMBER('Inputs'!$B$48),ISNUMBER('Inputs'!$B$33),'Inputs'!$B$33<>0),'Inputs'!$B$48/'Inputs'!$B$33,"n/m") | C20: =IF(AND(ISNUMBER('Inputs'!$C$48),ISNUMBER('Inputs'!$C$33),'Inputs'!$C$33<>0),'Inputs'!$C$48/'Inputs'!$C$33,"n/m") | D20: =IF(AND(ISNUMBER('Inputs'!$D$48),ISNUMBER('Inputs'!$D$33),'Inputs'!$D$33<>0),'Inputs'!$D$48/'Inputs'!$D$33,"n/m") | E20: =IF(AND(ISNUMBER('Inputs'!$E$48),ISNUMBER('Inputs'!$E$33),'Inputs'!$E$33<>0),'Inputs'!$E$48/'Inputs'!$E$33,"n/m") | F20: =IF(AND(ISNUMBER('Inputs'!$F$48),ISNUMBER('Inputs'!$F$33),'Inputs'!$F$33<>0),'Inputs'!$F$48/'Inputs'!$F$33,"n/m") | G20: =IF(NOT(AND(ISNUMBER($F$20),ISNUMBER(AVERAGE($B$20:$E$20)))),"n/a",IF($F$20>AVERAGE($B$20:$E$20)*(1+0.05),"Expanding",IF($F$20<AVERAGE($B$20:$E$20)*(1-0.05),"Compressing","Stable")))
A21: SG&A % of revenue | B21: =IF(AND(ISNUMBER('Inputs'!$B$36),ISNUMBER('Inputs'!$B$33),'Inputs'!$B$33<>0),'Inputs'!$B$36/'Inputs'!$B$33,"n/m") | C21: =IF(AND(ISNUMBER('Inputs'!$C$36),ISNUMBER('Inputs'!$C$33),'Inputs'!$C$33<>0),'Inputs'!$C$36/'Inputs'!$C$33,"n/m") | D21: =IF(AND(ISNUMBER('Inputs'!$D$36),ISNUMBER('Inputs'!$D$33),'Inputs'!$D$33<>0),'Inputs'!$D$36/'Inputs'!$D$33,"n/m") | E21: =IF(AND(ISNUMBER('Inputs'!$E$36),ISNUMBER('Inputs'!$E$33),'Inputs'!$E$33<>0),'Inputs'!$E$36/'Inputs'!$E$33,"n/m") | F21: =IF(AND(ISNUMBER('Inputs'!$F$36),ISNUMBER('Inputs'!$F$33),'Inputs'!$F$33<>0),'Inputs'!$F$36/'Inputs'!$F$33,"n/m") | G21: =IF(NOT(AND(ISNUMBER($F$21),ISNUMBER(AVERAGE($B$21:$E$21)))),"n/a",IF($F$21>AVERAGE($B$21:$E$21)*(1+0.05),"Deteriorating",IF($F$21<AVERAGE($B$21:$E$21)*(1-0.05),"Improving","Stable")))
A22: R&D % of revenue | B22: =IF(AND(ISNUMBER('Inputs'!$B$37),ISNUMBER('Inputs'!$B$33),'Inputs'!$B$33<>0),'Inputs'!$B$37/'Inputs'!$B$33,"n/m") | C22: =IF(AND(ISNUMBER('Inputs'!$C$37),ISNUMBER('Inputs'!$C$33),'Inputs'!$C$33<>0),'Inputs'!$C$37/'Inputs'!$C$33,"n/m") | D22: =IF(AND(ISNUMBER('Inputs'!$D$37),ISNUMBER('Inputs'!$D$33),'Inputs'!$D$33<>0),'Inputs'!$D$37/'Inputs'!$D$33,"n/m") | E22: =IF(AND(ISNUMBER('Inputs'!$E$37),ISNUMBER('Inputs'!$E$33),'Inputs'!$E$33<>0),'Inputs'!$E$37/'Inputs'!$E$33,"n/m") | F22: =IF(AND(ISNUMBER('Inputs'!$F$37),ISNUMBER('Inputs'!$F$33),'Inputs'!$F$33<>0),'Inputs'!$F$37/'Inputs'!$F$33,"n/m") | G22: =IF(NOT(AND(ISNUMBER($F$22),ISNUMBER(AVERAGE($B$22:$E$22)))),"n/a",IF($F$22>AVERAGE($B$22:$E$22)*(1+0.05),"Deteriorating",IF($F$22<AVERAGE($B$22:$E$22)*(1-0.05),"Improving","Stable")))
A23: D&A % of revenue | B23: =IF(AND(ISNUMBER('Inputs'!$B$40),ISNUMBER('Inputs'!$B$33),'Inputs'!$B$33<>0),'Inputs'!$B$40/'Inputs'!$B$33,"n/m") | C23: =IF(AND(ISNUMBER('Inputs'!$C$40),ISNUMBER('Inputs'!$C$33),'Inputs'!$C$33<>0),'Inputs'!$C$40/'Inputs'!$C$33,"n/m") | D23: =IF(AND(ISNUMBER('Inputs'!$D$40),ISNUMBER('Inputs'!$D$33),'Inputs'!$D$33<>0),'Inputs'!$D$40/'Inputs'!$D$33,"n/m") | E23: =IF(AND(ISNUMBER('Inputs'!$E$40),ISNUMBER('Inputs'!$E$33),'Inputs'!$E$33<>0),'Inputs'!$E$40/'Inputs'!$E$33,"n/m") | F23: =IF(AND(ISNUMBER('Inputs'!$F$40),ISNUMBER('Inputs'!$F$33),'Inputs'!$F$33<>0),'Inputs'!$F$40/'Inputs'!$F$33,"n/m")
A24: Interest burden (EBT / EBIT) | B24: =IF(AND(ISNUMBER('Inputs'!$B$45),ISNUMBER('Inputs'!$B$39),'Inputs'!$B$39<>0),'Inputs'!$B$45/'Inputs'!$B$39,"n/m") | C24: =IF(AND(ISNUMBER('Inputs'!$C$45),ISNUMBER('Inputs'!$C$39),'Inputs'!$C$39<>0),'Inputs'!$C$45/'Inputs'!$C$39,"n/m") | D24: =IF(AND(ISNUMBER('Inputs'!$D$45),ISNUMBER('Inputs'!$D$39),'Inputs'!$D$39<>0),'Inputs'!$D$45/'Inputs'!$D$39,"n/m") | E24: =IF(AND(ISNUMBER('Inputs'!$E$45),ISNUMBER('Inputs'!$E$39),'Inputs'!$E$39<>0),'Inputs'!$E$45/'Inputs'!$E$39,"n/m") | F24: =IF(AND(ISNUMBER('Inputs'!$F$45),ISNUMBER('Inputs'!$F$39),'Inputs'!$F$39<>0),'Inputs'!$F$45/'Inputs'!$F$39,"n/m") | G24: =IF(NOT(AND(ISNUMBER($F$24),ISNUMBER(AVERAGE($B$24:$E$24)))),"n/a",IF($F$24>AVERAGE($B$24:$E$24)*(1+0.05),"Improving",IF($F$24<AVERAGE($B$24:$E$24)*(1-0.05),"Deteriorating","Stable")))
A25: Tax burden (NI / EBT) | B25: =IF(AND(ISNUMBER('Inputs'!$B$48),ISNUMBER('Inputs'!$B$45),'Inputs'!$B$45<>0),'Inputs'!$B$48/'Inputs'!$B$45,"n/m") | C25: =IF(AND(ISNUMBER('Inputs'!$C$48),ISNUMBER('Inputs'!$C$45),'Inputs'!$C$45<>0),'Inputs'!$C$48/'Inputs'!$C$45,"n/m") | D25: =IF(AND(ISNUMBER('Inputs'!$D$48),ISNUMBER('Inputs'!$D$45),'Inputs'!$D$45<>0),'Inputs'!$D$48/'Inputs'!$D$45,"n/m") | E25: =IF(AND(ISNUMBER('Inputs'!$E$48),ISNUMBER('Inputs'!$E$45),'Inputs'!$E$45<>0),'Inputs'!$E$48/'Inputs'!$E$45,"n/m") | F25: =IF(AND(ISNUMBER('Inputs'!$F$48),ISNUMBER('Inputs'!$F$45),'Inputs'!$F$45<>0),'Inputs'!$F$48/'Inputs'!$F$45,"n/m") | G25: =IF(NOT(AND(ISNUMBER($F$25),ISNUMBER(AVERAGE($B$25:$E$25)))),"n/a",IF($F$25>AVERAGE($B$25:$E$25)*(1+0.05),"Improving",IF($F$25<AVERAGE($B$25:$E$25)*(1-0.05),"Deteriorating","Stable")))
A26: Effective tax rate | B26: =IF(AND(ISNUMBER('Inputs'!$B$46),ISNUMBER('Inputs'!$B$45),'Inputs'!$B$45<>0),'Inputs'!$B$46/'Inputs'!$B$45,"n/m") | C26: =IF(AND(ISNUMBER('Inputs'!$C$46),ISNUMBER('Inputs'!$C$45),'Inputs'!$C$45<>0),'Inputs'!$C$46/'Inputs'!$C$45,"n/m") | D26: =IF(AND(ISNUMBER('Inputs'!$D$46),ISNUMBER('Inputs'!$D$45),'Inputs'!$D$45<>0),'Inputs'!$D$46/'Inputs'!$D$45,"n/m") | E26: =IF(AND(ISNUMBER('Inputs'!$E$46),ISNUMBER('Inputs'!$E$45),'Inputs'!$E$45<>0),'Inputs'!$E$46/'Inputs'!$E$45,"n/m") | F26: =IF(AND(ISNUMBER('Inputs'!$F$46),ISNUMBER('Inputs'!$F$45),'Inputs'!$F$45<>0),'Inputs'!$F$46/'Inputs'!$F$45,"n/m")
A28: Returns on Capital
B29: FY—4 | C29: FY—3 | D29: FY—2 | E29: FY—1 | F29: FY—0 | G29: Latest read
A30: NOPAT = EBIT × (1 − effective tax) | B30: =IF(AND(ISNUMBER('Inputs'!$B$39),ISNUMBER('Inputs'!$B$46),ISNUMBER('Inputs'!$B$45)),'Inputs'!$B$39*(1-'Inputs'!$B$46/'Inputs'!$B$45),"n/m") | C30: =IF(AND(ISNUMBER('Inputs'!$C$39),ISNUMBER('Inputs'!$C$46),ISNUMBER('Inputs'!$C$45)),'Inputs'!$C$39*(1-'Inputs'!$C$46/'Inputs'!$C$45),"n/m") | D30: =IF(AND(ISNUMBER('Inputs'!$D$39),ISNUMBER('Inputs'!$D$46),ISNUMBER('Inputs'!$D$45)),'Inputs'!$D$39*(1-'Inputs'!$D$46/'Inputs'!$D$45),"n/m") | E30: =IF(AND(ISNUMBER('Inputs'!$E$39),ISNUMBER('Inputs'!$E$46),ISNUMBER('Inputs'!$E$45)),'Inputs'!$E$39*(1-'Inputs'!$E$46/'Inputs'!$E$45),"n/m") | F30: =IF(AND(ISNUMBER('Inputs'!$F$39),ISNUMBER('Inputs'!$F$46),ISNUMBER('Inputs'!$F$45)),'Inputs'!$F$39*(1-'Inputs'!$F$46/'Inputs'!$F$45),"n/m")
A31: Invested capital (debt + equity − cash) | B31: ='Inputs'!$B$71+'Inputs'!$B$72+'Inputs'!$B$64+'Inputs'!$B$67-'Inputs'!$B$52-'Inputs'!$B$53 | C31: ='Inputs'!$C$71+'Inputs'!$C$72+'Inputs'!$C$64+'Inputs'!$C$67-'Inputs'!$C$52-'Inputs'!$C$53 | D31: ='Inputs'!$D$71+'Inputs'!$D$72+'Inputs'!$D$64+'Inputs'!$D$67-'Inputs'!$D$52-'Inputs'!$D$53 | E31: ='Inputs'!$E$71+'Inputs'!$E$72+'Inputs'!$E$64+'Inputs'!$E$67-'Inputs'!$E$52-'Inputs'!$E$53 | F31: ='Inputs'!$F$71+'Inputs'!$F$72+'Inputs'!$F$64+'Inputs'!$F$67-'Inputs'!$F$52-'Inputs'!$F$53
A32: Return on equity (ROE) | B32: =IF(AND(ISNUMBER('Inputs'!$B$48),ISNUMBER('Inputs'!$B$71),'Inputs'!$B$71<>0),'Inputs'!$B$48/'Inputs'!$B$71,"n/m") | C32: =IF(AND(ISNUMBER('Inputs'!$C$48),ISNUMBER('Inputs'!$C$71),'Inputs'!$C$71<>0),'Inputs'!$C$48/'Inputs'!$C$71,"n/m") | D32: =IF(AND(ISNUMBER('Inputs'!$D$48),ISNUMBER('Inputs'!$D$71),'Inputs'!$D$71<>0),'Inputs'!$D$48/'Inputs'!$D$71,"n/m") | E32: =IF(AND(ISNUMBER('Inputs'!$E$48),ISNUMBER('Inputs'!$E$71),'Inputs'!$E$71<>0),'Inputs'!$E$48/'Inputs'!$E$71,"n/m") | F32: =IF(AND(ISNUMBER('Inputs'!$F$48),ISNUMBER('Inputs'!$F$71),'Inputs'!$F$71<>0),'Inputs'!$F$48/'Inputs'!$F$71,"n/m") | G32: =IF(NOT(ISNUMBER($F$32)),"n/a",IF($F$32<0.08,"Weak",IF($F$32<0.15,"Moderate","Strong")))
A33: Return on assets (ROA) | B33: =IF(AND(ISNUMBER('Inputs'!$B$48),ISNUMBER('Inputs'!$B$62),'Inputs'!$B$62<>0),'Inputs'!$B$48/'Inputs'!$B$62,"n/m") | C33: =IF(AND(ISNUMBER('Inputs'!$C$48),ISNUMBER('Inputs'!$C$62),'Inputs'!$C$62<>0),'Inputs'!$C$48/'Inputs'!$C$62,"n/m") | D33: =IF(AND(ISNUMBER('Inputs'!$D$48),ISNUMBER('Inputs'!$D$62),'Inputs'!$D$62<>0),'Inputs'!$D$48/'Inputs'!$D$62,"n/m") | E33: =IF(AND(ISNUMBER('Inputs'!$E$48),ISNUMBER('Inputs'!$E$62),'Inputs'!$E$62<>0),'Inputs'!$E$48/'Inputs'!$E$62,"n/m") | F33: =IF(AND(ISNUMBER('Inputs'!$F$48),ISNUMBER('Inputs'!$F$62),'Inputs'!$F$62<>0),'Inputs'!$F$48/'Inputs'!$F$62,"n/m") | G33: =IF(NOT(ISNUMBER($F$33)),"n/a",IF($F$33<0.03,"Weak",IF($F$33<0.07,"Moderate","Strong")))
A34: Return on invested capital (ROIC) | B34: =IF(AND(ISNUMBER('Historical'!$B$30),ISNUMBER('Historical'!$B$31),'Historical'!$B$31<>0),'Historical'!$B$30/'Historical'!$B$31,"n/m") | C34: =IF(AND(ISNUMBER('Historical'!$C$30),ISNUMBER('Historical'!$C$31),'Historical'!$C$31<>0),'Historical'!$C$30/'Historical'!$C$31,"n/m") | D34: =IF(AND(ISNUMBER('Historical'!$D$30),ISNUMBER('Historical'!$D$31),'Historical'!$D$31<>0),'Historical'!$D$30/'Historical'!$D$31,"n/m") | E34: =IF(AND(ISNUMBER('Historical'!$E$30),ISNUMBER('Historical'!$E$31),'Historical'!$E$31<>0),'Historical'!$E$30/'Historical'!$E$31,"n/m") | F34: =IF(AND(ISNUMBER('Historical'!$F$30),ISNUMBER('Historical'!$F$31),'Historical'!$F$31<>0),'Historical'!$F$30/'Historical'!$F$31,"n/m") | G34: =IF(NOT(ISNUMBER($F$34)),"n/a",IF($F$34<0.08,"Weak",IF($F$34<0.12,"Moderate","Strong")))
A35: Return on capital employed (ROCE) | B35: =IF(AND(ISNUMBER('Inputs'!$B$39),ISNUMBER(('Inputs'!$B$62-'Inputs'!$B$66)),('Inputs'!$B$62-'Inputs'!$B$66)<>0),'Inputs'!$B$39/('Inputs'!$B$62-'Inputs'!$B$66),"n/m") | C35: =IF(AND(ISNUMBER('Inputs'!$C$39),ISNUMBER(('Inputs'!$C$62-'Inputs'!$C$66)),('Inputs'!$C$62-'Inputs'!$C$66)<>0),'Inputs'!$C$39/('Inputs'!$C$62-'Inputs'!$C$66),"n/m") | D35: =IF(AND(ISNUMBER('Inputs'!$D$39),ISNUMBER(('Inputs'!$D$62-'Inputs'!$D$66)),('Inputs'!$D$62-'Inputs'!$D$66)<>0),'Inputs'!$D$39/('Inputs'!$D$62-'Inputs'!$D$66),"n/m") | E35: =IF(AND(ISNUMBER('Inputs'!$E$39),ISNUMBER(('Inputs'!$E$62-'Inputs'!$E$66)),('Inputs'!$E$62-'Inputs'!$E$66)<>0),'Inputs'!$E$39/('Inputs'!$E$62-'Inputs'!$E$66),"n/m") | F35: =IF(AND(ISNUMBER('Inputs'!$F$39),ISNUMBER(('Inputs'!$F$62-'Inputs'!$F$66)),('Inputs'!$F$62-'Inputs'!$F$66)<>0),'Inputs'!$F$39/('Inputs'!$F$62-'Inputs'!$F$66),"n/m") | G35: =IF(NOT(ISNUMBER($F$35)),"n/a",IF($F$35<0.08,"Weak",IF($F$35<0.12,"Moderate","Strong")))
A37: Liquidity
B38: FY—4 | C38: FY—3 | D38: FY—2 | E38: FY—1 | F38: FY—0 | G38: Latest read
A39: Current ratio | B39: =IF(AND(ISNUMBER('Inputs'!$B$57),ISNUMBER('Inputs'!$B$66),'Inputs'!$B$66<>0),'Inputs'!$B$57/'Inputs'!$B$66,"n/m") | C39: =IF(AND(ISNUMBER('Inputs'!$C$57),ISNUMBER('Inputs'!$C$66),'Inputs'!$C$66<>0),'Inputs'!$C$57/'Inputs'!$C$66,"n/m") | D39: =IF(AND(ISNUMBER('Inputs'!$D$57),ISNUMBER('Inputs'!$D$66),'Inputs'!$D$66<>0),'Inputs'!$D$57/'Inputs'!$D$66,"n/m") | E39: =IF(AND(ISNUMBER('Inputs'!$E$57),ISNUMBER('Inputs'!$E$66),'Inputs'!$E$66<>0),'Inputs'!$E$57/'Inputs'!$E$66,"n/m") | F39: =IF(AND(ISNUMBER('Inputs'!$F$57),ISNUMBER('Inputs'!$F$66),'Inputs'!$F$66<>0),'Inputs'!$F$57/'Inputs'!$F$66,"n/m") | G39: =IF(NOT(ISNUMBER($F$39)),"n/a",IF($F$39<1.0,"Weak",IF($F$39<2.0,"Adequate","Strong")))
A40: Quick ratio (ex-inventory) | B40: =IF(AND(ISNUMBER(('Inputs'!$B$57-'Inputs'!$B$55)),ISNUMBER('Inputs'!$B$66),'Inputs'!$B$66<>0),('Inputs'!$B$57-'Inputs'!$B$55)/'Inputs'!$B$66,"n/m") | C40: =IF(AND(ISNUMBER(('Inputs'!$C$57-'Inputs'!$C$55)),ISNUMBER('Inputs'!$C$66),'Inputs'!$C$66<>0),('Inputs'!$C$57-'Inputs'!$C$55)/'Inputs'!$C$66,"n/m") | D40: =IF(AND(ISNUMBER(('Inputs'!$D$57-'Inputs'!$D$55)),ISNUMBER('Inputs'!$D$66),'Inputs'!$D$66<>0),('Inputs'!$D$57-'Inputs'!$D$55)/'Inputs'!$D$66,"n/m") | E40: =IF(AND(ISNUMBER(('Inputs'!$E$57-'Inputs'!$E$55)),ISNUMBER('Inputs'!$E$66),'Inputs'!$E$66<>0),('Inputs'!$E$57-'Inputs'!$E$55)/'Inputs'!$E$66,"n/m") | F40: =IF(AND(ISNUMBER(('Inputs'!$F$57-'Inputs'!$F$55)),ISNUMBER('Inputs'!$F$66),'Inputs'!$F$66<>0),('Inputs'!$F$57-'Inputs'!$F$55)/'Inputs'!$F$66,"n/m") | G40: =IF(NOT(ISNUMBER($F$40)),"n/a",IF($F$40<0.8,"Weak",IF($F$40<1.2,"Adequate","Strong")))
A41: Cash ratio | B41: =IF(AND(ISNUMBER(('Inputs'!$B$52+'Inputs'!$B$53)),ISNUMBER('Inputs'!$B$66),'Inputs'!$B$66<>0),('Inputs'!$B$52+'Inputs'!$B$53)/'Inputs'!$B$66,"n/m") | C41: =IF(AND(ISNUMBER(('Inputs'!$C$52+'Inputs'!$C$53)),ISNUMBER('Inputs'!$C$66),'Inputs'!$C$66<>0),('Inputs'!$C$52+'Inputs'!$C$53)/'Inputs'!$C$66,"n/m") | D41: =IF(AND(ISNUMBER(('Inputs'!$D$52+'Inputs'!$D$53)),ISNUMBER('Inputs'!$D$66),'Inputs'!$D$66<>0),('Inputs'!$D$52+'Inputs'!$D$53)/'Inputs'!$D$66,"n/m") | E41: =IF(AND(ISNUMBER(('Inputs'!$E$52+'Inputs'!$E$53)),ISNUMBER('Inputs'!$E$66),'Inputs'!$E$66<>0),('Inputs'!$E$52+'Inputs'!$E$53)/'Inputs'!$E$66,"n/m") | F41: =IF(AND(ISNUMBER(('Inputs'!$F$52+'Inputs'!$F$53)),ISNUMBER('Inputs'!$F$66),'Inputs'!$F$66<>0),('Inputs'!$F$52+'Inputs'!$F$53)/'Inputs'!$F$66,"n/m") | G41: =IF(NOT(ISNUMBER($F$41)),"n/a",IF($F$41<0.2,"Weak",IF($F$41<0.5,"Adequate","Strong")))
A43: Leverage & Solvency
B44: FY—4 | C44: FY—3 | D44: FY—2 | E44: FY—1 | F44: FY—0 | G44: Latest read
A45: Total debt | B45: ='Inputs'!$B$64+'Inputs'!$B$67 | C45: ='Inputs'!$C$64+'Inputs'!$C$67 | D45: ='Inputs'!$D$64+'Inputs'!$D$67 | E45: ='Inputs'!$E$64+'Inputs'!$E$67 | F45: ='Inputs'!$F$64+'Inputs'!$F$67
A46: Net debt (debt − cash & investments) | B46: ='Historical'!$B$45-'Inputs'!$B$52-'Inputs'!$B$53 | C46: ='Historical'!$C$45-'Inputs'!$C$52-'Inputs'!$C$53 | D46: ='Historical'!$D$45-'Inputs'!$D$52-'Inputs'!$D$53 | E46: ='Historical'!$E$45-'Inputs'!$E$52-'Inputs'!$E$53 | F46: ='Historical'!$F$45-'Inputs'!$F$52-'Inputs'!$F$53
A47: Debt / equity | B47: =IF(AND(ISNUMBER('Historical'!$B$45),ISNUMBER('Inputs'!$B$71),'Inputs'!$B$71<>0),'Historical'!$B$45/'Inputs'!$B$71,"n/m") | C47: =IF(AND(ISNUMBER('Historical'!$C$45),ISNUMBER('Inputs'!$C$71),'Inputs'!$C$71<>0),'Historical'!$C$45/'Inputs'!$C$71,"n/m") | D47: =IF(AND(ISNUMBER('Historical'!$D$45),ISNUMBER('Inputs'!$D$71),'Inputs'!$D$71<>0),'Historical'!$D$45/'Inputs'!$D$71,"n/m") | E47: =IF(AND(ISNUMBER('Historical'!$E$45),ISNUMBER('Inputs'!$E$71),'Inputs'!$E$71<>0),'Historical'!$E$45/'Inputs'!$E$71,"n/m") | F47: =IF(AND(ISNUMBER('Historical'!$F$45),ISNUMBER('Inputs'!$F$71),'Inputs'!$F$71<>0),'Historical'!$F$45/'Inputs'!$F$71,"n/m") | G47: =IF(NOT(ISNUMBER($F$47)),"n/a",IF($F$47<0.5,"Conservative",IF($F$47<1.0,"Moderate",IF($F$47<2.0,"Elevated","Stretched"))))
A48: Net debt / EBITDA | B48: =IF(AND(ISNUMBER('Historical'!$B$46),ISNUMBER('Inputs'!$B$41),'Inputs'!$B$41<>0),'Historical'!$B$46/'Inputs'!$B$41,"n/m") | C48: =IF(AND(ISNUMBER('Historical'!$C$46),ISNUMBER('Inputs'!$C$41),'Inputs'!$C$41<>0),'Historical'!$C$46/'Inputs'!$C$41,"n/m") | D48: =IF(AND(ISNUMBER('Historical'!$D$46),ISNUMBER('Inputs'!$D$41),'Inputs'!$D$41<>0),'Historical'!$D$46/'Inputs'!$D$41,"n/m") | E48: =IF(AND(ISNUMBER('Historical'!$E$46),ISNUMBER('Inputs'!$E$41),'Inputs'!$E$41<>0),'Historical'!$E$46/'Inputs'!$E$41,"n/m") | F48: =IF(AND(ISNUMBER('Historical'!$F$46),ISNUMBER('Inputs'!$F$41),'Inputs'!$F$41<>0),'Historical'!$F$46/'Inputs'!$F$41,"n/m") | G48: =IF(NOT(ISNUMBER($F$48)),"n/a",IF($F$48<1.0,"Conservative",IF($F$48<2.5,"Moderate",IF($F$48<4.0,"Elevated","Stretched"))))
A49: Interest coverage (EBIT / interest) | B49: =IF(AND(ISNUMBER('Inputs'!$B$39),ISNUMBER('Inputs'!$B$42),'Inputs'!$B$42<>0),'Inputs'!$B$39/'Inputs'!$B$42,"n/m") | C49: =IF(AND(ISNUMBER('Inputs'!$C$39),ISNUMBER('Inputs'!$C$42),'Inputs'!$C$42<>0),'Inputs'!$C$39/'Inputs'!$C$42,"n/m") | D49: =IF(AND(ISNUMBER('Inputs'!$D$39),ISNUMBER('Inputs'!$D$42),'Inputs'!$D$42<>0),'Inputs'!$D$39/'Inputs'!$D$42,"n/m") | E49: =IF(AND(ISNUMBER('Inputs'!$E$39),ISNUMBER('Inputs'!$E$42),'Inputs'!$E$42<>0),'Inputs'!$E$39/'Inputs'!$E$42,"n/m") | F49: =IF(AND(ISNUMBER('Inputs'!$F$39),ISNUMBER('Inputs'!$F$42),'Inputs'!$F$42<>0),'Inputs'!$F$39/'Inputs'!$F$42,"n/m") | G49: =IF(NOT(ISNUMBER($F$49)),"n/a",IF($F$49<2.0,"Weak",IF($F$49<4.0,"Moderate","Strong")))
A50: EBITDA / interest | B50: =IF(AND(ISNUMBER('Inputs'!$B$41),ISNUMBER('Inputs'!$B$42),'Inputs'!$B$42<>0),'Inputs'!$B$41/'Inputs'!$B$42,"n/m") | C50: =IF(AND(ISNUMBER('Inputs'!$C$41),ISNUMBER('Inputs'!$C$42),'Inputs'!$C$42<>0),'Inputs'!$C$41/'Inputs'!$C$42,"n/m") | D50: =IF(AND(ISNUMBER('Inputs'!$D$41),ISNUMBER('Inputs'!$D$42),'Inputs'!$D$42<>0),'Inputs'!$D$41/'Inputs'!$D$42,"n/m") | E50: =IF(AND(ISNUMBER('Inputs'!$E$41),ISNUMBER('Inputs'!$E$42),'Inputs'!$E$42<>0),'Inputs'!$E$41/'Inputs'!$E$42,"n/m") | F50: =IF(AND(ISNUMBER('Inputs'!$F$41),ISNUMBER('Inputs'!$F$42),'Inputs'!$F$42<>0),'Inputs'!$F$41/'Inputs'!$F$42,"n/m") | G50: =IF(NOT(ISNUMBER($F$50)),"n/a",IF($F$50<3.0,"Weak",IF($F$50<6.0,"Moderate","Strong")))
A52: Capital Efficiency & Working Capital
B53: FY—4 | C53: FY—3 | D53: FY—2 | E53: FY—1 | F53: FY—0 | G53: Latest read
A54: Days sales outstanding (DSO) | B54: =IF(AND(ISNUMBER('Inputs'!$B$54),ISNUMBER('Inputs'!$B$33)),'Inputs'!$B$54/'Inputs'!$B$33*365,"n/m") | C54: =IF(AND(ISNUMBER('Inputs'!$C$54),ISNUMBER('Inputs'!$C$33)),'Inputs'!$C$54/'Inputs'!$C$33*365,"n/m") | D54: =IF(AND(ISNUMBER('Inputs'!$D$54),ISNUMBER('Inputs'!$D$33)),'Inputs'!$D$54/'Inputs'!$D$33*365,"n/m") | E54: =IF(AND(ISNUMBER('Inputs'!$E$54),ISNUMBER('Inputs'!$E$33)),'Inputs'!$E$54/'Inputs'!$E$33*365,"n/m") | F54: =IF(AND(ISNUMBER('Inputs'!$F$54),ISNUMBER('Inputs'!$F$33)),'Inputs'!$F$54/'Inputs'!$F$33*365,"n/m")
A55: Days inventory outstanding (DIO) | B55: =IF(AND(ISNUMBER('Inputs'!$B$55),ISNUMBER('Inputs'!$B$34)),'Inputs'!$B$55/'Inputs'!$B$34*365,"n/m") | C55: =IF(AND(ISNUMBER('Inputs'!$C$55),ISNUMBER('Inputs'!$C$34)),'Inputs'!$C$55/'Inputs'!$C$34*365,"n/m") | D55: =IF(AND(ISNUMBER('Inputs'!$D$55),ISNUMBER('Inputs'!$D$34)),'Inputs'!$D$55/'Inputs'!$D$34*365,"n/m") | E55: =IF(AND(ISNUMBER('Inputs'!$E$55),ISNUMBER('Inputs'!$E$34)),'Inputs'!$E$55/'Inputs'!$E$34*365,"n/m") | F55: =IF(AND(ISNUMBER('Inputs'!$F$55),ISNUMBER('Inputs'!$F$34)),'Inputs'!$F$55/'Inputs'!$F$34*365,"n/m")
A56: Days payable outstanding (DPO) | B56: =IF(AND(ISNUMBER('Inputs'!$B$63),ISNUMBER('Inputs'!$B$34)),'Inputs'!$B$63/'Inputs'!$B$34*365,"n/m") | C56: =IF(AND(ISNUMBER('Inputs'!$C$63),ISNUMBER('Inputs'!$C$34)),'Inputs'!$C$63/'Inputs'!$C$34*365,"n/m") | D56: =IF(AND(ISNUMBER('Inputs'!$D$63),ISNUMBER('Inputs'!$D$34)),'Inputs'!$D$63/'Inputs'!$D$34*365,"n/m") | E56: =IF(AND(ISNUMBER('Inputs'!$E$63),ISNUMBER('Inputs'!$E$34)),'Inputs'!$E$63/'Inputs'!$E$34*365,"n/m") | F56: =IF(AND(ISNUMBER('Inputs'!$F$63),ISNUMBER('Inputs'!$F$34)),'Inputs'!$F$63/'Inputs'!$F$34*365,"n/m")
A57: Cash conversion cycle (DSO+DIO−DPO) | B57: =IF(AND(ISNUMBER('Historical'!$B$54),ISNUMBER('Historical'!$B$55),ISNUMBER('Historical'!$B$56)),'Historical'!$B$54+'Historical'!$B$55-'Historical'!$B$56,"n/m") | C57: =IF(AND(ISNUMBER('Historical'!$C$54),ISNUMBER('Historical'!$C$55),ISNUMBER('Historical'!$C$56)),'Historical'!$C$54+'Historical'!$C$55-'Historical'!$C$56,"n/m") | D57: =IF(AND(ISNUMBER('Historical'!$D$54),ISNUMBER('Historical'!$D$55),ISNUMBER('Historical'!$D$56)),'Historical'!$D$54+'Historical'!$D$55-'Historical'!$D$56,"n/m") | E57: =IF(AND(ISNUMBER('Historical'!$E$54),ISNUMBER('Historical'!$E$55),ISNUMBER('Historical'!$E$56)),'Historical'!$E$54+'Historical'!$E$55-'Historical'!$E$56,"n/m") | F57: =IF(AND(ISNUMBER('Historical'!$F$54),ISNUMBER('Historical'!$F$55),ISNUMBER('Historical'!$F$56)),'Historical'!$F$54+'Historical'!$F$55-'Historical'!$F$56,"n/m") | G57: =IF(NOT(AND(ISNUMBER($F$57),ISNUMBER(AVERAGE($B$57:$E$57)))),"n/a",IF($F$57>AVERAGE($B$57:$E$57)*(1+0.05),"Deteriorating",IF($F$57<AVERAGE($B$57:$E$57)*(1-0.05),"Improving","Stable")))
A58: Asset turnover (rev / assets) | B58: =IF(AND(ISNUMBER('Inputs'!$B$33),ISNUMBER('Inputs'!$B$62),'Inputs'!$B$62<>0),'Inputs'!$B$33/'Inputs'!$B$62,"n/m") | C58: =IF(AND(ISNUMBER('Inputs'!$C$33),ISNUMBER('Inputs'!$C$62),'Inputs'!$C$62<>0),'Inputs'!$C$33/'Inputs'!$C$62,"n/m") | D58: =IF(AND(ISNUMBER('Inputs'!$D$33),ISNUMBER('Inputs'!$D$62),'Inputs'!$D$62<>0),'Inputs'!$D$33/'Inputs'!$D$62,"n/m") | E58: =IF(AND(ISNUMBER('Inputs'!$E$33),ISNUMBER('Inputs'!$E$62),'Inputs'!$E$62<>0),'Inputs'!$E$33/'Inputs'!$E$62,"n/m") | F58: =IF(AND(ISNUMBER('Inputs'!$F$33),ISNUMBER('Inputs'!$F$62),'Inputs'!$F$62<>0),'Inputs'!$F$33/'Inputs'!$F$62,"n/m") | G58: =IF(NOT(AND(ISNUMBER($F$58),ISNUMBER(AVERAGE($B$58:$E$58)))),"n/a",IF($F$58>AVERAGE($B$58:$E$58)*(1+0.05),"Improving",IF($F$58<AVERAGE($B$58:$E$58)*(1-0.05),"Deteriorating","Stable")))
A59: Inventory turnover (COGS / inv) | B59: =IF(AND(ISNUMBER('Inputs'!$B$34),ISNUMBER('Inputs'!$B$55),'Inputs'!$B$55<>0),'Inputs'!$B$34/'Inputs'!$B$55,"n/m") | C59: =IF(AND(ISNUMBER('Inputs'!$C$34),ISNUMBER('Inputs'!$C$55),'Inputs'!$C$55<>0),'Inputs'!$C$34/'Inputs'!$C$55,"n/m") | D59: =IF(AND(ISNUMBER('Inputs'!$D$34),ISNUMBER('Inputs'!$D$55),'Inputs'!$D$55<>0),'Inputs'!$D$34/'Inputs'!$D$55,"n/m") | E59: =IF(AND(ISNUMBER('Inputs'!$E$34),ISNUMBER('Inputs'!$E$55),'Inputs'!$E$55<>0),'Inputs'!$E$34/'Inputs'!$E$55,"n/m") | F59: =IF(AND(ISNUMBER('Inputs'!$F$34),ISNUMBER('Inputs'!$F$55),'Inputs'!$F$55<>0),'Inputs'!$F$34/'Inputs'!$F$55,"n/m") | G59: =IF(NOT(AND(ISNUMBER($F$59),ISNUMBER(AVERAGE($B$59:$E$59)))),"n/a",IF($F$59>AVERAGE($B$59:$E$59)*(1+0.05),"Improving",IF($F$59<AVERAGE($B$59:$E$59)*(1-0.05),"Deteriorating","Stable")))
A60: Receivables turnover | B60: =IF(AND(ISNUMBER('Inputs'!$B$33),ISNUMBER('Inputs'!$B$54),'Inputs'!$B$54<>0),'Inputs'!$B$33/'Inputs'!$B$54,"n/m") | C60: =IF(AND(ISNUMBER('Inputs'!$C$33),ISNUMBER('Inputs'!$C$54),'Inputs'!$C$54<>0),'Inputs'!$C$33/'Inputs'!$C$54,"n/m") | D60: =IF(AND(ISNUMBER('Inputs'!$D$33),ISNUMBER('Inputs'!$D$54),'Inputs'!$D$54<>0),'Inputs'!$D$33/'Inputs'!$D$54,"n/m") | E60: =IF(AND(ISNUMBER('Inputs'!$E$33),ISNUMBER('Inputs'!$E$54),'Inputs'!$E$54<>0),'Inputs'!$E$33/'Inputs'!$E$54,"n/m") | F60: =IF(AND(ISNUMBER('Inputs'!$F$33),ISNUMBER('Inputs'!$F$54),'Inputs'!$F$54<>0),'Inputs'!$F$33/'Inputs'!$F$54,"n/m") | G60: =IF(NOT(AND(ISNUMBER($F$60),ISNUMBER(AVERAGE($B$60:$E$60)))),"n/a",IF($F$60>AVERAGE($B$60:$E$60)*(1+0.05),"Improving",IF($F$60<AVERAGE($B$60:$E$60)*(1-0.05),"Deteriorating","Stable")))
A61: Payables turnover | B61: =IF(AND(ISNUMBER('Inputs'!$B$34),ISNUMBER('Inputs'!$B$63),'Inputs'!$B$63<>0),'Inputs'!$B$34/'Inputs'!$B$63,"n/m") | C61: =IF(AND(ISNUMBER('Inputs'!$C$34),ISNUMBER('Inputs'!$C$63),'Inputs'!$C$63<>0),'Inputs'!$C$34/'Inputs'!$C$63,"n/m") | D61: =IF(AND(ISNUMBER('Inputs'!$D$34),ISNUMBER('Inputs'!$D$63),'Inputs'!$D$63<>0),'Inputs'!$D$34/'Inputs'!$D$63,"n/m") | E61: =IF(AND(ISNUMBER('Inputs'!$E$34),ISNUMBER('Inputs'!$E$63),'Inputs'!$E$63<>0),'Inputs'!$E$34/'Inputs'!$E$63,"n/m") | F61: =IF(AND(ISNUMBER('Inputs'!$F$34),ISNUMBER('Inputs'!$F$63),'Inputs'!$F$63<>0),'Inputs'!$F$34/'Inputs'!$F$63,"n/m")
A63: Cash-Flow Quality
B64: FY—4 | C64: FY—3 | D64: FY—2 | E64: FY—1 | F64: FY—0 | G64: Latest read
A65: CFO margin | B65: =IF(AND(ISNUMBER('Inputs'!$B$81),ISNUMBER('Inputs'!$B$33),'Inputs'!$B$33<>0),'Inputs'!$B$81/'Inputs'!$B$33,"n/m") | C65: =IF(AND(ISNUMBER('Inputs'!$C$81),ISNUMBER('Inputs'!$C$33),'Inputs'!$C$33<>0),'Inputs'!$C$81/'Inputs'!$C$33,"n/m") | D65: =IF(AND(ISNUMBER('Inputs'!$D$81),ISNUMBER('Inputs'!$D$33),'Inputs'!$D$33<>0),'Inputs'!$D$81/'Inputs'!$D$33,"n/m") | E65: =IF(AND(ISNUMBER('Inputs'!$E$81),ISNUMBER('Inputs'!$E$33),'Inputs'!$E$33<>0),'Inputs'!$E$81/'Inputs'!$E$33,"n/m") | F65: =IF(AND(ISNUMBER('Inputs'!$F$81),ISNUMBER('Inputs'!$F$33),'Inputs'!$F$33<>0),'Inputs'!$F$81/'Inputs'!$F$33,"n/m") | G65: =IF(NOT(AND(ISNUMBER($F$65),ISNUMBER(AVERAGE($B$65:$E$65)))),"n/a",IF($F$65>AVERAGE($B$65:$E$65)*(1+0.05),"Improving",IF($F$65<AVERAGE($B$65:$E$65)*(1-0.05),"Deteriorating","Stable")))
A66: Free cash flow (CFO − capex) | B66: ='Inputs'!$B$81-'Inputs'!$B$82 | C66: ='Inputs'!$C$81-'Inputs'!$C$82 | D66: ='Inputs'!$D$81-'Inputs'!$D$82 | E66: ='Inputs'!$E$81-'Inputs'!$E$82 | F66: ='Inputs'!$F$81-'Inputs'!$F$82
A67: FCF margin | B67: =IF(AND(ISNUMBER('Historical'!$B$66),ISNUMBER('Inputs'!$B$33),'Inputs'!$B$33<>0),'Historical'!$B$66/'Inputs'!$B$33,"n/m") | C67: =IF(AND(ISNUMBER('Historical'!$C$66),ISNUMBER('Inputs'!$C$33),'Inputs'!$C$33<>0),'Historical'!$C$66/'Inputs'!$C$33,"n/m") | D67: =IF(AND(ISNUMBER('Historical'!$D$66),ISNUMBER('Inputs'!$D$33),'Inputs'!$D$33<>0),'Historical'!$D$66/'Inputs'!$D$33,"n/m") | E67: =IF(AND(ISNUMBER('Historical'!$E$66),ISNUMBER('Inputs'!$E$33),'Inputs'!$E$33<>0),'Historical'!$E$66/'Inputs'!$E$33,"n/m") | F67: =IF(AND(ISNUMBER('Historical'!$F$66),ISNUMBER('Inputs'!$F$33),'Inputs'!$F$33<>0),'Historical'!$F$66/'Inputs'!$F$33,"n/m") | G67: =IF(NOT(ISNUMBER($F$67)),"n/a",IF($F$67<0.03,"Weak",IF($F$67<0.1,"Moderate","Strong")))
A68: Capex intensity (capex / revenue) | B68: =IF(AND(ISNUMBER('Inputs'!$B$82),ISNUMBER('Inputs'!$B$33),'Inputs'!$B$33<>0),'Inputs'!$B$82/'Inputs'!$B$33,"n/m") | C68: =IF(AND(ISNUMBER('Inputs'!$C$82),ISNUMBER('Inputs'!$C$33),'Inputs'!$C$33<>0),'Inputs'!$C$82/'Inputs'!$C$33,"n/m") | D68: =IF(AND(ISNUMBER('Inputs'!$D$82),ISNUMBER('Inputs'!$D$33),'Inputs'!$D$33<>0),'Inputs'!$D$82/'Inputs'!$D$33,"n/m") | E68: =IF(AND(ISNUMBER('Inputs'!$E$82),ISNUMBER('Inputs'!$E$33),'Inputs'!$E$33<>0),'Inputs'!$E$82/'Inputs'!$E$33,"n/m") | F68: =IF(AND(ISNUMBER('Inputs'!$F$82),ISNUMBER('Inputs'!$F$33),'Inputs'!$F$33<>0),'Inputs'!$F$82/'Inputs'!$F$33,"n/m")
A69: FCF conversion (FCF / net income) | B69: =IF(AND(ISNUMBER('Historical'!$B$66),ISNUMBER('Inputs'!$B$48),'Inputs'!$B$48<>0),'Historical'!$B$66/'Inputs'!$B$48,"n/m") | C69: =IF(AND(ISNUMBER('Historical'!$C$66),ISNUMBER('Inputs'!$C$48),'Inputs'!$C$48<>0),'Historical'!$C$66/'Inputs'!$C$48,"n/m") | D69: =IF(AND(ISNUMBER('Historical'!$D$66),ISNUMBER('Inputs'!$D$48),'Inputs'!$D$48<>0),'Historical'!$D$66/'Inputs'!$D$48,"n/m") | E69: =IF(AND(ISNUMBER('Historical'!$E$66),ISNUMBER('Inputs'!$E$48),'Inputs'!$E$48<>0),'Historical'!$E$66/'Inputs'!$E$48,"n/m") | F69: =IF(AND(ISNUMBER('Historical'!$F$66),ISNUMBER('Inputs'!$F$48),'Inputs'!$F$48<>0),'Historical'!$F$66/'Inputs'!$F$48,"n/m") | G69: =IF(NOT(AND(ISNUMBER($F$69),ISNUMBER(AVERAGE($B$69:$E$69)))),"n/a",IF($F$69>AVERAGE($B$69:$E$69)*(1+0.05),"Improving",IF($F$69<AVERAGE($B$69:$E$69)*(1-0.05),"Deteriorating","Stable")))
A70: Cash conversion (CFO / EBITDA) | B70: =IF(AND(ISNUMBER('Inputs'!$B$81),ISNUMBER('Inputs'!$B$41),'Inputs'!$B$41<>0),'Inputs'!$B$81/'Inputs'!$B$41,"n/m") | C70: =IF(AND(ISNUMBER('Inputs'!$C$81),ISNUMBER('Inputs'!$C$41),'Inputs'!$C$41<>0),'Inputs'!$C$81/'Inputs'!$C$41,"n/m") | D70: =IF(AND(ISNUMBER('Inputs'!$D$81),ISNUMBER('Inputs'!$D$41),'Inputs'!$D$41<>0),'Inputs'!$D$81/'Inputs'!$D$41,"n/m") | E70: =IF(AND(ISNUMBER('Inputs'!$E$81),ISNUMBER('Inputs'!$E$41),'Inputs'!$E$41<>0),'Inputs'!$E$81/'Inputs'!$E$41,"n/m") | F70: =IF(AND(ISNUMBER('Inputs'!$F$81),ISNUMBER('Inputs'!$F$41),'Inputs'!$F$41<>0),'Inputs'!$F$81/'Inputs'!$F$41,"n/m") | G70: =IF(NOT(AND(ISNUMBER($F$70),ISNUMBER(AVERAGE($B$70:$E$70)))),"n/a",IF($F$70>AVERAGE($B$70:$E$70)*(1+0.05),"Improving",IF($F$70<AVERAGE($B$70:$E$70)*(1-0.05),"Deteriorating","Stable")))
A72: Shareholder Returns
B73: FY—4 | C73: FY—3 | D73: FY—2 | E73: FY—1 | F73: FY—0 | G73: Latest read
A74: Dividend payout ratio | B74: =IF(AND(ISNUMBER('Inputs'!$B$87),ISNUMBER('Inputs'!$B$48),'Inputs'!$B$48<>0),'Inputs'!$B$87/'Inputs'!$B$48,"n/m") | C74: =IF(AND(ISNUMBER('Inputs'!$C$87),ISNUMBER('Inputs'!$C$48),'Inputs'!$C$48<>0),'Inputs'!$C$87/'Inputs'!$C$48,"n/m") | D74: =IF(AND(ISNUMBER('Inputs'!$D$87),ISNUMBER('Inputs'!$D$48),'Inputs'!$D$48<>0),'Inputs'!$D$87/'Inputs'!$D$48,"n/m") | E74: =IF(AND(ISNUMBER('Inputs'!$E$87),ISNUMBER('Inputs'!$E$48),'Inputs'!$E$48<>0),'Inputs'!$E$87/'Inputs'!$E$48,"n/m") | F74: =IF(AND(ISNUMBER('Inputs'!$F$87),ISNUMBER('Inputs'!$F$48),'Inputs'!$F$48<>0),'Inputs'!$F$87/'Inputs'!$F$48,"n/m")
A75: Buyback intensity (/ net income) | B75: =IF(AND(ISNUMBER('Inputs'!$B$88),ISNUMBER('Inputs'!$B$48),'Inputs'!$B$48<>0),'Inputs'!$B$88/'Inputs'!$B$48,"n/m") | C75: =IF(AND(ISNUMBER('Inputs'!$C$88),ISNUMBER('Inputs'!$C$48),'Inputs'!$C$48<>0),'Inputs'!$C$88/'Inputs'!$C$48,"n/m") | D75: =IF(AND(ISNUMBER('Inputs'!$D$88),ISNUMBER('Inputs'!$D$48),'Inputs'!$D$48<>0),'Inputs'!$D$88/'Inputs'!$D$48,"n/m") | E75: =IF(AND(ISNUMBER('Inputs'!$E$88),ISNUMBER('Inputs'!$E$48),'Inputs'!$E$48<>0),'Inputs'!$E$88/'Inputs'!$E$48,"n/m") | F75: =IF(AND(ISNUMBER('Inputs'!$F$88),ISNUMBER('Inputs'!$F$48),'Inputs'!$F$48<>0),'Inputs'!$F$88/'Inputs'!$F$48,"n/m")
A76: Total payout ratio (div + buyback) | B76: =IF(AND(ISNUMBER(('Inputs'!$B$87+'Inputs'!$B$88)),ISNUMBER('Inputs'!$B$48),'Inputs'!$B$48<>0),('Inputs'!$B$87+'Inputs'!$B$88)/'Inputs'!$B$48,"n/m") | C76: =IF(AND(ISNUMBER(('Inputs'!$C$87+'Inputs'!$C$88)),ISNUMBER('Inputs'!$C$48),'Inputs'!$C$48<>0),('Inputs'!$C$87+'Inputs'!$C$88)/'Inputs'!$C$48,"n/m") | D76: =IF(AND(ISNUMBER(('Inputs'!$D$87+'Inputs'!$D$88)),ISNUMBER('Inputs'!$D$48),'Inputs'!$D$48<>0),('Inputs'!$D$87+'Inputs'!$D$88)/'Inputs'!$D$48,"n/m") | E76: =IF(AND(ISNUMBER(('Inputs'!$E$87+'Inputs'!$E$88)),ISNUMBER('Inputs'!$E$48),'Inputs'!$E$48<>0),('Inputs'!$E$87+'Inputs'!$E$88)/'Inputs'!$E$48,"n/m") | F76: =IF(AND(ISNUMBER(('Inputs'!$F$87+'Inputs'!$F$88)),ISNUMBER('Inputs'!$F$48),'Inputs'!$F$48<>0),('Inputs'!$F$87+'Inputs'!$F$88)/'Inputs'!$F$48,"n/m")

Sheet Assumptions
A1: ASSUMPTIONS
A2: DCF assumption engine — driver-based, scenario-aware, fully sourced
A3: Investment-Grade Company Analysis Engine · v1.0
A5: Scenario Selector
A6: Active scenario (1=Base, 2=Bull, 3=Bear, 4=Downside) | B6: 1 | E6: ← active scenario: | F6: input | G6: =CHOOSE('Assumptions'!$B$6,"Base","Bull","Bear","Downside")
A8: Derived Historical Anchors (read-only)
A9: These are computed from the Historical sheet and feed the base case.
A10: Historical revenue CAGR (full window) | B10: =IF(AND(ISNUMBER('Inputs'!$F$33),ISNUMBER('Inputs'!$B$33),'Inputs'!$B$33>0,'Inputs'!$F$33>0,4>0),('Inputs'!$F$33/'Inputs'!$B$33)^(1/4)-1,"n/m") | F10: model-derived | G10: Compound annual revenue growth across all reported years.
A11: Latest-year revenue growth | B11: ='Historical'!$F$8 | F11: model-derived | G11: Most recent year-on-year growth.
A12: Avg EBIT margin (last 3y) | B12: =IFERROR(AVERAGE('Historical'!$D$19,'Historical'!$E$19,'Historical'!$F$19),"n/a") | F12: model-derived | G12: Anchor for the sustainable operating margin.
A13: Avg D&A % of revenue (last 3y) | B13: =IFERROR(AVERAGE('Historical'!$D$23,'Historical'!$E$23,'Historical'!$F$23),"n/a") | F13: model-derived | G13: Drives forecast depreciation & amortisation.
A14: Avg capex intensity (last 3y) | B14: =IFERROR(AVERAGE('Historical'!$D$68,'Historical'!$E$68,'Historical'!$F$68),"n/a") | F14: model-derived | G14: Drives forecast capital expenditure.
A15: Net working capital % of revenue | B15: =IF(AND(ISNUMBER(('Inputs'!$F$54+'Inputs'!$F$55-'Inputs'!$F$63)),ISNUMBER('Inputs'!$F$33),'Inputs'!$F$33<>0),('Inputs'!$F$54+'Inputs'!$F$55-'Inputs'!$F$63)/'Inputs'!$F$33,"n/m") | F15: model-derived | G15: Working capital scales with sales at this ratio.
A17: Forecast Drivers by Scenario
A18: Driver | B18: Base | C18: Bull | D18: Bear | E18: Downside | F18: Source | G18: Rationale
A19: Blended raw start growth | B19: =IF(AND(ISNUMBER('Assumptions'!$B$10),ISNUMBER('Assumptions'!$B$11)),('Assumptions'!$B$10+'Assumptions'!$B$11)/2,IF(ISNUMBER('Assumptions'!$B$10),'Assumptions'!$B$10,IF(ISNUMBER('Assumptions'!$B$11),'Assumptions'!$B$11,0.03))) | G19: Average of historical CAGR and latest growth (fallback to long-run).
A20: Revenue growth — year 1 (start) | B20: =MAX(-0.05,MIN(0.20,'Assumptions'!$B$19)) | C20: =MAX(-0.3,MIN(0.3,'Assumptions'!$B$20+0.03)) | D20: =MAX(-0.3,MIN(0.3,'Assumptions'!$B$20+-0.03)) | E20: =MAX(-0.3,MIN(0.3,'Assumptions'!$B$20+-0.06)) | F20: model-derived | G20: Start of the revenue path; clamped to a sane band. Bull/Bear/Downside add ±tilts.
A21: Terminal / perpetuity growth (g) | B21: =MIN(0.025,'WACC'!$B$24-0.01) | C21: =MAX(-0.02,MIN('WACC'!$B$24-0.01,'Assumptions'!$B$21+0.005)) | D21: =MAX(-0.02,MIN('WACC'!$B$24-0.01,'Assumptions'!$B$21+-0.005)) | E21: =MAX(-0.02,MIN('WACC'!$B$24-0.01,'Assumptions'!$B$21+-0.01)) | F21: assumption | G21: Long-run growth into perpetuity; capped at WACC−1% so TV stays finite.
A22: Terminal EBIT margin | B22: =IF(ISNUMBER('Assumptions'!$B$12),MAX(0,MIN(0.60,'Assumptions'!$B$12)),0.12) | C22: =MAX(0.0,MIN(0.6,'Assumptions'!$B$22+0.02)) | D22: =MAX(0.0,MIN(0.6,'Assumptions'!$B$22+-0.02)) | E22: =MAX(0.0,MIN(0.6,'Assumptions'!$B$22+-0.05)) | F22: model-derived | G22: Operating margin the business converges to by the terminal year.
A24: Scenario-Invariant Drivers
A25: D&A as % of revenue | B25: =IF(ISNUMBER('Assumptions'!$B$13),'Assumptions'!$B$13,0.05) | F25: derived/fallback | G25: Historical average; conservative fallback if no history.
A26: Capex as % of revenue | B26: =IF(ISNUMBER('Assumptions'!$B$14),'Assumptions'!$B$14,0.05) | F26: derived/fallback | G26: Historical average; in steady state ≈ D&A.
A27: Net working capital % of revenue | B27: =IF(ISNUMBER('Assumptions'!$B$15),'Assumptions'!$B$15,0.1) | F27: derived/fallback | G27: ΔWC each year = this % × the change in revenue.
A28: Tax rate (from WACC sheet) | B28: ='WACC'!$B$13 | F28: linked | G28: Marginal tax rate applied to EBIT to get NOPAT.
A29: Exit EBITDA multiple (TV cross-check) | B29: 8.0 | F29: fallback | G29: Generic multiple for the exit-multiple terminal-value cross-check only.
A30: Forecast horizon (years) | B30: 5 | F30: setting | G30: Number of explicitly forecast years before terminal value.
A32: Active Assumptions (resolved by selector)
A33: These are the values the Forecast & DCF actually use.
A34: Active start revenue growth | B34: =CHOOSE('Assumptions'!$B$6,'Assumptions'!$B$20,'Assumptions'!$C$20,'Assumptions'!$D$20,'Assumptions'!$E$20) | F34: active | G34: Year-1 revenue growth for the selected scenario.
A35: Active terminal growth (g) | B35: =CHOOSE('Assumptions'!$B$6,'Assumptions'!$B$21,'Assumptions'!$C$21,'Assumptions'!$D$21,'Assumptions'!$E$21) | F35: active | G35: Perpetuity growth; also the year-N revenue growth (smooth hand-off to TV).
A36: Active terminal EBIT margin | B36: =CHOOSE('Assumptions'!$B$6,'Assumptions'!$B$22,'Assumptions'!$C$22,'Assumptions'!$D$22,'Assumptions'!$E$22) | F36: active | G36: EBIT margin the forecast converges to.
A38: Methodology Notes
A39: • Revenue is forecast by fading the year-1 growth rate linearly to the terminal growth rate over the horizon — a transparent mean-reversion that avoids an arbitrary flat growth assumption.
A40: • Operating margin fades linearly from the last reported EBIT margin to the terminal target margin, reflecting gradual normalisation rather than a step change.
A41: • Capex, D&A and working capital are tied to revenue via historical intensity ratios, so they scale with the business instead of being guessed.
A42: • Scenarios change only a few economically meaningful levers (growth and margin); this keeps the bull/bear/downside cases comparable and interpretable.
A43: • Where a needed figure is missing, the model falls back to a clearly-labelled conservative default rather than inventing a number.

Sheet WACC
A1: WACC
A2: Weighted average cost of capital — built up step by step
A3: Investment-Grade Company Analysis Engine · v1.0
A5: 1 · Cost of Equity — CAPM
A6: Risk-free rate (Rf) | B6: =IF(ISNUMBER('Inputs'!$B$115),'Inputs'!$B$115,0.04) | C6: =IF(ISNUMBER('Inputs'!$B$115),"input","fallback") | D6: Long-dated government bond yield in the reporting currency.
A7: Equity risk premium (ERP) | B7: =IF(ISNUMBER('Inputs'!$B$116),'Inputs'!$B$116,0.05) | C7: =IF(ISNUMBER('Inputs'!$B$116),"input","fallback") | D7: Expected return of equities over the risk-free rate.
A8: Beta (β) | B8: =IF(ISNUMBER('Inputs'!$B$114),'Inputs'!$B$114,1.0) | C8: =IF(ISNUMBER('Inputs'!$B$114),"input","fallback") | D8: Levered equity beta vs the market; fallback 1.00 (market risk).
A9: Cost of equity Ke = Rf + β × ERP | B9: ='WACC'!$B$6+'WACC'!$B$8*'WACC'!$B$7 | C9: computed | D9: CAPM. Ke is the return equity holders require.
A11: 2 · Cost of Debt
A12: Pre-tax cost of debt (Kd) | B12: =IF(ISNUMBER('Inputs'!$B$117),'Inputs'!$B$117,0.06) | C12: =IF(ISNUMBER('Inputs'!$B$117),"input","fallback") | D12: Marginal borrowing rate. Cross-check vs implied rate below.
A13: Marginal tax rate (t) | B13: =IF(ISNUMBER('Inputs'!$B$118),'Inputs'!$B$118,0.25) | C13: =IF(ISNUMBER('Inputs'!$B$118),"input","fallback") | D13: Used to tax-shield debt and for NOPAT in the DCF.
A14: After-tax cost of debt Kd × (1 − t) | B14: ='WACC'!$B$12*(1-'WACC'!$B$13) | C14: computed | D14: Interest is tax-deductible, lowering its effective cost.
A15: Implied rate cross-check (int. exp / debt) | B15: =IFERROR('Inputs'!$F$42/'Historical'!$F$45,"n/a") | C15: computed | D15: Sanity check on the assumed pre-tax cost of debt.
A17: 3 · Capital Structure (market weights)
A18: Equity value (E) | B18: =IF(ISNUMBER('Inputs'!$B$119),'Inputs'!$B$119,'Inputs'!$F$71) | C18: =IF(ISNUMBER('Inputs'!$B$119),"market","book (fallback)") | D18: Market capitalisation; falls back to book equity if price/shares missing.
A19: Debt value (D) | B19: ='Historical'!$F$45 | C19: book | D19: Total interest-bearing debt (book value as a proxy for market value).
A20: Equity weight We = E / (E + D) | B20: =IFERROR('WACC'!$B$18/('WACC'!$B$18+'WACC'!$B$19),1) | C20: computed | D20: Share of capital funded by equity.
A21: Debt weight Wd = D / (E + D) | B21: =IFERROR('WACC'!$B$19/('WACC'!$B$18+'WACC'!$B$19),0) | C21: computed | D21: Share of capital funded by debt.
A23: 4 · Weighted Average Cost of Capital
A24: WACC = We × Ke + Wd × Kd(1−t) | B24: ='WACC'!$B$20*'WACC'!$B$9+'WACC'!$B$21*'WACC'!$B$14 | D24: The blended required return used to discount the forecast cash flows.
A25: Plausibility | D25: =IF(AND('WACC'!$B$24>=0.035,'WACC'!$B$24>=0.04,'WACC'!$B$24<=0.18),"Within a reasonable range","Outside typical 4–18% range — review inputs")
A27: How to read this
A28: • WACC rises with beta, the equity risk premium and leverage cost, and falls with the tax shield on debt. It is the single most important valuation input.
A29: • If you have no market data, the fallback defaults give a defensible starting point; replace them with company-specific figures for a real valuation.
A30: • Equity value uses market cap where available — the market's own view of equity — rather than book value, which can be stale.

Sheet Forecast
A1: FORECAST
A2: Driver-based operating forecast & unlevered free cash flow
A3: Investment-Grade Company Analysis Engine · v1.0
A4: Active scenario: | B4: ='Assumptions'!$G$6 | H4: All figures in USD millions unless stated.
A6: Forecast line item | B6: ="FY—0 (base)" | C6: Year +1 | D6: Year +2 | E6: Year +3 | F6: Year +4 | G6: Year +5 | H6: Driver / logic
A7: Revenue growth | B7: ='Historical'!$F$8 | C7: ='Assumptions'!$B$34+('Assumptions'!$B$35-'Assumptions'!$B$34)*0.000000 | D7: ='Assumptions'!$B$34+('Assumptions'!$B$35-'Assumptions'!$B$34)*0.250000 | E7: ='Assumptions'!$B$34+('Assumptions'!$B$35-'Assumptions'!$B$34)*0.500000 | F7: ='Assumptions'!$B$34+('Assumptions'!$B$35-'Assumptions'!$B$34)*0.750000 | G7: ='Assumptions'!$B$34+('Assumptions'!$B$35-'Assumptions'!$B$34)*1.000000 | H7: Linear fade from start growth to terminal growth.
A8: Revenue | B8: ='Inputs'!$F$33 | C8: ='Forecast'!$B$8*(1+'Forecast'!$C$7) | D8: ='Forecast'!$C$8*(1+'Forecast'!$D$7) | E8: ='Forecast'!$D$8*(1+'Forecast'!$E$7) | F8: ='Forecast'!$E$8*(1+'Forecast'!$F$7) | G8: ='Forecast'!$F$8*(1+'Forecast'!$G$7) | H8: Compounds off the last actual by the growth path.
A9: EBIT margin | B9: =IF(ISNUMBER('Historical'!$F$19),'Historical'!$F$19,'Assumptions'!$B$36) | C9: ='Forecast'!$B$9+('Assumptions'!$B$36-'Forecast'!$B$9)*0.200000 | D9: ='Forecast'!$B$9+('Assumptions'!$B$36-'Forecast'!$B$9)*0.400000 | E9: ='Forecast'!$B$9+('Assumptions'!$B$36-'Forecast'!$B$9)*0.600000 | F9: ='Forecast'!$B$9+('Assumptions'!$B$36-'Forecast'!$B$9)*0.800000 | G9: ='Forecast'!$B$9+('Assumptions'!$B$36-'Forecast'!$B$9)*1.000000 | H9: Linear fade from last-actual margin to terminal target.
A10: EBIT (operating profit) | B10: ='Inputs'!$F$39 | C10: ='Forecast'!$C$8*'Forecast'!$C$9 | D10: ='Forecast'!$D$8*'Forecast'!$D$9 | E10: ='Forecast'!$E$8*'Forecast'!$E$9 | F10: ='Forecast'!$F$8*'Forecast'!$F$9 | G10: ='Forecast'!$G$8*'Forecast'!$G$9 | H10: Revenue × EBIT margin.
A11: (+) Depreciation & amortisation | B11: ='Inputs'!$F$40 | C11: ='Forecast'!$C$8*'Assumptions'!$B$25 | D11: ='Forecast'!$D$8*'Assumptions'!$B$25 | E11: ='Forecast'!$E$8*'Assumptions'!$B$25 | F11: ='Forecast'!$F$8*'Assumptions'!$B$25 | G11: ='Forecast'!$G$8*'Assumptions'!$B$25 | H11: Revenue × D&A intensity (historical average).
A12: EBITDA | B12: ='Inputs'!$F$41 | C12: ='Forecast'!$C$10+'Forecast'!$C$11 | D12: ='Forecast'!$D$10+'Forecast'!$D$11 | E12: ='Forecast'!$E$10+'Forecast'!$E$11 | F12: ='Forecast'!$F$10+'Forecast'!$F$11 | G12: ='Forecast'!$G$10+'Forecast'!$G$11 | H12: EBIT + D&A.
A14: Unlevered Free Cash Flow
A15: EBIT (operating profit) | C15: ='Forecast'!$C$10 | D15: ='Forecast'!$D$10 | E15: ='Forecast'!$E$10 | F15: ='Forecast'!$F$10 | G15: ='Forecast'!$G$10
A16: (−) Cash tax on EBIT | C16: =-'Forecast'!$C$10*'Assumptions'!$B$28 | D16: =-'Forecast'!$D$10*'Assumptions'!$B$28 | E16: =-'Forecast'!$E$10*'Assumptions'!$B$28 | F16: =-'Forecast'!$F$10*'Assumptions'!$B$28 | G16: =-'Forecast'!$G$10*'Assumptions'!$B$28 | H16: EBIT × marginal tax rate (unlevered, so no interest tax shield here).
A17: NOPAT | C17: ='Forecast'!$C$10*(1-'Assumptions'!$B$28) | D17: ='Forecast'!$D$10*(1-'Assumptions'!$B$28) | E17: ='Forecast'!$E$10*(1-'Assumptions'!$B$28) | F17: ='Forecast'!$F$10*(1-'Assumptions'!$B$28) | G17: ='Forecast'!$G$10*(1-'Assumptions'!$B$28) | H17: Net operating profit after tax = EBIT × (1 − tax).
A18: (+) Depreciation & amortisation | C18: ='Forecast'!$C$11 | D18: ='Forecast'!$D$11 | E18: ='Forecast'!$E$11 | F18: ='Forecast'!$F$11 | G18: ='Forecast'!$G$11 | H18: Non-cash; added back.
A19: (−) Capital expenditure | C19: =-'Forecast'!$C$8*'Assumptions'!$B$26 | D19: =-'Forecast'!$D$8*'Assumptions'!$B$26 | E19: =-'Forecast'!$E$8*'Assumptions'!$B$26 | F19: =-'Forecast'!$F$8*'Assumptions'!$B$26 | G19: =-'Forecast'!$G$8*'Assumptions'!$B$26 | H19: Revenue × capex intensity (historical average).
A20: (−) Increase in net working capital | C20: =-'Assumptions'!$B$27*('Forecast'!$C$8-'Forecast'!$B$8) | D20: =-'Assumptions'!$B$27*('Forecast'!$D$8-'Forecast'!$C$8) | E20: =-'Assumptions'!$B$27*('Forecast'!$E$8-'Forecast'!$D$8) | F20: =-'Assumptions'!$B$27*('Forecast'!$F$8-'Forecast'!$E$8) | G20: =-'Assumptions'!$B$27*('Forecast'!$G$8-'Forecast'!$F$8) | H20: WC % × change in revenue; cash use when revenue grows.
A21: Unlevered free cash flow (FCFF) | C21: ='Forecast'!$C$17+'Forecast'!$C$18+'Forecast'!$C$19+'Forecast'!$C$20 | D21: ='Forecast'!$D$17+'Forecast'!$D$18+'Forecast'!$D$19+'Forecast'!$D$20 | E21: ='Forecast'!$E$17+'Forecast'!$E$18+'Forecast'!$E$19+'Forecast'!$E$20 | F21: ='Forecast'!$F$17+'Forecast'!$F$18+'Forecast'!$F$19+'Forecast'!$F$20 | G21: ='Forecast'!$G$17+'Forecast'!$G$18+'Forecast'!$G$19+'Forecast'!$G$20 | H21: NOPAT + D&A − Capex − ΔWC. Discounted on the DCF sheet.
A23: Forecast Method
A24: Revenue method: trend + mean-reversion (growth fades from FY—0 drivers to the long-run rate). If unit volume and price are entered on Inputs, a bottom-up volume × price override can be used instead. Operating costs, capex, D&A and working capital are tied to revenue, so the forecast is driver-based rather than a flat assumption.

Sheet DCF
A1: DCF VALUATION
A2: Discounted unlevered free cash flow — every step shown
A3: Investment-Grade Company Analysis Engine · v1.0
A4: Active scenario: | B4: ='Assumptions'!$G$6 | H4: All figures in USD millions unless stated.
A6: 1 · Present Value of Explicit Free Cash Flows
A7: Forecast year | B7: Year +1 | C7: Year +2 | D7: Year +3 | E7: Year +4 | F7: Year +5 | G7: Total
A8: Unlevered FCF (FCFF) | B8: ='Forecast'!$C$21 | C8: ='Forecast'!$D$21 | D8: ='Forecast'!$E$21 | E8: ='Forecast'!$F$21 | F8: ='Forecast'!$G$21
A9: Discount period (years) | B9: 1 | C9: 2 | D9: 3 | E9: 4 | F9: 5 | H9: End-of-year discounting convention.
A10: Discount factor = 1/(1+WACC)^t | B10: =1/(1+'WACC'!$B$24)^'DCF'!$B$9 | C10: =1/(1+'WACC'!$B$24)^'DCF'!$C$9 | D10: =1/(1+'WACC'!$B$24)^'DCF'!$D$9 | E10: =1/(1+'WACC'!$B$24)^'DCF'!$E$9 | F10: =1/(1+'WACC'!$B$24)^'DCF'!$F$9
A11: PV of FCFF | B11: ='Forecast'!$C$21*'DCF'!$B$10 | C11: ='Forecast'!$D$21*'DCF'!$C$10 | D11: ='Forecast'!$E$21*'DCF'!$D$10 | E11: ='Forecast'!$F$21*'DCF'!$E$10 | F11: ='Forecast'!$G$21*'DCF'!$F$10 | G11: =SUM($B$11:$F$11) | H11: Sum of discounted explicit-period cash flows.
A13: 2 · Terminal Value
A14: — Method A: Perpetuity growth (Gordon) —
A15: Terminal-year FCFF (year N) | B15: ='Forecast'!$G$21 | H15: Last explicit-year unlevered cash flow.
A16: Terminal growth (g) | B16: ='Assumptions'!$B$35 | H16: Perpetuity growth, from active assumptions.
A17: WACC | B17: ='WACC'!$B$24 | H17: From the WACC sheet.
A18: Terminal value at year N = FCFF×(1+g)/(WACC−g) | B18: =IFERROR('DCF'!$B$15*(1+'DCF'!$B$16)/('DCF'!$B$17-'DCF'!$B$16),"n/m") | H18: Gordon growth perpetuity, valued as of year N.
A19: PV of terminal value | B19: ='DCF'!$B$18*'DCF'!$F$10 | H19: Terminal value discounted to today.
A21: — Method B: Exit multiple (cross-check only) —
A22: Terminal-year EBITDA | B22: ='Forecast'!$G$12 | H22: Year-N EBITDA from the forecast.
A23: Exit EBITDA multiple | B23: ='Assumptions'!$B$29 | H23: Generic assumption; not used in the headline value.
A24: TV (exit multiple) at year N | B24: ='DCF'!$B$22*'DCF'!$B$23 | H24: Sanity check against the perpetuity TV.
A25: PV of TV (exit multiple) | B25: ='DCF'!$B$24*'DCF'!$F$10 | H25: For comparison with the perpetuity PV of TV.
A28: 3 · Enterprise Value → Equity Value → Per Share
A29: Σ PV of explicit FCFF | B29: ='DCF'!$G$11 | H29: From section 1.
A30: (+) PV of terminal value | B30: ='DCF'!$B$19 | H30: Perpetuity method (section 2A).
A31: Enterprise value (EV) | B31: ='DCF'!$B$29+'DCF'!$B$30 | H31: Value of the operating business to all capital providers.
A32: (−) Net debt | B32: =-'Historical'!$F$46 | H32: Total debt less cash & investments (latest balance sheet).
A33: (−) Minority interest | B33: =-'Inputs'!$F$72 | H33: Equity not attributable to shareholders.
A34: Equity value | B34: ='DCF'!$B$31+'DCF'!$B$32+'DCF'!$B$33 | H34: Intrinsic value attributable to shareholders.
A35: Shares outstanding | B35: =IF(ISNUMBER('Inputs'!$B$113),'Inputs'!$B$113,'Inputs'!$F$96) | H35: Current shares; falls back to diluted weighted-average.
A36: Implied value per share | B36: =IF(AND(ISNUMBER('DCF'!$B$34),ISNUMBER('DCF'!$B$35),'DCF'!$B$35<>0),'DCF'!$B$34/'DCF'!$B$35,"n/m") | H36: Headline DCF output.
A38: 4 · Cross-Checks & Valuation Read
A39: Current share price | B39: ='Inputs'!$B$112 | H39: Market reference input (blank if unknown).
A40: Upside / (downside) to DCF value | B40: =IFERROR('DCF'!$B$36/'DCF'!$B$39-1,"n/a") | H40: How far the price sits from intrinsic value.
A41: Valuation read | B41: =IF(NOT(AND(ISNUMBER('DCF'!$B$36),ISNUMBER('DCF'!$B$39),'DCF'!$B$39>0)),"n/a",IF('DCF'!$B$36>'DCF'!$B$39*(1+0.15),"Undervalued",IF('DCF'!$B$36<'DCF'!$B$39*(1-0.15),"Overvalued","Fairly valued"))) | H41: ±15% band around the price defines 'fairly valued'.
A43: Terminal value as % of EV | B43: =IF(AND(ISNUMBER('DCF'!$B$30),ISNUMBER('DCF'!$B$31),'DCF'!$B$31<>0),'DCF'!$B$30/'DCF'!$B$31,"n/m") | H43: =IF('DCF'!$B$43>0.8,"TV-heavy — scrutinise terminal assumptions","Reasonable split between explicit and terminal value")
A44: Implied exit multiple (from perpetuity TV) | B44: =IF(AND(ISNUMBER('DCF'!$B$18),ISNUMBER('DCF'!$B$22),'DCF'!$B$22<>0),'DCF'!$B$18/'DCF'!$B$22,"n/m") | H44: Cross-check: compare with the assumed exit multiple above.
A45: EV / next-year EBITDA | B45: =IF(AND(ISNUMBER('DCF'!$B$31),ISNUMBER('Forecast'!$C$12),'Forecast'!$C$12<>0),'DCF'!$B$31/'Forecast'!$C$12,"n/m") | H45: Forward valuation multiple implied by the DCF.

Sheet Sensitivity
A1: SENSITIVITY ANALYSIS
A2: Implied value per share across key assumptions
A3: Investment-Grade Company Analysis Engine · v1.0
A4: Each cell recomputes the full valuation for its row/column pair. Centre cell (boxed) = active base case.
A6: Table 1 · WACC (down) × Terminal growth g (across)
A7: Value / share | C7: ='Assumptions'!$B$35-0.01 | D7: ='Assumptions'!$B$35-0.005 | E7: ='Assumptions'!$B$35+0 | F7: ='Assumptions'!$B$35+0.005 | G7: ='Assumptions'!$B$35+0.01
B8: ='WACC'!$B$24-0.015 | C8: =IF($B$8-$C$7<=0.005,"n/m",IFERROR(((('Forecast'!$C$21/(1+$B$8)^1+'Forecast'!$D$21/(1+$B$8)^2+'Forecast'!$E$21/(1+$B$8)^3+'Forecast'!$F$21/(1+$B$8)^4+'Forecast'!$G$21/(1+$B$8)^5)+('Forecast'!$G$21*(1+$C$7)/($B$8-$C$7))/(1+$B$8)^5)-'Historical'!$F$46-'Inputs'!$F$72)/'DCF'!$B$35,"n/m")) | D8: =IF($B$8-$D$7<=0.005,"n/m",IFERROR(((('Forecast'!$C$21/(1+$B$8)^1+'Forecast'!$D$21/(1+$B$8)^2+'Forecast'!$E$21/(1+$B$8)^3+'Forecast'!$F$21/(1+$B$8)^4+'Forecast'!$G$21/(1+$B$8)^5)+('Forecast'!$G$21*(1+$D$7)/($B$8-$D$7))/(1+$B$8)^5)-'Historical'!$F$46-'Inputs'!$F$72)/'DCF'!$B$35,"n/m")) | E8: =IF($B$8-$E$7<=0.005,"n/m",IFERROR(((('Forecast'!$C$21/(1+$B$8)^1+'Forecast'!$D$21/(1+$B$8)^2+'Forecast'!$E$21/(1+$B$8)^3+'Forecast'!$F$21/(1+$B$8)^4+'Forecast'!$G$21/(1+$B$8)^5)+('Forecast'!$G$21*(1+$E$7)/($B$8-$E$7))/(1+$B$8)^5)-'Historical'!$F$46-'Inputs'!$F$72)/'DCF'!$B$35,"n/m")) | F8: =IF($B$8-$F$7<=0.005,"n/m",IFERROR(((('Forecast'!$C$21/(1+$B$8)^1+'Forecast'!$D$21/(1+$B$8)^2+'Forecast'!$E$21/(1+$B$8)^3+'Forecast'!$F$21/(1+$B$8)^4+'Forecast'!$G$21/(1+$B$8)^5)+('Forecast'!$G$21*(1+$F$7)/($B$8-$F$7))/(1+$B$8)^5)-'Historical'!$F$46-'Inputs'!$F$72)/'DCF'!$B$35,"n/m")) | G8: =IF($B$8-$G$7<=0.005,"n/m",IFERROR(((('Forecast'!$C$21/(1+$B$8)^1+'Forecast'!$D$21/(1+$B$8)^2+'Forecast'!$E$21/(1+$B$8)^3+'Forecast'!$F$21/(1+$B$8)^4+'Forecast'!$G$21/(1+$B$8)^5)+('Forecast'!$G$21*(1+$G$7)/($B$8-$G$7))/(1+$B$8)^5)-'Historical'!$F$46-'Inputs'!$F$72)/'DCF'!$B$35,"n/m"))
B9: ='WACC'!$B$24-0.0075 | C9: =IF($B$9-$C$7<=0.005,"n/m",IFERROR(((('Forecast'!$C$21/(1+$B$9)^1+'Forecast'!$D$21/(1+$B$9)^2+'Forecast'!$E$21/(1+$B$9)^3+'Forecast'!$F$21/(1+$B$9)^4+'Forecast'!$G$21/(1+$B$9)^5)+('Forecast'!$G$21*(1+$C$7)/($B$9-$C$7))/(1+$B$9)^5)-'Historical'!$F$46-'Inputs'!$F$72)/'DCF'!$B$35,"n/m")) | D9: =IF($B$9-$D$7<=0.005,"n/m",IFERROR(((('Forecast'!$C$21/(1+$B$9)^1+'Forecast'!$D$21/(1+$B$9)^2+'Forecast'!$E$21/(1+$B$9)^3+'Forecast'!$F$21/(1+$B$9)^4+'Forecast'!$G$21/(1+$B$9)^5)+('Forecast'!$G$21*(1+$D$7)/($B$9-$D$7))/(1+$B$9)^5)-'Historical'!$F$46-'Inputs'!$F$72)/'DCF'!$B$35,"n/m")) | E9: =IF($B$9-$E$7<=0.005,"n/m",IFERROR(((('Forecast'!$C$21/(1+$B$9)^1+'Forecast'!$D$21/(1+$B$9)^2+'Forecast'!$E$21/(1+$B$9)^3+'Forecast'!$F$21/(1+$B$9)^4+'Forecast'!$G$21/(1+$B$9)^5)+('Forecast'!$G$21*(1+$E$7)/($B$9-$E$7))/(1+$B$9)^5)-'Historical'!$F$46-'Inputs'!$F$72)/'DCF'!$B$35,"n/m")) | F9: =IF($B$9-$F$7<=0.005,"n/m",IFERROR(((('Forecast'!$C$21/(1+$B$9)^1+'Forecast'!$D$21/(1+$B$9)^2+'Forecast'!$E$21/(1+$B$9)^3+'Forecast'!$F$21/(1+$B$9)^4+'Forecast'!$G$21/(1+$B$9)^5)+('Forecast'!$G$21*(1+$F$7)/($B$9-$F$7))/(1+$B$9)^5)-'Historical'!$F$46-'Inputs'!$F$72)/'DCF'!$B$35,"n/m")) | G9: =IF($B$9-$G$7<=0.005,"n/m",IFERROR(((('Forecast'!$C$21/(1+$B$9)^1+'Forecast'!$D$21/(1+$B$9)^2+'Forecast'!$E$21/(1+$B$9)^3+'Forecast'!$F$21/(1+$B$9)^4+'Forecast'!$G$21/(1+$B$9)^5)+('Forecast'!$G$21*(1+$G$7)/($B$9-$G$7))/(1+$B$9)^5)-'Historical'!$F$46-'Inputs'!$F$72)/'DCF'!$B$35,"n/m"))
B10: ='WACC'!$B$24+0 | C10: =IF($B$10-$C$7<=0.005,"n/m",IFERROR(((('Forecast'!$C$21/(1+$B$10)^1+'Forecast'!$D$21/(1+$B$10)^2+'Forecast'!$E$21/(1+$B$10)^3+'Forecast'!$F$21/(1+$B$10)^4+'Forecast'!$G$21/(1+$B$10)^5)+('Forecast'!$G$21*(1+$C$7)/($B$10-$C$7))/(1+$B$10)^5)-'Historical'!$F$46-'Inputs'!$F$72)/'DCF'!$B$35,"n/m")) | D10: =IF($B$10-$D$7<=0.005,"n/m",IFERROR(((('Forecast'!$C$21/(1+$B$10)^1+'Forecast'!$D$21/(1+$B$10)^2+'Forecast'!$E$21/(1+$B$10)^3+'Forecast'!$F$21/(1+$B$10)^4+'Forecast'!$G$21/(1+$B$10)^5)+('Forecast'!$G$21*(1+$D$7)/($B$10-$D$7))/(1+$B$10)^5)-'Historical'!$F$46-'Inputs'!$F$72)/'DCF'!$B$35,"n/m")) | E10: =IF($B$10-$E$7<=0.005,"n/m",IFERROR(((('Forecast'!$C$21/(1+$B$10)^1+'Forecast'!$D$21/(1+$B$10)^2+'Forecast'!$E$21/(1+$B$10)^3+'Forecast'!$F$21/(1+$B$10)^4+'Forecast'!$G$21/(1+$B$10)^5)+('Forecast'!$G$21*(1+$E$7)/($B$10-$E$7))/(1+$B$10)^5)-'Historical'!$F$46-'Inputs'!$F$72)/'DCF'!$B$35,"n/m")) | F10: =IF($B$10-$F$7<=0.005,"n/m",IFERROR(((('Forecast'!$C$21/(1+$B$10)^1+'Forecast'!$D$21/(1+$B$10)^2+'Forecast'!$E$21/(1+$B$10)^3+'Forecast'!$F$21/(1+$B$10)^4+'Forecast'!$G$21/(1+$B$10)^5)+('Forecast'!$G$21*(1+$F$7)/($B$10-$F$7))/(1+$B$10)^5)-'Historical'!$F$46-'Inputs'!$F$72)/'DCF'!$B$35,"n/m")) | G10: =IF($B$10-$G$7<=0.005,"n/m",IFERROR(((('Forecast'!$C$21/(1+$B$10)^1+'Forecast'!$D$21/(1+$B$10)^2+'Forecast'!$E$21/(1+$B$10)^3+'Forecast'!$F$21/(1+$B$10)^4+'Forecast'!$G$21/(1+$B$10)^5)+('Forecast'!$G$21*(1+$G$7)/($B$10-$G$7))/(1+$B$10)^5)-'Historical'!$F$46-'Inputs'!$F$72)/'DCF'!$B$35,"n/m"))
B11: ='WACC'!$B$24+0.0075 | C11: =IF($B$11-$C$7<=0.005,"n/m",IFERROR(((('Forecast'!$C$21/(1+$B$11)^1+'Forecast'!$D$21/(1+$B$11)^2+'Forecast'!$E$21/(1+$B$11)^3+'Forecast'!$F$21/(1+$B$11)^4+'Forecast'!$G$21/(1+$B$11)^5)+('Forecast'!$G$21*(1+$C$7)/($B$11-$C$7))/(1+$B$11)^5)-'Historical'!$F$46-'Inputs'!$F$72)/'DCF'!$B$35,"n/m")) | D11: =IF($B$11-$D$7<=0.005,"n/m",IFERROR(((('Forecast'!$C$21/(1+$B$11)^1+'Forecast'!$D$21/(1+$B$11)^2+'Forecast'!$E$21/(1+$B$11)^3+'Forecast'!$F$21/(1+$B$11)^4+'Forecast'!$G$21/(1+$B$11)^5)+('Forecast'!$G$21*(1+$D$7)/($B$11-$D$7))/(1+$B$11)^5)-'Historical'!$F$46-'Inputs'!$F$72)/'DCF'!$B$35,"n/m")) | E11: =IF($B$11-$E$7<=0.005,"n/m",IFERROR(((('Forecast'!$C$21/(1+$B$11)^1+'Forecast'!$D$21/(1+$B$11)^2+'Forecast'!$E$21/(1+$B$11)^3+'Forecast'!$F$21/(1+$B$11)^4+'Forecast'!$G$21/(1+$B$11)^5)+('Forecast'!$G$21*(1+$E$7)/($B$11-$E$7))/(1+$B$11)^5)-'Historical'!$F$46-'Inputs'!$F$72)/'DCF'!$B$35,"n/m")) | F11: =IF($B$11-$F$7<=0.005,"n/m",IFERROR(((('Forecast'!$C$21/(1+$B$11)^1+'Forecast'!$D$21/(1+$B$11)^2+'Forecast'!$E$21/(1+$B$11)^3+'Forecast'!$F$21/(1+$B$11)^4+'Forecast'!$G$21/(1+$B$11)^5)+('Forecast'!$G$21*(1+$F$7)/($B$11-$F$7))/(1+$B$11)^5)-'Historical'!$F$46-'Inputs'!$F$72)/'DCF'!$B$35,"n/m")) | G11: =IF($B$11-$G$7<=0.005,"n/m",IFERROR(((('Forecast'!$C$21/(1+$B$11)^1+'Forecast'!$D$21/(1+$B$11)^2+'Forecast'!$E$21/(1+$B$11)^3+'Forecast'!$F$21/(1+$B$11)^4+'Forecast'!$G$21/(1+$B$11)^5)+('Forecast'!$G$21*(1+$G$7)/($B$11-$G$7))/(1+$B$11)^5)-'Historical'!$F$46-'Inputs'!$F$72)/'DCF'!$B$35,"n/m"))
B12: ='WACC'!$B$24+0.015 | C12: =IF($B$12-$C$7<=0.005,"n/m",IFERROR(((('Forecast'!$C$21/(1+$B$12)^1+'Forecast'!$D$21/(1+$B$12)^2+'Forecast'!$E$21/(1+$B$12)^3+'Forecast'!$F$21/(1+$B$12)^4+'Forecast'!$G$21/(1+$B$12)^5)+('Forecast'!$G$21*(1+$C$7)/($B$12-$C$7))/(1+$B$12)^5)-'Historical'!$F$46-'Inputs'!$F$72)/'DCF'!$B$35,"n/m")) | D12: =IF($B$12-$D$7<=0.005,"n/m",IFERROR(((('Forecast'!$C$21/(1+$B$12)^1+'Forecast'!$D$21/(1+$B$12)^2+'Forecast'!$E$21/(1+$B$12)^3+'Forecast'!$F$21/(1+$B$12)^4+'Forecast'!$G$21/(1+$B$12)^5)+('Forecast'!$G$21*(1+$D$7)/($B$12-$D$7))/(1+$B$12)^5)-'Historical'!$F$46-'Inputs'!$F$72)/'DCF'!$B$35,"n/m")) | E12: =IF($B$12-$E$7<=0.005,"n/m",IFERROR(((('Forecast'!$C$21/(1+$B$12)^1+'Forecast'!$D$21/(1+$B$12)^2+'Forecast'!$E$21/(1+$B$12)^3+'Forecast'!$F$21/(1+$B$12)^4+'Forecast'!$G$21/(1+$B$12)^5)+('Forecast'!$G$21*(1+$E$7)/($B$12-$E$7))/(1+$B$12)^5)-'Historical'!$F$46-'Inputs'!$F$72)/'DCF'!$B$35,"n/m")) | F12: =IF($B$12-$F$7<=0.005,"n/m",IFERROR(((('Forecast'!$C$21/(1+$B$12)^1+'Forecast'!$D$21/(1+$B$12)^2+'Forecast'!$E$21/(1+$B$12)^3+'Forecast'!$F$21/(1+$B$12)^4+'Forecast'!$G$21/(1+$B$12)^5)+('Forecast'!$G$21*(1+$F$7)/($B$12-$F$7))/(1+$B$12)^5)-'Historical'!$F$46-'Inputs'!$F$72)/'DCF'!$B$35,"n/m")) | G12: =IF($B$12-$G$7<=0.005,"n/m",IFERROR(((('Forecast'!$C$21/(1+$B$12)^1+'Forecast'!$D$21/(1+$B$12)^2+'Forecast'!$E$21/(1+$B$12)^3+'Forecast'!$F$21/(1+$B$12)^4+'Forecast'!$G$21/(1+$B$12)^5)+('Forecast'!$G$21*(1+$G$7)/($B$12-$G$7))/(1+$B$12)^5)-'Historical'!$F$46-'Inputs'!$F$72)/'DCF'!$B$35,"n/m"))
A15: Table 2 · WACC (down) × Exit EBITDA multiple (across)
A16: Value / share | C16: ='Assumptions'!$B$29-2 | D16: ='Assumptions'!$B$29-1 | E16: ='Assumptions'!$B$29+0 | F16: ='Assumptions'!$B$29+1 | G16: ='Assumptions'!$B$29+2
B17: ='WACC'!$B$24-0.015 | C17: =IFERROR(((('Forecast'!$C$21/(1+$B$17)^1+'Forecast'!$D$21/(1+$B$17)^2+'Forecast'!$E$21/(1+$B$17)^3+'Forecast'!$F$21/(1+$B$17)^4+'Forecast'!$G$21/(1+$B$17)^5)+('Forecast'!$G$12*$C$16)/(1+$B$17)^5)-'Historical'!$F$46-'Inputs'!$F$72)/'DCF'!$B$35,"n/m") | D17: =IFERROR(((('Forecast'!$C$21/(1+$B$17)^1+'Forecast'!$D$21/(1+$B$17)^2+'Forecast'!$E$21/(1+$B$17)^3+'Forecast'!$F$21/(1+$B$17)^4+'Forecast'!$G$21/(1+$B$17)^5)+('Forecast'!$G$12*$D$16)/(1+$B$17)^5)-'Historical'!$F$46-'Inputs'!$F$72)/'DCF'!$B$35,"n/m") | E17: =IFERROR(((('Forecast'!$C$21/(1+$B$17)^1+'Forecast'!$D$21/(1+$B$17)^2+'Forecast'!$E$21/(1+$B$17)^3+'Forecast'!$F$21/(1+$B$17)^4+'Forecast'!$G$21/(1+$B$17)^5)+('Forecast'!$G$12*$E$16)/(1+$B$17)^5)-'Historical'!$F$46-'Inputs'!$F$72)/'DCF'!$B$35,"n/m") | F17: =IFERROR(((('Forecast'!$C$21/(1+$B$17)^1+'Forecast'!$D$21/(1+$B$17)^2+'Forecast'!$E$21/(1+$B$17)^3+'Forecast'!$F$21/(1+$B$17)^4+'Forecast'!$G$21/(1+$B$17)^5)+('Forecast'!$G$12*$F$16)/(1+$B$17)^5)-'Historical'!$F$46-'Inputs'!$F$72)/'DCF'!$B$35,"n/m") | G17: =IFERROR(((('Forecast'!$C$21/(1+$B$17)^1+'Forecast'!$D$21/(1+$B$17)^2+'Forecast'!$E$21/(1+$B$17)^3+'Forecast'!$F$21/(1+$B$17)^4+'Forecast'!$G$21/(1+$B$17)^5)+('Forecast'!$G$12*$G$16)/(1+$B$17)^5)-'Historical'!$F$46-'Inputs'!$F$72)/'DCF'!$B$35,"n/m")
B18: ='WACC'!$B$24-0.0075 | C18: =IFERROR(((('Forecast'!$C$21/(1+$B$18)^1+'Forecast'!$D$21/(1+$B$18)^2+'Forecast'!$E$21/(1+$B$18)^3+'Forecast'!$F$21/(1+$B$18)^4+'Forecast'!$G$21/(1+$B$18)^5)+('Forecast'!$G$12*$C$16)/(1+$B$18)^5)-'Historical'!$F$46-'Inputs'!$F$72)/'DCF'!$B$35,"n/m") | D18: =IFERROR(((('Forecast'!$C$21/(1+$B$18)^1+'Forecast'!$D$21/(1+$B$18)^2+'Forecast'!$E$21/(1+$B$18)^3+'Forecast'!$F$21/(1+$B$18)^4+'Forecast'!$G$21/(1+$B$18)^5)+('Forecast'!$G$12*$D$16)/(1+$B$18)^5)-'Historical'!$F$46-'Inputs'!$F$72)/'DCF'!$B$35,"n/m") | E18: =IFERROR(((('Forecast'!$C$21/(1+$B$18)^1+'Forecast'!$D$21/(1+$B$18)^2+'Forecast'!$E$21/(1+$B$18)^3+'Forecast'!$F$21/(1+$B$18)^4+'Forecast'!$G$21/(1+$B$18)^5)+('Forecast'!$G$12*$E$16)/(1+$B$18)^5)-'Historical'!$F$46-'Inputs'!$F$72)/'DCF'!$B$35,"n/m") | F18: =IFERROR(((('Forecast'!$C$21/(1+$B$18)^1+'Forecast'!$D$21/(1+$B$18)^2+'Forecast'!$E$21/(1+$B$18)^3+'Forecast'!$F$21/(1+$B$18)^4+'Forecast'!$G$21/(1+$B$18)^5)+('Forecast'!$G$12*$F$16)/(1+$B$18)^5)-'Historical'!$F$46-'Inputs'!$F$72)/'DCF'!$B$35,"n/m") | G18: =IFERROR(((('Forecast'!$C$21/(1+$B$18)^1+'Forecast'!$D$21/(1+$B$18)^2+'Forecast'!$E$21/(1+$B$18)^3+'Forecast'!$F$21/(1+$B$18)^4+'Forecast'!$G$21/(1+$B$18)^5)+('Forecast'!$G$12*$G$16)/(1+$B$18)^5)-'Historical'!$F$46-'Inputs'!$F$72)/'DCF'!$B$35,"n/m")
B19: ='WACC'!$B$24+0 | C19: =IFERROR(((('Forecast'!$C$21/(1+$B$19)^1+'Forecast'!$D$21/(1+$B$19)^2+'Forecast'!$E$21/(1+$B$19)^3+'Forecast'!$F$21/(1+$B$19)^4+'Forecast'!$G$21/(1+$B$19)^5)+('Forecast'!$G$12*$C$16)/(1+$B$19)^5)-'Historical'!$F$46-'Inputs'!$F$72)/'DCF'!$B$35,"n/m") | D19: =IFERROR(((('Forecast'!$C$21/(1+$B$19)^1+'Forecast'!$D$21/(1+$B$19)^2+'Forecast'!$E$21/(1+$B$19)^3+'Forecast'!$F$21/(1+$B$19)^4+'Forecast'!$G$21/(1+$B$19)^5)+('Forecast'!$G$12*$D$16)/(1+$B$19)^5)-'Historical'!$F$46-'Inputs'!$F$72)/'DCF'!$B$35,"n/m") | E19: =IFERROR(((('Forecast'!$C$21/(1+$B$19)^1+'Forecast'!$D$21/(1+$B$19)^2+'Forecast'!$E$21/(1+$B$19)^3+'Forecast'!$F$21/(1+$B$19)^4+'Forecast'!$G$21/(1+$B$19)^5)+('Forecast'!$G$12*$E$16)/(1+$B$19)^5)-'Historical'!$F$46-'Inputs'!$F$72)/'DCF'!$B$35,"n/m") | F19: =IFERROR(((('Forecast'!$C$21/(1+$B$19)^1+'Forecast'!$D$21/(1+$B$19)^2+'Forecast'!$E$21/(1+$B$19)^3+'Forecast'!$F$21/(1+$B$19)^4+'Forecast'!$G$21/(1+$B$19)^5)+('Forecast'!$G$12*$F$16)/(1+$B$19)^5)-'Historical'!$F$46-'Inputs'!$F$72)/'DCF'!$B$35,"n/m") | G19: =IFERROR(((('Forecast'!$C$21/(1+$B$19)^1+'Forecast'!$D$21/(1+$B$19)^2+'Forecast'!$E$21/(1+$B$19)^3+'Forecast'!$F$21/(1+$B$19)^4+'Forecast'!$G$21/(1+$B$19)^5)+('Forecast'!$G$12*$G$16)/(1+$B$19)^5)-'Historical'!$F$46-'Inputs'!$F$72)/'DCF'!$B$35,"n/m")
B20: ='WACC'!$B$24+0.0075 | C20: =IFERROR(((('Forecast'!$C$21/(1+$B$20)^1+'Forecast'!$D$21/(1+$B$20)^2+'Forecast'!$E$21/(1+$B$20)^3+'Forecast'!$F$21/(1+$B$20)^4+'Forecast'!$G$21/(1+$B$20)^5)+('Forecast'!$G$12*$C$16)/(1+$B$20)^5)-'Historical'!$F$46-'Inputs'!$F$72)/'DCF'!$B$35,"n/m") | D20: =IFERROR(((('Forecast'!$C$21/(1+$B$20)^1+'Forecast'!$D$21/(1+$B$20)^2+'Forecast'!$E$21/(1+$B$20)^3+'Forecast'!$F$21/(1+$B$20)^4+'Forecast'!$G$21/(1+$B$20)^5)+('Forecast'!$G$12*$D$16)/(1+$B$20)^5)-'Historical'!$F$46-'Inputs'!$F$72)/'DCF'!$B$35,"n/m") | E20: =IFERROR(((('Forecast'!$C$21/(1+$B$20)^1+'Forecast'!$D$21/(1+$B$20)^2+'Forecast'!$E$21/(1+$B$20)^3+'Forecast'!$F$21/(1+$B$20)^4+'Forecast'!$G$21/(1+$B$20)^5)+('Forecast'!$G$12*$E$16)/(1+$B$20)^5)-'Historical'!$F$46-'Inputs'!$F$72)/'DCF'!$B$35,"n/m") | F20: =IFERROR(((('Forecast'!$C$21/(1+$B$20)^1+'Forecast'!$D$21/(1+$B$20)^2+'Forecast'!$E$21/(1+$B$20)^3+'Forecast'!$F$21/(1+$B$20)^4+'Forecast'!$G$21/(1+$B$20)^5)+('Forecast'!$G$12*$F$16)/(1+$B$20)^5)-'Historical'!$F$46-'Inputs'!$F$72)/'DCF'!$B$35,"n/m") | G20: =IFERROR(((('Forecast'!$C$21/(1+$B$20)^1+'Forecast'!$D$21/(1+$B$20)^2+'Forecast'!$E$21/(1+$B$20)^3+'Forecast'!$F$21/(1+$B$20)^4+'Forecast'!$G$21/(1+$B$20)^5)+('Forecast'!$G$12*$G$16)/(1+$B$20)^5)-'Historical'!$F$46-'Inputs'!$F$72)/'DCF'!$B$35,"n/m")
B21: ='WACC'!$B$24+0.015 | C21: =IFERROR(((('Forecast'!$C$21/(1+$B$21)^1+'Forecast'!$D$21/(1+$B$21)^2+'Forecast'!$E$21/(1+$B$21)^3+'Forecast'!$F$21/(1+$B$21)^4+'Forecast'!$G$21/(1+$B$21)^5)+('Forecast'!$G$12*$C$16)/(1+$B$21)^5)-'Historical'!$F$46-'Inputs'!$F$72)/'DCF'!$B$35,"n/m") | D21: =IFERROR(((('Forecast'!$C$21/(1+$B$21)^1+'Forecast'!$D$21/(1+$B$21)^2+'Forecast'!$E$21/(1+$B$21)^3+'Forecast'!$F$21/(1+$B$21)^4+'Forecast'!$G$21/(1+$B$21)^5)+('Forecast'!$G$12*$D$16)/(1+$B$21)^5)-'Historical'!$F$46-'Inputs'!$F$72)/'DCF'!$B$35,"n/m") | E21: =IFERROR(((('Forecast'!$C$21/(1+$B$21)^1+'Forecast'!$D$21/(1+$B$21)^2+'Forecast'!$E$21/(1+$B$21)^3+'Forecast'!$F$21/(1+$B$21)^4+'Forecast'!$G$21/(1+$B$21)^5)+('Forecast'!$G$12*$E$16)/(1+$B$21)^5)-'Historical'!$F$46-'Inputs'!$F$72)/'DCF'!$B$35,"n/m") | F21: =IFERROR(((('Forecast'!$C$21/(1+$B$21)^1+'Forecast'!$D$21/(1+$B$21)^2+'Forecast'!$E$21/(1+$B$21)^3+'Forecast'!$F$21/(1+$B$21)^4+'Forecast'!$G$21/(1+$B$21)^5)+('Forecast'!$G$12*$F$16)/(1+$B$21)^5)-'Historical'!$F$46-'Inputs'!$F$72)/'DCF'!$B$35,"n/m") | G21: =IFERROR(((('Forecast'!$C$21/(1+$B$21)^1+'Forecast'!$D$21/(1+$B$21)^2+'Forecast'!$E$21/(1+$B$21)^3+'Forecast'!$F$21/(1+$B$21)^4+'Forecast'!$G$21/(1+$B$21)^5)+('Forecast'!$G$12*$G$16)/(1+$B$21)^5)-'Historical'!$F$46-'Inputs'!$F$72)/'DCF'!$B$35,"n/m")
A23: Exit-multiple TV is a cross-check; the headline uses the perpetuity method.
A25: Table 3 · Start revenue growth (down) × Terminal EBIT margin (across)
A26: Value / share | C26: ='Assumptions'!$B$36-0.03 | D26: ='Assumptions'!$B$36-0.015 | E26: ='Assumptions'!$B$36+0 | F26: ='Assumptions'!$B$36+0.015 | G26: ='Assumptions'!$B$36+0.03
B27: ='Assumptions'!$B$34-0.03 | C27: =IFERROR((((('Forecast'!$B$8*((1+$B$27)*($C$26*(1-'Assumptions'!$B$28)+'Assumptions'!$B$25-'Assumptions'!$B$26)-'Assumptions'!$B$27*$B$27)/(1+'WACC'!$B$24))*(1-((1+$B$27)/(1+'WACC'!$B$24))^5)/(1-((1+$B$27)/(1+'WACC'!$B$24))))+('Forecast'!$B$8*((1+$B$27)*($C$26*(1-'Assumptions'!$B$28)+'Assumptions'!$B$25-'Assumptions'!$B$26)-'Assumptions'!$B$27*$B$27)*(1+$B$27)^4*(1+'Assumptions'!$B$35)/('WACC'!$B$24-'Assumptions'!$B$35))/(1+'WACC'!$B$24)^5)-'Historical'!$F$46-'Inputs'!$F$72)/'DCF'!$B$35,"n/m") | D27: =IFERROR((((('Forecast'!$B$8*((1+$B$27)*($D$26*(1-'Assumptions'!$B$28)+'Assumptions'!$B$25-'Assumptions'!$B$26)-'Assumptions'!$B$27*$B$27)/(1+'WACC'!$B$24))*(1-((1+$B$27)/(1+'WACC'!$B$24))^5)/(1-((1+$B$27)/(1+'WACC'!$B$24))))+('Forecast'!$B$8*((1+$B$27)*($D$26*(1-'Assumptions'!$B$28)+'Assumptions'!$B$25-'Assumptions'!$B$26)-'Assumptions'!$B$27*$B$27)*(1+$B$27)^4*(1+'Assumptions'!$B$35)/('WACC'!$B$24-'Assumptions'!$B$35))/(1+'WACC'!$B$24)^5)-'Historical'!$F$46-'Inputs'!$F$72)/'DCF'!$B$35,"n/m") | E27: =IFERROR((((('Forecast'!$B$8*((1+$B$27)*($E$26*(1-'Assumptions'!$B$28)+'Assumptions'!$B$25-'Assumptions'!$B$26)-'Assumptions'!$B$27*$B$27)/(1+'WACC'!$B$24))*(1-((1+$B$27)/(1+'WACC'!$B$24))^5)/(1-((1+$B$27)/(1+'WACC'!$B$24))))+('Forecast'!$B$8*((1+$B$27)*($E$26*(1-'Assumptions'!$B$28)+'Assumptions'!$B$25-'Assumptions'!$B$26)-'Assumptions'!$B$27*$B$27)*(1+$B$27)^4*(1+'Assumptions'!$B$35)/('WACC'!$B$24-'Assumptions'!$B$35))/(1+'WACC'!$B$24)^5)-'Historical'!$F$46-'Inputs'!$F$72)/'DCF'!$B$35,"n/m") | F27: =IFERROR((((('Forecast'!$B$8*((1+$B$27)*($F$26*(1-'Assumptions'!$B$28)+'Assumptions'!$B$25-'Assumptions'!$B$26)-'Assumptions'!$B$27*$B$27)/(1+'WACC'!$B$24))*(1-((1+$B$27)/(1+'WACC'!$B$24))^5)/(1-((1+$B$27)/(1+'WACC'!$B$24))))+('Forecast'!$B$8*((1+$B$27)*($F$26*(1-'Assumptions'!$B$28)+'Assumptions'!$B$25-'Assumptions'!$B$26)-'Assumptions'!$B$27*$B$27)*(1+$B$27)^4*(1+'Assumptions'!$B$35)/('WACC'!$B$24-'Assumptions'!$B$35))/(1+'WACC'!$B$24)^5)-'Historical'!$F$46-'Inputs'!$F$72)/'DCF'!$B$35,"n/m") | G27: =IFERROR((((('Forecast'!$B$8*((1+$B$27)*($G$26*(1-'Assumptions'!$B$28)+'Assumptions'!$B$25-'Assumptions'!$B$26)-'Assumptions'!$B$27*$B$27)/(1+'WACC'!$B$24))*(1-((1+$B$27)/(1+'WACC'!$B$24))^5)/(1-((1+$B$27)/(1+'WACC'!$B$24))))+('Forecast'!$B$8*((1+$B$27)*($G$26*(1-'Assumptions'!$B$28)+'Assumptions'!$B$25-'Assumptions'!$B$26)-'Assumptions'!$B$27*$B$27)*(1+$B$27)^4*(1+'Assumptions'!$B$35)/('WACC'!$B$24-'Assumptions'!$B$35))/(1+'WACC'!$B$24)^5)-'Historical'!$F$46-'Inputs'!$F$72)/'DCF'!$B$35,"n/m")
B28: ='Assumptions'!$B$34-0.015 | C28: =IFERROR((((('Forecast'!$B$8*((1+$B$28)*($C$26*(1-'Assumptions'!$B$28)+'Assumptions'!$B$25-'Assumptions'!$B$26)-'Assumptions'!$B$27*$B$28)/(1+'WACC'!$B$24))*(1-((1+$B$28)/(1+'WACC'!$B$24))^5)/(1-((1+$B$28)/(1+'WACC'!$B$24))))+('Forecast'!$B$8*((1+$B$28)*($C$26*(1-'Assumptions'!$B$28)+'Assumptions'!$B$25-'Assumptions'!$B$26)-'Assumptions'!$B$27*$B$28)*(1+$B$28)^4*(1+'Assumptions'!$B$35)/('WACC'!$B$24-'Assumptions'!$B$35))/(1+'WACC'!$B$24)^5)-'Historical'!$F$46-'Inputs'!$F$72)/'DCF'!$B$35,"n/m") | D28: =IFERROR((((('Forecast'!$B$8*((1+$B$28)*($D$26*(1-'Assumptions'!$B$28)+'Assumptions'!$B$25-'Assumptions'!$B$26)-'Assumptions'!$B$27*$B$28)/(1+'WACC'!$B$24))*(1-((1+$B$28)/(1+'WACC'!$B$24))^5)/(1-((1+$B$28)/(1+'WACC'!$B$24))))+('Forecast'!$B$8*((1+$B$28)*($D$26*(1-'Assumptions'!$B$28)+'Assumptions'!$B$25-'Assumptions'!$B$26)-'Assumptions'!$B$27*$B$28)*(1+$B$28)^4*(1+'Assumptions'!$B$35)/('WACC'!$B$24-'Assumptions'!$B$35))/(1+'WACC'!$B$24)^5)-'Historical'!$F$46-'Inputs'!$F$72)/'DCF'!$B$35,"n/m") | E28: =IFERROR((((('Forecast'!$B$8*((1+$B$28)*($E$26*(1-'Assumptions'!$B$28)+'Assumptions'!$B$25-'Assumptions'!$B$26)-'Assumptions'!$B$27*$B$28)/(1+'WACC'!$B$24))*(1-((1+$B$28)/(1+'WACC'!$B$24))^5)/(1-((1+$B$28)/(1+'WACC'!$B$24))))+('Forecast'!$B$8*((1+$B$28)*($E$26*(1-'Assumptions'!$B$28)+'Assumptions'!$B$25-'Assumptions'!$B$26)-'Assumptions'!$B$27*$B$28)*(1+$B$28)^4*(1+'Assumptions'!$B$35)/('WACC'!$B$24-'Assumptions'!$B$35))/(1+'WACC'!$B$24)^5)-'Historical'!$F$46-'Inputs'!$F$72)/'DCF'!$B$35,"n/m") | F28: =IFERROR((((('Forecast'!$B$8*((1+$B$28)*($F$26*(1-'Assumptions'!$B$28)+'Assumptions'!$B$25-'Assumptions'!$B$26)-'Assumptions'!$B$27*$B$28)/(1+'WACC'!$B$24))*(1-((1+$B$28)/(1+'WACC'!$B$24))^5)/(1-((1+$B$28)/(1+'WACC'!$B$24))))+('Forecast'!$B$8*((1+$B$28)*($F$26*(1-'Assumptions'!$B$28)+'Assumptions'!$B$25-'Assumptions'!$B$26)-'Assumptions'!$B$27*$B$28)*(1+$B$28)^4*(1+'Assumptions'!$B$35)/('WACC'!$B$24-'Assumptions'!$B$35))/(1+'WACC'!$B$24)^5)-'Historical'!$F$46-'Inputs'!$F$72)/'DCF'!$B$35,"n/m") | G28: =IFERROR((((('Forecast'!$B$8*((1+$B$28)*($G$26*(1-'Assumptions'!$B$28)+'Assumptions'!$B$25-'Assumptions'!$B$26)-'Assumptions'!$B$27*$B$28)/(1+'WACC'!$B$24))*(1-((1+$B$28)/(1+'WACC'!$B$24))^5)/(1-((1+$B$28)/(1+'WACC'!$B$24))))+('Forecast'!$B$8*((1+$B$28)*($G$26*(1-'Assumptions'!$B$28)+'Assumptions'!$B$25-'Assumptions'!$B$26)-'Assumptions'!$B$27*$B$28)*(1+$B$28)^4*(1+'Assumptions'!$B$35)/('WACC'!$B$24-'Assumptions'!$B$35))/(1+'WACC'!$B$24)^5)-'Historical'!$F$46-'Inputs'!$F$72)/'DCF'!$B$35,"n/m")
B29: ='Assumptions'!$B$34+0 | C29: =IFERROR((((('Forecast'!$B$8*((1+$B$29)*($C$26*(1-'Assumptions'!$B$28)+'Assumptions'!$B$25-'Assumptions'!$B$26)-'Assumptions'!$B$27*$B$29)/(1+'WACC'!$B$24))*(1-((1+$B$29)/(1+'WACC'!$B$24))^5)/(1-((1+$B$29)/(1+'WACC'!$B$24))))+('Forecast'!$B$8*((1+$B$29)*($C$26*(1-'Assumptions'!$B$28)+'Assumptions'!$B$25-'Assumptions'!$B$26)-'Assumptions'!$B$27*$B$29)*(1+$B$29)^4*(1+'Assumptions'!$B$35)/('WACC'!$B$24-'Assumptions'!$B$35))/(1+'WACC'!$B$24)^5)-'Historical'!$F$46-'Inputs'!$F$72)/'DCF'!$B$35,"n/m") | D29: =IFERROR((((('Forecast'!$B$8*((1+$B$29)*($D$26*(1-'Assumptions'!$B$28)+'Assumptions'!$B$25-'Assumptions'!$B$26)-'Assumptions'!$B$27*$B$29)/(1+'WACC'!$B$24))*(1-((1+$B$29)/(1+'WACC'!$B$24))^5)/(1-((1+$B$29)/(1+'WACC'!$B$24))))+('Forecast'!$B$8*((1+$B$29)*($D$26*(1-'Assumptions'!$B$28)+'Assumptions'!$B$25-'Assumptions'!$B$26)-'Assumptions'!$B$27*$B$29)*(1+$B$29)^4*(1+'Assumptions'!$B$35)/('WACC'!$B$24-'Assumptions'!$B$35))/(1+'WACC'!$B$24)^5)-'Historical'!$F$46-'Inputs'!$F$72)/'DCF'!$B$35,"n/m") | E29: =IFERROR((((('Forecast'!$B$8*((1+$B$29)*($E$26*(1-'Assumptions'!$B$28)+'Assumptions'!$B$25-'Assumptions'!$B$26)-'Assumptions'!$B$27*$B$29)/(1+'WACC'!$B$24))*(1-((1+$B$29)/(1+'WACC'!$B$24))^5)/(1-((1+$B$29)/(1+'WACC'!$B$24))))+('Forecast'!$B$8*((1+$B$29)*($E$26*(1-'Assumptions'!$B$28)+'Assumptions'!$B$25-'Assumptions'!$B$26)-'Assumptions'!$B$27*$B$29)*(1+$B$29)^4*(1+'Assumptions'!$B$35)/('WACC'!$B$24-'Assumptions'!$B$35))/(1+'WACC'!$B$24)^5)-'Historical'!$F$46-'Inputs'!$F$72)/'DCF'!$B$35,"n/m") | F29: =IFERROR((((('Forecast'!$B$8*((1+$B$29)*($F$26*(1-'Assumptions'!$B$28)+'Assumptions'!$B$25-'Assumptions'!$B$26)-'Assumptions'!$B$27*$B$29)/(1+'WACC'!$B$24))*(1-((1+$B$29)/(1+'WACC'!$B$24))^5)/(1-((1+$B$29)/(1+'WACC'!$B$24))))+('Forecast'!$B$8*((1+$B$29)*($F$26*(1-'Assumptions'!$B$28)+'Assumptions'!$B$25-'Assumptions'!$B$26)-'Assumptions'!$B$27*$B$29)*(1+$B$29)^4*(1+'Assumptions'!$B$35)/('WACC'!$B$24-'Assumptions'!$B$35))/(1+'WACC'!$B$24)^5)-'Historical'!$F$46-'Inputs'!$F$72)/'DCF'!$B$35,"n/m") | G29: =IFERROR((((('Forecast'!$B$8*((1+$B$29)*($G$26*(1-'Assumptions'!$B$28)+'Assumptions'!$B$25-'Assumptions'!$B$26)-'Assumptions'!$B$27*$B$29)/(1+'WACC'!$B$24))*(1-((1+$B$29)/(1+'WACC'!$B$24))^5)/(1-((1+$B$29)/(1+'WACC'!$B$24))))+('Forecast'!$B$8*((1+$B$29)*($G$26*(1-'Assumptions'!$B$28)+'Assumptions'!$B$25-'Assumptions'!$B$26)-'Assumptions'!$B$27*$B$29)*(1+$B$29)^4*(1+'Assumptions'!$B$35)/('WACC'!$B$24-'Assumptions'!$B$35))/(1+'WACC'!$B$24)^5)-'Historical'!$F$46-'Inputs'!$F$72)/'DCF'!$B$35,"n/m")
B30: ='Assumptions'!$B$34+0.015 | C30: =IFERROR((((('Forecast'!$B$8*((1+$B$30)*($C$26*(1-'Assumptions'!$B$28)+'Assumptions'!$B$25-'Assumptions'!$B$26)-'Assumptions'!$B$27*$B$30)/(1+'WACC'!$B$24))*(1-((1+$B$30)/(1+'WACC'!$B$24))^5)/(1-((1+$B$30)/(1+'WACC'!$B$24))))+('Forecast'!$B$8*((1+$B$30)*($C$26*(1-'Assumptions'!$B$28)+'Assumptions'!$B$25-'Assumptions'!$B$26)-'Assumptions'!$B$27*$B$30)*(1+$B$30)^4*(1+'Assumptions'!$B$35)/('WACC'!$B$24-'Assumptions'!$B$35))/(1+'WACC'!$B$24)^5)-'Historical'!$F$46-'Inputs'!$F$72)/'DCF'!$B$35,"n/m") | D30: =IFERROR((((('Forecast'!$B$8*((1+$B$30)*($D$26*(1-'Assumptions'!$B$28)+'Assumptions'!$B$25-'Assumptions'!$B$26)-'Assumptions'!$B$27*$B$30)/(1+'WACC'!$B$24))*(1-((1+$B$30)/(1+'WACC'!$B$24))^5)/(1-((1+$B$30)/(1+'WACC'!$B$24))))+('Forecast'!$B$8*((1+$B$30)*($D$26*(1-'Assumptions'!$B$28)+'Assumptions'!$B$25-'Assumptions'!$B$26)-'Assumptions'!$B$27*$B$30)*(1+$B$30)^4*(1+'Assumptions'!$B$35)/('WACC'!$B$24-'Assumptions'!$B$35))/(1+'WACC'!$B$24)^5)-'Historical'!$F$46-'Inputs'!$F$72)/'DCF'!$B$35,"n/m") | E30: =IFERROR((((('Forecast'!$B$8*((1+$B$30)*($E$26*(1-'Assumptions'!$B$28)+'Assumptions'!$B$25-'Assumptions'!$B$26)-'Assumptions'!$B$27*$B$30)/(1+'WACC'!$B$24))*(1-((1+$B$30)/(1+'WACC'!$B$24))^5)/(1-((1+$B$30)/(1+'WACC'!$B$24))))+('Forecast'!$B$8*((1+$B$30)*($E$26*(1-'Assumptions'!$B$28)+'Assumptions'!$B$25-'Assumptions'!$B$26)-'Assumptions'!$B$27*$B$30)*(1+$B$30)^4*(1+'Assumptions'!$B$35)/('WACC'!$B$24-'Assumptions'!$B$35))/(1+'WACC'!$B$24)^5)-'Historical'!$F$46-'Inputs'!$F$72)/'DCF'!$B$35,"n/m") | F30: =IFERROR((((('Forecast'!$B$8*((1+$B$30)*($F$26*(1-'Assumptions'!$B$28)+'Assumptions'!$B$25-'Assumptions'!$B$26)-'Assumptions'!$B$27*$B$30)/(1+'WACC'!$B$24))*(1-((1+$B$30)/(1+'WACC'!$B$24))^5)/(1-((1+$B$30)/(1+'WACC'!$B$24))))+('Forecast'!$B$8*((1+$B$30)*($F$26*(1-'Assumptions'!$B$28)+'Assumptions'!$B$25-'Assumptions'!$B$26)-'Assumptions'!$B$27*$B$30)*(1+$B$30)^4*(1+'Assumptions'!$B$35)/('WACC'!$B$24-'Assumptions'!$B$35))/(1+'WACC'!$B$24)^5)-'Historical'!$F$46-'Inputs'!$F$72)/'DCF'!$B$35,"n/m") | G30: =IFERROR((((('Forecast'!$B$8*((1+$B$30)*($G$26*(1-'Assumptions'!$B$28)+'Assumptions'!$B$25-'Assumptions'!$B$26)-'Assumptions'!$B$27*$B$30)/(1+'WACC'!$B$24))*(1-((1+$B$30)/(1+'WACC'!$B$24))^5)/(1-((1+$B$30)/(1+'WACC'!$B$24))))+('Forecast'!$B$8*((1+$B$30)*($G$26*(1-'Assumptions'!$B$28)+'Assumptions'!$B$25-'Assumptions'!$B$26)-'Assumptions'!$B$27*$B$30)*(1+$B$30)^4*(1+'Assumptions'!$B$35)/('WACC'!$B$24-'Assumptions'!$B$35))/(1+'WACC'!$B$24)^5)-'Historical'!$F$46-'Inputs'!$F$72)/'DCF'!$B$35,"n/m")
B31: ='Assumptions'!$B$34+0.03 | C31: =IFERROR((((('Forecast'!$B$8*((1+$B$31)*($C$26*(1-'Assumptions'!$B$28)+'Assumptions'!$B$25-'Assumptions'!$B$26)-'Assumptions'!$B$27*$B$31)/(1+'WACC'!$B$24))*(1-((1+$B$31)/(1+'WACC'!$B$24))^5)/(1-((1+$B$31)/(1+'WACC'!$B$24))))+('Forecast'!$B$8*((1+$B$31)*($C$26*(1-'Assumptions'!$B$28)+'Assumptions'!$B$25-'Assumptions'!$B$26)-'Assumptions'!$B$27*$B$31)*(1+$B$31)^4*(1+'Assumptions'!$B$35)/('WACC'!$B$24-'Assumptions'!$B$35))/(1+'WACC'!$B$24)^5)-'Historical'!$F$46-'Inputs'!$F$72)/'DCF'!$B$35,"n/m") | D31: =IFERROR((((('Forecast'!$B$8*((1+$B$31)*($D$26*(1-'Assumptions'!$B$28)+'Assumptions'!$B$25-'Assumptions'!$B$26)-'Assumptions'!$B$27*$B$31)/(1+'WACC'!$B$24))*(1-((1+$B$31)/(1+'WACC'!$B$24))^5)/(1-((1+$B$31)/(1+'WACC'!$B$24))))+('Forecast'!$B$8*((1+$B$31)*($D$26*(1-'Assumptions'!$B$28)+'Assumptions'!$B$25-'Assumptions'!$B$26)-'Assumptions'!$B$27*$B$31)*(1+$B$31)^4*(1+'Assumptions'!$B$35)/('WACC'!$B$24-'Assumptions'!$B$35))/(1+'WACC'!$B$24)^5)-'Historical'!$F$46-'Inputs'!$F$72)/'DCF'!$B$35,"n/m") | E31: =IFERROR((((('Forecast'!$B$8*((1+$B$31)*($E$26*(1-'Assumptions'!$B$28)+'Assumptions'!$B$25-'Assumptions'!$B$26)-'Assumptions'!$B$27*$B$31)/(1+'WACC'!$B$24))*(1-((1+$B$31)/(1+'WACC'!$B$24))^5)/(1-((1+$B$31)/(1+'WACC'!$B$24))))+('Forecast'!$B$8*((1+$B$31)*($E$26*(1-'Assumptions'!$B$28)+'Assumptions'!$B$25-'Assumptions'!$B$26)-'Assumptions'!$B$27*$B$31)*(1+$B$31)^4*(1+'Assumptions'!$B$35)/('WACC'!$B$24-'Assumptions'!$B$35))/(1+'WACC'!$B$24)^5)-'Historical'!$F$46-'Inputs'!$F$72)/'DCF'!$B$35,"n/m") | F31: =IFERROR((((('Forecast'!$B$8*((1+$B$31)*($F$26*(1-'Assumptions'!$B$28)+'Assumptions'!$B$25-'Assumptions'!$B$26)-'Assumptions'!$B$27*$B$31)/(1+'WACC'!$B$24))*(1-((1+$B$31)/(1+'WACC'!$B$24))^5)/(1-((1+$B$31)/(1+'WACC'!$B$24))))+('Forecast'!$B$8*((1+$B$31)*($F$26*(1-'Assumptions'!$B$28)+'Assumptions'!$B$25-'Assumptions'!$B$26)-'Assumptions'!$B$27*$B$31)*(1+$B$31)^4*(1+'Assumptions'!$B$35)/('WACC'!$B$24-'Assumptions'!$B$35))/(1+'WACC'!$B$24)^5)-'Historical'!$F$46-'Inputs'!$F$72)/'DCF'!$B$35,"n/m") | G31: =IFERROR((((('Forecast'!$B$8*((1+$B$31)*($G$26*(1-'Assumptions'!$B$28)+'Assumptions'!$B$25-'Assumptions'!$B$26)-'Assumptions'!$B$27*$B$31)/(1+'WACC'!$B$24))*(1-((1+$B$31)/(1+'WACC'!$B$24))^5)/(1-((1+$B$31)/(1+'WACC'!$B$24))))+('Forecast'!$B$8*((1+$B$31)*($G$26*(1-'Assumptions'!$B$28)+'Assumptions'!$B$25-'Assumptions'!$B$26)-'Assumptions'!$B$27*$B$31)*(1+$B$31)^4*(1+'Assumptions'!$B$35)/('WACC'!$B$24-'Assumptions'!$B$35))/(1+'WACC'!$B$24)^5)-'Historical'!$F$46-'Inputs'!$F$72)/'DCF'!$B$35,"n/m")
A33: Simplified constant-growth model for this 2-way view (the staged DCF fades growth & margin, so levels differ slightly from the headline).

Sheet Scenario
A1: SCENARIO ANALYSIS
A2: Four full DCF runs — base, bull, bear and downside stress
A3: Investment-Grade Company Analysis Engine · v1.0
A5: Scenario Assumptions
B6: Base | C6: Bull | D6: Bear | E6: Downside
A7: Year-1 revenue growth | B7: ='Assumptions'!$B$20 | C7: ='Assumptions'!$C$20 | D7: ='Assumptions'!$D$20 | E7: ='Assumptions'!$E$20
A8: Terminal growth (g) | B8: ='Assumptions'!$B$21 | C8: ='Assumptions'!$C$21 | D8: ='Assumptions'!$D$21 | E8: ='Assumptions'!$E$21
A9: Terminal EBIT margin | B9: ='Assumptions'!$B$22 | C9: ='Assumptions'!$C$22 | D9: ='Assumptions'!$D$22 | E9: ='Assumptions'!$E$22
A11: Revenue by Forecast Year
B12: Base | C12: Bull | D12: Bear | E12: Downside
A13: Year +1 | B13: ='Forecast'!$B$8*(1+('Assumptions'!$B$20+('Assumptions'!$B$21-'Assumptions'!$B$20)*0.000000)) | C13: ='Forecast'!$B$8*(1+('Assumptions'!$C$20+('Assumptions'!$C$21-'Assumptions'!$C$20)*0.000000)) | D13: ='Forecast'!$B$8*(1+('Assumptions'!$D$20+('Assumptions'!$D$21-'Assumptions'!$D$20)*0.000000)) | E13: ='Forecast'!$B$8*(1+('Assumptions'!$E$20+('Assumptions'!$E$21-'Assumptions'!$E$20)*0.000000))
A14: Year +2 | B14: ='Scenario'!$B$13*(1+('Assumptions'!$B$20+('Assumptions'!$B$21-'Assumptions'!$B$20)*0.250000)) | C14: ='Scenario'!$C$13*(1+('Assumptions'!$C$20+('Assumptions'!$C$21-'Assumptions'!$C$20)*0.250000)) | D14: ='Scenario'!$D$13*(1+('Assumptions'!$D$20+('Assumptions'!$D$21-'Assumptions'!$D$20)*0.250000)) | E14: ='Scenario'!$E$13*(1+('Assumptions'!$E$20+('Assumptions'!$E$21-'Assumptions'!$E$20)*0.250000))
A15: Year +3 | B15: ='Scenario'!$B$14*(1+('Assumptions'!$B$20+('Assumptions'!$B$21-'Assumptions'!$B$20)*0.500000)) | C15: ='Scenario'!$C$14*(1+('Assumptions'!$C$20+('Assumptions'!$C$21-'Assumptions'!$C$20)*0.500000)) | D15: ='Scenario'!$D$14*(1+('Assumptions'!$D$20+('Assumptions'!$D$21-'Assumptions'!$D$20)*0.500000)) | E15: ='Scenario'!$E$14*(1+('Assumptions'!$E$20+('Assumptions'!$E$21-'Assumptions'!$E$20)*0.500000))
A16: Year +4 | B16: ='Scenario'!$B$15*(1+('Assumptions'!$B$20+('Assumptions'!$B$21-'Assumptions'!$B$20)*0.750000)) | C16: ='Scenario'!$C$15*(1+('Assumptions'!$C$20+('Assumptions'!$C$21-'Assumptions'!$C$20)*0.750000)) | D16: ='Scenario'!$D$15*(1+('Assumptions'!$D$20+('Assumptions'!$D$21-'Assumptions'!$D$20)*0.750000)) | E16: ='Scenario'!$E$15*(1+('Assumptions'!$E$20+('Assumptions'!$E$21-'Assumptions'!$E$20)*0.750000))
A17: Year +5 | B17: ='Scenario'!$B$16*(1+('Assumptions'!$B$20+('Assumptions'!$B$21-'Assumptions'!$B$20)*1.000000)) | C17: ='Scenario'!$C$16*(1+('Assumptions'!$C$20+('Assumptions'!$C$21-'Assumptions'!$C$20)*1.000000)) | D17: ='Scenario'!$D$16*(1+('Assumptions'!$D$20+('Assumptions'!$D$21-'Assumptions'!$D$20)*1.000000)) | E17: ='Scenario'!$E$16*(1+('Assumptions'!$E$20+('Assumptions'!$E$21-'Assumptions'!$E$20)*1.000000))
A19: Unlevered Free Cash Flow by Year
B20: Base | C20: Bull | D20: Bear | E20: Downside
A21: Year +1 | B21: ='Scenario'!$B$13*('Forecast'!$B$9+('Assumptions'!$B$22-'Forecast'!$B$9)*0.200000)*(1-'Assumptions'!$B$28)+'Scenario'!$B$13*'Assumptions'!$B$25-'Scenario'!$B$13*'Assumptions'!$B$26-'Assumptions'!$B$27*('Scenario'!$B$13-'Forecast'!$B$8) | C21: ='Scenario'!$C$13*('Forecast'!$B$9+('Assumptions'!$C$22-'Forecast'!$B$9)*0.200000)*(1-'Assumptions'!$B$28)+'Scenario'!$C$13*'Assumptions'!$B$25-'Scenario'!$C$13*'Assumptions'!$B$26-'Assumptions'!$B$27*('Scenario'!$C$13-'Forecast'!$B$8) | D21: ='Scenario'!$D$13*('Forecast'!$B$9+('Assumptions'!$D$22-'Forecast'!$B$9)*0.200000)*(1-'Assumptions'!$B$28)+'Scenario'!$D$13*'Assumptions'!$B$25-'Scenario'!$D$13*'Assumptions'!$B$26-'Assumptions'!$B$27*('Scenario'!$D$13-'Forecast'!$B$8) | E21: ='Scenario'!$E$13*('Forecast'!$B$9+('Assumptions'!$E$22-'Forecast'!$B$9)*0.200000)*(1-'Assumptions'!$B$28)+'Scenario'!$E$13*'Assumptions'!$B$25-'Scenario'!$E$13*'Assumptions'!$B$26-'Assumptions'!$B$27*('Scenario'!$E$13-'Forecast'!$B$8)
A22: Year +2 | B22: ='Scenario'!$B$14*('Forecast'!$B$9+('Assumptions'!$B$22-'Forecast'!$B$9)*0.400000)*(1-'Assumptions'!$B$28)+'Scenario'!$B$14*'Assumptions'!$B$25-'Scenario'!$B$14*'Assumptions'!$B$26-'Assumptions'!$B$27*('Scenario'!$B$14-'Scenario'!$B$13) | C22: ='Scenario'!$C$14*('Forecast'!$B$9+('Assumptions'!$C$22-'Forecast'!$B$9)*0.400000)*(1-'Assumptions'!$B$28)+'Scenario'!$C$14*'Assumptions'!$B$25-'Scenario'!$C$14*'Assumptions'!$B$26-'Assumptions'!$B$27*('Scenario'!$C$14-'Scenario'!$C$13) | D22: ='Scenario'!$D$14*('Forecast'!$B$9+('Assumptions'!$D$22-'Forecast'!$B$9)*0.400000)*(1-'Assumptions'!$B$28)+'Scenario'!$D$14*'Assumptions'!$B$25-'Scenario'!$D$14*'Assumptions'!$B$26-'Assumptions'!$B$27*('Scenario'!$D$14-'Scenario'!$D$13) | E22: ='Scenario'!$E$14*('Forecast'!$B$9+('Assumptions'!$E$22-'Forecast'!$B$9)*0.400000)*(1-'Assumptions'!$B$28)+'Scenario'!$E$14*'Assumptions'!$B$25-'Scenario'!$E$14*'Assumptions'!$B$26-'Assumptions'!$B$27*('Scenario'!$E$14-'Scenario'!$E$13)
A23: Year +3 | B23: ='Scenario'!$B$15*('Forecast'!$B$9+('Assumptions'!$B$22-'Forecast'!$B$9)*0.600000)*(1-'Assumptions'!$B$28)+'Scenario'!$B$15*'Assumptions'!$B$25-'Scenario'!$B$15*'Assumptions'!$B$26-'Assumptions'!$B$27*('Scenario'!$B$15-'Scenario'!$B$14) | C23: ='Scenario'!$C$15*('Forecast'!$B$9+('Assumptions'!$C$22-'Forecast'!$B$9)*0.600000)*(1-'Assumptions'!$B$28)+'Scenario'!$C$15*'Assumptions'!$B$25-'Scenario'!$C$15*'Assumptions'!$B$26-'Assumptions'!$B$27*('Scenario'!$C$15-'Scenario'!$C$14) | D23: ='Scenario'!$D$15*('Forecast'!$B$9+('Assumptions'!$D$22-'Forecast'!$B$9)*0.600000)*(1-'Assumptions'!$B$28)+'Scenario'!$D$15*'Assumptions'!$B$25-'Scenario'!$D$15*'Assumptions'!$B$26-'Assumptions'!$B$27*('Scenario'!$D$15-'Scenario'!$D$14) | E23: ='Scenario'!$E$15*('Forecast'!$B$9+('Assumptions'!$E$22-'Forecast'!$B$9)*0.600000)*(1-'Assumptions'!$B$28)+'Scenario'!$E$15*'Assumptions'!$B$25-'Scenario'!$E$15*'Assumptions'!$B$26-'Assumptions'!$B$27*('Scenario'!$E$15-'Scenario'!$E$14)
A24: Year +4 | B24: ='Scenario'!$B$16*('Forecast'!$B$9+('Assumptions'!$B$22-'Forecast'!$B$9)*0.800000)*(1-'Assumptions'!$B$28)+'Scenario'!$B$16*'Assumptions'!$B$25-'Scenario'!$B$16*'Assumptions'!$B$26-'Assumptions'!$B$27*('Scenario'!$B$16-'Scenario'!$B$15) | C24: ='Scenario'!$C$16*('Forecast'!$B$9+('Assumptions'!$C$22-'Forecast'!$B$9)*0.800000)*(1-'Assumptions'!$B$28)+'Scenario'!$C$16*'Assumptions'!$B$25-'Scenario'!$C$16*'Assumptions'!$B$26-'Assumptions'!$B$27*('Scenario'!$C$16-'Scenario'!$C$15) | D24: ='Scenario'!$D$16*('Forecast'!$B$9+('Assumptions'!$D$22-'Forecast'!$B$9)*0.800000)*(1-'Assumptions'!$B$28)+'Scenario'!$D$16*'Assumptions'!$B$25-'Scenario'!$D$16*'Assumptions'!$B$26-'Assumptions'!$B$27*('Scenario'!$D$16-'Scenario'!$D$15) | E24: ='Scenario'!$E$16*('Forecast'!$B$9+('Assumptions'!$E$22-'Forecast'!$B$9)*0.800000)*(1-'Assumptions'!$B$28)+'Scenario'!$E$16*'Assumptions'!$B$25-'Scenario'!$E$16*'Assumptions'!$B$26-'Assumptions'!$B$27*('Scenario'!$E$16-'Scenario'!$E$15)
A25: Year +5 | B25: ='Scenario'!$B$17*('Forecast'!$B$9+('Assumptions'!$B$22-'Forecast'!$B$9)*1.000000)*(1-'Assumptions'!$B$28)+'Scenario'!$B$17*'Assumptions'!$B$25-'Scenario'!$B$17*'Assumptions'!$B$26-'Assumptions'!$B$27*('Scenario'!$B$17-'Scenario'!$B$16) | C25: ='Scenario'!$C$17*('Forecast'!$B$9+('Assumptions'!$C$22-'Forecast'!$B$9)*1.000000)*(1-'Assumptions'!$B$28)+'Scenario'!$C$17*'Assumptions'!$B$25-'Scenario'!$C$17*'Assumptions'!$B$26-'Assumptions'!$B$27*('Scenario'!$C$17-'Scenario'!$C$16) | D25: ='Scenario'!$D$17*('Forecast'!$B$9+('Assumptions'!$D$22-'Forecast'!$B$9)*1.000000)*(1-'Assumptions'!$B$28)+'Scenario'!$D$17*'Assumptions'!$B$25-'Scenario'!$D$17*'Assumptions'!$B$26-'Assumptions'!$B$27*('Scenario'!$D$17-'Scenario'!$D$16) | E25: ='Scenario'!$E$17*('Forecast'!$B$9+('Assumptions'!$E$22-'Forecast'!$B$9)*1.000000)*(1-'Assumptions'!$B$28)+'Scenario'!$E$17*'Assumptions'!$B$25-'Scenario'!$E$17*'Assumptions'!$B$26-'Assumptions'!$B$27*('Scenario'!$E$17-'Scenario'!$E$16)
A27: Valuation by Scenario
B28: Base | C28: Bull | D28: Bear | E28: Downside
A29: Σ PV of explicit FCFF | B29: =('Scenario'!$B$21/(1+'WACC'!$B$24)^1+'Scenario'!$B$22/(1+'WACC'!$B$24)^2+'Scenario'!$B$23/(1+'WACC'!$B$24)^3+'Scenario'!$B$24/(1+'WACC'!$B$24)^4+'Scenario'!$B$25/(1+'WACC'!$B$24)^5) | C29: =('Scenario'!$C$21/(1+'WACC'!$B$24)^1+'Scenario'!$C$22/(1+'WACC'!$B$24)^2+'Scenario'!$C$23/(1+'WACC'!$B$24)^3+'Scenario'!$C$24/(1+'WACC'!$B$24)^4+'Scenario'!$C$25/(1+'WACC'!$B$24)^5) | D29: =('Scenario'!$D$21/(1+'WACC'!$B$24)^1+'Scenario'!$D$22/(1+'WACC'!$B$24)^2+'Scenario'!$D$23/(1+'WACC'!$B$24)^3+'Scenario'!$D$24/(1+'WACC'!$B$24)^4+'Scenario'!$D$25/(1+'WACC'!$B$24)^5) | E29: =('Scenario'!$E$21/(1+'WACC'!$B$24)^1+'Scenario'!$E$22/(1+'WACC'!$B$24)^2+'Scenario'!$E$23/(1+'WACC'!$B$24)^3+'Scenario'!$E$24/(1+'WACC'!$B$24)^4+'Scenario'!$E$25/(1+'WACC'!$B$24)^5)
A30: Terminal value (perpetuity) | B30: =IFERROR('Scenario'!$B$25*(1+'Assumptions'!$B$21)/('WACC'!$B$24-'Assumptions'!$B$21),"n/m") | C30: =IFERROR('Scenario'!$C$25*(1+'Assumptions'!$C$21)/('WACC'!$B$24-'Assumptions'!$C$21),"n/m") | D30: =IFERROR('Scenario'!$D$25*(1+'Assumptions'!$D$21)/('WACC'!$B$24-'Assumptions'!$D$21),"n/m") | E30: =IFERROR('Scenario'!$E$25*(1+'Assumptions'!$E$21)/('WACC'!$B$24-'Assumptions'!$E$21),"n/m")
A31: PV of terminal value | B31: ='Scenario'!$B$30/(1+'WACC'!$B$24)^5 | C31: ='Scenario'!$C$30/(1+'WACC'!$B$24)^5 | D31: ='Scenario'!$D$30/(1+'WACC'!$B$24)^5 | E31: ='Scenario'!$E$30/(1+'WACC'!$B$24)^5
A32: Enterprise value | B32: ='Scenario'!$B$29+'Scenario'!$B$31 | C32: ='Scenario'!$C$29+'Scenario'!$C$31 | D32: ='Scenario'!$D$29+'Scenario'!$D$31 | E32: ='Scenario'!$E$29+'Scenario'!$E$31
A33: Equity value | B33: ='Scenario'!$B$32-'Historical'!$F$46-'Inputs'!$F$72 | C33: ='Scenario'!$C$32-'Historical'!$F$46-'Inputs'!$F$72 | D33: ='Scenario'!$D$32-'Historical'!$F$46-'Inputs'!$F$72 | E33: ='Scenario'!$E$32-'Historical'!$F$46-'Inputs'!$F$72
A34: Implied value per share | B34: =IFERROR('Scenario'!$B$33/'DCF'!$B$35,"n/m") | C34: =IFERROR('Scenario'!$C$33/'DCF'!$B$35,"n/m") | D34: =IFERROR('Scenario'!$D$33/'DCF'!$B$35,"n/m") | E34: =IFERROR('Scenario'!$E$33/'DCF'!$B$35,"n/m")
A35: Upside / (downside) vs price | B35: =IFERROR('Scenario'!$B$34/'Inputs'!$B$112-1,"n/a") | C35: =IFERROR('Scenario'!$C$34/'Inputs'!$B$112-1,"n/a") | D35: =IFERROR('Scenario'!$D$34/'Inputs'!$B$112-1,"n/a") | E35: =IFERROR('Scenario'!$E$34/'Inputs'!$B$112-1,"n/a")
A36: Valuation read | B36: =IF(NOT(AND(ISNUMBER('Scenario'!$B$34),ISNUMBER('Inputs'!$B$112),'Inputs'!$B$112>0)),"n/a",IF('Scenario'!$B$34>'Inputs'!$B$112*(1+0.15),"Undervalued",IF('Scenario'!$B$34<'Inputs'!$B$112*(1-0.15),"Overvalued","Fairly valued"))) | C36: =IF(NOT(AND(ISNUMBER('Scenario'!$C$34),ISNUMBER('Inputs'!$B$112),'Inputs'!$B$112>0)),"n/a",IF('Scenario'!$C$34>'Inputs'!$B$112*(1+0.15),"Undervalued",IF('Scenario'!$C$34<'Inputs'!$B$112*(1-0.15),"Overvalued","Fairly valued"))) | D36: =IF(NOT(AND(ISNUMBER('Scenario'!$D$34),ISNUMBER('Inputs'!$B$112),'Inputs'!$B$112>0)),"n/a",IF('Scenario'!$D$34>'Inputs'!$B$112*(1+0.15),"Undervalued",IF('Scenario'!$D$34<'Inputs'!$B$112*(1-0.15),"Overvalued","Fairly valued"))) | E36: =IF(NOT(AND(ISNUMBER('Scenario'!$E$34),ISNUMBER('Inputs'!$B$112),'Inputs'!$B$112>0)),"n/a",IF('Scenario'!$E$34>'Inputs'!$B$112*(1+0.15),"Undervalued",IF('Scenario'!$E$34<'Inputs'!$B$112*(1-0.15),"Overvalued","Fairly valued")))
A38: Current share price (reference): | B38: ='Inputs'!$B$112
A40: Base reproduces the headline DCF; Downside is a stress case (low growth, compressed margins).

Sheet Checks
A1: CHECKS & DIAGNOSTICS
A2: Automated integrity, sanity and data-gap checks
A3: Investment-Grade Company Analysis Engine · v1.0
A5: Overall Data Health
A6: Overall verdict | B6: =IF('Checks'!$B$7>0,"FAIL — fix flagged items",IF('Checks'!$B$8>0,"REVIEW — some items to check","PASS — all checks clear"))
A7: Checks failed (FAIL) | B7: =COUNTIF(C11:C32,"FAIL")
A8: Checks to review (REVIEW) | B8: =COUNTIF(C11:C32,"REVIEW")
A10: Financial-Statement Integrity
A11: Balance sheet balances (max |A − (L+E)|) | B11: =MAX(ABS('Inputs'!$B$62-'Inputs'!$B$73),ABS('Inputs'!$C$62-'Inputs'!$C$73),ABS('Inputs'!$D$62-'Inputs'!$D$73),ABS('Inputs'!$E$62-'Inputs'!$E$73),ABS('Inputs'!$F$62-'Inputs'!$F$73)) | C11: =IF($B$11<=1,"PASS",IF($B$11<=0.005*'Inputs'!$F$62,"REVIEW","FAIL")) | D11: Assets should equal liabilities + equity every year (rounding aside).
A12: Cash flow ties (max |Δcash − net CF|) | B12: =MAX(ABS('Inputs'!$C$91-('Inputs'!$C$52-'Inputs'!$B$52)),ABS('Inputs'!$D$91-('Inputs'!$D$52-'Inputs'!$C$52)),ABS('Inputs'!$E$91-('Inputs'!$E$52-'Inputs'!$D$52)),ABS('Inputs'!$F$91-('Inputs'!$F$52-'Inputs'!$E$52))) | C12: =IF($B$12<=1,"PASS",IF($B$12<=0.01*'Inputs'!$F$52,"REVIEW","FAIL")) | D12: CFO + CFI + CFF should equal the change in the cash balance.
A13: Net income: IS vs cash-flow statement | B13: =ABS('Inputs'!$F$48-'Inputs'!$F$77) | C13: =IF($B$13<=1,"PASS",IF($B$13<=5,"REVIEW","FAIL")) | D13: Net income on the income statement should match the cash-flow start line.
A15: Sign, Units & Data Presence
A16: Sign sanity (cost/return lines entered positive) | B16: =SUM(IF('Inputs'!$F$33<0,1,0),IF('Inputs'!$F$34<0,1,0),IF('Inputs'!$F$82<0,1,0),IF('Inputs'!$F$87<0,1,0),IF('Inputs'!$F$88<0,1,0)) | C16: =IF($B$16=0,"PASS","REVIEW") | D16: Revenue, COGS, capex, dividends and buybacks should be entered as positives.
A17: Key inputs present (latest year) | B17: =IF(NOT(ISNUMBER('Inputs'!$F$33)),1,0)+IF(NOT(ISNUMBER('Inputs'!$F$34)),1,0)+IF(NOT(ISNUMBER('Inputs'!$F$71)),1,0)+IF(NOT(ISNUMBER('Inputs'!$F$62)),1,0)+IF(NOT(ISNUMBER('Inputs'!$F$52)),1,0)+IF(NOT(ISNUMBER('Inputs'!$F$96)),1,0)+IF(NOT(ISNUMBER('Inputs'!$F$78)),1,0)+IF(NOT(ISNUMBER('Inputs'!$F$82)),1,0) | C17: =IF($B$17=0,"PASS",IF($B$17<=2,"REVIEW","FAIL")) | D17: Count of essential latest-year inputs that are blank/missing.
A18: Currency & units specified | C18: =IF(AND(ISTEXT('Inputs'!$B$9),ISTEXT('Inputs'!$B$10)),"PASS","REVIEW") | D18: Currency and units should be stated so figures are unambiguous.
A20: Valuation & Assumption Sanity
A21: WACC within plausible range | B21: ='WACC'!$B$24 | C21: =IF(AND(ISNUMBER($B$21),$B$21>=0.04,$B$21<=0.18),"PASS","REVIEW") | D21: WACC should sit roughly within 4–18%.
A22: WACC exceeds terminal growth (g) | B22: ='WACC'!$B$24-'Assumptions'!$B$35 | C22: =IF(AND(ISNUMBER($B$22),$B$22>=0.01),"PASS","REVIEW") | D22: WACC must exceed g, with a safety margin, or terminal value is unstable.
A23: Terminal growth within sane bounds | B23: ='Assumptions'!$B$35 | C23: =IF(AND(ISNUMBER($B$23),$B$23>=-0.01,$B$23<=0.04),"PASS","REVIEW") | D23: Perpetuity growth should not exceed long-run nominal GDP (~4%).
A24: Terminal value as % of enterprise value | B24: ='DCF'!$B$43 | C24: =IF(AND(ISNUMBER($B$24),$B$24<=0.8),"PASS","REVIEW") | D24: A very high share means value rests heavily on terminal assumptions.
A25: Enterprise & equity value positive | B25: =MIN('DCF'!$B$31,'DCF'!$B$34) | C25: =IF(AND(ISNUMBER($B$25),$B$25>0),"PASS","FAIL") | D25: Negative EV or equity value would signal a broken or distressed case.
A27: Historical & Forecast Sanity
A28: Gross margin within [0, 100%] (latest) | B28: =IFERROR('Historical'!$F$17,-1) | C28: =IF(AND(ISNUMBER($B$28),$B$28>=0,$B$28<=1),"PASS","REVIEW") | D28: A gross margin outside 0–100% points to a sign or mapping error.
A29: Revenue positive in every year | B29: =MIN('Inputs'!$B$33,'Inputs'!$C$33,'Inputs'!$D$33,'Inputs'!$E$33,'Inputs'!$F$33) | C29: =IF(AND(ISNUMBER($B$29),$B$29>0),"PASS","FAIL") | D29: Zero/negative revenue breaks growth and margin calculations.
A30: Revenue-growth outliers (max |YoY|) | B30: =MAX(ABS(IFERROR('Inputs'!$C$33/'Inputs'!$B$33-1,0)),ABS(IFERROR('Inputs'!$D$33/'Inputs'!$C$33-1,0)),ABS(IFERROR('Inputs'!$E$33/'Inputs'!$D$33-1,0)),ABS(IFERROR('Inputs'!$F$33/'Inputs'!$E$33-1,0))) | C30: =IF($B$30<=1,"PASS","REVIEW") | D30: A year-on-year move above 100% may indicate a data-entry error.
A31: Forecast FCFF non-negative | B31: =MIN('Forecast'!$C$21,'Forecast'!$D$21,'Forecast'!$E$21,'Forecast'!$F$21,'Forecast'!$G$21) | C31: =IF($B$31>=0,"PASS","REVIEW") | D31: Negative forecast FCF is allowed (heavy investment) but worth noting.
A32: Model integrity (no circular references) | C32: ="PASS" | D32: The workbook is acyclic by construction — outputs trace one way to inputs.

Sheet Dashboard
A1: INVESTMENT DASHBOARD
A2: <Company name> — summary analysis pack
A3: Investment-Grade Company Analysis Engine · v1.0
A5: Company Snapshot | E5: Headline Valuation
A6: Company | B6: ='Inputs'!$B$6 | E6: DCF value per share | F6: ='DCF'!$B$36
A7: Ticker | B7: ='Inputs'!$B$7 | E7: Current share price | F7: ='DCF'!$B$39
A8: Business type | B8: ='Inputs'!$B$8 | E8: Upside / (downside) | F8: ='DCF'!$B$40
A9: Currency / units | B9: ='Inputs'!$B$9&" "&'Inputs'!$B$10 | E9: Valuation read | F9: ='DCF'!$B$41
A10: Fiscal year end | B10: ='Inputs'!$B$11 | E10: WACC | F10: ='WACC'!$B$24
A11: Revenue (FY—0) | B11: ='Inputs'!$F$33 | E11: Enterprise value | F11: ='DCF'!$B$31
A13: Operating KPIs (latest) | E13: Returns & Balance-Sheet Health
A14: Revenue growth | B14: ='Historical'!$F$8 | C14: ='Historical'!$G$8 | E14: ROE | F14: ='Historical'!$F$32 | G14: ='Historical'!$G$32
A15: Gross margin | B15: ='Historical'!$F$17 | C15: ='Historical'!$G$17 | E15: ROIC | F15: ='Historical'!$F$34 | G15: ='Historical'!$G$34
A16: EBITDA margin | B16: ='Historical'!$F$18 | C16: ='Historical'!$G$18 | E16: ROIC vs WACC | F16: =IFERROR('Historical'!$F$34-'WACC'!$B$24,"n/a") | G16: =IF(NOT(AND(ISNUMBER('Historical'!$F$34),ISNUMBER('WACC'!$B$24))),"n/a",IF('Historical'!$F$34>'WACC'!$B$24+0.01,"Value-creating",IF('Historical'!$F$34<'WACC'!$B$24-0.01,"Value-destroying","Roughly neutral")))
A17: EBIT margin | B17: ='Historical'!$F$19 | C17: ='Historical'!$G$19 | E17: Net debt / EBITDA | F17: ='Historical'!$F$48 | G17: ='Historical'!$G$48
A18: Net margin | B18: ='Historical'!$F$20 | C18: ='Historical'!$G$20 | E18: Interest coverage | F18: ='Historical'!$F$49 | G18: ='Historical'!$G$49
A19: FCF margin | B19: ='Historical'!$F$67 | C19: ='Historical'!$G$67 | E19: Current ratio | F19: ='Historical'!$F$39 | G19: ='Historical'!$G$39
A21: DCF Bridge | E21: Scenario Range (value / share)
A22: Σ PV explicit FCFF | B22: ='DCF'!$G$11 | E22: Base | F22: ='Scenario'!$B$34 | G22: ='Scenario'!$B$35
A23: (+) PV terminal value | B23: ='DCF'!$B$19 | E23: Bull | F23: ='Scenario'!$C$34 | G23: ='Scenario'!$C$35
A24: Enterprise value | B24: ='DCF'!$B$31 | E24: Bear | F24: ='Scenario'!$D$34 | G24: ='Scenario'!$D$35
A25: (−) Net debt | B25: ='DCF'!$B$32 | E25: Downside | F25: ='Scenario'!$E$34 | G25: ='Scenario'!$E$35
A26: Equity value | B26: ='DCF'!$B$34
A27: TV % of EV | B27: ='DCF'!$B$43
A29: Risk Flags
A30: Leverage (net debt / EBITDA) | B30: ='Historical'!$G$48 | E30: Interest coverage | F30: ='Historical'!$G$49
A31: Liquidity (current ratio) | B31: ='Historical'!$G$39 | E31: Revenue growth trend | F31: ='Historical'!$G$8
A32: Margin trend (gross) | B32: ='Historical'!$G$17 | E32: Capital efficiency (ROIC) | F32: ='Historical'!$G$34
A33: Value creation (ROIC vs WACC) | B33: =IF(NOT(AND(ISNUMBER('Historical'!$F$34),ISNUMBER('WACC'!$B$24))),"n/a",IF('Historical'!$F$34>'WACC'!$B$24+0.01,"Value-creating",IF('Historical'!$F$34<'WACC'!$B$24-0.01,"Value-destroying","Roughly neutral"))) | E33: Valuation vs price | F33: ='DCF'!$B$41
A34: Data & model health | B34: ='Checks'!$B$6
A36: Investment View
A37: =IF(ISNUMBER('DCF'!$B$40),IF('DCF'!$B$40>0.15,"The shares look UNDERVALUED on this DCF",IF('DCF'!$B$40<-0.15,"The shares look EXPENSIVE on this DCF","The shares look ~FAIRLY VALUED")),"No market price entered — see DCF value per share")&" ("&TEXT('DCF'!$B$36,"0.00")&" vs "&IF(ISNUMBER('DCF'!$B$39),TEXT('DCF'!$B$39,"0.00"),"n/a")&"). "&IF(AND(ISNUMBER('Historical'!$F$34),'Historical'!$F$34>'WACC'!$B$24+0.01),"Returns are above the cost of capital (value-creating); ",IF(AND(ISNUMBER('Historical'!$F$34),'Historical'!$F$34<'WACC'!$B$24-0.01),"Returns are below the cost of capital; ","Returns ~ cost of capital; "))&"see the Conclusion sheet for the full thesis."
A40: Tip: change the scenario selector on the Assumptions sheet (1–4) to flex the whole model; every figure here updates automatically.

Sheet Conclusion
A1: INVESTMENT CONCLUSION
A2: <Company name> — thesis, drivers, risks & stance
A3: Investment-Grade Company Analysis Engine · v1.0
A5: Final Stance
A6: ="Stance: "&IF(ISNUMBER('DCF'!$B$40),IF('DCF'!$B$40>0.15,"CONSTRUCTIVE — the DCF implies meaningful upside.",IF('DCF'!$B$40<-0.15,"CAUTIOUS — the DCF implies the price is rich.","NEUTRAL — price is close to intrinsic value.")),"VALUE-ONLY — no market price entered; compare to the DCF value per share.")&" Business quality is "&IF(AND(ISNUMBER('Historical'!$F$34),'Historical'!$F$34>'WACC'!$B$24+0.01),"GOOD (ROIC above WACC). ",IF(AND(ISNUMBER('Historical'!$F$34),'Historical'!$F$34<'WACC'!$B$24-0.01),"CHALLENGED (ROIC below WACC). ","ADEQUATE (ROIC ~ WACC). "))
A8: Valuation Summary
A9: ="The base-case DCF values the equity at "&TEXT('DCF'!$B$36,"#,##0.00")&" per share, versus a market price of "&IF(ISNUMBER('DCF'!$B$39),TEXT('DCF'!$B$39,"#,##0.00"),"n/a")&" — "&IF(ISNUMBER('DCF'!$B$40),TEXT('DCF'!$B$40,"+0.0%;-0.0%")&" upside/(downside).","no price entered.")&" The scenario range runs from "&TEXT('Scenario'!$E$34,"#,##0.00")&" (downside) to "&TEXT('Scenario'!$C$34,"#,##0.00")&" (bull)."
A11: What Is Driving Value
A12: ="• Capital returns: ROIC "&TEXT('Historical'!$F$34,"0.0%")&" vs WACC "&TEXT('WACC'!$B$24,"0.0%")&" — "&IF(AND(ISNUMBER('Historical'!$F$34),'Historical'!$F$34>'WACC'!$B$24+0.01),"value-creating.",IF(AND(ISNUMBER('Historical'!$F$34),'Historical'!$F$34<'WACC'!$B$24-0.01),"value-destroying.","roughly neutral."))
A13: ="• Profitability: EBIT margin "&TEXT('Historical'!$F$19,"0.0%")&" ("&'Historical'!$G$19&"), gross margin "&TEXT('Historical'!$F$17,"0.0%")&" ("&'Historical'!$G$17&")."
A14: ="• Cash generation: FCF margin "&TEXT('Historical'!$F$67,"0.0%")&" ("&'Historical'!$G$67&"); CFO/EBITDA "&TEXT('Historical'!$F$70,"0.0%")&"."
A15: ="• Growth: latest revenue growth "&TEXT('Historical'!$F$8,"0.0%")&" ("&'Historical'!$G$8&"); forecast fades toward the long-run rate."
A16: ="• Balance sheet: net debt / EBITDA "&TEXT('Historical'!$F$48,"0.0")&"x ("&'Historical'!$G$48&"), interest coverage "&TEXT('Historical'!$F$49,"0.0")&"x."
A18: What Is Hurting Value / Key Risks
A19: ="• Valuation: "&'DCF'!$B$41&" at the current price ("&IF(ISNUMBER('DCF'!$B$40),TEXT('DCF'!$B$40,"+0.0%;-0.0%")&" vs DCF value).","n/a).")
A20: ="• Leverage & coverage: "&'Historical'!$G$48&" leverage; "&'Historical'!$G$49&" interest coverage."
A21: ="• Growth & margin trend: revenue "&'Historical'!$G$8&"; gross margin "&'Historical'!$G$17&"."
A22: ="• Terminal-value reliance: "&TEXT('DCF'!$B$43,"0.0%")&" of enterprise value sits in the terminal value — sensitive to WACC and g."
A23: ="• Data & model health: "&'Checks'!$B$6&" (see Checks sheet)."
A25: Key Assumptions That Matter Most
A26: Assumption | B26: Active value | D26: Why it matters (see Sensitivity sheet for the swing)
A27: WACC (discount rate) | B27: ='WACC'!$B$24 | D27: The single biggest lever; lower WACC raises value sharply.
A28: Terminal growth (g) | B28: ='Assumptions'!$B$35 | D28: Drives the terminal value; capped below WACC for stability.
A29: Terminal EBIT margin | B29: ='Assumptions'!$B$36 | D29: Sets steady-state profitability and hence cash flow.
A30: Year-1 revenue growth | B30: ='Assumptions'!$B$34 | D30: Anchors the near-term trajectory before mean reversion.
A31: Exit EBITDA multiple | B31: ='Assumptions'!$B$29 | D31: Cross-check only; compare to the implied perpetuity multiple.
A33: Upside & Downside
A34: ="Upside (bull): value per share "&TEXT('Scenario'!$C$34,"#,##0.00")&" ("&IF(ISNUMBER('Scenario'!$C$35),TEXT('Scenario'!$C$35,"+0.0%;-0.0%"),"n/a")&") on faster growth and wider margins. Downside (stress): value per share "&TEXT('Scenario'!$E$34,"#,##0.00")&" ("&IF(ISNUMBER('Scenario'!$E$35),TEXT('Scenario'!$E$35,"+0.0%;-0.0%"),"n/a")&") on weak growth and margin compression."
A36: Caveats & Limitations
A37: ="• A DCF is only as good as its inputs: revise the market data, growth and margin assumptions for your own view before relying on the output."
A38: ="• Where data was missing the model used clearly-labelled fallbacks; replace them with company-specific figures to firm up the valuation."
A39: ="• Terminal value typically dominates a DCF — treat WACC and terminal growth as the key swing factors and lean on the Sensitivity and Scenario sheets."
A40: ="• This is an analytical tool, not investment advice. Validate against filings, peers and qualitative judgement before acting."
