Workbook
Name FirstYear: 'Historical'!$C$9
Name LastActual: 'Historical'!$C$11

Sheet Dashboard
A1: EXECUTIVE DASHBOARD
A2: <Company name> -- forecast summary
A3: Institutional Forecasting Engine - v2.0
A5: Methodology | B5: Historical | C5: Assumptions | D5: Forecast | E5: Bridge | F5: Diagnostics
A7: Company Overview | F7: Forecast Quality
A8: Company name | B8: <Company name> | F8: Forecast Health Score | H8: ='Diagnostics'!$B$8
A9: Ticker | B9: <TICKER> | F9: Balance-sheet integrity | H9: =IF(MAX(MAX('Forecast'!$C$32:$L$32),-MIN('Forecast'!$C$32:$L$32))<=1,"PASS","FAIL")
A10: Currency | B10: USD | F10: Last actual year | H10: =LastActual
A11: Fiscal year end | B11: 31 December | F11: Forecast window | H11: ="FY"&(LastActual+1)&" - FY"&(LastActual+10)
A13: Key Forecast Outputs -- 10-Year CAGR
A14: Revenue CAGR | C14: EBITDA CAGR | E14: EBIT CAGR | G14: Net income CAGR | I14: Free cash flow CAGR
A15: =IFERROR(('Forecast'!$L$12/'Forecast'!$B$12)^(1/10)-1,"") | C15: =IFERROR(('Forecast'!$L$13/'Forecast'!$B$13)^(1/10)-1,"") | E15: =IFERROR(('Forecast'!$L$15/'Forecast'!$B$15)^(1/10)-1,"") | G15: =IFERROR(('Forecast'!$L$19/'Forecast'!$B$19)^(1/10)-1,"") | I15: =IFERROR(('Forecast'!$L$40/'Forecast'!$B$40)^(1/10)-1,"")
A17: Forecast Trends
A18: Metric | B18: =LastActual | C18: =$B$18+1 | D18: =$C$18+1 | E18: =$D$18+1 | F18: =$E$18+1 | G18: =$F$18+1 | H18: =$G$18+1 | I18: =$H$18+1 | J18: =$I$18+1 | K18: =$J$18+1 | L18: =$K$18+1
A19: Revenue | B19: ='Forecast'!$B$12 | C19: ='Forecast'!$C$12 | D19: ='Forecast'!$D$12 | E19: ='Forecast'!$E$12 | F19: ='Forecast'!$F$12 | G19: ='Forecast'!$G$12 | H19: ='Forecast'!$H$12 | I19: ='Forecast'!$I$12 | J19: ='Forecast'!$J$12 | K19: ='Forecast'!$K$12 | L19: ='Forecast'!$L$12
A20: EBITDA | B20: ='Forecast'!$B$13 | C20: ='Forecast'!$C$13 | D20: ='Forecast'!$D$13 | E20: ='Forecast'!$E$13 | F20: ='Forecast'!$F$13 | G20: ='Forecast'!$G$13 | H20: ='Forecast'!$H$13 | I20: ='Forecast'!$I$13 | J20: ='Forecast'!$J$13 | K20: ='Forecast'!$K$13 | L20: ='Forecast'!$L$13
A21: Net income | B21: ='Forecast'!$B$19 | C21: ='Forecast'!$C$19 | D21: ='Forecast'!$D$19 | E21: ='Forecast'!$E$19 | F21: ='Forecast'!$F$19 | G21: ='Forecast'!$G$19 | H21: ='Forecast'!$H$19 | I21: ='Forecast'!$I$19 | J21: ='Forecast'!$J$19 | K21: ='Forecast'!$K$19 | L21: ='Forecast'!$L$19
A22: Free cash flow | B22: ='Forecast'!$B$40 | C22: ='Forecast'!$C$40 | D22: ='Forecast'!$D$40 | E22: ='Forecast'!$E$40 | F22: ='Forecast'!$F$40 | G22: ='Forecast'!$G$40 | H22: ='Forecast'!$H$40 | I22: ='Forecast'!$I$40 | J22: ='Forecast'!$J$40 | K22: ='Forecast'!$K$40 | L22: ='Forecast'!$L$40
A23: EBITDA margin | B23: =IFERROR('Forecast'!$B$13/'Forecast'!$B$12,"") | C23: =IFERROR('Forecast'!$C$13/'Forecast'!$C$12,"") | D23: =IFERROR('Forecast'!$D$13/'Forecast'!$D$12,"") | E23: =IFERROR('Forecast'!$E$13/'Forecast'!$E$12,"") | F23: =IFERROR('Forecast'!$F$13/'Forecast'!$F$12,"") | G23: =IFERROR('Forecast'!$G$13/'Forecast'!$G$12,"") | H23: =IFERROR('Forecast'!$H$13/'Forecast'!$H$12,"") | I23: =IFERROR('Forecast'!$I$13/'Forecast'!$I$12,"") | J23: =IFERROR('Forecast'!$J$13/'Forecast'!$J$12,"") | K23: =IFERROR('Forecast'!$K$13/'Forecast'!$K$12,"") | L23: =IFERROR('Forecast'!$L$13/'Forecast'!$L$12,"")
A24: EBIT margin | B24: =IFERROR('Forecast'!$B$15/'Forecast'!$B$12,"") | C24: =IFERROR('Forecast'!$C$15/'Forecast'!$C$12,"") | D24: =IFERROR('Forecast'!$D$15/'Forecast'!$D$12,"") | E24: =IFERROR('Forecast'!$E$15/'Forecast'!$E$12,"") | F24: =IFERROR('Forecast'!$F$15/'Forecast'!$F$12,"") | G24: =IFERROR('Forecast'!$G$15/'Forecast'!$G$12,"") | H24: =IFERROR('Forecast'!$H$15/'Forecast'!$H$12,"") | I24: =IFERROR('Forecast'!$I$15/'Forecast'!$I$12,"") | J24: =IFERROR('Forecast'!$J$15/'Forecast'!$J$12,"") | K24: =IFERROR('Forecast'!$K$15/'Forecast'!$K$12,"") | L24: =IFERROR('Forecast'!$L$15/'Forecast'!$L$12,"")
A25: Net margin | B25: =IFERROR('Forecast'!$B$19/'Forecast'!$B$12,"") | C25: =IFERROR('Forecast'!$C$19/'Forecast'!$C$12,"") | D25: =IFERROR('Forecast'!$D$19/'Forecast'!$D$12,"") | E25: =IFERROR('Forecast'!$E$19/'Forecast'!$E$12,"") | F25: =IFERROR('Forecast'!$F$19/'Forecast'!$F$12,"") | G25: =IFERROR('Forecast'!$G$19/'Forecast'!$G$12,"") | H25: =IFERROR('Forecast'!$H$19/'Forecast'!$H$12,"") | I25: =IFERROR('Forecast'!$I$19/'Forecast'!$I$12,"") | J25: =IFERROR('Forecast'!$J$19/'Forecast'!$J$12,"") | K25: =IFERROR('Forecast'!$K$19/'Forecast'!$K$12,"") | L25: =IFERROR('Forecast'!$L$19/'Forecast'!$L$12,"")

Sheet Methodology
A1: FORECAST METHODOLOGY
A2: How this model works -- and how to audit and update it
A3: Institutional Forecasting Engine - v2.0
A5: Dashboard | B5: Methodology | C5: Historical | D5: Assumptions | E5: Forecast | F5: Bridge | G5: Diagnostics
A7: Design philosophy
A8: This workbook prioritises, in strict order: TRANSPARENCY, CLARITY, AUDITABILITY and USABILITY -- ahead of sophistication, automation and flexibility. If a forecast number would require tracing through several layers, or a formula would need a paragraph to explain, the design was reconsidered instead. Every forecast line is one short formula driven by one assumption.
A9: Two layers: historical = input, forecast = output
A10: HISTORICAL (the Historical sheet) is the ACTUAL layer: every figure -- including the subtotals (gross profit, EBITDA, EBIT, net income, total assets, total liabilities) -- is a hard-coded blue input, pasted from the filings. Nothing on that sheet is reconstructed by a formula except explicit audit checks.
A11: FORECAST (the Forecast sheet) is the OUTPUT layer: every figure is a formula. The two are never mixed, and they are shaded differently (blue 'Actual' headers vs green 'Forecast' headers) so they can never be confused.
A12: Colour code: blue = input - black = formula - green = key output - red = warning.
A13: The dynamic timeline (forecasts begin after the last reported year)
A14: The model counts the reported years on the Historical sheet and derives the last actual year automatically; the forecast begins the very next year. Paste in another year of actuals and the forecast shifts forward on its own -- no other edits, no overlap with a year that is now reported.
A15: First fiscal year | C15: =FirstYear | E15: (input on the Historical sheet)
A16: Last actual year | C16: =LastActual | E16: auto-detected = FirstYear + reported years - 1
A17: Forecast window | C17: ="FY"&(LastActual+1)&" to FY"&(LastActual+10)
A19: One driver per line
A20: Each forecast line reads exactly one assumption from the Assumptions sheet. There is no scenario selector and no method engine -- to change the forecast you change a driver, and the link is a single visible hop.
A21: Driver | D21: Drives this forecast line
A22: Revenue growth | D22: Revenue = prior revenue x (1 + growth)
A23: EBITDA margin | D23: EBITDA = revenue x EBITDA margin
A24: D&A (% of revenue) | D24: D&A = revenue x D&A%
A25: Capex (% of revenue) | D25: Capex = revenue x capex%
A26: Net working capital (% of revenue) | D26: Net working capital = revenue x NWC%
A27: Net interest rate (on opening net debt) | D27: Net interest = rate x opening net debt (no circularity)
A28: Tax rate | D28: Tax = tax rate x pre-tax income
A29: Dividend payout | D29: Dividends = payout x max(0, net income)
A30: Net new debt raised | D30: Debt = prior debt + net new debt
A32: The forecast, written out (t = each forecast year)
A33: Revenue = prior revenue x (1 + revenue growth)
A34: EBITDA = revenue x EBITDA margin
A35: D&A = revenue x D&A% EBIT = EBITDA - D&A
A36: Net interest = net interest rate x OPENING net debt (so there is no circularity)
A37: Pre-tax = EBIT - net interest Tax = tax rate x pre-tax Net income = pre-tax - tax
A38: Net working capital = revenue x NWC%
A39: Net PP&E = prior net PP&E + capex - D&A Capex = revenue x capex%
A40: Other assets / other liabilities = held flat at the last actual
A41: Total debt = prior debt + net new debt
A42: Equity = prior equity + net income - dividends Dividends = payout x max(0, net income)
A43: Cash = prior cash + CFO + CFI + CFF (the residual -- no plug)
... A51: Net interest uses opening balances (an institutional norm that keeps the model circularity-free). Other assets and other liabilities are held flat -- adjust on the Forecast sheet if they are material to your company. This is an analytical tool to support judgement, not investment advice.

Sheet Historical
A1: HISTORICAL FINANCIAL STATEMENTS (ACTUAL)
A2: Reported results -- every figure is a hard-coded input pasted from the filings
A3: Institutional Forecasting Engine - v2.0
A5: Dashboard | B5: Methodology | C5: Historical | D5: Assumptions | E5: Forecast | F5: Bridge | G5: Diagnostics
A7: All figures in USD millions unless stated. Colour code: blue = input - black = formula - green = key output - red = warning.
A8: Timeline - auto-detected (the forecast begins the year after the last actual)
A9: First fiscal year | C9: 2015 | E9: Type the first reported year here (e.g. 2015). Everything else keys off it.
A10: Reported years detected | C10: =COUNT('Historical'!$B$17:$P$17)
A11: Last actual year | C11: =FirstYear+'Historical'!$C$10-1
A12: Forecast begins (next year) | C12: =LastActual+1 | E12: The Forecast sheet starts here automatically.
A14: Fiscal year | B14: =FirstYear | C14: =$B$14+1 | D14: =$C$14+1 | E14: =$D$14+1 | F14: =$E$14+1 | G14: =$F$14+1 | H14: =$G$14+1 | I14: =$H$14+1 | J14: =$I$14+1 | K14: =$J$14+1 | L14: =$K$14+1 | M14: =$L$14+1 | N14: =$M$14+1 | O14: =$N$14+1 | P14: =$O$14+1
A15: Status | B15: =IF($B$14<=LastActual,"Actual","- spare -") | C15: =IF($C$14<=LastActual,"Actual","- spare -") | D15: =IF($D$14<=LastActual,"Actual","- spare -") | E15: =IF($E$14<=LastActual,"Actual","- spare -") | F15: =IF($F$14<=LastActual,"Actual","- spare -") | G15: =IF($G$14<=LastActual,"Actual","- spare -") | H15: =IF($H$14<=LastActual,"Actual","- spare -") | I15: =IF($I$14<=LastActual,"Actual","- spare -") | J15: =IF($J$14<=LastActual,"Actual","- spare -") | K15: =IF($K$14<=LastActual,"Actual","- spare -") | L15: =IF($L$14<=LastActual,"Actual","- spare -") | M15: =IF($M$14<=LastActual,"Actual","- spare -") | N15: =IF($N$14<=LastActual,"Actual","- spare -") | O15: =IF($O$14<=LastActual,"Actual","- spare -") | P15: =IF($P$14<=LastActual,"Actual","- spare -")
A16: Income Statement
A17: Revenue
A18: Cost of goods sold
A19: Gross profit
A20: Operating expenses (ex-D&A)
A21: EBITDA
A22: Depreciation & amortisation
A23: EBIT
A24: Net interest expense
A25: Pre-tax income
A26: Tax expense
A27: Net income
... A38: Shareholders' equity
A39: Total liabilities & equity | B39: ='Historical'!$B$37+'Historical'!$B$38 | C39: ='Historical'!$C$37+'Historical'!$C$38 | D39: ='Historical'!$D$37+'Historical'!$D$38 | E39: ='Historical'!$E$37+'Historical'!$E$38 | F39: ='Historical'!$F$37+'Historical'!$F$38 | G39: ='Historical'!$G$37+'Historical'!$G$38 | H39: ='Historical'!$H$37+'Historical'!$H$38 | I39: ='Historical'!$I$37+'Historical'!$I$38 | J39: ='Historical'!$J$37+'Historical'!$J$38 | K39: ='Historical'!$K$37+'Historical'!$K$38 | L39: ='Historical'!$L$37+'Historical'!$L$38 | M39: ='Historical'!$M$37+'Historical'!$M$38 | N39: ='Historical'!$N$37+'Historical'!$N$38 | O39: ='Historical'!$O$37+'Historical'!$O$38 | P39: ='Historical'!$P$37+'Historical'!$P$38
A40: Cash Flow Statement
A41: Operating cash flow
A42: Capital expenditure
A43: Free cash flow
A44: Audit Checks (every value should be 0 -- they confirm the pasted statements tie)
A45: Balance check (assets - (liabilities + equity)) | B45: ='Historical'!$B$33-'Historical'!$B$39 | C45: ='Historical'!$C$33-'Historical'!$C$39 | D45: ='Historical'!$D$33-'Historical'!$D$39 | E45: ='Historical'!$E$33-'Historical'!$E$39 | F45: ='Historical'!$F$33-'Historical'!$F$39 | G45: ='Historical'!$G$33-'Historical'!$G$39 | H45: ='Historical'!$H$33-'Historical'!$H$39 | I45: ='Historical'!$I$33-'Historical'!$I$39 | J45: ='Historical'!$J$33-'Historical'!$J$39 | K45: ='Historical'!$K$33-'Historical'!$K$39 | L45: ='Historical'!$L$33-'Historical'!$L$39 | M45: ='Historical'!$M$33-'Historical'!$M$39 | N45: ='Historical'!$N$33-'Historical'!$N$39 | O45: ='Historical'!$O$33-'Historical'!$O$39 | P45: ='Historical'!$P$33-'Historical'!$P$39
A46: Asset build check (components - total assets) | B46: ='Historical'!$B$29+'Historical'!$B$30+'Historical'!$B$31+'Historical'!$B$32-'Historical'!$B$33 | C46: ='Historical'!$C$29+'Historical'!$C$30+'Historical'!$C$31+'Historical'!$C$32-'Historical'!$C$33 | D46: ='Historical'!$D$29+'Historical'!$D$30+'Historical'!$D$31+'Historical'!$D$32-'Historical'!$D$33 | E46: ='Historical'!$E$29+'Historical'!$E$30+'Historical'!$E$31+'Historical'!$E$32-'Historical'!$E$33 | F46: ='Historical'!$F$29+'Historical'!$F$30+'Historical'!$F$31+'Historical'!$F$32-'Historical'!$F$33 | G46: ='Historical'!$G$29+'Historical'!$G$30+'Historical'!$G$31+'Historical'!$G$32-'Historical'!$G$33 | H46: ='Historical'!$H$29+'Historical'!$H$30+'Historical'!$H$31+'Historical'!$H$32-'Historical'!$H$33 | I46: ='Historical'!$I$29+'Historical'!$I$30+'Historical'!$I$31+'Historical'!$I$32-'Historical'!$I$33 | J46: ='Historical'!$J$29+'Historical'!$J$30+'Historical'!$J$31+'Historical'!$J$32-'Historical'!$J$33 | K46: ='Historical'!$K$29+'Historical'!$K$30+'Historical'!$K$31+'Historical'!$K$32-'Historical'!$K$33 | L46: ='Historical'!$L$29+'Historical'!$L$30+'Historical'!$L$31+'Historical'!$L$32-'Historical'!$L$33 | M46: ='Historical'!$M$29+'Historical'!$M$30+'Historical'!$M$31+'Historical'!$M$32-'Historical'!$M$33 | N46: ='Historical'!$N$29+'Historical'!$N$30+'Historical'!$N$31+'Historical'!$N$32-'Historical'!$N$33 | O46: ='Historical'!$O$29+'Historical'!$O$30+'Historical'!$O$31+'Historical'!$O$32-'Historical'!$O$33 | P46: ='Historical'!$P$29+'Historical'!$P$30+'Historical'!$P$31+'Historical'!$P$32-'Historical'!$P$33
A47: Liability build check (components - total liabilities) | B47: ='Historical'!$B$35+'Historical'!$B$36-'Historical'!$B$37 | C47: ='Historical'!$C$35+'Historical'!$C$36-'Historical'!$C$37 | D47: ='Historical'!$D$35+'Historical'!$D$36-'Historical'!$D$37 | E47: ='Historical'!$E$35+'Historical'!$E$36-'Historical'!$E$37 | F47: ='Historical'!$F$35+'Historical'!$F$36-'Historical'!$F$37 | G47: ='Historical'!$G$35+'Historical'!$G$36-'Historical'!$G$37 | H47: ='Historical'!$H$35+'Historical'!$H$36-'Historical'!$H$37 | I47: ='Historical'!$I$35+'Historical'!$I$36-'Historical'!$I$37 | J47: ='Historical'!$J$35+'Historical'!$J$36-'Historical'!$J$37 | K47: ='Historical'!$K$35+'Historical'!$K$36-'Historical'!$K$37 | L47: ='Historical'!$L$35+'Historical'!$L$36-'Historical'!$L$37 | M47: ='Historical'!$M$35+'Historical'!$M$36-'Historical'!$M$37 | N47: ='Historical'!$N$35+'Historical'!$N$36-'Historical'!$N$37 | O47: ='Historical'!$O$35+'Historical'!$O$36-'Historical'!$O$37 | P47: ='Historical'!$P$35+'Historical'!$P$36-'Historical'!$P$37

Sheet Assumptions
A1: FORECAST ASSUMPTIONS (DRIVERS)
A2: One editable input per line -- the Forecast sheet reads these cells directly
A3: Institutional Forecasting Engine - v2.0
A5: Dashboard | B5: Methodology | C5: Historical | D5: Assumptions | E5: Forecast | F5: Bridge | G5: Diagnostics
A7: All figures in USD millions unless stated. Colour code: blue = input - black = formula - green = key output - red = warning.
A9: Forecast Drivers
A10: Driver | B10: =LastActual+1 | C10: =$B$10+1 | D10: =$C$10+1 | E10: =$D$10+1 | F10: =$E$10+1 | G10: =$F$10+1 | H10: =$G$10+1 | I10: =$H$10+1 | J10: =$I$10+1 | K10: =$J$10+1 | L10: Drives (what this assumption feeds)
A11: Revenue growth | L11: Revenue = prior revenue x (1 + growth)
A12: EBITDA margin | L12: EBITDA = revenue x EBITDA margin
A13: D&A (% of revenue) | L13: D&A = revenue x D&A%
A14: Capex (% of revenue) | L14: Capex = revenue x capex%
A15: Net working capital (% of revenue) | L15: Net working capital = revenue x NWC%
A16: Net interest rate (on opening net debt) | L16: Net interest = rate x opening net debt (no circularity)
A17: Tax rate | L17: Tax = tax rate x pre-tax income
A18: Dividend payout | L18: Dividends = payout x max(0, net income)
A19: Net new debt raised | L19: Debt = prior debt + net new debt
A21: How to use: edit any cell. Each driver maps to exactly one forecast line (see the Drives column and the Methodology sheet). To change a single year, just overwrite that year's cell.

Sheet Forecast
A1: INTEGRATED FORECAST MODEL (FORECAST)
A2: One driver per line; reconciles to the cent with no plug and no circularity
A3: Institutional Forecasting Engine - v2.0
A5: Dashboard | B5: Methodology | C5: Historical | D5: Assumptions | E5: Forecast | F5: Bridge | G5: Diagnostics
A7: ="Forecast window: FY"&(LastActual+1)&" through FY"&(LastActual+10) | G7: All figures in USD millions unless stated. Colour code: blue = input - black = formula - green = key output - red = warning.
A9: Line item | B9: =LastActual | C9: =$B$9+1 | D9: =$C$9+1 | E9: =$D$9+1 | F9: =$E$9+1 | G9: =$F$9+1 | H9: =$G$9+1 | I9: =$H$9+1 | J9: =$I$9+1 | K9: =$J$9+1 | L9: =$K$9+1
B10: Actual | C10: Forecast | D10: Forecast | E10: Forecast | F10: Forecast | G10: Forecast | H10: Forecast | I10: Forecast | J10: Forecast | K10: Forecast | L10: Forecast
A11: Income Statement
A12: Revenue | B12: =IFERROR(INDEX('Historical'!$B$17:$P$17,'Historical'!$C$10),0) | C12: ='Forecast'!$B$12*(1+'Assumptions'!$B$11) | D12: ='Forecast'!$C$12*(1+'Assumptions'!$C$11) | E12: ='Forecast'!$D$12*(1+'Assumptions'!$D$11) | F12: ='Forecast'!$E$12*(1+'Assumptions'!$E$11) | G12: ='Forecast'!$F$12*(1+'Assumptions'!$F$11) | H12: ='Forecast'!$G$12*(1+'Assumptions'!$G$11) | I12: ='Forecast'!$H$12*(1+'Assumptions'!$H$11) | J12: ='Forecast'!$I$12*(1+'Assumptions'!$I$11) | K12: ='Forecast'!$J$12*(1+'Assumptions'!$J$11) | L12: ='Forecast'!$K$12*(1+'Assumptions'!$K$11)
A13: EBITDA | B13: =IFERROR(INDEX('Historical'!$B$21:$P$21,'Historical'!$C$10),0) | C13: ='Forecast'!$C$12*'Assumptions'!$B$12 | D13: ='Forecast'!$D$12*'Assumptions'!$C$12 | E13: ='Forecast'!$E$12*'Assumptions'!$D$12 | F13: ='Forecast'!$F$12*'Assumptions'!$E$12 | G13: ='Forecast'!$G$12*'Assumptions'!$F$12 | H13: ='Forecast'!$H$12*'Assumptions'!$G$12 | I13: ='Forecast'!$I$12*'Assumptions'!$H$12 | J13: ='Forecast'!$J$12*'Assumptions'!$I$12 | K13: ='Forecast'!$K$12*'Assumptions'!$J$12 | L13: ='Forecast'!$L$12*'Assumptions'!$K$12
A14: Depreciation & amortisation | B14: =IFERROR(INDEX('Historical'!$B$22:$P$22,'Historical'!$C$10),0) | C14: ='Forecast'!$C$12*'Assumptions'!$B$13 | D14: ='Forecast'!$D$12*'Assumptions'!$C$13 | E14: ='Forecast'!$E$12*'Assumptions'!$D$13 | F14: ='Forecast'!$F$12*'Assumptions'!$E$13 | G14: ='Forecast'!$G$12*'Assumptions'!$F$13 | H14: ='Forecast'!$H$12*'Assumptions'!$G$13 | I14: ='Forecast'!$I$12*'Assumptions'!$H$13 | J14: ='Forecast'!$J$12*'Assumptions'!$I$13 | K14: ='Forecast'!$K$12*'Assumptions'!$J$13 | L14: ='Forecast'!$L$12*'Assumptions'!$K$13
A15: EBIT | B15: =IFERROR(INDEX('Historical'!$B$23:$P$23,'Historical'!$C$10),0) | C15: ='Forecast'!$C$13-'Forecast'!$C$14 | D15: ='Forecast'!$D$13-'Forecast'!$D$14 | E15: ='Forecast'!$E$13-'Forecast'!$E$14 | F15: ='Forecast'!$F$13-'Forecast'!$F$14 | G15: ='Forecast'!$G$13-'Forecast'!$G$14 | H15: ='Forecast'!$H$13-'Forecast'!$H$14 | I15: ='Forecast'!$I$13-'Forecast'!$I$14 | J15: ='Forecast'!$J$13-'Forecast'!$J$14 | K15: ='Forecast'!$K$13-'Forecast'!$K$14 | L15: ='Forecast'!$L$13-'Forecast'!$L$14
A16: Net interest expense | B16: =IFERROR(INDEX('Historical'!$B$24:$P$24,'Historical'!$C$10),0) | C16: ='Assumptions'!$B$16*'Forecast'!$B$42 | D16: ='Assumptions'!$C$16*'Forecast'!$C$42 | E16: ='Assumptions'!$D$16*'Forecast'!$D$42 | F16: ='Assumptions'!$E$16*'Forecast'!$E$42 | G16: ='Assumptions'!$F$16*'Forecast'!$F$42 | H16: ='Assumptions'!$G$16*'Forecast'!$G$42 | I16: ='Assumptions'!$H$16*'Forecast'!$H$42 | J16: ='Assumptions'!$I$16*'Forecast'!$I$42 | K16: ='Assumptions'!$J$16*'Forecast'!$J$42 | L16: ='Assumptions'!$K$16*'Forecast'!$K$42
A17: Pre-tax income | B17: =IFERROR(INDEX('Historical'!$B$25:$P$25,'Historical'!$C$10),0) | C17: ='Forecast'!$C$15-'Forecast'!$C$16 | D17: ='Forecast'!$D$15-'Forecast'!$D$16 | E17: ='Forecast'!$E$15-'Forecast'!$E$16 | F17: ='Forecast'!$F$15-'Forecast'!$F$16 | G17: ='Forecast'!$G$15-'Forecast'!$G$16 | H17: ='Forecast'!$H$15-'Forecast'!$H$16 | I17: ='Forecast'!$I$15-'Forecast'!$I$16 | J17: ='Forecast'!$J$15-'Forecast'!$J$16 | K17: ='Forecast'!$K$15-'Forecast'!$K$16 | L17: ='Forecast'!$L$15-'Forecast'!$L$16
A18: Tax expense | B18: =IFERROR(INDEX('Historical'!$B$26:$P$26,'Historical'!$C$10),0) | C18: ='Assumptions'!$B$17*'Forecast'!$C$17 | D18: ='Assumptions'!$C$17*'Forecast'!$D$17 | E18: ='Assumptions'!$D$17*'Forecast'!$E$17 | F18: ='Assumptions'!$E$17*'Forecast'!$F$17 | G18: ='Assumptions'!$F$17*'Forecast'!$G$17 | H18: ='Assumptions'!$G$17*'Forecast'!$H$17 | I18: ='Assumptions'!$H$17*'Forecast'!$I$17 | J18: ='Assumptions'!$I$17*'Forecast'!$J$17 | K18: ='Assumptions'!$J$17*'Forecast'!$K$17 | L18: ='Assumptions'!$K$17*'Forecast'!$L$17
A19: Net income | B19: =IFERROR(INDEX('Historical'!$B$27:$P$27,'Historical'!$C$10),0) | C19: ='Forecast'!$C$17-'Forecast'!$C$18 | D19: ='Forecast'!$D$17-'Forecast'!$D$18 | E19: ='Forecast'!$E$17-'Forecast'!$E$18 | F19: ='Forecast'!$F$17-'Forecast'!$F$18 | G19: ='Forecast'!$G$17-'Forecast'!$G$18 | H19: ='Forecast'!$H$17-'Forecast'!$H$18 | I19: ='Forecast'!$I$17-'Forecast'!$I$18 | J19: ='Forecast'!$J$17-'Forecast'!$J$18 | K19: ='Forecast'!$K$17-'Forecast'!$K$18 | L19: ='Forecast'!$L$17-'Forecast'!$L$18
A20: Balance Sheet - Assets
A21: Cash & equivalents | B21: =IFERROR(INDEX('Historical'!$B$29:$P$29,'Historical'!$C$10),0) | C21: ='Forecast'!$B$21+'Forecast'!$C$35+'Forecast'!$C$37+'Forecast'!$C$39 | D21: ='Forecast'!$C$21+'Forecast'!$D$35+'Forecast'!$D$37+'Forecast'!$D$39 | E21: ='Forecast'!$D$21+'Forecast'!$E$35+'Forecast'!$E$37+'Forecast'!$E$39 | F21: ='Forecast'!$E$21+'Forecast'!$F$35+'Forecast'!$F$37+'Forecast'!$F$39 | G21: ='Forecast'!$F$21+'Forecast'!$G$35+'Forecast'!$G$37+'Forecast'!$G$39 | H21: ='Forecast'!$G$21+'Forecast'!$H$35+'Forecast'!$H$37+'Forecast'!$H$39 | I21: ='Forecast'!$H$21+'Forecast'!$I$35+'Forecast'!$I$37+'Forecast'!$I$39 | J21: ='Forecast'!$I$21+'Forecast'!$J$35+'Forecast'!$J$37+'Forecast'!$J$39 | K21: ='Forecast'!$J$21+'Forecast'!$K$35+'Forecast'!$K$37+'Forecast'!$K$39 | L21: ='Forecast'!$K$21+'Forecast'!$L$35+'Forecast'!$L$37+'Forecast'!$L$39
A22: Net working capital | B22: =IFERROR(INDEX('Historical'!$B$30:$P$30,'Historical'!$C$10),0) | C22: ='Assumptions'!$B$15*'Forecast'!$C$12 | D22: ='Assumptions'!$C$15*'Forecast'!$D$12 | E22: ='Assumptions'!$D$15*'Forecast'!$E$12 | F22: ='Assumptions'!$E$15*'Forecast'!$F$12 | G22: ='Assumptions'!$F$15*'Forecast'!$G$12 | H22: ='Assumptions'!$G$15*'Forecast'!$H$12 | I22: ='Assumptions'!$H$15*'Forecast'!$I$12 | J22: ='Assumptions'!$I$15*'Forecast'!$J$12 | K22: ='Assumptions'!$J$15*'Forecast'!$K$12 | L22: ='Assumptions'!$K$15*'Forecast'!$L$12
A23: Net PP&E | B23: =IFERROR(INDEX('Historical'!$B$31:$P$31,'Historical'!$C$10),0) | C23: ='Forecast'!$B$23+'Forecast'!$C$36-'Forecast'!$C$14 | D23: ='Forecast'!$C$23+'Forecast'!$D$36-'Forecast'!$D$14 | E23: ='Forecast'!$D$23+'Forecast'!$E$36-'Forecast'!$E$14 | F23: ='Forecast'!$E$23+'Forecast'!$F$36-'Forecast'!$F$14 | G23: ='Forecast'!$F$23+'Forecast'!$G$36-'Forecast'!$G$14 | H23: ='Forecast'!$G$23+'Forecast'!$H$36-'Forecast'!$H$14 | I23: ='Forecast'!$H$23+'Forecast'!$I$36-'Forecast'!$I$14 | J23: ='Forecast'!$I$23+'Forecast'!$J$36-'Forecast'!$J$14 | K23: ='Forecast'!$J$23+'Forecast'!$K$36-'Forecast'!$K$14 | L23: ='Forecast'!$K$23+'Forecast'!$L$36-'Forecast'!$L$14
A24: Other assets (held flat) | B24: =IFERROR(INDEX('Historical'!$B$32:$P$32,'Historical'!$C$10),0) | C24: ='Forecast'!$B$24 | D24: ='Forecast'!$C$24 | E24: ='Forecast'!$D$24 | F24: ='Forecast'!$E$24 | G24: ='Forecast'!$F$24 | H24: ='Forecast'!$G$24 | I24: ='Forecast'!$H$24 | J24: ='Forecast'!$I$24 | K24: ='Forecast'!$J$24 | L24: ='Forecast'!$K$24
A25: Total assets | B25: =IFERROR(INDEX('Historical'!$B$33:$P$33,'Historical'!$C$10),0) | C25: ='Forecast'!$C$21+'Forecast'!$C$22+'Forecast'!$C$23+'Forecast'!$C$24 | D25: ='Forecast'!$D$21+'Forecast'!$D$22+'Forecast'!$D$23+'Forecast'!$D$24 | E25: ='Forecast'!$E$21+'Forecast'!$E$22+'Forecast'!$E$23+'Forecast'!$E$24 | F25: ='Forecast'!$F$21+'Forecast'!$F$22+'Forecast'!$F$23+'Forecast'!$F$24 | G25: ='Forecast'!$G$21+'Forecast'!$G$22+'Forecast'!$G$23+'Forecast'!$G$24 | H25: ='Forecast'!$H$21+'Forecast'!$H$22+'Forecast'!$H$23+'Forecast'!$H$24 | I25: ='Forecast'!$I$21+'Forecast'!$I$22+'Forecast'!$I$23+'Forecast'!$I$24 | J25: ='Forecast'!$J$21+'Forecast'!$J$22+'Forecast'!$J$23+'Forecast'!$J$24 | K25: ='Forecast'!$K$21+'Forecast'!$K$22+'Forecast'!$K$23+'Forecast'!$K$24 | L25: ='Forecast'!$L$21+'Forecast'!$L$22+'Forecast'!$L$23+'Forecast'!$L$24
A26: Balance Sheet - Liabilities & Equity
A27: Total debt | B27: =IFERROR(INDEX('Historical'!$B$35:$P$35,'Historical'!$C$10),0) | C27: ='Forecast'!$B$27+'Assumptions'!$B$19 | D27: ='Forecast'!$C$27+'Assumptions'!$C$19 | E27: ='Forecast'!$D$27+'Assumptions'!$D$19 | F27: ='Forecast'!$E$27+'Assumptions'!$E$19 | G27: ='Forecast'!$F$27+'Assumptions'!$F$19 | H27: ='Forecast'!$G$27+'Assumptions'!$G$19 | I27: ='Forecast'!$H$27+'Assumptions'!$H$19 | J27: ='Forecast'!$I$27+'Assumptions'!$I$19 | K27: ='Forecast'!$J$27+'Assumptions'!$J$19 | L27: ='Forecast'!$K$27+'Assumptions'!$K$19
A28: Other liabilities (held flat) | B28: =IFERROR(INDEX('Historical'!$B$36:$P$36,'Historical'!$C$10),0) | C28: ='Forecast'!$B$28 | D28: ='Forecast'!$C$28 | E28: ='Forecast'!$D$28 | F28: ='Forecast'!$E$28 | G28: ='Forecast'!$F$28 | H28: ='Forecast'!$G$28 | I28: ='Forecast'!$H$28 | J28: ='Forecast'!$I$28 | K28: ='Forecast'!$J$28 | L28: ='Forecast'!$K$28
A29: Total liabilities | B29: =IFERROR(INDEX('Historical'!$B$37:$P$37,'Historical'!$C$10),0) | C29: ='Forecast'!$C$27+'Forecast'!$C$28 | D29: ='Forecast'!$D$27+'Forecast'!$D$28 | E29: ='Forecast'!$E$27+'Forecast'!$E$28 | F29: ='Forecast'!$F$27+'Forecast'!$F$28 | G29: ='Forecast'!$G$27+'Forecast'!$G$28 | H29: ='Forecast'!$H$27+'Forecast'!$H$28 | I29: ='Forecast'!$I$27+'Forecast'!$I$28 | J29: ='Forecast'!$J$27+'Forecast'!$J$28 | K29: ='Forecast'!$K$27+'Forecast'!$K$28 | L29: ='Forecast'!$L$27+'Forecast'!$L$28
A30: Shareholders' equity | B30: =IFERROR(INDEX('Historical'!$B$38:$P$38,'Historical'!$C$10),0) | C30: ='Forecast'!$B$30+'Forecast'!$C$19-'Forecast'!$C$38 | D30: ='Forecast'!$C$30+'Forecast'!$D$19-'Forecast'!$D$38 | E30: ='Forecast'!$D$30+'Forecast'!$E$19-'Forecast'!$E$38 | F30: ='Forecast'!$E$30+'Forecast'!$F$19-'Forecast'!$F$38 | G30: ='Forecast'!$F$30+'Forecast'!$G$19-'Forecast'!$G$38 | H30: ='Forecast'!$G$30+'Forecast'!$H$19-'Forecast'!$H$38 | I30: ='Forecast'!$H$30+'Forecast'!$I$19-'Forecast'!$I$38 | J30: ='Forecast'!$I$30+'Forecast'!$J$19-'Forecast'!$J$38 | K30: ='Forecast'!$J$30+'Forecast'!$K$19-'Forecast'!$K$38 | L30: ='Forecast'!$K$30+'Forecast'!$L$19-'Forecast'!$L$38
A31: Total liabilities & equity | B31: =IFERROR(INDEX('Historical'!$B$39:$P$39,'Historical'!$C$10),0) | C31: ='Forecast'!$C$29+'Forecast'!$C$30 | D31: ='Forecast'!$D$29+'Forecast'!$D$30 | E31: ='Forecast'!$E$29+'Forecast'!$E$30 | F31: ='Forecast'!$F$29+'Forecast'!$F$30 | G31: ='Forecast'!$G$29+'Forecast'!$G$30 | H31: ='Forecast'!$H$29+'Forecast'!$H$30 | I31: ='Forecast'!$I$29+'Forecast'!$I$30 | J31: ='Forecast'!$J$29+'Forecast'!$J$30 | K31: ='Forecast'!$K$29+'Forecast'!$K$30 | L31: ='Forecast'!$L$29+'Forecast'!$L$30
A32: Balance check (must be 0) | B32: 0 | C32: ='Forecast'!$C$25-'Forecast'!$C$31 | D32: ='Forecast'!$D$25-'Forecast'!$D$31 | E32: ='Forecast'!$E$25-'Forecast'!$E$31 | F32: ='Forecast'!$F$25-'Forecast'!$F$31 | G32: ='Forecast'!$G$25-'Forecast'!$G$31 | H32: ='Forecast'!$H$25-'Forecast'!$H$31 | I32: ='Forecast'!$I$25-'Forecast'!$I$31 | J32: ='Forecast'!$J$25-'Forecast'!$J$31 | K32: ='Forecast'!$K$25-'Forecast'!$K$31 | L32: ='Forecast'!$L$25-'Forecast'!$L$31
A33: Cash Flow
A34: (-) Increase in net working capital | B34: 0 | C34: ='Forecast'!$C$22-'Forecast'!$B$22 | D34: ='Forecast'!$D$22-'Forecast'!$C$22 | E34: ='Forecast'!$E$22-'Forecast'!$D$22 | F34: ='Forecast'!$F$22-'Forecast'!$E$22 | G34: ='Forecast'!$G$22-'Forecast'!$F$22 | H34: ='Forecast'!$H$22-'Forecast'!$G$22 | I34: ='Forecast'!$I$22-'Forecast'!$H$22 | J34: ='Forecast'!$J$22-'Forecast'!$I$22 | K34: ='Forecast'!$K$22-'Forecast'!$J$22 | L34: ='Forecast'!$L$22-'Forecast'!$K$22
A35: Operating cash flow | B35: =IFERROR(INDEX('Historical'!$B$41:$P$41,'Historical'!$C$10),0) | C35: ='Forecast'!$C$19+'Forecast'!$C$14-'Forecast'!$C$34 | D35: ='Forecast'!$D$19+'Forecast'!$D$14-'Forecast'!$D$34 | E35: ='Forecast'!$E$19+'Forecast'!$E$14-'Forecast'!$E$34 | F35: ='Forecast'!$F$19+'Forecast'!$F$14-'Forecast'!$F$34 | G35: ='Forecast'!$G$19+'Forecast'!$G$14-'Forecast'!$G$34 | H35: ='Forecast'!$H$19+'Forecast'!$H$14-'Forecast'!$H$34 | I35: ='Forecast'!$I$19+'Forecast'!$I$14-'Forecast'!$I$34 | J35: ='Forecast'!$J$19+'Forecast'!$J$14-'Forecast'!$J$34 | K35: ='Forecast'!$K$19+'Forecast'!$K$14-'Forecast'!$K$34 | L35: ='Forecast'!$L$19+'Forecast'!$L$14-'Forecast'!$L$34
A36: Capital expenditure | B36: =IFERROR(INDEX('Historical'!$B$42:$P$42,'Historical'!$C$10),0) | C36: ='Assumptions'!$B$14*'Forecast'!$C$12 | D36: ='Assumptions'!$C$14*'Forecast'!$D$12 | E36: ='Assumptions'!$D$14*'Forecast'!$E$12 | F36: ='Assumptions'!$E$14*'Forecast'!$F$12 | G36: ='Assumptions'!$F$14*'Forecast'!$G$12 | H36: ='Assumptions'!$G$14*'Forecast'!$H$12 | I36: ='Assumptions'!$H$14*'Forecast'!$I$12 | J36: ='Assumptions'!$I$14*'Forecast'!$J$12 | K36: ='Assumptions'!$J$14*'Forecast'!$K$12 | L36: ='Assumptions'!$K$14*'Forecast'!$L$12
A37: Investing cash flow | B37: 0 | C37: =-'Forecast'!$C$36-('Forecast'!$C$24-'Forecast'!$B$24) | D37: =-'Forecast'!$D$36-('Forecast'!$D$24-'Forecast'!$C$24) | E37: =-'Forecast'!$E$36-('Forecast'!$E$24-'Forecast'!$D$24) | F37: =-'Forecast'!$F$36-('Forecast'!$F$24-'Forecast'!$E$24) | G37: =-'Forecast'!$G$36-('Forecast'!$G$24-'Forecast'!$F$24) | H37: =-'Forecast'!$H$36-('Forecast'!$H$24-'Forecast'!$G$24) | I37: =-'Forecast'!$I$36-('Forecast'!$I$24-'Forecast'!$H$24) | J37: =-'Forecast'!$J$36-('Forecast'!$J$24-'Forecast'!$I$24) | K37: =-'Forecast'!$K$36-('Forecast'!$K$24-'Forecast'!$J$24) | L37: =-'Forecast'!$L$36-('Forecast'!$L$24-'Forecast'!$K$24)
A38: Dividends paid | B38: 0 | C38: ='Assumptions'!$B$18*MAX(0,'Forecast'!$C$19) | D38: ='Assumptions'!$C$18*MAX(0,'Forecast'!$D$19) | E38: ='Assumptions'!$D$18*MAX(0,'Forecast'!$E$19) | F38: ='Assumptions'!$E$18*MAX(0,'Forecast'!$F$19) | G38: ='Assumptions'!$F$18*MAX(0,'Forecast'!$G$19) | H38: ='Assumptions'!$G$18*MAX(0,'Forecast'!$H$19) | I38: ='Assumptions'!$H$18*MAX(0,'Forecast'!$I$19) | J38: ='Assumptions'!$I$18*MAX(0,'Forecast'!$J$19) | K38: ='Assumptions'!$J$18*MAX(0,'Forecast'!$K$19) | L38: ='Assumptions'!$K$18*MAX(0,'Forecast'!$L$19)
A39: Financing cash flow | B39: 0 | C39: ='Assumptions'!$B$19-'Forecast'!$C$38 | D39: ='Assumptions'!$C$19-'Forecast'!$D$38 | E39: ='Assumptions'!$D$19-'Forecast'!$E$38 | F39: ='Assumptions'!$E$19-'Forecast'!$F$38 | G39: ='Assumptions'!$F$19-'Forecast'!$G$38 | H39: ='Assumptions'!$G$19-'Forecast'!$H$38 | I39: ='Assumptions'!$H$19-'Forecast'!$I$38 | J39: ='Assumptions'!$I$19-'Forecast'!$J$38 | K39: ='Assumptions'!$J$19-'Forecast'!$K$38 | L39: ='Assumptions'!$K$19-'Forecast'!$L$38
A40: Free cash flow | B40: =IFERROR(INDEX('Historical'!$B$43:$P$43,'Historical'!$C$10),0) | C40: ='Forecast'!$C$35-'Forecast'!$C$36 | D40: ='Forecast'!$D$35-'Forecast'!$D$36 | E40: ='Forecast'!$E$35-'Forecast'!$E$36 | F40: ='Forecast'!$F$35-'Forecast'!$F$36 | G40: ='Forecast'!$G$35-'Forecast'!$G$36 | H40: ='Forecast'!$H$35-'Forecast'!$H$36 | I40: ='Forecast'!$I$35-'Forecast'!$I$36 | J40: ='Forecast'!$J$35-'Forecast'!$J$36 | K40: ='Forecast'!$K$35-'Forecast'!$K$36 | L40: ='Forecast'!$L$35-'Forecast'!$L$36
A41: Memo
A42: Net debt (debt - cash) | B42: ='Forecast'!$B$27-'Forecast'!$B$21 | C42: ='Forecast'!$C$27-'Forecast'!$C$21 | D42: ='Forecast'!$D$27-'Forecast'!$D$21 | E42: ='Forecast'!$E$27-'Forecast'!$E$21 | F42: ='Forecast'!$F$27-'Forecast'!$F$21 | G42: ='Forecast'!$G$27-'Forecast'!$G$21 | H42: ='Forecast'!$H$27-'Forecast'!$H$21 | I42: ='Forecast'!$I$27-'Forecast'!$I$21 | J42: ='Forecast'!$J$27-'Forecast'!$J$21 | K42: ='Forecast'!$K$27-'Forecast'!$K$21 | L42: ='Forecast'!$L$27-'Forecast'!$L$21

Sheet Bridge
A1: FORECAST BRIDGE
A2: Why revenue, EBITDA and net income change each year -- exact effect decomposition
A3: Institutional Forecasting Engine - v2.0
A5: Dashboard | B5: Methodology | C5: Historical | D5: Assumptions | E5: Forecast | F5: Bridge | G5: Diagnostics
A7: All figures in USD millions unless stated. Colour code: blue = input - black = formula - green = key output - red = warning.
A9: Effect | B9: =LastActual+1 | C9: =$B$9+1 | D9: =$C$9+1 | E9: =$D$9+1 | F9: =$E$9+1 | G9: =$F$9+1 | H9: =$G$9+1 | I9: =$H$9+1 | J9: =$I$9+1 | K9: =$J$9+1
A10: Revenue Bridge
A11: Prior-year revenue | B11: ='Forecast'!$B$12 | C11: ='Forecast'!$C$12 | D11: ='Forecast'!$D$12 | E11: ='Forecast'!$E$12 | F11: ='Forecast'!$F$12 | G11: ='Forecast'!$G$12 | H11: ='Forecast'!$H$12 | I11: ='Forecast'!$I$12 | J11: ='Forecast'!$J$12 | K11: ='Forecast'!$K$12
A12: (+) Growth effect | B12: ='Forecast'!$C$12-'Forecast'!$B$12 | C12: ='Forecast'!$D$12-'Forecast'!$C$12 | D12: ='Forecast'!$E$12-'Forecast'!$D$12 | E12: ='Forecast'!$F$12-'Forecast'!$E$12 | F12: ='Forecast'!$G$12-'Forecast'!$F$12 | G12: ='Forecast'!$H$12-'Forecast'!$G$12 | H12: ='Forecast'!$I$12-'Forecast'!$H$12 | I12: ='Forecast'!$J$12-'Forecast'!$I$12 | J12: ='Forecast'!$K$12-'Forecast'!$J$12 | K12: ='Forecast'!$L$12-'Forecast'!$K$12
A13: (=) Current revenue | B13: ='Forecast'!$C$12 | C13: ='Forecast'!$D$12 | D13: ='Forecast'!$E$12 | E13: ='Forecast'!$F$12 | F13: ='Forecast'!$G$12 | G13: ='Forecast'!$H$12 | H13: ='Forecast'!$I$12 | I13: ='Forecast'!$J$12 | J13: ='Forecast'!$K$12 | K13: ='Forecast'!$L$12
A14: Check (effects - actual change) | B14: =($B$12)-('Forecast'!$C$12-'Forecast'!$B$12) | C14: =($C$12)-('Forecast'!$D$12-'Forecast'!$C$12) | D14: =($D$12)-('Forecast'!$E$12-'Forecast'!$D$12) | E14: =($E$12)-('Forecast'!$F$12-'Forecast'!$E$12) | F14: =($F$12)-('Forecast'!$G$12-'Forecast'!$F$12) | G14: =($G$12)-('Forecast'!$H$12-'Forecast'!$G$12) | H14: =($H$12)-('Forecast'!$I$12-'Forecast'!$H$12) | I14: =($I$12)-('Forecast'!$J$12-'Forecast'!$I$12) | J14: =($J$12)-('Forecast'!$K$12-'Forecast'!$J$12) | K14: =($K$12)-('Forecast'!$L$12-'Forecast'!$K$12)
A16: EBITDA Bridge
A17: Prior-year EBITDA | B17: ='Forecast'!$B$13 | C17: ='Forecast'!$C$13 | D17: ='Forecast'!$D$13 | E17: ='Forecast'!$E$13 | F17: ='Forecast'!$F$13 | G17: ='Forecast'!$G$13 | H17: ='Forecast'!$H$13 | I17: ='Forecast'!$I$13 | J17: ='Forecast'!$J$13 | K17: ='Forecast'!$K$13
A18: (+) Revenue (volume) effect | B18: =('Forecast'!$C$12-'Forecast'!$B$12)*IFERROR('Forecast'!$B$13/'Forecast'!$B$12,0) | C18: =('Forecast'!$D$12-'Forecast'!$C$12)*IFERROR('Forecast'!$C$13/'Forecast'!$C$12,0) | D18: =('Forecast'!$E$12-'Forecast'!$D$12)*IFERROR('Forecast'!$D$13/'Forecast'!$D$12,0) | E18: =('Forecast'!$F$12-'Forecast'!$E$12)*IFERROR('Forecast'!$E$13/'Forecast'!$E$12,0) | F18: =('Forecast'!$G$12-'Forecast'!$F$12)*IFERROR('Forecast'!$F$13/'Forecast'!$F$12,0) | G18: =('Forecast'!$H$12-'Forecast'!$G$12)*IFERROR('Forecast'!$G$13/'Forecast'!$G$12,0) | H18: =('Forecast'!$I$12-'Forecast'!$H$12)*IFERROR('Forecast'!$H$13/'Forecast'!$H$12,0) | I18: =('Forecast'!$J$12-'Forecast'!$I$12)*IFERROR('Forecast'!$I$13/'Forecast'!$I$12,0) | J18: =('Forecast'!$K$12-'Forecast'!$J$12)*IFERROR('Forecast'!$J$13/'Forecast'!$J$12,0) | K18: =('Forecast'!$L$12-'Forecast'!$K$12)*IFERROR('Forecast'!$K$13/'Forecast'!$K$12,0)
A19: (+) Margin effect | B19: =(IFERROR('Forecast'!$C$13/'Forecast'!$C$12,0)-IFERROR('Forecast'!$B$13/'Forecast'!$B$12,0))*'Forecast'!$C$12 | C19: =(IFERROR('Forecast'!$D$13/'Forecast'!$D$12,0)-IFERROR('Forecast'!$C$13/'Forecast'!$C$12,0))*'Forecast'!$D$12 | D19: =(IFERROR('Forecast'!$E$13/'Forecast'!$E$12,0)-IFERROR('Forecast'!$D$13/'Forecast'!$D$12,0))*'Forecast'!$E$12 | E19: =(IFERROR('Forecast'!$F$13/'Forecast'!$F$12,0)-IFERROR('Forecast'!$E$13/'Forecast'!$E$12,0))*'Forecast'!$F$12 | F19: =(IFERROR('Forecast'!$G$13/'Forecast'!$G$12,0)-IFERROR('Forecast'!$F$13/'Forecast'!$F$12,0))*'Forecast'!$G$12 | G19: =(IFERROR('Forecast'!$H$13/'Forecast'!$H$12,0)-IFERROR('Forecast'!$G$13/'Forecast'!$G$12,0))*'Forecast'!$H$12 | H19: =(IFERROR('Forecast'!$I$13/'Forecast'!$I$12,0)-IFERROR('Forecast'!$H$13/'Forecast'!$H$12,0))*'Forecast'!$I$12 | I19: =(IFERROR('Forecast'!$J$13/'Forecast'!$J$12,0)-IFERROR('Forecast'!$I$13/'Forecast'!$I$12,0))*'Forecast'!$J$12 | J19: =(IFERROR('Forecast'!$K$13/'Forecast'!$K$12,0)-IFERROR('Forecast'!$J$13/'Forecast'!$J$12,0))*'Forecast'!$K$12 | K19: =(IFERROR('Forecast'!$L$13/'Forecast'!$L$12,0)-IFERROR('Forecast'!$K$13/'Forecast'!$K$12,0))*'Forecast'!$L$12
A20: (=) Current EBITDA | B20: ='Forecast'!$C$13 | C20: ='Forecast'!$D$13 | D20: ='Forecast'!$E$13 | E20: ='Forecast'!$F$13 | F20: ='Forecast'!$G$13 | G20: ='Forecast'!$H$13 | H20: ='Forecast'!$I$13 | I20: ='Forecast'!$J$13 | J20: ='Forecast'!$K$13 | K20: ='Forecast'!$L$13
A21: Check (effects - actual change) | B21: =($B$18+$B$19)-('Forecast'!$C$13-'Forecast'!$B$13) | C21: =($C$18+$C$19)-('Forecast'!$D$13-'Forecast'!$C$13) | D21: =($D$18+$D$19)-('Forecast'!$E$13-'Forecast'!$D$13) | E21: =($E$18+$E$19)-('Forecast'!$F$13-'Forecast'!$E$13) | F21: =($F$18+$F$19)-('Forecast'!$G$13-'Forecast'!$F$13) | G21: =($G$18+$G$19)-('Forecast'!$H$13-'Forecast'!$G$13) | H21: =($H$18+$H$19)-('Forecast'!$I$13-'Forecast'!$H$13) | I21: =($I$18+$I$19)-('Forecast'!$J$13-'Forecast'!$I$13) | J21: =($J$18+$J$19)-('Forecast'!$K$13-'Forecast'!$J$13) | K21: =($K$18+$K$19)-('Forecast'!$L$13-'Forecast'!$K$13)
A23: EBIT Bridge
A24: Prior-year EBIT | B24: ='Forecast'!$B$15 | C24: ='Forecast'!$C$15 | D24: ='Forecast'!$D$15 | E24: ='Forecast'!$E$15 | F24: ='Forecast'!$F$15 | G24: ='Forecast'!$G$15 | H24: ='Forecast'!$H$15 | I24: ='Forecast'!$I$15 | J24: ='Forecast'!$J$15 | K24: ='Forecast'!$K$15
A25: (+) Revenue (volume) effect | B25: =('Forecast'!$C$12-'Forecast'!$B$12)*IFERROR('Forecast'!$B$13/'Forecast'!$B$12,0) | C25: =('Forecast'!$D$12-'Forecast'!$C$12)*IFERROR('Forecast'!$C$13/'Forecast'!$C$12,0) | D25: =('Forecast'!$E$12-'Forecast'!$D$12)*IFERROR('Forecast'!$D$13/'Forecast'!$D$12,0) | E25: =('Forecast'!$F$12-'Forecast'!$E$12)*IFERROR('Forecast'!$E$13/'Forecast'!$E$12,0) | F25: =('Forecast'!$G$12-'Forecast'!$F$12)*IFERROR('Forecast'!$F$13/'Forecast'!$F$12,0) | G25: =('Forecast'!$H$12-'Forecast'!$G$12)*IFERROR('Forecast'!$G$13/'Forecast'!$G$12,0) | H25: =('Forecast'!$I$12-'Forecast'!$H$12)*IFERROR('Forecast'!$H$13/'Forecast'!$H$12,0) | I25: =('Forecast'!$J$12-'Forecast'!$I$12)*IFERROR('Forecast'!$I$13/'Forecast'!$I$12,0) | J25: =('Forecast'!$K$12-'Forecast'!$J$12)*IFERROR('Forecast'!$J$13/'Forecast'!$J$12,0) | K25: =('Forecast'!$L$12-'Forecast'!$K$12)*IFERROR('Forecast'!$K$13/'Forecast'!$K$12,0)
A26: (+) EBITDA margin effect | B26: =(IFERROR('Forecast'!$C$13/'Forecast'!$C$12,0)-IFERROR('Forecast'!$B$13/'Forecast'!$B$12,0))*'Forecast'!$C$12 | C26: =(IFERROR('Forecast'!$D$13/'Forecast'!$D$12,0)-IFERROR('Forecast'!$C$13/'Forecast'!$C$12,0))*'Forecast'!$D$12 | D26: =(IFERROR('Forecast'!$E$13/'Forecast'!$E$12,0)-IFERROR('Forecast'!$D$13/'Forecast'!$D$12,0))*'Forecast'!$E$12 | E26: =(IFERROR('Forecast'!$F$13/'Forecast'!$F$12,0)-IFERROR('Forecast'!$E$13/'Forecast'!$E$12,0))*'Forecast'!$F$12 | F26: =(IFERROR('Forecast'!$G$13/'Forecast'!$G$12,0)-IFERROR('Forecast'!$F$13/'Forecast'!$F$12,0))*'Forecast'!$G$12 | G26: =(IFERROR('Forecast'!$H$13/'Forecast'!$H$12,0)-IFERROR('Forecast'!$G$13/'Forecast'!$G$12,0))*'Forecast'!$H$12 | H26: =(IFERROR('Forecast'!$I$13/'Forecast'!$I$12,0)-IFERROR('Forecast'!$H$13/'Forecast'!$H$12,0))*'Forecast'!$I$12 | I26: =(IFERROR('Forecast'!$J$13/'Forecast'!$J$12,0)-IFERROR('Forecast'!$I$13/'Forecast'!$I$12,0))*'Forecast'!$J$12 | J26: =(IFERROR('Forecast'!$K$13/'Forecast'!$K$12,0)-IFERROR('Forecast'!$J$13/'Forecast'!$J$12,0))*'Forecast'!$K$12 | K26: =(IFERROR('Forecast'!$L$13/'Forecast'!$L$12,0)-IFERROR('Forecast'!$K$13/'Forecast'!$K$12,0))*'Forecast'!$L$12
A27: (-) D&A effect | B27: =-('Forecast'!$C$14-'Forecast'!$B$14) | C27: =-('Forecast'!$D$14-'Forecast'!$C$14) | D27: =-('Forecast'!$E$14-'Forecast'!$D$14) | E27: =-('Forecast'!$F$14-'Forecast'!$E$14) | F27: =-('Forecast'!$G$14-'Forecast'!$F$14) | G27: =-('Forecast'!$H$14-'Forecast'!$G$14) | H27: =-('Forecast'!$I$14-'Forecast'!$H$14) | I27: =-('Forecast'!$J$14-'Forecast'!$I$14) | J27: =-('Forecast'!$K$14-'Forecast'!$J$14) | K27: =-('Forecast'!$L$14-'Forecast'!$K$14)
A28: (=) Current EBIT | B28: ='Forecast'!$C$15 | C28: ='Forecast'!$D$15 | D28: ='Forecast'!$E$15 | E28: ='Forecast'!$F$15 | F28: ='Forecast'!$G$15 | G28: ='Forecast'!$H$15 | H28: ='Forecast'!$I$15 | I28: ='Forecast'!$J$15 | J28: ='Forecast'!$K$15 | K28: ='Forecast'!$L$15
A29: Check (effects - actual change) | B29: =($B$25+$B$26+$B$27)-('Forecast'!$C$15-'Forecast'!$B$15) | C29: =($C$25+$C$26+$C$27)-('Forecast'!$D$15-'Forecast'!$C$15) | D29: =($D$25+$D$26+$D$27)-('Forecast'!$E$15-'Forecast'!$D$15) | E29: =($E$25+$E$26+$E$27)-('Forecast'!$F$15-'Forecast'!$E$15) | F29: =($F$25+$F$26+$F$27)-('Forecast'!$G$15-'Forecast'!$F$15) | G29: =($G$25+$G$26+$G$27)-('Forecast'!$H$15-'Forecast'!$G$15) | H29: =($H$25+$H$26+$H$27)-('Forecast'!$I$15-'Forecast'!$H$15) | I29: =($I$25+$I$26+$I$27)-('Forecast'!$J$15-'Forecast'!$I$15) | J29: =($J$25+$J$26+$J$27)-('Forecast'!$K$15-'Forecast'!$J$15) | K29: =($K$25+$K$26+$K$27)-('Forecast'!$L$15-'Forecast'!$K$15)
A31: Net Income Bridge
A32: Prior-year net income | B32: ='Forecast'!$B$19 | C32: ='Forecast'!$C$19 | D32: ='Forecast'!$D$19 | E32: ='Forecast'!$E$19 | F32: ='Forecast'!$F$19 | G32: ='Forecast'!$G$19 | H32: ='Forecast'!$H$19 | I32: ='Forecast'!$I$19 | J32: ='Forecast'!$J$19 | K32: ='Forecast'!$K$19
A33: (+) EBITDA effect | B33: =('Forecast'!$C$13-'Forecast'!$B$13)*(1-IFERROR('Forecast'!$B$18/'Forecast'!$B$17,0)) | C33: =('Forecast'!$D$13-'Forecast'!$C$13)*(1-IFERROR('Forecast'!$C$18/'Forecast'!$C$17,0)) | D33: =('Forecast'!$E$13-'Forecast'!$D$13)*(1-IFERROR('Forecast'!$D$18/'Forecast'!$D$17,0)) | E33: =('Forecast'!$F$13-'Forecast'!$E$13)*(1-IFERROR('Forecast'!$E$18/'Forecast'!$E$17,0)) | F33: =('Forecast'!$G$13-'Forecast'!$F$13)*(1-IFERROR('Forecast'!$F$18/'Forecast'!$F$17,0)) | G33: =('Forecast'!$H$13-'Forecast'!$G$13)*(1-IFERROR('Forecast'!$G$18/'Forecast'!$G$17,0)) | H33: =('Forecast'!$I$13-'Forecast'!$H$13)*(1-IFERROR('Forecast'!$H$18/'Forecast'!$H$17,0)) | I33: =('Forecast'!$J$13-'Forecast'!$I$13)*(1-IFERROR('Forecast'!$I$18/'Forecast'!$I$17,0)) | J33: =('Forecast'!$K$13-'Forecast'!$J$13)*(1-IFERROR('Forecast'!$J$18/'Forecast'!$J$17,0)) | K33: =('Forecast'!$L$13-'Forecast'!$K$13)*(1-IFERROR('Forecast'!$K$18/'Forecast'!$K$17,0))
A34: (-) D&A effect | B34: =-('Forecast'!$C$14-'Forecast'!$B$14)*(1-IFERROR('Forecast'!$B$18/'Forecast'!$B$17,0)) | C34: =-('Forecast'!$D$14-'Forecast'!$C$14)*(1-IFERROR('Forecast'!$C$18/'Forecast'!$C$17,0)) | D34: =-('Forecast'!$E$14-'Forecast'!$D$14)*(1-IFERROR('Forecast'!$D$18/'Forecast'!$D$17,0)) | E34: =-('Forecast'!$F$14-'Forecast'!$E$14)*(1-IFERROR('Forecast'!$E$18/'Forecast'!$E$17,0)) | F34: =-('Forecast'!$G$14-'Forecast'!$F$14)*(1-IFERROR('Forecast'!$F$18/'Forecast'!$F$17,0)) | G34: =-('Forecast'!$H$14-'Forecast'!$G$14)*(1-IFERROR('Forecast'!$G$18/'Forecast'!$G$17,0)) | H34: =-('Forecast'!$I$14-'Forecast'!$H$14)*(1-IFERROR('Forecast'!$H$18/'Forecast'!$H$17,0)) | I34: =-('Forecast'!$J$14-'Forecast'!$I$14)*(1-IFERROR('Forecast'!$I$18/'Forecast'!$I$17,0)) | J34: =-('Forecast'!$K$14-'Forecast'!$J$14)*(1-IFERROR('Forecast'!$J$18/'Forecast'!$J$17,0)) | K34: =-('Forecast'!$L$14-'Forecast'!$K$14)*(1-IFERROR('Forecast'!$K$18/'Forecast'!$K$17,0))
A35: (-) Financing (net interest) effect | B35: =-('Forecast'!$C$16-'Forecast'!$B$16)*(1-IFERROR('Forecast'!$B$18/'Forecast'!$B$17,0)) | C35: =-('Forecast'!$D$16-'Forecast'!$C$16)*(1-IFERROR('Forecast'!$C$18/'Forecast'!$C$17,0)) | D35: =-('Forecast'!$E$16-'Forecast'!$D$16)*(1-IFERROR('Forecast'!$D$18/'Forecast'!$D$17,0)) | E35: =-('Forecast'!$F$16-'Forecast'!$E$16)*(1-IFERROR('Forecast'!$E$18/'Forecast'!$E$17,0)) | F35: =-('Forecast'!$G$16-'Forecast'!$F$16)*(1-IFERROR('Forecast'!$F$18/'Forecast'!$F$17,0)) | G35: =-('Forecast'!$H$16-'Forecast'!$G$16)*(1-IFERROR('Forecast'!$G$18/'Forecast'!$G$17,0)) | H35: =-('Forecast'!$I$16-'Forecast'!$H$16)*(1-IFERROR('Forecast'!$H$18/'Forecast'!$H$17,0)) | I35: =-('Forecast'!$J$16-'Forecast'!$I$16)*(1-IFERROR('Forecast'!$I$18/'Forecast'!$I$17,0)) | J35: =-('Forecast'!$K$16-'Forecast'!$J$16)*(1-IFERROR('Forecast'!$J$18/'Forecast'!$J$17,0)) | K35: =-('Forecast'!$L$16-'Forecast'!$K$16)*(1-IFERROR('Forecast'!$K$18/'Forecast'!$K$17,0))
A36: (-) Tax-rate effect | B36: =-'Forecast'!$C$17*(IFERROR('Forecast'!$C$18/'Forecast'!$C$17,0)-IFERROR('Forecast'!$B$18/'Forecast'!$B$17,0)) | C36: =-'Forecast'!$D$17*(IFERROR('Forecast'!$D$18/'Forecast'!$D$17,0)-IFERROR('Forecast'!$C$18/'Forecast'!$C$17,0)) | D36: =-'Forecast'!$E$17*(IFERROR('Forecast'!$E$18/'Forecast'!$E$17,0)-IFERROR('Forecast'!$D$18/'Forecast'!$D$17,0)) | E36: =-'Forecast'!$F$17*(IFERROR('Forecast'!$F$18/'Forecast'!$F$17,0)-IFERROR('Forecast'!$E$18/'Forecast'!$E$17,0)) | F36: =-'Forecast'!$G$17*(IFERROR('Forecast'!$G$18/'Forecast'!$G$17,0)-IFERROR('Forecast'!$F$18/'Forecast'!$F$17,0)) | G36: =-'Forecast'!$H$17*(IFERROR('Forecast'!$H$18/'Forecast'!$H$17,0)-IFERROR('Forecast'!$G$18/'Forecast'!$G$17,0)) | H36: =-'Forecast'!$I$17*(IFERROR('Forecast'!$I$18/'Forecast'!$I$17,0)-IFERROR('Forecast'!$H$18/'Forecast'!$H$17,0)) | I36: =-'Forecast'!$J$17*(IFERROR('Forecast'!$J$18/'Forecast'!$J$17,0)-IFERROR('Forecast'!$I$18/'Forecast'!$I$17,0)) | J36: =-'Forecast'!$K$17*(IFERROR('Forecast'!$K$18/'Forecast'!$K$17,0)-IFERROR('Forecast'!$J$18/'Forecast'!$J$17,0)) | K36: =-'Forecast'!$L$17*(IFERROR('Forecast'!$L$18/'Forecast'!$L$17,0)-IFERROR('Forecast'!$K$18/'Forecast'!$K$17,0))
A37: (=) Current net income | B37: ='Forecast'!$C$19 | C37: ='Forecast'!$D$19 | D37: ='Forecast'!$E$19 | E37: ='Forecast'!$F$19 | F37: ='Forecast'!$G$19 | G37: ='Forecast'!$H$19 | H37: ='Forecast'!$I$19 | I37: ='Forecast'!$J$19 | J37: ='Forecast'!$K$19 | K37: ='Forecast'!$L$19
A38: Check (effects - actual change) | B38: =($B$33+$B$34+$B$35+$B$36)-('Forecast'!$C$19-'Forecast'!$B$19) | C38: =($C$33+$C$34+$C$35+$C$36)-('Forecast'!$D$19-'Forecast'!$C$19) | D38: =($D$33+$D$34+$D$35+$D$36)-('Forecast'!$E$19-'Forecast'!$D$19) | E38: =($E$33+$E$34+$E$35+$E$36)-('Forecast'!$F$19-'Forecast'!$E$19) | F38: =($F$33+$F$34+$F$35+$F$36)-('Forecast'!$G$19-'Forecast'!$F$19) | G38: =($G$33+$G$34+$G$35+$G$36)-('Forecast'!$H$19-'Forecast'!$G$19) | H38: =($H$33+$H$34+$H$35+$H$36)-('Forecast'!$I$19-'Forecast'!$H$19) | I38: =($I$33+$I$34+$I$35+$I$36)-('Forecast'!$J$19-'Forecast'!$I$19) | J38: =($J$33+$J$34+$J$35+$J$36)-('Forecast'!$K$19-'Forecast'!$J$19) | K38: =($K$33+$K$34+$K$35+$K$36)-('Forecast'!$L$19-'Forecast'!$K$19)

Sheet Diagnostics
A1: FORECAST DIAGNOSTICS
A2: Accounting integrity, reasonableness checks and the Forecast Health Score
A3: Institutional Forecasting Engine - v2.0
A5: Dashboard | B5: Methodology | C5: Historical | D5: Assumptions | E5: Forecast | F5: Bridge | G5: Diagnostics
A7: Forecast Health
A8: Forecast Health Score (0-100) | B8: =ROUND((COUNTIF(C11:C23,"PASS")+0.5*COUNTIF(C11:C23,"WARN"))/11*100,0) | D8: 100 = every check passes. WARN counts as half; FAIL as zero.
A9: Checks failed / to review | B9: =COUNTIF(C11:C23,"FAIL")&" / "&COUNTIF(C11:C23,"WARN")
A10: Accounting Integrity
A11: Historical data present | B11: ='Historical'!$C$10 | C11: =IF($B$11>=1,"PASS","FAIL") | D11: Counts the reported years entered on the Historical sheet. Fails on a blank template.
A12: Historical statements tie | B12: =MAX(MAX('Historical'!$B$45:$P$45),-MIN('Historical'!$B$45:$P$45)) | C12: =IF($B$12<=1.0,"PASS","FAIL") | D12: Largest |assets - (liabilities + equity)| across the actual years (should be 0).
A13: Forecast Assets = Liab + Equity | B13: =MAX(MAX('Forecast'!$C$32:$L$32),-MIN('Forecast'!$C$32:$L$32)) | C13: =IF($B$13<=1.0,"PASS","FAIL") | D13: Largest forecast imbalance (the model reconciles with no plug, so this is 0).
A15: Forecast Reasonableness
A16: Revenue growth | B16: =MAX('Assumptions'!$B$11:$K$11) | C16: =IF(AND(MAX('Assumptions'!$B$11:$K$11)<=0.3,MIN('Assumptions'!$B$11:$K$11)>=-0.2),"PASS","WARN") | D16: Warns if any year's growth exceeds 30% or falls below -20%.
A17: EBITDA-margin drift (per year) | B17: =(IFERROR('Forecast'!$L$13/'Forecast'!$L$12,0)-IFERROR('Forecast'!$C$13/'Forecast'!$C$12,0))/9 | C17: =IF(ABS($B$17)<=0.04,"PASS","WARN") | D17: Warns if EBITDA margin drifts more than 400 bps per year on average.
A18: Positive cash | B18: =MIN('Forecast'!$C$21:$L$21) | C18: =IF($B$18>=0,"PASS","FAIL") | D18: Fails if the forecast runs cash negative (there is no revolver plug).
A19: Positive equity | B19: =MIN('Forecast'!$C$30:$L$30) | C19: =IF($B$19>=0,"PASS","FAIL") | D19: Fails if forecast equity turns negative.
A20: Non-negative debt | B20: =MIN('Forecast'!$C$27:$L$27) | C20: =IF($B$20>=0,"PASS","WARN") | D20: Warns if net repayment drives the debt balance below zero.
A21: Working capital intensity | B21: =MAX('Assumptions'!$B$15:$K$15) | C21: =IF($B$21<=0.4,"PASS","WARN") | D21: Warns if net working capital exceeds 40% of revenue.
A22: Capex intensity | B22: =MAX('Assumptions'!$B$14:$K$14) | C22: =IF($B$22<=0.25,"PASS","WARN") | D22: Warns if capex exceeds 25% of revenue.
A23: Tax rate | B23: =MAX('Assumptions'!$B$17:$K$17) | C23: =IF(AND(MAX('Assumptions'!$B$17:$K$17)<=0.5,MIN('Assumptions'!$B$17:$K$17)>=0.0),"PASS","WARN") | D23: Warns if the tax rate falls outside 0-50%.
