Workbook

Sheet Home
A1: Institutional Financial Ratio Analysis
A2: A fully formula-driven, auditable ratio-analysis platform · v1.0
A4: Company Profile
A5: Company name | B5: <Company name>
A6: Ticker | B6: <TICKER>
A7: Industry | B7: <Industry>
A8: Reporting currency | B8: USD
A9: Units | B9: millions
A10: Fiscal year end | B10: 31 December
A11: Analysis date | B11: =TODAY()
A13: Navigation
A14: Dashboard | B14: Inputs | C14: Common Size | D14: Profitability | E14: Liquidity | F14: Solvency | G14: Efficiency | H14: Growth
A15: Valuation | B15: Capital Allocation | C15: Quality | D15: Benchmarking | E15: Guide | F15: Quality Control
A17: LEGEND
B18: Input — editable (yellow)
B19: Formula / helper — protected (blue)
B20: Output — read-only result (green)
B21: Error / flag (red)
A22: Strong | B22: Moderate | C22: Weak | D22: ← traffic-light classification
A24: About This Workbook
A25: • 15 sheets covering every major ratio family plus quality scores, peer benchmarking, an interpretation guide and automated quality-control checks.
A26: • Every output is a live formula that traces back to the Inputs sheet — no hardcoded results. Yellow cells are the only ones you edit.
A27: • Calculations are deliberately broken into helper rows and short formulas so each ratio is understandable without opening Excel's formula auditor.
A28: • Classifications, trend arrows and commentary update automatically as you change the inputs.

Sheet Dashboard
A1: EXECUTIVE DASHBOARD
A2: <Company name> — quality scorecard & key signals
A3: Institutional Financial Ratio Analysis · v1.0
A5: Dashboard | B5: Inputs | C5: Common Size | D5: Profitability | E5: Liquidity | F5: Solvency | G5: Efficiency | H5: Growth
A6: Valuation | B6: Capital Allocation | C6: Quality | D6: Benchmarking | E6: Guide | F6: Quality Control
A7: Quality Scorecard (0–100, higher = better) | F7: Key-Metric Trends
A8: Category | B8: Score | C8: Assessment | F8: Metric | G8: Latest | H8: Trend | I8: Read
A9: Profitability | B9: =IFERROR(ROUND(AVERAGE(MIN('Profitability'!$K$14/0.2,1),MIN('Profitability'!$K$18/0.15,1),MIN('Profitability'!$K$20/0.12,1),MIN('Profitability'!$K$12/0.18,1))*100,0),"") | C9: =IF(ISNUMBER($B$9),CHOOSE(1+($B$9>=40)+($B$9>=70),"Weak","Moderate","Strong"),"") | F9: ROE | G9: ='Profitability'!$K$18 | H9: =IF(AND(ISNUMBER('Profitability'!$K$18),ISNUMBER('Profitability'!$J$18)),CHOOSE(2+('Profitability'!$K$18>'Profitability'!$J$18)-('Profitability'!$K$18<'Profitability'!$J$18),"▼","►","▲"),"") | I9: ='Profitability'!$R$18
A10: Liquidity | B10: =IFERROR(ROUND(AVERAGE(MIN('Liquidity'!$K$10/2,1),MIN('Liquidity'!$K$12/0.5,1),MIN('Liquidity'!$K$19/1,1))*100,0),"") | C10: =IF(ISNUMBER($B$10),CHOOSE(1+($B$10>=40)+($B$10>=70),"Weak","Moderate","Strong"),"") | F10: Operating margin | G10: ='Profitability'!$K$12 | H10: =IF(AND(ISNUMBER('Profitability'!$K$12),ISNUMBER('Profitability'!$J$12)),CHOOSE(2+('Profitability'!$K$12>'Profitability'!$J$12)-('Profitability'!$K$12<'Profitability'!$J$12),"▼","►","▲"),"") | I10: ='Profitability'!$R$12
A11: Solvency | B11: =IFERROR(ROUND(AVERAGE(MIN('Solvency'!$K$21/6,1),MIN('Solvency'!$K$14,1),MIN(MAX(0,1-'Solvency'!$K$18/4),1))*100,0),"") | C11: =IF(ISNUMBER($B$11),CHOOSE(1+($B$11>=40)+($B$11>=70),"Weak","Moderate","Strong"),"") | F11: Revenue growth | G11: ='Growth'!$K$10 | H11: =IF(AND(ISNUMBER('Growth'!$K$10),ISNUMBER('Growth'!$J$10)),CHOOSE(2+('Growth'!$K$10>'Growth'!$J$10)-('Growth'!$K$10<'Growth'!$J$10),"▼","►","▲"),"") | I11: ='Growth'!$R$10
A12: Efficiency | B12: =IFERROR(ROUND(AVERAGE(MIN('Efficiency'!$K$10/1,1),MIN('Efficiency'!$K$12/8,1),MIN('Efficiency'!$K$13/10,1))*100,0),"") | C12: =IF(ISNUMBER($B$12),CHOOSE(1+($B$12>=40)+($B$12>=70),"Weak","Moderate","Strong"),"") | F12: Net debt / EBITDA | G12: ='Solvency'!$K$18 | H12: =IF(AND(ISNUMBER('Solvency'!$K$18),ISNUMBER('Solvency'!$J$18)),CHOOSE(2+('Solvency'!$K$18>'Solvency'!$J$18)-('Solvency'!$K$18<'Solvency'!$J$18),"▼","►","▲"),"") | I12: ='Solvency'!$R$18
A13: Growth | B13: =IFERROR(ROUND(AVERAGE(MIN('Growth'!$C$20/0.1,1),MIN('Growth'!$C$23/0.1,1))*100,0),"") | C13: =IF(ISNUMBER($B$13),CHOOSE(1+($B$13>=40)+($B$13>=70),"Weak","Moderate","Strong"),"") | F13: FCF margin | G13: ='Profitability'!$K$15 | H13: =IF(AND(ISNUMBER('Profitability'!$K$15),ISNUMBER('Profitability'!$J$15)),CHOOSE(2+('Profitability'!$K$15>'Profitability'!$J$15)-('Profitability'!$K$15<'Profitability'!$J$15),"▼","►","▲"),"") | I13: ='Profitability'!$R$15
A14: Valuation (cheapness) | B14: =IFERROR(ROUND(AVERAGE(MIN('Valuation'!$K$31/0.06,1),MIN('Valuation'!$K$19/0.05,1))*100,0),"") | C14: =IF(ISNUMBER($B$14),CHOOSE(1+($B$14>=40)+($B$14>=70),"Weak","Moderate","Strong"),"") | F14: ROIC | G14: ='Profitability'!$K$20 | H14: =IF(AND(ISNUMBER('Profitability'!$K$20),ISNUMBER('Profitability'!$J$20)),CHOOSE(2+('Profitability'!$K$20>'Profitability'!$J$20)-('Profitability'!$K$20<'Profitability'!$J$20),"▼","►","▲"),"") | I14: ='Profitability'!$R$20
A15: OVERALL QUALITY SCORE | B15: =IFERROR(ROUND(AVERAGE(B9:B14),0),"") | C15: =IF(ISNUMBER($B$15),CHOOSE(1+($B$15>=40)+($B$15>=70),"Weak","Moderate","Strong"),"")
A16: Headline Metrics (latest year)
A17: Revenue | B17: Net income | C17: FCF | D17: ROIC − WACC | E17: Altman Z | F17: Piotroski F
A18: ='Inputs'!$K$10 | B18: ='Inputs'!$K$21 | C18: ='Inputs'!$K$48 | D18: =IFERROR('Profitability'!$K$20-'Inputs'!$B$82,"") | E18: ='Quality'!$K$15 | F18: ='Quality'!$K$33
A20: Automated Observations
A21: =IFERROR("» Profitability: ROE "&TEXT('Profitability'!$K$18,"0.0%")&" ("&'Profitability'!$R$18&"), ROIC "&TEXT('Profitability'!$K$20,"0.0%")&" vs WACC "&TEXT('Inputs'!$B$82,"0.0%")&".","(insufficient data — populate inputs)")
A22: =IFERROR("» Margins: operating margin "&TEXT('Profitability'!$K$12,"0.0%")&" — "&'Profitability'!$R$12&" versus history.","(insufficient data — populate inputs)")
A23: =IFERROR("» Leverage: net debt / EBITDA "&TEXT('Solvency'!$K$18,"0.0")&"x — "&'Solvency'!$R$18&" risk.","(insufficient data — populate inputs)")
A24: =IFERROR("» Cash: FCF margin "&TEXT('Profitability'!$K$15,"0.0%")&" ("&'Profitability'!$R$15&"); FCF "&TEXT('Inputs'!$K$48,"#,##0")&".","(insufficient data — populate inputs)")
A25: =IFERROR("» Quality: Altman Z "&TEXT('Quality'!$K$15,"0.0")&" ("&'Quality'!$R$15&"), Piotroski "&TEXT('Quality'!$K$33,"0")&"/9, Beneish "&'Quality'!$R$44&".","(insufficient data — populate inputs)")
A26: =IFERROR("» Data health: "&'Quality Control'!$B$8&".","(insufficient data — populate inputs)")

Sheet Inputs
A1: RAW FINANCIAL INPUTS
A2: 10 historical + 5 forecast years — the single data-entry layer
A3: Institutional Financial Ratio Analysis · v1.0
A5: Dashboard | B5: Inputs | C5: Common Size | D5: Profitability | E5: Liquidity | F5: Solvency | G5: Efficiency | H5: Growth
A6: Valuation | B6: Capital Allocation | C6: Quality | D6: Benchmarking | E6: Guide | F6: Quality Control
A7: All figures in USD millions unless stated; (F) = forecast year.
A8: Metric | B8: FY2015 | C8: FY2016 | D8: FY2017 | E8: FY2018 | F8: FY2019 | G8: FY2020 | H8: FY2021 | I8: FY2022 | J8: FY2023 | K8: FY2024 | L8: FY2025 (F) | M8: FY2026 (F) | N8: FY2027 (F) | O8: FY2028 (F) | P8: FY2029 (F)
A9: Income Statement
A10: Revenue
A11: Cost of goods sold
A12: Gross profit | B12: ='Inputs'!$B$10-'Inputs'!$B$11 | C12: ='Inputs'!$C$10-'Inputs'!$C$11 | D12: ='Inputs'!$D$10-'Inputs'!$D$11 | E12: ='Inputs'!$E$10-'Inputs'!$E$11 | F12: ='Inputs'!$F$10-'Inputs'!$F$11 | G12: ='Inputs'!$G$10-'Inputs'!$G$11 | H12: ='Inputs'!$H$10-'Inputs'!$H$11 | I12: ='Inputs'!$I$10-'Inputs'!$I$11 | J12: ='Inputs'!$J$10-'Inputs'!$J$11 | K12: ='Inputs'!$K$10-'Inputs'!$K$11 | L12: ='Inputs'!$L$10-'Inputs'!$L$11 | M12: ='Inputs'!$M$10-'Inputs'!$M$11 | N12: ='Inputs'!$N$10-'Inputs'!$N$11 | O12: ='Inputs'!$O$10-'Inputs'!$O$11 | P12: ='Inputs'!$P$10-'Inputs'!$P$11
A13: Operating expenses (ex-D&A)
A14: EBITDA | B14: ='Inputs'!$B$12-'Inputs'!$B$13 | C14: ='Inputs'!$C$12-'Inputs'!$C$13 | D14: ='Inputs'!$D$12-'Inputs'!$D$13 | E14: ='Inputs'!$E$12-'Inputs'!$E$13 | F14: ='Inputs'!$F$12-'Inputs'!$F$13 | G14: ='Inputs'!$G$12-'Inputs'!$G$13 | H14: ='Inputs'!$H$12-'Inputs'!$H$13 | I14: ='Inputs'!$I$12-'Inputs'!$I$13 | J14: ='Inputs'!$J$12-'Inputs'!$J$13 | K14: ='Inputs'!$K$12-'Inputs'!$K$13 | L14: ='Inputs'!$L$12-'Inputs'!$L$13 | M14: ='Inputs'!$M$12-'Inputs'!$M$13 | N14: ='Inputs'!$N$12-'Inputs'!$N$13 | O14: ='Inputs'!$O$12-'Inputs'!$O$13 | P14: ='Inputs'!$P$12-'Inputs'!$P$13
A15: Depreciation & amortisation
A16: EBIT (operating income) | B16: ='Inputs'!$B$14-'Inputs'!$B$15 | C16: ='Inputs'!$C$14-'Inputs'!$C$15 | D16: ='Inputs'!$D$14-'Inputs'!$D$15 | E16: ='Inputs'!$E$14-'Inputs'!$E$15 | F16: ='Inputs'!$F$14-'Inputs'!$F$15 | G16: ='Inputs'!$G$14-'Inputs'!$G$15 | H16: ='Inputs'!$H$14-'Inputs'!$H$15 | I16: ='Inputs'!$I$14-'Inputs'!$I$15 | J16: ='Inputs'!$J$14-'Inputs'!$J$15 | K16: ='Inputs'!$K$14-'Inputs'!$K$15 | L16: ='Inputs'!$L$14-'Inputs'!$L$15 | M16: ='Inputs'!$M$14-'Inputs'!$M$15 | N16: ='Inputs'!$N$14-'Inputs'!$N$15 | O16: ='Inputs'!$O$14-'Inputs'!$O$15 | P16: ='Inputs'!$P$14-'Inputs'!$P$15
A17: Interest expense
A18: Other income / (expense)
A19: Pre-tax income | B19: ='Inputs'!$B$16-'Inputs'!$B$17+'Inputs'!$B$18 | C19: ='Inputs'!$C$16-'Inputs'!$C$17+'Inputs'!$C$18 | D19: ='Inputs'!$D$16-'Inputs'!$D$17+'Inputs'!$D$18 | E19: ='Inputs'!$E$16-'Inputs'!$E$17+'Inputs'!$E$18 | F19: ='Inputs'!$F$16-'Inputs'!$F$17+'Inputs'!$F$18 | G19: ='Inputs'!$G$16-'Inputs'!$G$17+'Inputs'!$G$18 | H19: ='Inputs'!$H$16-'Inputs'!$H$17+'Inputs'!$H$18 | I19: ='Inputs'!$I$16-'Inputs'!$I$17+'Inputs'!$I$18 | J19: ='Inputs'!$J$16-'Inputs'!$J$17+'Inputs'!$J$18 | K19: ='Inputs'!$K$16-'Inputs'!$K$17+'Inputs'!$K$18 | L19: ='Inputs'!$L$16-'Inputs'!$L$17+'Inputs'!$L$18 | M19: ='Inputs'!$M$16-'Inputs'!$M$17+'Inputs'!$M$18 | N19: ='Inputs'!$N$16-'Inputs'!$N$17+'Inputs'!$N$18 | O19: ='Inputs'!$O$16-'Inputs'!$O$17+'Inputs'!$O$18 | P19: ='Inputs'!$P$16-'Inputs'!$P$17+'Inputs'!$P$18
A20: Income tax expense
A21: Net income | B21: ='Inputs'!$B$19-'Inputs'!$B$20 | C21: ='Inputs'!$C$19-'Inputs'!$C$20 | D21: ='Inputs'!$D$19-'Inputs'!$D$20 | E21: ='Inputs'!$E$19-'Inputs'!$E$20 | F21: ='Inputs'!$F$19-'Inputs'!$F$20 | G21: ='Inputs'!$G$19-'Inputs'!$G$20 | H21: ='Inputs'!$H$19-'Inputs'!$H$20 | I21: ='Inputs'!$I$19-'Inputs'!$I$20 | J21: ='Inputs'!$J$19-'Inputs'!$J$20 | K21: ='Inputs'!$K$19-'Inputs'!$K$20 | L21: ='Inputs'!$L$19-'Inputs'!$L$20 | M21: ='Inputs'!$M$19-'Inputs'!$M$20 | N21: ='Inputs'!$N$19-'Inputs'!$N$20 | O21: ='Inputs'!$O$19-'Inputs'!$O$20 | P21: ='Inputs'!$P$19-'Inputs'!$P$20
A22: Balance Sheet — Assets
A23: Cash & equivalents
A24: Accounts receivable
A25: Inventory
A26: Other current assets
A27: Total current assets | B27: =SUM('Inputs'!$B$23,'Inputs'!$B$24,'Inputs'!$B$25,'Inputs'!$B$26) | C27: =SUM('Inputs'!$C$23,'Inputs'!$C$24,'Inputs'!$C$25,'Inputs'!$C$26) | D27: =SUM('Inputs'!$D$23,'Inputs'!$D$24,'Inputs'!$D$25,'Inputs'!$D$26) | E27: =SUM('Inputs'!$E$23,'Inputs'!$E$24,'Inputs'!$E$25,'Inputs'!$E$26) | F27: =SUM('Inputs'!$F$23,'Inputs'!$F$24,'Inputs'!$F$25,'Inputs'!$F$26) | G27: =SUM('Inputs'!$G$23,'Inputs'!$G$24,'Inputs'!$G$25,'Inputs'!$G$26) | H27: =SUM('Inputs'!$H$23,'Inputs'!$H$24,'Inputs'!$H$25,'Inputs'!$H$26) | I27: =SUM('Inputs'!$I$23,'Inputs'!$I$24,'Inputs'!$I$25,'Inputs'!$I$26) | J27: =SUM('Inputs'!$J$23,'Inputs'!$J$24,'Inputs'!$J$25,'Inputs'!$J$26) | K27: =SUM('Inputs'!$K$23,'Inputs'!$K$24,'Inputs'!$K$25,'Inputs'!$K$26) | L27: =SUM('Inputs'!$L$23,'Inputs'!$L$24,'Inputs'!$L$25,'Inputs'!$L$26) | M27: =SUM('Inputs'!$M$23,'Inputs'!$M$24,'Inputs'!$M$25,'Inputs'!$M$26) | N27: =SUM('Inputs'!$N$23,'Inputs'!$N$24,'Inputs'!$N$25,'Inputs'!$N$26) | O27: =SUM('Inputs'!$O$23,'Inputs'!$O$24,'Inputs'!$O$25,'Inputs'!$O$26) | P27: =SUM('Inputs'!$P$23,'Inputs'!$P$24,'Inputs'!$P$25,'Inputs'!$P$26)
A28: Property, plant & equipment (net)
A29: Goodwill & intangibles
A30: Other non-current assets
A31: Total non-current assets | B31: =SUM('Inputs'!$B$28,'Inputs'!$B$29,'Inputs'!$B$30) | C31: =SUM('Inputs'!$C$28,'Inputs'!$C$29,'Inputs'!$C$30) | D31: =SUM('Inputs'!$D$28,'Inputs'!$D$29,'Inputs'!$D$30) | E31: =SUM('Inputs'!$E$28,'Inputs'!$E$29,'Inputs'!$E$30) | F31: =SUM('Inputs'!$F$28,'Inputs'!$F$29,'Inputs'!$F$30) | G31: =SUM('Inputs'!$G$28,'Inputs'!$G$29,'Inputs'!$G$30) | H31: =SUM('Inputs'!$H$28,'Inputs'!$H$29,'Inputs'!$H$30) | I31: =SUM('Inputs'!$I$28,'Inputs'!$I$29,'Inputs'!$I$30) | J31: =SUM('Inputs'!$J$28,'Inputs'!$J$29,'Inputs'!$J$30) | K31: =SUM('Inputs'!$K$28,'Inputs'!$K$29,'Inputs'!$K$30) | L31: =SUM('Inputs'!$L$28,'Inputs'!$L$29,'Inputs'!$L$30) | M31: =SUM('Inputs'!$M$28,'Inputs'!$M$29,'Inputs'!$M$30) | N31: =SUM('Inputs'!$N$28,'Inputs'!$N$29,'Inputs'!$N$30) | O31: =SUM('Inputs'!$O$28,'Inputs'!$O$29,'Inputs'!$O$30) | P31: =SUM('Inputs'!$P$28,'Inputs'!$P$29,'Inputs'!$P$30)
A32: TOTAL ASSETS | B32: ='Inputs'!$B$27+'Inputs'!$B$31 | C32: ='Inputs'!$C$27+'Inputs'!$C$31 | D32: ='Inputs'!$D$27+'Inputs'!$D$31 | E32: ='Inputs'!$E$27+'Inputs'!$E$31 | F32: ='Inputs'!$F$27+'Inputs'!$F$31 | G32: ='Inputs'!$G$27+'Inputs'!$G$31 | H32: ='Inputs'!$H$27+'Inputs'!$H$31 | I32: ='Inputs'!$I$27+'Inputs'!$I$31 | J32: ='Inputs'!$J$27+'Inputs'!$J$31 | K32: ='Inputs'!$K$27+'Inputs'!$K$31 | L32: ='Inputs'!$L$27+'Inputs'!$L$31 | M32: ='Inputs'!$M$27+'Inputs'!$M$31 | N32: ='Inputs'!$N$27+'Inputs'!$N$31 | O32: ='Inputs'!$O$27+'Inputs'!$O$31 | P32: ='Inputs'!$P$27+'Inputs'!$P$31
A33: Balance Sheet — Liabilities & Equity
A34: Accounts payable
A35: Short-term debt
A36: Other current liabilities
A37: Total current liabilities | B37: =SUM('Inputs'!$B$34,'Inputs'!$B$35,'Inputs'!$B$36) | C37: =SUM('Inputs'!$C$34,'Inputs'!$C$35,'Inputs'!$C$36) | D37: =SUM('Inputs'!$D$34,'Inputs'!$D$35,'Inputs'!$D$36) | E37: =SUM('Inputs'!$E$34,'Inputs'!$E$35,'Inputs'!$E$36) | F37: =SUM('Inputs'!$F$34,'Inputs'!$F$35,'Inputs'!$F$36) | G37: =SUM('Inputs'!$G$34,'Inputs'!$G$35,'Inputs'!$G$36) | H37: =SUM('Inputs'!$H$34,'Inputs'!$H$35,'Inputs'!$H$36) | I37: =SUM('Inputs'!$I$34,'Inputs'!$I$35,'Inputs'!$I$36) | J37: =SUM('Inputs'!$J$34,'Inputs'!$J$35,'Inputs'!$J$36) | K37: =SUM('Inputs'!$K$34,'Inputs'!$K$35,'Inputs'!$K$36) | L37: =SUM('Inputs'!$L$34,'Inputs'!$L$35,'Inputs'!$L$36) | M37: =SUM('Inputs'!$M$34,'Inputs'!$M$35,'Inputs'!$M$36) | N37: =SUM('Inputs'!$N$34,'Inputs'!$N$35,'Inputs'!$N$36) | O37: =SUM('Inputs'!$O$34,'Inputs'!$O$35,'Inputs'!$O$36) | P37: =SUM('Inputs'!$P$34,'Inputs'!$P$35,'Inputs'!$P$36)
A38: Long-term debt
A39: Other non-current liabilities
A40: Total non-current liabilities | B40: ='Inputs'!$B$38+'Inputs'!$B$39 | C40: ='Inputs'!$C$38+'Inputs'!$C$39 | D40: ='Inputs'!$D$38+'Inputs'!$D$39 | E40: ='Inputs'!$E$38+'Inputs'!$E$39 | F40: ='Inputs'!$F$38+'Inputs'!$F$39 | G40: ='Inputs'!$G$38+'Inputs'!$G$39 | H40: ='Inputs'!$H$38+'Inputs'!$H$39 | I40: ='Inputs'!$I$38+'Inputs'!$I$39 | J40: ='Inputs'!$J$38+'Inputs'!$J$39 | K40: ='Inputs'!$K$38+'Inputs'!$K$39 | L40: ='Inputs'!$L$38+'Inputs'!$L$39 | M40: ='Inputs'!$M$38+'Inputs'!$M$39 | N40: ='Inputs'!$N$38+'Inputs'!$N$39 | O40: ='Inputs'!$O$38+'Inputs'!$O$39 | P40: ='Inputs'!$P$38+'Inputs'!$P$39
A41: TOTAL LIABILITIES | B41: ='Inputs'!$B$37+'Inputs'!$B$40 | C41: ='Inputs'!$C$37+'Inputs'!$C$40 | D41: ='Inputs'!$D$37+'Inputs'!$D$40 | E41: ='Inputs'!$E$37+'Inputs'!$E$40 | F41: ='Inputs'!$F$37+'Inputs'!$F$40 | G41: ='Inputs'!$G$37+'Inputs'!$G$40 | H41: ='Inputs'!$H$37+'Inputs'!$H$40 | I41: ='Inputs'!$I$37+'Inputs'!$I$40 | J41: ='Inputs'!$J$37+'Inputs'!$J$40 | K41: ='Inputs'!$K$37+'Inputs'!$K$40 | L41: ='Inputs'!$L$37+'Inputs'!$L$40 | M41: ='Inputs'!$M$37+'Inputs'!$M$40 | N41: ='Inputs'!$N$37+'Inputs'!$N$40 | O41: ='Inputs'!$O$37+'Inputs'!$O$40 | P41: ='Inputs'!$P$37+'Inputs'!$P$40
A42: Shareholders' equity
A43: of which: retained earnings
A44: TOTAL LIABILITIES & EQUITY | B44: ='Inputs'!$B$41+'Inputs'!$B$42 | C44: ='Inputs'!$C$41+'Inputs'!$C$42 | D44: ='Inputs'!$D$41+'Inputs'!$D$42 | E44: ='Inputs'!$E$41+'Inputs'!$E$42 | F44: ='Inputs'!$F$41+'Inputs'!$F$42 | G44: ='Inputs'!$G$41+'Inputs'!$G$42 | H44: ='Inputs'!$H$41+'Inputs'!$H$42 | I44: ='Inputs'!$I$41+'Inputs'!$I$42 | J44: ='Inputs'!$J$41+'Inputs'!$J$42 | K44: ='Inputs'!$K$41+'Inputs'!$K$42 | L44: ='Inputs'!$L$41+'Inputs'!$L$42 | M44: ='Inputs'!$M$41+'Inputs'!$M$42 | N44: ='Inputs'!$N$41+'Inputs'!$N$42 | O44: ='Inputs'!$O$41+'Inputs'!$O$42 | P44: ='Inputs'!$P$41+'Inputs'!$P$42
A45: Cash Flow Statement
A46: Operating cash flow
A47: Capital expenditure
A48: Free cash flow | B48: ='Inputs'!$B$46-'Inputs'!$B$47 | C48: ='Inputs'!$C$46-'Inputs'!$C$47 | D48: ='Inputs'!$D$46-'Inputs'!$D$47 | E48: ='Inputs'!$E$46-'Inputs'!$E$47 | F48: ='Inputs'!$F$46-'Inputs'!$F$47 | G48: ='Inputs'!$G$46-'Inputs'!$G$47 | H48: ='Inputs'!$H$46-'Inputs'!$H$47 | I48: ='Inputs'!$I$46-'Inputs'!$I$47 | J48: ='Inputs'!$J$46-'Inputs'!$J$47 | K48: ='Inputs'!$K$46-'Inputs'!$K$47 | L48: ='Inputs'!$L$46-'Inputs'!$L$47 | M48: ='Inputs'!$M$46-'Inputs'!$M$47 | N48: ='Inputs'!$N$46-'Inputs'!$N$47 | O48: ='Inputs'!$O$46-'Inputs'!$O$47 | P48: ='Inputs'!$P$46-'Inputs'!$P$47
A49: Dividends paid
A50: Share buybacks (net)
A51: Market Data & Per-Share
A52: Share price (period close)
A53: Shares outstanding (m)
A54: Market capitalisation | B54: ='Inputs'!$B$52*'Inputs'!$B$53 | C54: ='Inputs'!$C$52*'Inputs'!$C$53 | D54: ='Inputs'!$D$52*'Inputs'!$D$53 | E54: ='Inputs'!$E$52*'Inputs'!$E$53 | F54: ='Inputs'!$F$52*'Inputs'!$F$53 | G54: ='Inputs'!$G$52*'Inputs'!$G$53 | H54: ='Inputs'!$H$52*'Inputs'!$H$53 | I54: ='Inputs'!$I$52*'Inputs'!$I$53 | J54: ='Inputs'!$J$52*'Inputs'!$J$53 | K54: ='Inputs'!$K$52*'Inputs'!$K$53 | L54: ='Inputs'!$L$52*'Inputs'!$L$53 | M54: ='Inputs'!$M$52*'Inputs'!$M$53 | N54: ='Inputs'!$N$52*'Inputs'!$N$53 | O54: ='Inputs'!$O$52*'Inputs'!$O$53 | P54: ='Inputs'!$P$52*'Inputs'!$P$53
A55: Earnings per share (EPS) | B55: =IFERROR('Inputs'!$B$21/'Inputs'!$B$53,"") | C55: =IFERROR('Inputs'!$C$21/'Inputs'!$C$53,"") | D55: =IFERROR('Inputs'!$D$21/'Inputs'!$D$53,"") | E55: =IFERROR('Inputs'!$E$21/'Inputs'!$E$53,"") | F55: =IFERROR('Inputs'!$F$21/'Inputs'!$F$53,"") | G55: =IFERROR('Inputs'!$G$21/'Inputs'!$G$53,"") | H55: =IFERROR('Inputs'!$H$21/'Inputs'!$H$53,"") | I55: =IFERROR('Inputs'!$I$21/'Inputs'!$I$53,"") | J55: =IFERROR('Inputs'!$J$21/'Inputs'!$J$53,"") | K55: =IFERROR('Inputs'!$K$21/'Inputs'!$K$53,"") | L55: =IFERROR('Inputs'!$L$21/'Inputs'!$L$53,"") | M55: =IFERROR('Inputs'!$M$21/'Inputs'!$M$53,"") | N55: =IFERROR('Inputs'!$N$21/'Inputs'!$N$53,"") | O55: =IFERROR('Inputs'!$O$21/'Inputs'!$O$53,"") | P55: =IFERROR('Inputs'!$P$21/'Inputs'!$P$53,"")
A56: Dividend per share (DPS) | B56: =IFERROR('Inputs'!$B$49/'Inputs'!$B$53,"") | C56: =IFERROR('Inputs'!$C$49/'Inputs'!$C$53,"") | D56: =IFERROR('Inputs'!$D$49/'Inputs'!$D$53,"") | E56: =IFERROR('Inputs'!$E$49/'Inputs'!$E$53,"") | F56: =IFERROR('Inputs'!$F$49/'Inputs'!$F$53,"") | G56: =IFERROR('Inputs'!$G$49/'Inputs'!$G$53,"") | H56: =IFERROR('Inputs'!$H$49/'Inputs'!$H$53,"") | I56: =IFERROR('Inputs'!$I$49/'Inputs'!$I$53,"") | J56: =IFERROR('Inputs'!$J$49/'Inputs'!$J$53,"") | K56: =IFERROR('Inputs'!$K$49/'Inputs'!$K$53,"") | L56: =IFERROR('Inputs'!$L$49/'Inputs'!$L$53,"") | M56: =IFERROR('Inputs'!$M$49/'Inputs'!$M$53,"") | N56: =IFERROR('Inputs'!$N$49/'Inputs'!$N$53,"") | O56: =IFERROR('Inputs'!$O$49/'Inputs'!$O$53,"") | P56: =IFERROR('Inputs'!$P$49/'Inputs'!$P$53,"")
A57: Cost of Capital (for ROIC vs WACC)
A58: Risk-free rate | C58: ← input
A59: Equity risk premium | C59: ← input
A60: Beta | C60: ← input
A61: Pre-tax cost of debt | C61: ← input
A62: Tax rate | C62: ← input
A63: Cost of equity Ke = Rf + β×ERP | B63: ='Inputs'!$B$58+'Inputs'!$B$60*'Inputs'!$B$59
A64: After-tax cost of debt | B64: ='Inputs'!$B$61*(1-'Inputs'!$B$62)
A65: Helper Calculations (intermediate steps reused across the workbook)
A66: Total debt = ST + LT debt | B66: ='Inputs'!$B$35+'Inputs'!$B$38 | C66: ='Inputs'!$C$35+'Inputs'!$C$38 | D66: ='Inputs'!$D$35+'Inputs'!$D$38 | E66: ='Inputs'!$E$35+'Inputs'!$E$38 | F66: ='Inputs'!$F$35+'Inputs'!$F$38 | G66: ='Inputs'!$G$35+'Inputs'!$G$38 | H66: ='Inputs'!$H$35+'Inputs'!$H$38 | I66: ='Inputs'!$I$35+'Inputs'!$I$38 | J66: ='Inputs'!$J$35+'Inputs'!$J$38 | K66: ='Inputs'!$K$35+'Inputs'!$K$38 | L66: ='Inputs'!$L$35+'Inputs'!$L$38 | M66: ='Inputs'!$M$35+'Inputs'!$M$38 | N66: ='Inputs'!$N$35+'Inputs'!$N$38 | O66: ='Inputs'!$O$35+'Inputs'!$O$38 | P66: ='Inputs'!$P$35+'Inputs'!$P$38
A67: Net debt = total debt − cash | B67: ='Inputs'!$B$66-'Inputs'!$B$23 | C67: ='Inputs'!$C$66-'Inputs'!$C$23 | D67: ='Inputs'!$D$66-'Inputs'!$D$23 | E67: ='Inputs'!$E$66-'Inputs'!$E$23 | F67: ='Inputs'!$F$66-'Inputs'!$F$23 | G67: ='Inputs'!$G$66-'Inputs'!$G$23 | H67: ='Inputs'!$H$66-'Inputs'!$H$23 | I67: ='Inputs'!$I$66-'Inputs'!$I$23 | J67: ='Inputs'!$J$66-'Inputs'!$J$23 | K67: ='Inputs'!$K$66-'Inputs'!$K$23 | L67: ='Inputs'!$L$66-'Inputs'!$L$23 | M67: ='Inputs'!$M$66-'Inputs'!$M$23 | N67: ='Inputs'!$N$66-'Inputs'!$N$23 | O67: ='Inputs'!$O$66-'Inputs'!$O$23 | P67: ='Inputs'!$P$66-'Inputs'!$P$23
A68: Working capital = CA − CL | B68: ='Inputs'!$B$27-'Inputs'!$B$37 | C68: ='Inputs'!$C$27-'Inputs'!$C$37 | D68: ='Inputs'!$D$27-'Inputs'!$D$37 | E68: ='Inputs'!$E$27-'Inputs'!$E$37 | F68: ='Inputs'!$F$27-'Inputs'!$F$37 | G68: ='Inputs'!$G$27-'Inputs'!$G$37 | H68: ='Inputs'!$H$27-'Inputs'!$H$37 | I68: ='Inputs'!$I$27-'Inputs'!$I$37 | J68: ='Inputs'!$J$27-'Inputs'!$J$37 | K68: ='Inputs'!$K$27-'Inputs'!$K$37 | L68: ='Inputs'!$L$27-'Inputs'!$L$37 | M68: ='Inputs'!$M$27-'Inputs'!$M$37 | N68: ='Inputs'!$N$27-'Inputs'!$N$37 | O68: ='Inputs'!$O$27-'Inputs'!$O$37 | P68: ='Inputs'!$P$27-'Inputs'!$P$37
A69: Capital employed = TA − CL | B69: ='Inputs'!$B$32-'Inputs'!$B$37 | C69: ='Inputs'!$C$32-'Inputs'!$C$37 | D69: ='Inputs'!$D$32-'Inputs'!$D$37 | E69: ='Inputs'!$E$32-'Inputs'!$E$37 | F69: ='Inputs'!$F$32-'Inputs'!$F$37 | G69: ='Inputs'!$G$32-'Inputs'!$G$37 | H69: ='Inputs'!$H$32-'Inputs'!$H$37 | I69: ='Inputs'!$I$32-'Inputs'!$I$37 | J69: ='Inputs'!$J$32-'Inputs'!$J$37 | K69: ='Inputs'!$K$32-'Inputs'!$K$37 | L69: ='Inputs'!$L$32-'Inputs'!$L$37 | M69: ='Inputs'!$M$32-'Inputs'!$M$37 | N69: ='Inputs'!$N$32-'Inputs'!$N$37 | O69: ='Inputs'!$O$32-'Inputs'!$O$37 | P69: ='Inputs'!$P$32-'Inputs'!$P$37
A70: Invested capital = equity + debt − cash | B70: ='Inputs'!$B$42+'Inputs'!$B$66-'Inputs'!$B$23 | C70: ='Inputs'!$C$42+'Inputs'!$C$66-'Inputs'!$C$23 | D70: ='Inputs'!$D$42+'Inputs'!$D$66-'Inputs'!$D$23 | E70: ='Inputs'!$E$42+'Inputs'!$E$66-'Inputs'!$E$23 | F70: ='Inputs'!$F$42+'Inputs'!$F$66-'Inputs'!$F$23 | G70: ='Inputs'!$G$42+'Inputs'!$G$66-'Inputs'!$G$23 | H70: ='Inputs'!$H$42+'Inputs'!$H$66-'Inputs'!$H$23 | I70: ='Inputs'!$I$42+'Inputs'!$I$66-'Inputs'!$I$23 | J70: ='Inputs'!$J$42+'Inputs'!$J$66-'Inputs'!$J$23 | K70: ='Inputs'!$K$42+'Inputs'!$K$66-'Inputs'!$K$23 | L70: ='Inputs'!$L$42+'Inputs'!$L$66-'Inputs'!$L$23 | M70: ='Inputs'!$M$42+'Inputs'!$M$66-'Inputs'!$M$23 | N70: ='Inputs'!$N$42+'Inputs'!$N$66-'Inputs'!$N$23 | O70: ='Inputs'!$O$42+'Inputs'!$O$66-'Inputs'!$O$23 | P70: ='Inputs'!$P$42+'Inputs'!$P$66-'Inputs'!$P$23
A71: NOPAT = EBIT × (1 − tax rate) | B71: ='Inputs'!$B$16*(1-'Inputs'!$B$62) | C71: ='Inputs'!$C$16*(1-'Inputs'!$B$62) | D71: ='Inputs'!$D$16*(1-'Inputs'!$B$62) | E71: ='Inputs'!$E$16*(1-'Inputs'!$B$62) | F71: ='Inputs'!$F$16*(1-'Inputs'!$B$62) | G71: ='Inputs'!$G$16*(1-'Inputs'!$B$62) | H71: ='Inputs'!$H$16*(1-'Inputs'!$B$62) | I71: ='Inputs'!$I$16*(1-'Inputs'!$B$62) | J71: ='Inputs'!$J$16*(1-'Inputs'!$B$62) | K71: ='Inputs'!$K$16*(1-'Inputs'!$B$62) | L71: ='Inputs'!$L$16*(1-'Inputs'!$B$62) | M71: ='Inputs'!$M$16*(1-'Inputs'!$B$62) | N71: ='Inputs'!$N$16*(1-'Inputs'!$B$62) | O71: ='Inputs'!$O$16*(1-'Inputs'!$B$62) | P71: ='Inputs'!$P$16*(1-'Inputs'!$B$62)
A72: Tangible book = equity − goodwill | B72: ='Inputs'!$B$42-'Inputs'!$B$29 | C72: ='Inputs'!$C$42-'Inputs'!$C$29 | D72: ='Inputs'!$D$42-'Inputs'!$D$29 | E72: ='Inputs'!$E$42-'Inputs'!$E$29 | F72: ='Inputs'!$F$42-'Inputs'!$F$29 | G72: ='Inputs'!$G$42-'Inputs'!$G$29 | H72: ='Inputs'!$H$42-'Inputs'!$H$29 | I72: ='Inputs'!$I$42-'Inputs'!$I$29 | J72: ='Inputs'!$J$42-'Inputs'!$J$29 | K72: ='Inputs'!$K$42-'Inputs'!$K$29 | L72: ='Inputs'!$L$42-'Inputs'!$L$29 | M72: ='Inputs'!$M$42-'Inputs'!$M$29 | N72: ='Inputs'!$N$42-'Inputs'!$N$29 | O72: ='Inputs'!$O$42-'Inputs'!$O$29 | P72: ='Inputs'!$P$42-'Inputs'!$P$29
A73: Enterprise value = mkt cap + debt − cash | B73: ='Inputs'!$B$54+'Inputs'!$B$66-'Inputs'!$B$23 | C73: ='Inputs'!$C$54+'Inputs'!$C$66-'Inputs'!$C$23 | D73: ='Inputs'!$D$54+'Inputs'!$D$66-'Inputs'!$D$23 | E73: ='Inputs'!$E$54+'Inputs'!$E$66-'Inputs'!$E$23 | F73: ='Inputs'!$F$54+'Inputs'!$F$66-'Inputs'!$F$23 | G73: ='Inputs'!$G$54+'Inputs'!$G$66-'Inputs'!$G$23 | H73: ='Inputs'!$H$54+'Inputs'!$H$66-'Inputs'!$H$23 | I73: ='Inputs'!$I$54+'Inputs'!$I$66-'Inputs'!$I$23 | J73: ='Inputs'!$J$54+'Inputs'!$J$66-'Inputs'!$J$23 | K73: ='Inputs'!$K$54+'Inputs'!$K$66-'Inputs'!$K$23 | L73: ='Inputs'!$L$54+'Inputs'!$L$66-'Inputs'!$L$23 | M73: ='Inputs'!$M$54+'Inputs'!$M$66-'Inputs'!$M$23 | N73: ='Inputs'!$N$54+'Inputs'!$N$66-'Inputs'!$N$23 | O73: ='Inputs'!$O$54+'Inputs'!$O$66-'Inputs'!$O$23 | P73: ='Inputs'!$P$54+'Inputs'!$P$66-'Inputs'!$P$23
A74: Average equity | C74: =('Inputs'!$B$42+'Inputs'!$C$42)/2 | D74: =('Inputs'!$C$42+'Inputs'!$D$42)/2 | E74: =('Inputs'!$D$42+'Inputs'!$E$42)/2 | F74: =('Inputs'!$E$42+'Inputs'!$F$42)/2 | G74: =('Inputs'!$F$42+'Inputs'!$G$42)/2 | H74: =('Inputs'!$G$42+'Inputs'!$H$42)/2 | I74: =('Inputs'!$H$42+'Inputs'!$I$42)/2 | J74: =('Inputs'!$I$42+'Inputs'!$J$42)/2 | K74: =('Inputs'!$J$42+'Inputs'!$K$42)/2 | L74: =('Inputs'!$K$42+'Inputs'!$L$42)/2 | M74: =('Inputs'!$L$42+'Inputs'!$M$42)/2 | N74: =('Inputs'!$M$42+'Inputs'!$N$42)/2 | O74: =('Inputs'!$N$42+'Inputs'!$O$42)/2 | P74: =('Inputs'!$O$42+'Inputs'!$P$42)/2
A75: Average total assets | C75: =('Inputs'!$B$32+'Inputs'!$C$32)/2 | D75: =('Inputs'!$C$32+'Inputs'!$D$32)/2 | E75: =('Inputs'!$D$32+'Inputs'!$E$32)/2 | F75: =('Inputs'!$E$32+'Inputs'!$F$32)/2 | G75: =('Inputs'!$F$32+'Inputs'!$G$32)/2 | H75: =('Inputs'!$G$32+'Inputs'!$H$32)/2 | I75: =('Inputs'!$H$32+'Inputs'!$I$32)/2 | J75: =('Inputs'!$I$32+'Inputs'!$J$32)/2 | K75: =('Inputs'!$J$32+'Inputs'!$K$32)/2 | L75: =('Inputs'!$K$32+'Inputs'!$L$32)/2 | M75: =('Inputs'!$L$32+'Inputs'!$M$32)/2 | N75: =('Inputs'!$M$32+'Inputs'!$N$32)/2 | O75: =('Inputs'!$N$32+'Inputs'!$O$32)/2 | P75: =('Inputs'!$O$32+'Inputs'!$P$32)/2
A76: Average receivables | C76: =('Inputs'!$B$24+'Inputs'!$C$24)/2 | D76: =('Inputs'!$C$24+'Inputs'!$D$24)/2 | E76: =('Inputs'!$D$24+'Inputs'!$E$24)/2 | F76: =('Inputs'!$E$24+'Inputs'!$F$24)/2 | G76: =('Inputs'!$F$24+'Inputs'!$G$24)/2 | H76: =('Inputs'!$G$24+'Inputs'!$H$24)/2 | I76: =('Inputs'!$H$24+'Inputs'!$I$24)/2 | J76: =('Inputs'!$I$24+'Inputs'!$J$24)/2 | K76: =('Inputs'!$J$24+'Inputs'!$K$24)/2 | L76: =('Inputs'!$K$24+'Inputs'!$L$24)/2 | M76: =('Inputs'!$L$24+'Inputs'!$M$24)/2 | N76: =('Inputs'!$M$24+'Inputs'!$N$24)/2 | O76: =('Inputs'!$N$24+'Inputs'!$O$24)/2 | P76: =('Inputs'!$O$24+'Inputs'!$P$24)/2
A77: Average inventory | C77: =('Inputs'!$B$25+'Inputs'!$C$25)/2 | D77: =('Inputs'!$C$25+'Inputs'!$D$25)/2 | E77: =('Inputs'!$D$25+'Inputs'!$E$25)/2 | F77: =('Inputs'!$E$25+'Inputs'!$F$25)/2 | G77: =('Inputs'!$F$25+'Inputs'!$G$25)/2 | H77: =('Inputs'!$G$25+'Inputs'!$H$25)/2 | I77: =('Inputs'!$H$25+'Inputs'!$I$25)/2 | J77: =('Inputs'!$I$25+'Inputs'!$J$25)/2 | K77: =('Inputs'!$J$25+'Inputs'!$K$25)/2 | L77: =('Inputs'!$K$25+'Inputs'!$L$25)/2 | M77: =('Inputs'!$L$25+'Inputs'!$M$25)/2 | N77: =('Inputs'!$M$25+'Inputs'!$N$25)/2 | O77: =('Inputs'!$N$25+'Inputs'!$O$25)/2 | P77: =('Inputs'!$O$25+'Inputs'!$P$25)/2
A78: Average payables | C78: =('Inputs'!$B$34+'Inputs'!$C$34)/2 | D78: =('Inputs'!$C$34+'Inputs'!$D$34)/2 | E78: =('Inputs'!$D$34+'Inputs'!$E$34)/2 | F78: =('Inputs'!$E$34+'Inputs'!$F$34)/2 | G78: =('Inputs'!$F$34+'Inputs'!$G$34)/2 | H78: =('Inputs'!$G$34+'Inputs'!$H$34)/2 | I78: =('Inputs'!$H$34+'Inputs'!$I$34)/2 | J78: =('Inputs'!$I$34+'Inputs'!$J$34)/2 | K78: =('Inputs'!$J$34+'Inputs'!$K$34)/2 | L78: =('Inputs'!$K$34+'Inputs'!$L$34)/2 | M78: =('Inputs'!$L$34+'Inputs'!$M$34)/2 | N78: =('Inputs'!$M$34+'Inputs'!$N$34)/2 | O78: =('Inputs'!$N$34+'Inputs'!$O$34)/2 | P78: =('Inputs'!$O$34+'Inputs'!$P$34)/2
A79: Average net PP&E | C79: =('Inputs'!$B$28+'Inputs'!$C$28)/2 | D79: =('Inputs'!$C$28+'Inputs'!$D$28)/2 | E79: =('Inputs'!$D$28+'Inputs'!$E$28)/2 | F79: =('Inputs'!$E$28+'Inputs'!$F$28)/2 | G79: =('Inputs'!$F$28+'Inputs'!$G$28)/2 | H79: =('Inputs'!$G$28+'Inputs'!$H$28)/2 | I79: =('Inputs'!$H$28+'Inputs'!$I$28)/2 | J79: =('Inputs'!$I$28+'Inputs'!$J$28)/2 | K79: =('Inputs'!$J$28+'Inputs'!$K$28)/2 | L79: =('Inputs'!$K$28+'Inputs'!$L$28)/2 | M79: =('Inputs'!$L$28+'Inputs'!$M$28)/2 | N79: =('Inputs'!$M$28+'Inputs'!$N$28)/2 | O79: =('Inputs'!$N$28+'Inputs'!$O$28)/2 | P79: =('Inputs'!$O$28+'Inputs'!$P$28)/2
A80: Average invested capital | C80: =('Inputs'!$B$70+'Inputs'!$C$70)/2 | D80: =('Inputs'!$C$70+'Inputs'!$D$70)/2 | E80: =('Inputs'!$D$70+'Inputs'!$E$70)/2 | F80: =('Inputs'!$E$70+'Inputs'!$F$70)/2 | G80: =('Inputs'!$F$70+'Inputs'!$G$70)/2 | H80: =('Inputs'!$G$70+'Inputs'!$H$70)/2 | I80: =('Inputs'!$H$70+'Inputs'!$I$70)/2 | J80: =('Inputs'!$I$70+'Inputs'!$J$70)/2 | K80: =('Inputs'!$J$70+'Inputs'!$K$70)/2 | L80: =('Inputs'!$K$70+'Inputs'!$L$70)/2 | M80: =('Inputs'!$L$70+'Inputs'!$M$70)/2 | N80: =('Inputs'!$M$70+'Inputs'!$N$70)/2 | O80: =('Inputs'!$N$70+'Inputs'!$O$70)/2 | P80: =('Inputs'!$O$70+'Inputs'!$P$70)/2
A82: WACC (latest-year market-value weights) | B82: =IFERROR(('Inputs'!$K$54*'Inputs'!$B$63+'Inputs'!$K$66*'Inputs'!$B$64)/('Inputs'!$K$54+'Inputs'!$K$66),'Inputs'!$B$63) | C82: WACC = We·Ke + Wd·Kd(1−t)

Sheet Common Size
A1: COMMON SIZE & TREND ANALYSIS
A2: Income statement vs revenue, balance sheet vs assets, indexed trend
A3: Institutional Financial Ratio Analysis · v1.0
A5: Dashboard | B5: Inputs | C5: Common Size | D5: Profitability | E5: Liquidity | F5: Solvency | G5: Efficiency | H5: Growth
A6: Valuation | B6: Capital Allocation | C6: Quality | D6: Benchmarking | E6: Guide | F6: Quality Control
A7: All figures in USD millions unless stated; (F) = forecast year.
A8: Line item | B8: FY2015 | C8: FY2016 | D8: FY2017 | E8: FY2018 | F8: FY2019 | G8: FY2020 | H8: FY2021 | I8: FY2022 | J8: FY2023 | K8: FY2024 | L8: FY2025 (F) | M8: FY2026 (F) | N8: FY2027 (F) | O8: FY2028 (F) | P8: FY2029 (F) | Q8: Trend | R8: Assessment
A9: Income Statement — Common Size (% of revenue)
A10: Revenue | B10: =IFERROR('Inputs'!$B$10/'Inputs'!$B$10,"") | C10: =IFERROR('Inputs'!$C$10/'Inputs'!$C$10,"") | D10: =IFERROR('Inputs'!$D$10/'Inputs'!$D$10,"") | E10: =IFERROR('Inputs'!$E$10/'Inputs'!$E$10,"") | F10: =IFERROR('Inputs'!$F$10/'Inputs'!$F$10,"") | G10: =IFERROR('Inputs'!$G$10/'Inputs'!$G$10,"") | H10: =IFERROR('Inputs'!$H$10/'Inputs'!$H$10,"") | I10: =IFERROR('Inputs'!$I$10/'Inputs'!$I$10,"") | J10: =IFERROR('Inputs'!$J$10/'Inputs'!$J$10,"") | K10: =IFERROR('Inputs'!$K$10/'Inputs'!$K$10,"") | L10: =IFERROR('Inputs'!$L$10/'Inputs'!$L$10,"") | M10: =IFERROR('Inputs'!$M$10/'Inputs'!$M$10,"") | N10: =IFERROR('Inputs'!$N$10/'Inputs'!$N$10,"") | O10: =IFERROR('Inputs'!$O$10/'Inputs'!$O$10,"") | P10: =IFERROR('Inputs'!$P$10/'Inputs'!$P$10,"")
A11: Cost of goods sold | B11: =IFERROR('Inputs'!$B$11/'Inputs'!$B$10,"") | C11: =IFERROR('Inputs'!$C$11/'Inputs'!$C$10,"") | D11: =IFERROR('Inputs'!$D$11/'Inputs'!$D$10,"") | E11: =IFERROR('Inputs'!$E$11/'Inputs'!$E$10,"") | F11: =IFERROR('Inputs'!$F$11/'Inputs'!$F$10,"") | G11: =IFERROR('Inputs'!$G$11/'Inputs'!$G$10,"") | H11: =IFERROR('Inputs'!$H$11/'Inputs'!$H$10,"") | I11: =IFERROR('Inputs'!$I$11/'Inputs'!$I$10,"") | J11: =IFERROR('Inputs'!$J$11/'Inputs'!$J$10,"") | K11: =IFERROR('Inputs'!$K$11/'Inputs'!$K$10,"") | L11: =IFERROR('Inputs'!$L$11/'Inputs'!$L$10,"") | M11: =IFERROR('Inputs'!$M$11/'Inputs'!$M$10,"") | N11: =IFERROR('Inputs'!$N$11/'Inputs'!$N$10,"") | O11: =IFERROR('Inputs'!$O$11/'Inputs'!$O$10,"") | P11: =IFERROR('Inputs'!$P$11/'Inputs'!$P$10,"")
A12: Gross profit | B12: =IFERROR('Inputs'!$B$12/'Inputs'!$B$10,"") | C12: =IFERROR('Inputs'!$C$12/'Inputs'!$C$10,"") | D12: =IFERROR('Inputs'!$D$12/'Inputs'!$D$10,"") | E12: =IFERROR('Inputs'!$E$12/'Inputs'!$E$10,"") | F12: =IFERROR('Inputs'!$F$12/'Inputs'!$F$10,"") | G12: =IFERROR('Inputs'!$G$12/'Inputs'!$G$10,"") | H12: =IFERROR('Inputs'!$H$12/'Inputs'!$H$10,"") | I12: =IFERROR('Inputs'!$I$12/'Inputs'!$I$10,"") | J12: =IFERROR('Inputs'!$J$12/'Inputs'!$J$10,"") | K12: =IFERROR('Inputs'!$K$12/'Inputs'!$K$10,"") | L12: =IFERROR('Inputs'!$L$12/'Inputs'!$L$10,"") | M12: =IFERROR('Inputs'!$M$12/'Inputs'!$M$10,"") | N12: =IFERROR('Inputs'!$N$12/'Inputs'!$N$10,"") | O12: =IFERROR('Inputs'!$O$12/'Inputs'!$O$10,"") | P12: =IFERROR('Inputs'!$P$12/'Inputs'!$P$10,"")
A13: Operating expenses | B13: =IFERROR('Inputs'!$B$13/'Inputs'!$B$10,"") | C13: =IFERROR('Inputs'!$C$13/'Inputs'!$C$10,"") | D13: =IFERROR('Inputs'!$D$13/'Inputs'!$D$10,"") | E13: =IFERROR('Inputs'!$E$13/'Inputs'!$E$10,"") | F13: =IFERROR('Inputs'!$F$13/'Inputs'!$F$10,"") | G13: =IFERROR('Inputs'!$G$13/'Inputs'!$G$10,"") | H13: =IFERROR('Inputs'!$H$13/'Inputs'!$H$10,"") | I13: =IFERROR('Inputs'!$I$13/'Inputs'!$I$10,"") | J13: =IFERROR('Inputs'!$J$13/'Inputs'!$J$10,"") | K13: =IFERROR('Inputs'!$K$13/'Inputs'!$K$10,"") | L13: =IFERROR('Inputs'!$L$13/'Inputs'!$L$10,"") | M13: =IFERROR('Inputs'!$M$13/'Inputs'!$M$10,"") | N13: =IFERROR('Inputs'!$N$13/'Inputs'!$N$10,"") | O13: =IFERROR('Inputs'!$O$13/'Inputs'!$O$10,"") | P13: =IFERROR('Inputs'!$P$13/'Inputs'!$P$10,"")
A14: EBITDA | B14: =IFERROR('Inputs'!$B$14/'Inputs'!$B$10,"") | C14: =IFERROR('Inputs'!$C$14/'Inputs'!$C$10,"") | D14: =IFERROR('Inputs'!$D$14/'Inputs'!$D$10,"") | E14: =IFERROR('Inputs'!$E$14/'Inputs'!$E$10,"") | F14: =IFERROR('Inputs'!$F$14/'Inputs'!$F$10,"") | G14: =IFERROR('Inputs'!$G$14/'Inputs'!$G$10,"") | H14: =IFERROR('Inputs'!$H$14/'Inputs'!$H$10,"") | I14: =IFERROR('Inputs'!$I$14/'Inputs'!$I$10,"") | J14: =IFERROR('Inputs'!$J$14/'Inputs'!$J$10,"") | K14: =IFERROR('Inputs'!$K$14/'Inputs'!$K$10,"") | L14: =IFERROR('Inputs'!$L$14/'Inputs'!$L$10,"") | M14: =IFERROR('Inputs'!$M$14/'Inputs'!$M$10,"") | N14: =IFERROR('Inputs'!$N$14/'Inputs'!$N$10,"") | O14: =IFERROR('Inputs'!$O$14/'Inputs'!$O$10,"") | P14: =IFERROR('Inputs'!$P$14/'Inputs'!$P$10,"")
A15: Depreciation | B15: =IFERROR('Inputs'!$B$15/'Inputs'!$B$10,"") | C15: =IFERROR('Inputs'!$C$15/'Inputs'!$C$10,"") | D15: =IFERROR('Inputs'!$D$15/'Inputs'!$D$10,"") | E15: =IFERROR('Inputs'!$E$15/'Inputs'!$E$10,"") | F15: =IFERROR('Inputs'!$F$15/'Inputs'!$F$10,"") | G15: =IFERROR('Inputs'!$G$15/'Inputs'!$G$10,"") | H15: =IFERROR('Inputs'!$H$15/'Inputs'!$H$10,"") | I15: =IFERROR('Inputs'!$I$15/'Inputs'!$I$10,"") | J15: =IFERROR('Inputs'!$J$15/'Inputs'!$J$10,"") | K15: =IFERROR('Inputs'!$K$15/'Inputs'!$K$10,"") | L15: =IFERROR('Inputs'!$L$15/'Inputs'!$L$10,"") | M15: =IFERROR('Inputs'!$M$15/'Inputs'!$M$10,"") | N15: =IFERROR('Inputs'!$N$15/'Inputs'!$N$10,"") | O15: =IFERROR('Inputs'!$O$15/'Inputs'!$O$10,"") | P15: =IFERROR('Inputs'!$P$15/'Inputs'!$P$10,"")
A16: EBIT | B16: =IFERROR('Inputs'!$B$16/'Inputs'!$B$10,"") | C16: =IFERROR('Inputs'!$C$16/'Inputs'!$C$10,"") | D16: =IFERROR('Inputs'!$D$16/'Inputs'!$D$10,"") | E16: =IFERROR('Inputs'!$E$16/'Inputs'!$E$10,"") | F16: =IFERROR('Inputs'!$F$16/'Inputs'!$F$10,"") | G16: =IFERROR('Inputs'!$G$16/'Inputs'!$G$10,"") | H16: =IFERROR('Inputs'!$H$16/'Inputs'!$H$10,"") | I16: =IFERROR('Inputs'!$I$16/'Inputs'!$I$10,"") | J16: =IFERROR('Inputs'!$J$16/'Inputs'!$J$10,"") | K16: =IFERROR('Inputs'!$K$16/'Inputs'!$K$10,"") | L16: =IFERROR('Inputs'!$L$16/'Inputs'!$L$10,"") | M16: =IFERROR('Inputs'!$M$16/'Inputs'!$M$10,"") | N16: =IFERROR('Inputs'!$N$16/'Inputs'!$N$10,"") | O16: =IFERROR('Inputs'!$O$16/'Inputs'!$O$10,"") | P16: =IFERROR('Inputs'!$P$16/'Inputs'!$P$10,"")
A17: Interest expense | B17: =IFERROR('Inputs'!$B$17/'Inputs'!$B$10,"") | C17: =IFERROR('Inputs'!$C$17/'Inputs'!$C$10,"") | D17: =IFERROR('Inputs'!$D$17/'Inputs'!$D$10,"") | E17: =IFERROR('Inputs'!$E$17/'Inputs'!$E$10,"") | F17: =IFERROR('Inputs'!$F$17/'Inputs'!$F$10,"") | G17: =IFERROR('Inputs'!$G$17/'Inputs'!$G$10,"") | H17: =IFERROR('Inputs'!$H$17/'Inputs'!$H$10,"") | I17: =IFERROR('Inputs'!$I$17/'Inputs'!$I$10,"") | J17: =IFERROR('Inputs'!$J$17/'Inputs'!$J$10,"") | K17: =IFERROR('Inputs'!$K$17/'Inputs'!$K$10,"") | L17: =IFERROR('Inputs'!$L$17/'Inputs'!$L$10,"") | M17: =IFERROR('Inputs'!$M$17/'Inputs'!$M$10,"") | N17: =IFERROR('Inputs'!$N$17/'Inputs'!$N$10,"") | O17: =IFERROR('Inputs'!$O$17/'Inputs'!$O$10,"") | P17: =IFERROR('Inputs'!$P$17/'Inputs'!$P$10,"")
A18: Pre-tax income | B18: =IFERROR('Inputs'!$B$19/'Inputs'!$B$10,"") | C18: =IFERROR('Inputs'!$C$19/'Inputs'!$C$10,"") | D18: =IFERROR('Inputs'!$D$19/'Inputs'!$D$10,"") | E18: =IFERROR('Inputs'!$E$19/'Inputs'!$E$10,"") | F18: =IFERROR('Inputs'!$F$19/'Inputs'!$F$10,"") | G18: =IFERROR('Inputs'!$G$19/'Inputs'!$G$10,"") | H18: =IFERROR('Inputs'!$H$19/'Inputs'!$H$10,"") | I18: =IFERROR('Inputs'!$I$19/'Inputs'!$I$10,"") | J18: =IFERROR('Inputs'!$J$19/'Inputs'!$J$10,"") | K18: =IFERROR('Inputs'!$K$19/'Inputs'!$K$10,"") | L18: =IFERROR('Inputs'!$L$19/'Inputs'!$L$10,"") | M18: =IFERROR('Inputs'!$M$19/'Inputs'!$M$10,"") | N18: =IFERROR('Inputs'!$N$19/'Inputs'!$N$10,"") | O18: =IFERROR('Inputs'!$O$19/'Inputs'!$O$10,"") | P18: =IFERROR('Inputs'!$P$19/'Inputs'!$P$10,"")
A19: Income tax | B19: =IFERROR('Inputs'!$B$20/'Inputs'!$B$10,"") | C19: =IFERROR('Inputs'!$C$20/'Inputs'!$C$10,"") | D19: =IFERROR('Inputs'!$D$20/'Inputs'!$D$10,"") | E19: =IFERROR('Inputs'!$E$20/'Inputs'!$E$10,"") | F19: =IFERROR('Inputs'!$F$20/'Inputs'!$F$10,"") | G19: =IFERROR('Inputs'!$G$20/'Inputs'!$G$10,"") | H19: =IFERROR('Inputs'!$H$20/'Inputs'!$H$10,"") | I19: =IFERROR('Inputs'!$I$20/'Inputs'!$I$10,"") | J19: =IFERROR('Inputs'!$J$20/'Inputs'!$J$10,"") | K19: =IFERROR('Inputs'!$K$20/'Inputs'!$K$10,"") | L19: =IFERROR('Inputs'!$L$20/'Inputs'!$L$10,"") | M19: =IFERROR('Inputs'!$M$20/'Inputs'!$M$10,"") | N19: =IFERROR('Inputs'!$N$20/'Inputs'!$N$10,"") | O19: =IFERROR('Inputs'!$O$20/'Inputs'!$O$10,"") | P19: =IFERROR('Inputs'!$P$20/'Inputs'!$P$10,"")
A20: Net income | B20: =IFERROR('Inputs'!$B$21/'Inputs'!$B$10,"") | C20: =IFERROR('Inputs'!$C$21/'Inputs'!$C$10,"") | D20: =IFERROR('Inputs'!$D$21/'Inputs'!$D$10,"") | E20: =IFERROR('Inputs'!$E$21/'Inputs'!$E$10,"") | F20: =IFERROR('Inputs'!$F$21/'Inputs'!$F$10,"") | G20: =IFERROR('Inputs'!$G$21/'Inputs'!$G$10,"") | H20: =IFERROR('Inputs'!$H$21/'Inputs'!$H$10,"") | I20: =IFERROR('Inputs'!$I$21/'Inputs'!$I$10,"") | J20: =IFERROR('Inputs'!$J$21/'Inputs'!$J$10,"") | K20: =IFERROR('Inputs'!$K$21/'Inputs'!$K$10,"") | L20: =IFERROR('Inputs'!$L$21/'Inputs'!$L$10,"") | M20: =IFERROR('Inputs'!$M$21/'Inputs'!$M$10,"") | N20: =IFERROR('Inputs'!$N$21/'Inputs'!$N$10,"") | O20: =IFERROR('Inputs'!$O$21/'Inputs'!$O$10,"") | P20: =IFERROR('Inputs'!$P$21/'Inputs'!$P$10,"")
A22: Balance Sheet — Common Size (% of total assets)
A23: Cash & equivalents | B23: =IFERROR('Inputs'!$B$23/'Inputs'!$B$32,"") | C23: =IFERROR('Inputs'!$C$23/'Inputs'!$C$32,"") | D23: =IFERROR('Inputs'!$D$23/'Inputs'!$D$32,"") | E23: =IFERROR('Inputs'!$E$23/'Inputs'!$E$32,"") | F23: =IFERROR('Inputs'!$F$23/'Inputs'!$F$32,"") | G23: =IFERROR('Inputs'!$G$23/'Inputs'!$G$32,"") | H23: =IFERROR('Inputs'!$H$23/'Inputs'!$H$32,"") | I23: =IFERROR('Inputs'!$I$23/'Inputs'!$I$32,"") | J23: =IFERROR('Inputs'!$J$23/'Inputs'!$J$32,"") | K23: =IFERROR('Inputs'!$K$23/'Inputs'!$K$32,"") | L23: =IFERROR('Inputs'!$L$23/'Inputs'!$L$32,"") | M23: =IFERROR('Inputs'!$M$23/'Inputs'!$M$32,"") | N23: =IFERROR('Inputs'!$N$23/'Inputs'!$N$32,"") | O23: =IFERROR('Inputs'!$O$23/'Inputs'!$O$32,"") | P23: =IFERROR('Inputs'!$P$23/'Inputs'!$P$32,"")
A24: Receivables | B24: =IFERROR('Inputs'!$B$24/'Inputs'!$B$32,"") | C24: =IFERROR('Inputs'!$C$24/'Inputs'!$C$32,"") | D24: =IFERROR('Inputs'!$D$24/'Inputs'!$D$32,"") | E24: =IFERROR('Inputs'!$E$24/'Inputs'!$E$32,"") | F24: =IFERROR('Inputs'!$F$24/'Inputs'!$F$32,"") | G24: =IFERROR('Inputs'!$G$24/'Inputs'!$G$32,"") | H24: =IFERROR('Inputs'!$H$24/'Inputs'!$H$32,"") | I24: =IFERROR('Inputs'!$I$24/'Inputs'!$I$32,"") | J24: =IFERROR('Inputs'!$J$24/'Inputs'!$J$32,"") | K24: =IFERROR('Inputs'!$K$24/'Inputs'!$K$32,"") | L24: =IFERROR('Inputs'!$L$24/'Inputs'!$L$32,"") | M24: =IFERROR('Inputs'!$M$24/'Inputs'!$M$32,"") | N24: =IFERROR('Inputs'!$N$24/'Inputs'!$N$32,"") | O24: =IFERROR('Inputs'!$O$24/'Inputs'!$O$32,"") | P24: =IFERROR('Inputs'!$P$24/'Inputs'!$P$32,"")
A25: Inventory | B25: =IFERROR('Inputs'!$B$25/'Inputs'!$B$32,"") | C25: =IFERROR('Inputs'!$C$25/'Inputs'!$C$32,"") | D25: =IFERROR('Inputs'!$D$25/'Inputs'!$D$32,"") | E25: =IFERROR('Inputs'!$E$25/'Inputs'!$E$32,"") | F25: =IFERROR('Inputs'!$F$25/'Inputs'!$F$32,"") | G25: =IFERROR('Inputs'!$G$25/'Inputs'!$G$32,"") | H25: =IFERROR('Inputs'!$H$25/'Inputs'!$H$32,"") | I25: =IFERROR('Inputs'!$I$25/'Inputs'!$I$32,"") | J25: =IFERROR('Inputs'!$J$25/'Inputs'!$J$32,"") | K25: =IFERROR('Inputs'!$K$25/'Inputs'!$K$32,"") | L25: =IFERROR('Inputs'!$L$25/'Inputs'!$L$32,"") | M25: =IFERROR('Inputs'!$M$25/'Inputs'!$M$32,"") | N25: =IFERROR('Inputs'!$N$25/'Inputs'!$N$32,"") | O25: =IFERROR('Inputs'!$O$25/'Inputs'!$O$32,"") | P25: =IFERROR('Inputs'!$P$25/'Inputs'!$P$32,"")
A26: Other current assets | B26: =IFERROR('Inputs'!$B$26/'Inputs'!$B$32,"") | C26: =IFERROR('Inputs'!$C$26/'Inputs'!$C$32,"") | D26: =IFERROR('Inputs'!$D$26/'Inputs'!$D$32,"") | E26: =IFERROR('Inputs'!$E$26/'Inputs'!$E$32,"") | F26: =IFERROR('Inputs'!$F$26/'Inputs'!$F$32,"") | G26: =IFERROR('Inputs'!$G$26/'Inputs'!$G$32,"") | H26: =IFERROR('Inputs'!$H$26/'Inputs'!$H$32,"") | I26: =IFERROR('Inputs'!$I$26/'Inputs'!$I$32,"") | J26: =IFERROR('Inputs'!$J$26/'Inputs'!$J$32,"") | K26: =IFERROR('Inputs'!$K$26/'Inputs'!$K$32,"") | L26: =IFERROR('Inputs'!$L$26/'Inputs'!$L$32,"") | M26: =IFERROR('Inputs'!$M$26/'Inputs'!$M$32,"") | N26: =IFERROR('Inputs'!$N$26/'Inputs'!$N$32,"") | O26: =IFERROR('Inputs'!$O$26/'Inputs'!$O$32,"") | P26: =IFERROR('Inputs'!$P$26/'Inputs'!$P$32,"")
A27: Total current assets | B27: =IFERROR('Inputs'!$B$27/'Inputs'!$B$32,"") | C27: =IFERROR('Inputs'!$C$27/'Inputs'!$C$32,"") | D27: =IFERROR('Inputs'!$D$27/'Inputs'!$D$32,"") | E27: =IFERROR('Inputs'!$E$27/'Inputs'!$E$32,"") | F27: =IFERROR('Inputs'!$F$27/'Inputs'!$F$32,"") | G27: =IFERROR('Inputs'!$G$27/'Inputs'!$G$32,"") | H27: =IFERROR('Inputs'!$H$27/'Inputs'!$H$32,"") | I27: =IFERROR('Inputs'!$I$27/'Inputs'!$I$32,"") | J27: =IFERROR('Inputs'!$J$27/'Inputs'!$J$32,"") | K27: =IFERROR('Inputs'!$K$27/'Inputs'!$K$32,"") | L27: =IFERROR('Inputs'!$L$27/'Inputs'!$L$32,"") | M27: =IFERROR('Inputs'!$M$27/'Inputs'!$M$32,"") | N27: =IFERROR('Inputs'!$N$27/'Inputs'!$N$32,"") | O27: =IFERROR('Inputs'!$O$27/'Inputs'!$O$32,"") | P27: =IFERROR('Inputs'!$P$27/'Inputs'!$P$32,"")
A28: PP&E (net) | B28: =IFERROR('Inputs'!$B$28/'Inputs'!$B$32,"") | C28: =IFERROR('Inputs'!$C$28/'Inputs'!$C$32,"") | D28: =IFERROR('Inputs'!$D$28/'Inputs'!$D$32,"") | E28: =IFERROR('Inputs'!$E$28/'Inputs'!$E$32,"") | F28: =IFERROR('Inputs'!$F$28/'Inputs'!$F$32,"") | G28: =IFERROR('Inputs'!$G$28/'Inputs'!$G$32,"") | H28: =IFERROR('Inputs'!$H$28/'Inputs'!$H$32,"") | I28: =IFERROR('Inputs'!$I$28/'Inputs'!$I$32,"") | J28: =IFERROR('Inputs'!$J$28/'Inputs'!$J$32,"") | K28: =IFERROR('Inputs'!$K$28/'Inputs'!$K$32,"") | L28: =IFERROR('Inputs'!$L$28/'Inputs'!$L$32,"") | M28: =IFERROR('Inputs'!$M$28/'Inputs'!$M$32,"") | N28: =IFERROR('Inputs'!$N$28/'Inputs'!$N$32,"") | O28: =IFERROR('Inputs'!$O$28/'Inputs'!$O$32,"") | P28: =IFERROR('Inputs'!$P$28/'Inputs'!$P$32,"")
A29: Goodwill & intangibles | B29: =IFERROR('Inputs'!$B$29/'Inputs'!$B$32,"") | C29: =IFERROR('Inputs'!$C$29/'Inputs'!$C$32,"") | D29: =IFERROR('Inputs'!$D$29/'Inputs'!$D$32,"") | E29: =IFERROR('Inputs'!$E$29/'Inputs'!$E$32,"") | F29: =IFERROR('Inputs'!$F$29/'Inputs'!$F$32,"") | G29: =IFERROR('Inputs'!$G$29/'Inputs'!$G$32,"") | H29: =IFERROR('Inputs'!$H$29/'Inputs'!$H$32,"") | I29: =IFERROR('Inputs'!$I$29/'Inputs'!$I$32,"") | J29: =IFERROR('Inputs'!$J$29/'Inputs'!$J$32,"") | K29: =IFERROR('Inputs'!$K$29/'Inputs'!$K$32,"") | L29: =IFERROR('Inputs'!$L$29/'Inputs'!$L$32,"") | M29: =IFERROR('Inputs'!$M$29/'Inputs'!$M$32,"") | N29: =IFERROR('Inputs'!$N$29/'Inputs'!$N$32,"") | O29: =IFERROR('Inputs'!$O$29/'Inputs'!$O$32,"") | P29: =IFERROR('Inputs'!$P$29/'Inputs'!$P$32,"")
A30: Other non-current assets | B30: =IFERROR('Inputs'!$B$30/'Inputs'!$B$32,"") | C30: =IFERROR('Inputs'!$C$30/'Inputs'!$C$32,"") | D30: =IFERROR('Inputs'!$D$30/'Inputs'!$D$32,"") | E30: =IFERROR('Inputs'!$E$30/'Inputs'!$E$32,"") | F30: =IFERROR('Inputs'!$F$30/'Inputs'!$F$32,"") | G30: =IFERROR('Inputs'!$G$30/'Inputs'!$G$32,"") | H30: =IFERROR('Inputs'!$H$30/'Inputs'!$H$32,"") | I30: =IFERROR('Inputs'!$I$30/'Inputs'!$I$32,"") | J30: =IFERROR('Inputs'!$J$30/'Inputs'!$J$32,"") | K30: =IFERROR('Inputs'!$K$30/'Inputs'!$K$32,"") | L30: =IFERROR('Inputs'!$L$30/'Inputs'!$L$32,"") | M30: =IFERROR('Inputs'!$M$30/'Inputs'!$M$32,"") | N30: =IFERROR('Inputs'!$N$30/'Inputs'!$N$32,"") | O30: =IFERROR('Inputs'!$O$30/'Inputs'!$O$32,"") | P30: =IFERROR('Inputs'!$P$30/'Inputs'!$P$32,"")
A31: Total current liabilities | B31: =IFERROR('Inputs'!$B$37/'Inputs'!$B$32,"") | C31: =IFERROR('Inputs'!$C$37/'Inputs'!$C$32,"") | D31: =IFERROR('Inputs'!$D$37/'Inputs'!$D$32,"") | E31: =IFERROR('Inputs'!$E$37/'Inputs'!$E$32,"") | F31: =IFERROR('Inputs'!$F$37/'Inputs'!$F$32,"") | G31: =IFERROR('Inputs'!$G$37/'Inputs'!$G$32,"") | H31: =IFERROR('Inputs'!$H$37/'Inputs'!$H$32,"") | I31: =IFERROR('Inputs'!$I$37/'Inputs'!$I$32,"") | J31: =IFERROR('Inputs'!$J$37/'Inputs'!$J$32,"") | K31: =IFERROR('Inputs'!$K$37/'Inputs'!$K$32,"") | L31: =IFERROR('Inputs'!$L$37/'Inputs'!$L$32,"") | M31: =IFERROR('Inputs'!$M$37/'Inputs'!$M$32,"") | N31: =IFERROR('Inputs'!$N$37/'Inputs'!$N$32,"") | O31: =IFERROR('Inputs'!$O$37/'Inputs'!$O$32,"") | P31: =IFERROR('Inputs'!$P$37/'Inputs'!$P$32,"")
A32: Long-term debt | B32: =IFERROR('Inputs'!$B$38/'Inputs'!$B$32,"") | C32: =IFERROR('Inputs'!$C$38/'Inputs'!$C$32,"") | D32: =IFERROR('Inputs'!$D$38/'Inputs'!$D$32,"") | E32: =IFERROR('Inputs'!$E$38/'Inputs'!$E$32,"") | F32: =IFERROR('Inputs'!$F$38/'Inputs'!$F$32,"") | G32: =IFERROR('Inputs'!$G$38/'Inputs'!$G$32,"") | H32: =IFERROR('Inputs'!$H$38/'Inputs'!$H$32,"") | I32: =IFERROR('Inputs'!$I$38/'Inputs'!$I$32,"") | J32: =IFERROR('Inputs'!$J$38/'Inputs'!$J$32,"") | K32: =IFERROR('Inputs'!$K$38/'Inputs'!$K$32,"") | L32: =IFERROR('Inputs'!$L$38/'Inputs'!$L$32,"") | M32: =IFERROR('Inputs'!$M$38/'Inputs'!$M$32,"") | N32: =IFERROR('Inputs'!$N$38/'Inputs'!$N$32,"") | O32: =IFERROR('Inputs'!$O$38/'Inputs'!$O$32,"") | P32: =IFERROR('Inputs'!$P$38/'Inputs'!$P$32,"")
A33: Total liabilities | B33: =IFERROR('Inputs'!$B$41/'Inputs'!$B$32,"") | C33: =IFERROR('Inputs'!$C$41/'Inputs'!$C$32,"") | D33: =IFERROR('Inputs'!$D$41/'Inputs'!$D$32,"") | E33: =IFERROR('Inputs'!$E$41/'Inputs'!$E$32,"") | F33: =IFERROR('Inputs'!$F$41/'Inputs'!$F$32,"") | G33: =IFERROR('Inputs'!$G$41/'Inputs'!$G$32,"") | H33: =IFERROR('Inputs'!$H$41/'Inputs'!$H$32,"") | I33: =IFERROR('Inputs'!$I$41/'Inputs'!$I$32,"") | J33: =IFERROR('Inputs'!$J$41/'Inputs'!$J$32,"") | K33: =IFERROR('Inputs'!$K$41/'Inputs'!$K$32,"") | L33: =IFERROR('Inputs'!$L$41/'Inputs'!$L$32,"") | M33: =IFERROR('Inputs'!$M$41/'Inputs'!$M$32,"") | N33: =IFERROR('Inputs'!$N$41/'Inputs'!$N$32,"") | O33: =IFERROR('Inputs'!$O$41/'Inputs'!$O$32,"") | P33: =IFERROR('Inputs'!$P$41/'Inputs'!$P$32,"")
A34: Shareholders' equity | B34: =IFERROR('Inputs'!$B$42/'Inputs'!$B$32,"") | C34: =IFERROR('Inputs'!$C$42/'Inputs'!$C$32,"") | D34: =IFERROR('Inputs'!$D$42/'Inputs'!$D$32,"") | E34: =IFERROR('Inputs'!$E$42/'Inputs'!$E$32,"") | F34: =IFERROR('Inputs'!$F$42/'Inputs'!$F$32,"") | G34: =IFERROR('Inputs'!$G$42/'Inputs'!$G$32,"") | H34: =IFERROR('Inputs'!$H$42/'Inputs'!$H$32,"") | I34: =IFERROR('Inputs'!$I$42/'Inputs'!$I$32,"") | J34: =IFERROR('Inputs'!$J$42/'Inputs'!$J$32,"") | K34: =IFERROR('Inputs'!$K$42/'Inputs'!$K$32,"") | L34: =IFERROR('Inputs'!$L$42/'Inputs'!$L$32,"") | M34: =IFERROR('Inputs'!$M$42/'Inputs'!$M$32,"") | N34: =IFERROR('Inputs'!$N$42/'Inputs'!$N$32,"") | O34: =IFERROR('Inputs'!$O$42/'Inputs'!$O$32,"") | P34: =IFERROR('Inputs'!$P$42/'Inputs'!$P$32,"")
A36: Horizontal / Trend Analysis (indexed to first year = 100)
A37: Revenue index (FY2015=100) | B37: =IFERROR('Inputs'!$B$10/'Inputs'!$B$10*100,"") | C37: =IFERROR('Inputs'!$C$10/'Inputs'!$B$10*100,"") | D37: =IFERROR('Inputs'!$D$10/'Inputs'!$B$10*100,"") | E37: =IFERROR('Inputs'!$E$10/'Inputs'!$B$10*100,"") | F37: =IFERROR('Inputs'!$F$10/'Inputs'!$B$10*100,"") | G37: =IFERROR('Inputs'!$G$10/'Inputs'!$B$10*100,"") | H37: =IFERROR('Inputs'!$H$10/'Inputs'!$B$10*100,"") | I37: =IFERROR('Inputs'!$I$10/'Inputs'!$B$10*100,"") | J37: =IFERROR('Inputs'!$J$10/'Inputs'!$B$10*100,"") | K37: =IFERROR('Inputs'!$K$10/'Inputs'!$B$10*100,"") | L37: =IFERROR('Inputs'!$L$10/'Inputs'!$B$10*100,"") | M37: =IFERROR('Inputs'!$M$10/'Inputs'!$B$10*100,"") | N37: =IFERROR('Inputs'!$N$10/'Inputs'!$B$10*100,"") | O37: =IFERROR('Inputs'!$O$10/'Inputs'!$B$10*100,"") | P37: =IFERROR('Inputs'!$P$10/'Inputs'!$B$10*100,"")
A38: Net income index (FY2015=100) | B38: =IFERROR('Inputs'!$B$21/'Inputs'!$B$21*100,"") | C38: =IFERROR('Inputs'!$C$21/'Inputs'!$B$21*100,"") | D38: =IFERROR('Inputs'!$D$21/'Inputs'!$B$21*100,"") | E38: =IFERROR('Inputs'!$E$21/'Inputs'!$B$21*100,"") | F38: =IFERROR('Inputs'!$F$21/'Inputs'!$B$21*100,"") | G38: =IFERROR('Inputs'!$G$21/'Inputs'!$B$21*100,"") | H38: =IFERROR('Inputs'!$H$21/'Inputs'!$B$21*100,"") | I38: =IFERROR('Inputs'!$I$21/'Inputs'!$B$21*100,"") | J38: =IFERROR('Inputs'!$J$21/'Inputs'!$B$21*100,"") | K38: =IFERROR('Inputs'!$K$21/'Inputs'!$B$21*100,"") | L38: =IFERROR('Inputs'!$L$21/'Inputs'!$B$21*100,"") | M38: =IFERROR('Inputs'!$M$21/'Inputs'!$B$21*100,"") | N38: =IFERROR('Inputs'!$N$21/'Inputs'!$B$21*100,"") | O38: =IFERROR('Inputs'!$O$21/'Inputs'!$B$21*100,"") | P38: =IFERROR('Inputs'!$P$21/'Inputs'!$B$21*100,"")
A39: Equity index (FY2015=100) | B39: =IFERROR('Inputs'!$B$42/'Inputs'!$B$42*100,"") | C39: =IFERROR('Inputs'!$C$42/'Inputs'!$B$42*100,"") | D39: =IFERROR('Inputs'!$D$42/'Inputs'!$B$42*100,"") | E39: =IFERROR('Inputs'!$E$42/'Inputs'!$B$42*100,"") | F39: =IFERROR('Inputs'!$F$42/'Inputs'!$B$42*100,"") | G39: =IFERROR('Inputs'!$G$42/'Inputs'!$B$42*100,"") | H39: =IFERROR('Inputs'!$H$42/'Inputs'!$B$42*100,"") | I39: =IFERROR('Inputs'!$I$42/'Inputs'!$B$42*100,"") | J39: =IFERROR('Inputs'!$J$42/'Inputs'!$B$42*100,"") | K39: =IFERROR('Inputs'!$K$42/'Inputs'!$B$42*100,"") | L39: =IFERROR('Inputs'!$L$42/'Inputs'!$B$42*100,"") | M39: =IFERROR('Inputs'!$M$42/'Inputs'!$B$42*100,"") | N39: =IFERROR('Inputs'!$N$42/'Inputs'!$B$42*100,"") | O39: =IFERROR('Inputs'!$O$42/'Inputs'!$B$42*100,"") | P39: =IFERROR('Inputs'!$P$42/'Inputs'!$B$42*100,"")
A41: Common-size analysis normalises the statements so structural shifts and trends are visible regardless of absolute size. Heat-maps highlight the gradient.

Sheet Profitability
A1: PROFITABILITY RATIOS
A2: Margins, returns on capital and DuPont decomposition
A3: Institutional Financial Ratio Analysis · v1.0
A5: Dashboard | B5: Inputs | C5: Common Size | D5: Profitability | E5: Liquidity | F5: Solvency | G5: Efficiency | H5: Growth
A6: Valuation | B6: Capital Allocation | C6: Quality | D6: Benchmarking | E6: Guide | F6: Quality Control
A7: All figures in USD millions unless stated; (F) = forecast year.
A8: Profitability ratio | B8: FY2015 | C8: FY2016 | D8: FY2017 | E8: FY2018 | F8: FY2019 | G8: FY2020 | H8: FY2021 | I8: FY2022 | J8: FY2023 | K8: FY2024 | L8: FY2025 (F) | M8: FY2026 (F) | N8: FY2027 (F) | O8: FY2028 (F) | P8: FY2029 (F) | Q8: Trend | R8: Assessment
A9: Margins
A10: Gross margin | B10: =IFERROR('Inputs'!$B$12/'Inputs'!$B$10,"") | C10: =IFERROR('Inputs'!$C$12/'Inputs'!$C$10,"") | D10: =IFERROR('Inputs'!$D$12/'Inputs'!$D$10,"") | E10: =IFERROR('Inputs'!$E$12/'Inputs'!$E$10,"") | F10: =IFERROR('Inputs'!$F$12/'Inputs'!$F$10,"") | G10: =IFERROR('Inputs'!$G$12/'Inputs'!$G$10,"") | H10: =IFERROR('Inputs'!$H$12/'Inputs'!$H$10,"") | I10: =IFERROR('Inputs'!$I$12/'Inputs'!$I$10,"") | J10: =IFERROR('Inputs'!$J$12/'Inputs'!$J$10,"") | K10: =IFERROR('Inputs'!$K$12/'Inputs'!$K$10,"") | L10: =IFERROR('Inputs'!$L$12/'Inputs'!$L$10,"") | M10: =IFERROR('Inputs'!$M$12/'Inputs'!$M$10,"") | N10: =IFERROR('Inputs'!$N$12/'Inputs'!$N$10,"") | O10: =IFERROR('Inputs'!$O$12/'Inputs'!$O$10,"") | P10: =IFERROR('Inputs'!$P$12/'Inputs'!$P$10,"") | Q10: =IF(AND(ISNUMBER($K$10),ISNUMBER($J$10)),CHOOSE(2+($K$10>$J$10)-($K$10<$J$10),"▼","►","▲"),"") | R10: =IF(ISNUMBER($K$10),CHOOSE(1+($K$10>=0.2)+($K$10>=0.4),"Low","Average","High"),"")
A11: EBITDA margin | B11: =IFERROR('Inputs'!$B$14/'Inputs'!$B$10,"") | C11: =IFERROR('Inputs'!$C$14/'Inputs'!$C$10,"") | D11: =IFERROR('Inputs'!$D$14/'Inputs'!$D$10,"") | E11: =IFERROR('Inputs'!$E$14/'Inputs'!$E$10,"") | F11: =IFERROR('Inputs'!$F$14/'Inputs'!$F$10,"") | G11: =IFERROR('Inputs'!$G$14/'Inputs'!$G$10,"") | H11: =IFERROR('Inputs'!$H$14/'Inputs'!$H$10,"") | I11: =IFERROR('Inputs'!$I$14/'Inputs'!$I$10,"") | J11: =IFERROR('Inputs'!$J$14/'Inputs'!$J$10,"") | K11: =IFERROR('Inputs'!$K$14/'Inputs'!$K$10,"") | L11: =IFERROR('Inputs'!$L$14/'Inputs'!$L$10,"") | M11: =IFERROR('Inputs'!$M$14/'Inputs'!$M$10,"") | N11: =IFERROR('Inputs'!$N$14/'Inputs'!$N$10,"") | O11: =IFERROR('Inputs'!$O$14/'Inputs'!$O$10,"") | P11: =IFERROR('Inputs'!$P$14/'Inputs'!$P$10,"") | Q11: =IF(AND(ISNUMBER($K$11),ISNUMBER($J$11)),CHOOSE(2+($K$11>$J$11)-($K$11<$J$11),"▼","►","▲"),"") | R11: =IF(AND(ISNUMBER($K$11),ISNUMBER(AVERAGE($B$11:$K$11))),CHOOSE(2+($K$11>AVERAGE($B$11:$K$11)*(1+0.05))-($K$11<AVERAGE($B$11:$K$11)*(1-0.05)),"Compressing","Stable","Expanding"),"")
A12: Operating margin (EBIT) | B12: =IFERROR('Inputs'!$B$16/'Inputs'!$B$10,"") | C12: =IFERROR('Inputs'!$C$16/'Inputs'!$C$10,"") | D12: =IFERROR('Inputs'!$D$16/'Inputs'!$D$10,"") | E12: =IFERROR('Inputs'!$E$16/'Inputs'!$E$10,"") | F12: =IFERROR('Inputs'!$F$16/'Inputs'!$F$10,"") | G12: =IFERROR('Inputs'!$G$16/'Inputs'!$G$10,"") | H12: =IFERROR('Inputs'!$H$16/'Inputs'!$H$10,"") | I12: =IFERROR('Inputs'!$I$16/'Inputs'!$I$10,"") | J12: =IFERROR('Inputs'!$J$16/'Inputs'!$J$10,"") | K12: =IFERROR('Inputs'!$K$16/'Inputs'!$K$10,"") | L12: =IFERROR('Inputs'!$L$16/'Inputs'!$L$10,"") | M12: =IFERROR('Inputs'!$M$16/'Inputs'!$M$10,"") | N12: =IFERROR('Inputs'!$N$16/'Inputs'!$N$10,"") | O12: =IFERROR('Inputs'!$O$16/'Inputs'!$O$10,"") | P12: =IFERROR('Inputs'!$P$16/'Inputs'!$P$10,"") | Q12: =IF(AND(ISNUMBER($K$12),ISNUMBER($J$12)),CHOOSE(2+($K$12>$J$12)-($K$12<$J$12),"▼","►","▲"),"") | R12: =IF(ISNUMBER($K$12),CHOOSE(1+($K$12>=0.08)+($K$12>=0.18),"Low","Average","High"),"")
A13: Pre-tax margin | B13: =IFERROR('Inputs'!$B$19/'Inputs'!$B$10,"") | C13: =IFERROR('Inputs'!$C$19/'Inputs'!$C$10,"") | D13: =IFERROR('Inputs'!$D$19/'Inputs'!$D$10,"") | E13: =IFERROR('Inputs'!$E$19/'Inputs'!$E$10,"") | F13: =IFERROR('Inputs'!$F$19/'Inputs'!$F$10,"") | G13: =IFERROR('Inputs'!$G$19/'Inputs'!$G$10,"") | H13: =IFERROR('Inputs'!$H$19/'Inputs'!$H$10,"") | I13: =IFERROR('Inputs'!$I$19/'Inputs'!$I$10,"") | J13: =IFERROR('Inputs'!$J$19/'Inputs'!$J$10,"") | K13: =IFERROR('Inputs'!$K$19/'Inputs'!$K$10,"") | L13: =IFERROR('Inputs'!$L$19/'Inputs'!$L$10,"") | M13: =IFERROR('Inputs'!$M$19/'Inputs'!$M$10,"") | N13: =IFERROR('Inputs'!$N$19/'Inputs'!$N$10,"") | O13: =IFERROR('Inputs'!$O$19/'Inputs'!$O$10,"") | P13: =IFERROR('Inputs'!$P$19/'Inputs'!$P$10,"") | Q13: =IF(AND(ISNUMBER($K$13),ISNUMBER($J$13)),CHOOSE(2+($K$13>$J$13)-($K$13<$J$13),"▼","►","▲"),"") | R13: =IF(AND(ISNUMBER($K$13),ISNUMBER(AVERAGE($B$13:$K$13))),CHOOSE(2+($K$13>AVERAGE($B$13:$K$13)*(1+0.05))-($K$13<AVERAGE($B$13:$K$13)*(1-0.05)),"Compressing","Stable","Expanding"),"")
A14: Net margin | B14: =IFERROR('Inputs'!$B$21/'Inputs'!$B$10,"") | C14: =IFERROR('Inputs'!$C$21/'Inputs'!$C$10,"") | D14: =IFERROR('Inputs'!$D$21/'Inputs'!$D$10,"") | E14: =IFERROR('Inputs'!$E$21/'Inputs'!$E$10,"") | F14: =IFERROR('Inputs'!$F$21/'Inputs'!$F$10,"") | G14: =IFERROR('Inputs'!$G$21/'Inputs'!$G$10,"") | H14: =IFERROR('Inputs'!$H$21/'Inputs'!$H$10,"") | I14: =IFERROR('Inputs'!$I$21/'Inputs'!$I$10,"") | J14: =IFERROR('Inputs'!$J$21/'Inputs'!$J$10,"") | K14: =IFERROR('Inputs'!$K$21/'Inputs'!$K$10,"") | L14: =IFERROR('Inputs'!$L$21/'Inputs'!$L$10,"") | M14: =IFERROR('Inputs'!$M$21/'Inputs'!$M$10,"") | N14: =IFERROR('Inputs'!$N$21/'Inputs'!$N$10,"") | O14: =IFERROR('Inputs'!$O$21/'Inputs'!$O$10,"") | P14: =IFERROR('Inputs'!$P$21/'Inputs'!$P$10,"") | Q14: =IF(AND(ISNUMBER($K$14),ISNUMBER($J$14)),CHOOSE(2+($K$14>$J$14)-($K$14<$J$14),"▼","►","▲"),"") | R14: =IF(ISNUMBER($K$14),CHOOSE(1+($K$14>=0.05)+($K$14>=0.12),"Low","Average","High"),"")
A15: FCF margin | B15: =IFERROR('Inputs'!$B$48/'Inputs'!$B$10,"") | C15: =IFERROR('Inputs'!$C$48/'Inputs'!$C$10,"") | D15: =IFERROR('Inputs'!$D$48/'Inputs'!$D$10,"") | E15: =IFERROR('Inputs'!$E$48/'Inputs'!$E$10,"") | F15: =IFERROR('Inputs'!$F$48/'Inputs'!$F$10,"") | G15: =IFERROR('Inputs'!$G$48/'Inputs'!$G$10,"") | H15: =IFERROR('Inputs'!$H$48/'Inputs'!$H$10,"") | I15: =IFERROR('Inputs'!$I$48/'Inputs'!$I$10,"") | J15: =IFERROR('Inputs'!$J$48/'Inputs'!$J$10,"") | K15: =IFERROR('Inputs'!$K$48/'Inputs'!$K$10,"") | L15: =IFERROR('Inputs'!$L$48/'Inputs'!$L$10,"") | M15: =IFERROR('Inputs'!$M$48/'Inputs'!$M$10,"") | N15: =IFERROR('Inputs'!$N$48/'Inputs'!$N$10,"") | O15: =IFERROR('Inputs'!$O$48/'Inputs'!$O$10,"") | P15: =IFERROR('Inputs'!$P$48/'Inputs'!$P$10,"") | Q15: =IF(AND(ISNUMBER($K$15),ISNUMBER($J$15)),CHOOSE(2+($K$15>$J$15)-($K$15<$J$15),"▼","►","▲"),"") | R15: =IF(ISNUMBER($K$15),CHOOSE(1+($K$15>=0.03)+($K$15>=0.1),"Weak","Average","Strong"),"")
A17: Returns on Capital
A18: Return on equity (ROE) | C18: =IFERROR('Inputs'!$C$21/'Inputs'!$C$74,"") | D18: =IFERROR('Inputs'!$D$21/'Inputs'!$D$74,"") | E18: =IFERROR('Inputs'!$E$21/'Inputs'!$E$74,"") | F18: =IFERROR('Inputs'!$F$21/'Inputs'!$F$74,"") | G18: =IFERROR('Inputs'!$G$21/'Inputs'!$G$74,"") | H18: =IFERROR('Inputs'!$H$21/'Inputs'!$H$74,"") | I18: =IFERROR('Inputs'!$I$21/'Inputs'!$I$74,"") | J18: =IFERROR('Inputs'!$J$21/'Inputs'!$J$74,"") | K18: =IFERROR('Inputs'!$K$21/'Inputs'!$K$74,"") | L18: =IFERROR('Inputs'!$L$21/'Inputs'!$L$74,"") | M18: =IFERROR('Inputs'!$M$21/'Inputs'!$M$74,"") | N18: =IFERROR('Inputs'!$N$21/'Inputs'!$N$74,"") | O18: =IFERROR('Inputs'!$O$21/'Inputs'!$O$74,"") | P18: =IFERROR('Inputs'!$P$21/'Inputs'!$P$74,"") | Q18: =IF(AND(ISNUMBER($K$18),ISNUMBER($J$18)),CHOOSE(2+($K$18>$J$18)-($K$18<$J$18),"▼","►","▲"),"") | R18: =IF(ISNUMBER($K$18),CHOOSE(1+($K$18>=0.08)+($K$18>=0.15),"Weak","Average","Strong"),"")
A19: Return on assets (ROA) | C19: =IFERROR('Inputs'!$C$21/'Inputs'!$C$75,"") | D19: =IFERROR('Inputs'!$D$21/'Inputs'!$D$75,"") | E19: =IFERROR('Inputs'!$E$21/'Inputs'!$E$75,"") | F19: =IFERROR('Inputs'!$F$21/'Inputs'!$F$75,"") | G19: =IFERROR('Inputs'!$G$21/'Inputs'!$G$75,"") | H19: =IFERROR('Inputs'!$H$21/'Inputs'!$H$75,"") | I19: =IFERROR('Inputs'!$I$21/'Inputs'!$I$75,"") | J19: =IFERROR('Inputs'!$J$21/'Inputs'!$J$75,"") | K19: =IFERROR('Inputs'!$K$21/'Inputs'!$K$75,"") | L19: =IFERROR('Inputs'!$L$21/'Inputs'!$L$75,"") | M19: =IFERROR('Inputs'!$M$21/'Inputs'!$M$75,"") | N19: =IFERROR('Inputs'!$N$21/'Inputs'!$N$75,"") | O19: =IFERROR('Inputs'!$O$21/'Inputs'!$O$75,"") | P19: =IFERROR('Inputs'!$P$21/'Inputs'!$P$75,"") | Q19: =IF(AND(ISNUMBER($K$19),ISNUMBER($J$19)),CHOOSE(2+($K$19>$J$19)-($K$19<$J$19),"▼","►","▲"),"") | R19: =IF(ISNUMBER($K$19),CHOOSE(1+($K$19>=0.03)+($K$19>=0.07),"Weak","Average","Strong"),"")
A20: Return on invested capital (ROIC) | C20: =IFERROR('Inputs'!$C$71/'Inputs'!$C$80,"") | D20: =IFERROR('Inputs'!$D$71/'Inputs'!$D$80,"") | E20: =IFERROR('Inputs'!$E$71/'Inputs'!$E$80,"") | F20: =IFERROR('Inputs'!$F$71/'Inputs'!$F$80,"") | G20: =IFERROR('Inputs'!$G$71/'Inputs'!$G$80,"") | H20: =IFERROR('Inputs'!$H$71/'Inputs'!$H$80,"") | I20: =IFERROR('Inputs'!$I$71/'Inputs'!$I$80,"") | J20: =IFERROR('Inputs'!$J$71/'Inputs'!$J$80,"") | K20: =IFERROR('Inputs'!$K$71/'Inputs'!$K$80,"") | L20: =IFERROR('Inputs'!$L$71/'Inputs'!$L$80,"") | M20: =IFERROR('Inputs'!$M$71/'Inputs'!$M$80,"") | N20: =IFERROR('Inputs'!$N$71/'Inputs'!$N$80,"") | O20: =IFERROR('Inputs'!$O$71/'Inputs'!$O$80,"") | P20: =IFERROR('Inputs'!$P$71/'Inputs'!$P$80,"") | Q20: =IF(AND(ISNUMBER($K$20),ISNUMBER($J$20)),CHOOSE(2+($K$20>$J$20)-($K$20<$J$20),"▼","►","▲"),"") | R20: =IF(ISNUMBER($K$20),CHOOSE(1+($K$20>=0.08)+($K$20>=0.12),"Weak","Average","Strong"),"")
A21: Return on capital employed (ROCE) | B21: =IFERROR('Inputs'!$B$16/'Inputs'!$B$69,"") | C21: =IFERROR('Inputs'!$C$16/'Inputs'!$C$69,"") | D21: =IFERROR('Inputs'!$D$16/'Inputs'!$D$69,"") | E21: =IFERROR('Inputs'!$E$16/'Inputs'!$E$69,"") | F21: =IFERROR('Inputs'!$F$16/'Inputs'!$F$69,"") | G21: =IFERROR('Inputs'!$G$16/'Inputs'!$G$69,"") | H21: =IFERROR('Inputs'!$H$16/'Inputs'!$H$69,"") | I21: =IFERROR('Inputs'!$I$16/'Inputs'!$I$69,"") | J21: =IFERROR('Inputs'!$J$16/'Inputs'!$J$69,"") | K21: =IFERROR('Inputs'!$K$16/'Inputs'!$K$69,"") | L21: =IFERROR('Inputs'!$L$16/'Inputs'!$L$69,"") | M21: =IFERROR('Inputs'!$M$16/'Inputs'!$M$69,"") | N21: =IFERROR('Inputs'!$N$16/'Inputs'!$N$69,"") | O21: =IFERROR('Inputs'!$O$16/'Inputs'!$O$69,"") | P21: =IFERROR('Inputs'!$P$16/'Inputs'!$P$69,"") | Q21: =IF(AND(ISNUMBER($K$21),ISNUMBER($J$21)),CHOOSE(2+($K$21>$J$21)-($K$21<$J$21),"▼","►","▲"),"") | R21: =IF(ISNUMBER($K$21),CHOOSE(1+($K$21>=0.08)+($K$21>=0.12),"Weak","Average","Strong"),"")
A22: Cash ROIC (FCF / invested capital) | B22: =IFERROR('Inputs'!$B$48/'Inputs'!$B$70,"") | C22: =IFERROR('Inputs'!$C$48/'Inputs'!$C$70,"") | D22: =IFERROR('Inputs'!$D$48/'Inputs'!$D$70,"") | E22: =IFERROR('Inputs'!$E$48/'Inputs'!$E$70,"") | F22: =IFERROR('Inputs'!$F$48/'Inputs'!$F$70,"") | G22: =IFERROR('Inputs'!$G$48/'Inputs'!$G$70,"") | H22: =IFERROR('Inputs'!$H$48/'Inputs'!$H$70,"") | I22: =IFERROR('Inputs'!$I$48/'Inputs'!$I$70,"") | J22: =IFERROR('Inputs'!$J$48/'Inputs'!$J$70,"") | K22: =IFERROR('Inputs'!$K$48/'Inputs'!$K$70,"") | L22: =IFERROR('Inputs'!$L$48/'Inputs'!$L$70,"") | M22: =IFERROR('Inputs'!$M$48/'Inputs'!$M$70,"") | N22: =IFERROR('Inputs'!$N$48/'Inputs'!$N$70,"") | O22: =IFERROR('Inputs'!$O$48/'Inputs'!$O$70,"") | P22: =IFERROR('Inputs'!$P$48/'Inputs'!$P$70,"") | Q22: =IF(AND(ISNUMBER($K$22),ISNUMBER($J$22)),CHOOSE(2+($K$22>$J$22)-($K$22<$J$22),"▼","►","▲"),"") | R22: =IF(AND(ISNUMBER($K$22),ISNUMBER(AVERAGE($B$22:$K$22))),CHOOSE(2+($K$22>AVERAGE($B$22:$K$22)*(1+0.05))-($K$22<AVERAGE($B$22:$K$22)*(1-0.05)),"Weak","Stable","Strong"),"")
A24: DuPont Decomposition (ROE = Net margin × Asset turnover × Equity multiplier)
A25: Net profit margin | B25: =IFERROR('Inputs'!$B$21/'Inputs'!$B$10,"") | C25: =IFERROR('Inputs'!$C$21/'Inputs'!$C$10,"") | D25: =IFERROR('Inputs'!$D$21/'Inputs'!$D$10,"") | E25: =IFERROR('Inputs'!$E$21/'Inputs'!$E$10,"") | F25: =IFERROR('Inputs'!$F$21/'Inputs'!$F$10,"") | G25: =IFERROR('Inputs'!$G$21/'Inputs'!$G$10,"") | H25: =IFERROR('Inputs'!$H$21/'Inputs'!$H$10,"") | I25: =IFERROR('Inputs'!$I$21/'Inputs'!$I$10,"") | J25: =IFERROR('Inputs'!$J$21/'Inputs'!$J$10,"") | K25: =IFERROR('Inputs'!$K$21/'Inputs'!$K$10,"") | L25: =IFERROR('Inputs'!$L$21/'Inputs'!$L$10,"") | M25: =IFERROR('Inputs'!$M$21/'Inputs'!$M$10,"") | N25: =IFERROR('Inputs'!$N$21/'Inputs'!$N$10,"") | O25: =IFERROR('Inputs'!$O$21/'Inputs'!$O$10,"") | P25: =IFERROR('Inputs'!$P$21/'Inputs'!$P$10,"") | Q25: =IF(AND(ISNUMBER($K$25),ISNUMBER($J$25)),CHOOSE(2+($K$25>$J$25)-($K$25<$J$25),"▼","►","▲"),"")
A26: Asset turnover | C26: =IFERROR('Inputs'!$C$10/'Inputs'!$C$75,"") | D26: =IFERROR('Inputs'!$D$10/'Inputs'!$D$75,"") | E26: =IFERROR('Inputs'!$E$10/'Inputs'!$E$75,"") | F26: =IFERROR('Inputs'!$F$10/'Inputs'!$F$75,"") | G26: =IFERROR('Inputs'!$G$10/'Inputs'!$G$75,"") | H26: =IFERROR('Inputs'!$H$10/'Inputs'!$H$75,"") | I26: =IFERROR('Inputs'!$I$10/'Inputs'!$I$75,"") | J26: =IFERROR('Inputs'!$J$10/'Inputs'!$J$75,"") | K26: =IFERROR('Inputs'!$K$10/'Inputs'!$K$75,"") | L26: =IFERROR('Inputs'!$L$10/'Inputs'!$L$75,"") | M26: =IFERROR('Inputs'!$M$10/'Inputs'!$M$75,"") | N26: =IFERROR('Inputs'!$N$10/'Inputs'!$N$75,"") | O26: =IFERROR('Inputs'!$O$10/'Inputs'!$O$75,"") | P26: =IFERROR('Inputs'!$P$10/'Inputs'!$P$75,"") | Q26: =IF(AND(ISNUMBER($K$26),ISNUMBER($J$26)),CHOOSE(2+($K$26>$J$26)-($K$26<$J$26),"▼","►","▲"),"")
A27: Equity multiplier (leverage) | C27: =IFERROR('Inputs'!$C$75/'Inputs'!$C$74,"") | D27: =IFERROR('Inputs'!$D$75/'Inputs'!$D$74,"") | E27: =IFERROR('Inputs'!$E$75/'Inputs'!$E$74,"") | F27: =IFERROR('Inputs'!$F$75/'Inputs'!$F$74,"") | G27: =IFERROR('Inputs'!$G$75/'Inputs'!$G$74,"") | H27: =IFERROR('Inputs'!$H$75/'Inputs'!$H$74,"") | I27: =IFERROR('Inputs'!$I$75/'Inputs'!$I$74,"") | J27: =IFERROR('Inputs'!$J$75/'Inputs'!$J$74,"") | K27: =IFERROR('Inputs'!$K$75/'Inputs'!$K$74,"") | L27: =IFERROR('Inputs'!$L$75/'Inputs'!$L$74,"") | M27: =IFERROR('Inputs'!$M$75/'Inputs'!$M$74,"") | N27: =IFERROR('Inputs'!$N$75/'Inputs'!$N$74,"") | O27: =IFERROR('Inputs'!$O$75/'Inputs'!$O$74,"") | P27: =IFERROR('Inputs'!$P$75/'Inputs'!$P$74,"") | Q27: =IF(AND(ISNUMBER($K$27),ISNUMBER($J$27)),CHOOSE(2+($K$27>$J$27)-($K$27<$J$27),"▼","►","▲"),"")
A28: ROE (DuPont, computed) | C28: =IFERROR('Profitability'!$C$25*'Profitability'!$C$26*'Profitability'!$C$27,"") | D28: =IFERROR('Profitability'!$D$25*'Profitability'!$D$26*'Profitability'!$D$27,"") | E28: =IFERROR('Profitability'!$E$25*'Profitability'!$E$26*'Profitability'!$E$27,"") | F28: =IFERROR('Profitability'!$F$25*'Profitability'!$F$26*'Profitability'!$F$27,"") | G28: =IFERROR('Profitability'!$G$25*'Profitability'!$G$26*'Profitability'!$G$27,"") | H28: =IFERROR('Profitability'!$H$25*'Profitability'!$H$26*'Profitability'!$H$27,"") | I28: =IFERROR('Profitability'!$I$25*'Profitability'!$I$26*'Profitability'!$I$27,"") | J28: =IFERROR('Profitability'!$J$25*'Profitability'!$J$26*'Profitability'!$J$27,"") | K28: =IFERROR('Profitability'!$K$25*'Profitability'!$K$26*'Profitability'!$K$27,"") | L28: =IFERROR('Profitability'!$L$25*'Profitability'!$L$26*'Profitability'!$L$27,"") | M28: =IFERROR('Profitability'!$M$25*'Profitability'!$M$26*'Profitability'!$M$27,"") | N28: =IFERROR('Profitability'!$N$25*'Profitability'!$N$26*'Profitability'!$N$27,"") | O28: =IFERROR('Profitability'!$O$25*'Profitability'!$O$26*'Profitability'!$O$27,"") | P28: =IFERROR('Profitability'!$P$25*'Profitability'!$P$26*'Profitability'!$P$27,"") | Q28: =IF(AND(ISNUMBER($K$28),ISNUMBER($J$28)),CHOOSE(2+($K$28>$J$28)-($K$28<$J$28),"▼","►","▲"),"")
A29: DuPont ROE should equal the ROE above — a built-in audit of the decomposition.
A31: Capital Retention
A32: Retention ratio (1 − payout) | B32: =IFERROR(1-'Inputs'!$B$49/'Inputs'!$B$21,"") | C32: =IFERROR(1-'Inputs'!$C$49/'Inputs'!$C$21,"") | D32: =IFERROR(1-'Inputs'!$D$49/'Inputs'!$D$21,"") | E32: =IFERROR(1-'Inputs'!$E$49/'Inputs'!$E$21,"") | F32: =IFERROR(1-'Inputs'!$F$49/'Inputs'!$F$21,"") | G32: =IFERROR(1-'Inputs'!$G$49/'Inputs'!$G$21,"") | H32: =IFERROR(1-'Inputs'!$H$49/'Inputs'!$H$21,"") | I32: =IFERROR(1-'Inputs'!$I$49/'Inputs'!$I$21,"") | J32: =IFERROR(1-'Inputs'!$J$49/'Inputs'!$J$21,"") | K32: =IFERROR(1-'Inputs'!$K$49/'Inputs'!$K$21,"") | L32: =IFERROR(1-'Inputs'!$L$49/'Inputs'!$L$21,"") | M32: =IFERROR(1-'Inputs'!$M$49/'Inputs'!$M$21,"") | N32: =IFERROR(1-'Inputs'!$N$49/'Inputs'!$N$21,"") | O32: =IFERROR(1-'Inputs'!$O$49/'Inputs'!$O$21,"") | P32: =IFERROR(1-'Inputs'!$P$49/'Inputs'!$P$21,"") | Q32: =IF(AND(ISNUMBER($K$32),ISNUMBER($J$32)),CHOOSE(2+($K$32>$J$32)-($K$32<$J$32),"▼","►","▲"),"") | R32: =IF(AND(ISNUMBER($K$32),ISNUMBER(AVERAGE($B$32:$K$32))),CHOOSE(2+($K$32>AVERAGE($B$32:$K$32)*(1+0.05))-($K$32<AVERAGE($B$32:$K$32)*(1-0.05)),"Falling","Stable","Rising"),"")
A34: Automated Observations
A35: =IFERROR("» Operating margin "&CHOOSE(2+('Profitability'!$K$12>'Profitability'!$B$12)-('Profitability'!$K$12<'Profitability'!$B$12),"contracted","was broadly flat","expanded")&" by "&TEXT(ABS(('Profitability'!$K$12-'Profitability'!$B$12)*10000),"#,##0")&" bps over the historical period, to "&TEXT('Profitability'!$K$12,"0.0%")&".","(insufficient data — populate inputs)")
A36: =IFERROR("» ROIC of "&TEXT('Profitability'!$K$20,"0.0%")&" is "&IF('Profitability'!$K$20>'Inputs'!$B$82,"above","below")&" the WACC of "&TEXT('Inputs'!$B$82,"0.0%")&" — "&IF('Profitability'!$K$20>'Inputs'!$B$82,"the business is creating economic value.","the business is not covering its cost of capital."),"(insufficient data — populate inputs)")
A37: =IFERROR("» Net margin is currently "&TEXT('Profitability'!$K$14,"0.0%")&" — assessed "&'Profitability'!$R$14&".","(insufficient data — populate inputs)")

Sheet Liquidity
A1: LIQUIDITY RATIOS
A2: Short-term solvency and working-capital strength
A3: Institutional Financial Ratio Analysis · v1.0
A5: Dashboard | B5: Inputs | C5: Common Size | D5: Profitability | E5: Liquidity | F5: Solvency | G5: Efficiency | H5: Growth
A6: Valuation | B6: Capital Allocation | C6: Quality | D6: Benchmarking | E6: Guide | F6: Quality Control
A7: All figures in USD millions unless stated; (F) = forecast year.
A8: Liquidity ratio | B8: FY2015 | C8: FY2016 | D8: FY2017 | E8: FY2018 | F8: FY2019 | G8: FY2020 | H8: FY2021 | I8: FY2022 | J8: FY2023 | K8: FY2024 | L8: FY2025 (F) | M8: FY2026 (F) | N8: FY2027 (F) | O8: FY2028 (F) | P8: FY2029 (F) | Q8: Trend | R8: Assessment
A9: Coverage of Current Liabilities
A10: Current ratio | B10: =IFERROR('Inputs'!$B$27/'Inputs'!$B$37,"") | C10: =IFERROR('Inputs'!$C$27/'Inputs'!$C$37,"") | D10: =IFERROR('Inputs'!$D$27/'Inputs'!$D$37,"") | E10: =IFERROR('Inputs'!$E$27/'Inputs'!$E$37,"") | F10: =IFERROR('Inputs'!$F$27/'Inputs'!$F$37,"") | G10: =IFERROR('Inputs'!$G$27/'Inputs'!$G$37,"") | H10: =IFERROR('Inputs'!$H$27/'Inputs'!$H$37,"") | I10: =IFERROR('Inputs'!$I$27/'Inputs'!$I$37,"") | J10: =IFERROR('Inputs'!$J$27/'Inputs'!$J$37,"") | K10: =IFERROR('Inputs'!$K$27/'Inputs'!$K$37,"") | L10: =IFERROR('Inputs'!$L$27/'Inputs'!$L$37,"") | M10: =IFERROR('Inputs'!$M$27/'Inputs'!$M$37,"") | N10: =IFERROR('Inputs'!$N$27/'Inputs'!$N$37,"") | O10: =IFERROR('Inputs'!$O$27/'Inputs'!$O$37,"") | P10: =IFERROR('Inputs'!$P$27/'Inputs'!$P$37,"") | Q10: =IF(AND(ISNUMBER($K$10),ISNUMBER($J$10)),CHOOSE(2+($K$10>$J$10)-($K$10<$J$10),"▼","►","▲"),"") | R10: =IF(ISNUMBER($K$10),CHOOSE(1+($K$10>=1.0)+($K$10>=2.0),"Weak","Adequate","Strong"),"")
A11: Quick ratio (ex-inventory) | B11: =IFERROR(('Inputs'!$B$27-'Inputs'!$B$25)/'Inputs'!$B$37,"") | C11: =IFERROR(('Inputs'!$C$27-'Inputs'!$C$25)/'Inputs'!$C$37,"") | D11: =IFERROR(('Inputs'!$D$27-'Inputs'!$D$25)/'Inputs'!$D$37,"") | E11: =IFERROR(('Inputs'!$E$27-'Inputs'!$E$25)/'Inputs'!$E$37,"") | F11: =IFERROR(('Inputs'!$F$27-'Inputs'!$F$25)/'Inputs'!$F$37,"") | G11: =IFERROR(('Inputs'!$G$27-'Inputs'!$G$25)/'Inputs'!$G$37,"") | H11: =IFERROR(('Inputs'!$H$27-'Inputs'!$H$25)/'Inputs'!$H$37,"") | I11: =IFERROR(('Inputs'!$I$27-'Inputs'!$I$25)/'Inputs'!$I$37,"") | J11: =IFERROR(('Inputs'!$J$27-'Inputs'!$J$25)/'Inputs'!$J$37,"") | K11: =IFERROR(('Inputs'!$K$27-'Inputs'!$K$25)/'Inputs'!$K$37,"") | L11: =IFERROR(('Inputs'!$L$27-'Inputs'!$L$25)/'Inputs'!$L$37,"") | M11: =IFERROR(('Inputs'!$M$27-'Inputs'!$M$25)/'Inputs'!$M$37,"") | N11: =IFERROR(('Inputs'!$N$27-'Inputs'!$N$25)/'Inputs'!$N$37,"") | O11: =IFERROR(('Inputs'!$O$27-'Inputs'!$O$25)/'Inputs'!$O$37,"") | P11: =IFERROR(('Inputs'!$P$27-'Inputs'!$P$25)/'Inputs'!$P$37,"") | Q11: =IF(AND(ISNUMBER($K$11),ISNUMBER($J$11)),CHOOSE(2+($K$11>$J$11)-($K$11<$J$11),"▼","►","▲"),"") | R11: =IF(ISNUMBER($K$11),CHOOSE(1+($K$11>=0.8)+($K$11>=1.2),"Weak","Adequate","Strong"),"")
A12: Cash ratio | B12: =IFERROR('Inputs'!$B$23/'Inputs'!$B$37,"") | C12: =IFERROR('Inputs'!$C$23/'Inputs'!$C$37,"") | D12: =IFERROR('Inputs'!$D$23/'Inputs'!$D$37,"") | E12: =IFERROR('Inputs'!$E$23/'Inputs'!$E$37,"") | F12: =IFERROR('Inputs'!$F$23/'Inputs'!$F$37,"") | G12: =IFERROR('Inputs'!$G$23/'Inputs'!$G$37,"") | H12: =IFERROR('Inputs'!$H$23/'Inputs'!$H$37,"") | I12: =IFERROR('Inputs'!$I$23/'Inputs'!$I$37,"") | J12: =IFERROR('Inputs'!$J$23/'Inputs'!$J$37,"") | K12: =IFERROR('Inputs'!$K$23/'Inputs'!$K$37,"") | L12: =IFERROR('Inputs'!$L$23/'Inputs'!$L$37,"") | M12: =IFERROR('Inputs'!$M$23/'Inputs'!$M$37,"") | N12: =IFERROR('Inputs'!$N$23/'Inputs'!$N$37,"") | O12: =IFERROR('Inputs'!$O$23/'Inputs'!$O$37,"") | P12: =IFERROR('Inputs'!$P$23/'Inputs'!$P$37,"") | Q12: =IF(AND(ISNUMBER($K$12),ISNUMBER($J$12)),CHOOSE(2+($K$12>$J$12)-($K$12<$J$12),"▼","►","▲"),"") | R12: =IF(ISNUMBER($K$12),CHOOSE(1+($K$12>=0.2)+($K$12>=0.5),"Weak","Adequate","Strong"),"")
A14: Working Capital
A15: Working capital | B15: ='Inputs'!$B$68 | C15: ='Inputs'!$C$68 | D15: ='Inputs'!$D$68 | E15: ='Inputs'!$E$68 | F15: ='Inputs'!$F$68 | G15: ='Inputs'!$G$68 | H15: ='Inputs'!$H$68 | I15: ='Inputs'!$I$68 | J15: ='Inputs'!$J$68 | K15: ='Inputs'!$K$68 | L15: ='Inputs'!$L$68 | M15: ='Inputs'!$M$68 | N15: ='Inputs'!$N$68 | O15: ='Inputs'!$O$68 | P15: ='Inputs'!$P$68 | Q15: =IF(AND(ISNUMBER($K$15),ISNUMBER($J$15)),CHOOSE(2+($K$15>$J$15)-($K$15<$J$15),"▼","►","▲"),"") | R15: =IF(AND(ISNUMBER($K$15),ISNUMBER(AVERAGE($B$15:$K$15))),CHOOSE(2+($K$15>AVERAGE($B$15:$K$15)*(1+0.05))-($K$15<AVERAGE($B$15:$K$15)*(1-0.05)),"Falling","Stable","Rising"),"")
A16: Working capital / revenue | B16: =IFERROR('Inputs'!$B$68/'Inputs'!$B$10,"") | C16: =IFERROR('Inputs'!$C$68/'Inputs'!$C$10,"") | D16: =IFERROR('Inputs'!$D$68/'Inputs'!$D$10,"") | E16: =IFERROR('Inputs'!$E$68/'Inputs'!$E$10,"") | F16: =IFERROR('Inputs'!$F$68/'Inputs'!$F$10,"") | G16: =IFERROR('Inputs'!$G$68/'Inputs'!$G$10,"") | H16: =IFERROR('Inputs'!$H$68/'Inputs'!$H$10,"") | I16: =IFERROR('Inputs'!$I$68/'Inputs'!$I$10,"") | J16: =IFERROR('Inputs'!$J$68/'Inputs'!$J$10,"") | K16: =IFERROR('Inputs'!$K$68/'Inputs'!$K$10,"") | L16: =IFERROR('Inputs'!$L$68/'Inputs'!$L$10,"") | M16: =IFERROR('Inputs'!$M$68/'Inputs'!$M$10,"") | N16: =IFERROR('Inputs'!$N$68/'Inputs'!$N$10,"") | O16: =IFERROR('Inputs'!$O$68/'Inputs'!$O$10,"") | P16: =IFERROR('Inputs'!$P$68/'Inputs'!$P$10,"") | Q16: =IF(AND(ISNUMBER($K$16),ISNUMBER($J$16)),CHOOSE(2+($K$16>$J$16)-($K$16<$J$16),"▼","►","▲"),"") | R16: =IF(AND(ISNUMBER($K$16),ISNUMBER(AVERAGE($B$16:$K$16))),CHOOSE(2+($K$16>AVERAGE($B$16:$K$16)*(1+0.05))-($K$16<AVERAGE($B$16:$K$16)*(1-0.05)),"Falling","Stable","Rising"),"")
A18: Cash-Flow Liquidity
A19: Operating cash flow ratio | B19: =IFERROR('Inputs'!$B$46/'Inputs'!$B$37,"") | C19: =IFERROR('Inputs'!$C$46/'Inputs'!$C$37,"") | D19: =IFERROR('Inputs'!$D$46/'Inputs'!$D$37,"") | E19: =IFERROR('Inputs'!$E$46/'Inputs'!$E$37,"") | F19: =IFERROR('Inputs'!$F$46/'Inputs'!$F$37,"") | G19: =IFERROR('Inputs'!$G$46/'Inputs'!$G$37,"") | H19: =IFERROR('Inputs'!$H$46/'Inputs'!$H$37,"") | I19: =IFERROR('Inputs'!$I$46/'Inputs'!$I$37,"") | J19: =IFERROR('Inputs'!$J$46/'Inputs'!$J$37,"") | K19: =IFERROR('Inputs'!$K$46/'Inputs'!$K$37,"") | L19: =IFERROR('Inputs'!$L$46/'Inputs'!$L$37,"") | M19: =IFERROR('Inputs'!$M$46/'Inputs'!$M$37,"") | N19: =IFERROR('Inputs'!$N$46/'Inputs'!$N$37,"") | O19: =IFERROR('Inputs'!$O$46/'Inputs'!$O$37,"") | P19: =IFERROR('Inputs'!$P$46/'Inputs'!$P$37,"") | Q19: =IF(AND(ISNUMBER($K$19),ISNUMBER($J$19)),CHOOSE(2+($K$19>$J$19)-($K$19<$J$19),"▼","►","▲"),"") | R19: =IF(AND(ISNUMBER($K$19),ISNUMBER(AVERAGE($B$19:$K$19))),CHOOSE(2+($K$19>AVERAGE($B$19:$K$19)*(1+0.05))-($K$19<AVERAGE($B$19:$K$19)*(1-0.05)),"Weak","Stable","Strong"),"")
A20: Cash conversion (OCF / net income) | B20: =IFERROR('Inputs'!$B$46/'Inputs'!$B$21,"") | C20: =IFERROR('Inputs'!$C$46/'Inputs'!$C$21,"") | D20: =IFERROR('Inputs'!$D$46/'Inputs'!$D$21,"") | E20: =IFERROR('Inputs'!$E$46/'Inputs'!$E$21,"") | F20: =IFERROR('Inputs'!$F$46/'Inputs'!$F$21,"") | G20: =IFERROR('Inputs'!$G$46/'Inputs'!$G$21,"") | H20: =IFERROR('Inputs'!$H$46/'Inputs'!$H$21,"") | I20: =IFERROR('Inputs'!$I$46/'Inputs'!$I$21,"") | J20: =IFERROR('Inputs'!$J$46/'Inputs'!$J$21,"") | K20: =IFERROR('Inputs'!$K$46/'Inputs'!$K$21,"") | L20: =IFERROR('Inputs'!$L$46/'Inputs'!$L$21,"") | M20: =IFERROR('Inputs'!$M$46/'Inputs'!$M$21,"") | N20: =IFERROR('Inputs'!$N$46/'Inputs'!$N$21,"") | O20: =IFERROR('Inputs'!$O$46/'Inputs'!$O$21,"") | P20: =IFERROR('Inputs'!$P$46/'Inputs'!$P$21,"") | Q20: =IF(AND(ISNUMBER($K$20),ISNUMBER($J$20)),CHOOSE(2+($K$20>$J$20)-($K$20<$J$20),"▼","►","▲"),"") | R20: =IF(AND(ISNUMBER($K$20),ISNUMBER(AVERAGE($B$20:$K$20))),CHOOSE(2+($K$20>AVERAGE($B$20:$K$20)*(1+0.05))-($K$20<AVERAGE($B$20:$K$20)*(1-0.05)),"Weak","Stable","Strong"),"")
A22: Automated Observations
A23: =IFERROR("» Current ratio of "&TEXT('Liquidity'!$K$10,"0.00")&"x is assessed "&'Liquidity'!$R$10&"; the cash ratio is "&TEXT('Liquidity'!$K$12,"0.00")&"x.","(insufficient data — populate inputs)")
A24: =IFERROR("» Operations convert "&TEXT('Liquidity'!$K$20,"0%")&" of net income into operating cash — a check on earnings quality.","(insufficient data — populate inputs)")

Sheet Solvency
A1: SOLVENCY RATIOS
A2: Leverage, coverage and long-term financial risk
A3: Institutional Financial Ratio Analysis · v1.0
A5: Dashboard | B5: Inputs | C5: Common Size | D5: Profitability | E5: Liquidity | F5: Solvency | G5: Efficiency | H5: Growth
A6: Valuation | B6: Capital Allocation | C6: Quality | D6: Benchmarking | E6: Guide | F6: Quality Control
A7: All figures in USD millions unless stated; (F) = forecast year.
A8: Solvency ratio | B8: FY2015 | C8: FY2016 | D8: FY2017 | E8: FY2018 | F8: FY2019 | G8: FY2020 | H8: FY2021 | I8: FY2022 | J8: FY2023 | K8: FY2024 | L8: FY2025 (F) | M8: FY2026 (F) | N8: FY2027 (F) | O8: FY2028 (F) | P8: FY2029 (F) | Q8: Trend | R8: Assessment
A9: Leverage
A10: Debt / equity | B10: =IFERROR('Inputs'!$B$66/'Inputs'!$B$42,"") | C10: =IFERROR('Inputs'!$C$66/'Inputs'!$C$42,"") | D10: =IFERROR('Inputs'!$D$66/'Inputs'!$D$42,"") | E10: =IFERROR('Inputs'!$E$66/'Inputs'!$E$42,"") | F10: =IFERROR('Inputs'!$F$66/'Inputs'!$F$42,"") | G10: =IFERROR('Inputs'!$G$66/'Inputs'!$G$42,"") | H10: =IFERROR('Inputs'!$H$66/'Inputs'!$H$42,"") | I10: =IFERROR('Inputs'!$I$66/'Inputs'!$I$42,"") | J10: =IFERROR('Inputs'!$J$66/'Inputs'!$J$42,"") | K10: =IFERROR('Inputs'!$K$66/'Inputs'!$K$42,"") | L10: =IFERROR('Inputs'!$L$66/'Inputs'!$L$42,"") | M10: =IFERROR('Inputs'!$M$66/'Inputs'!$M$42,"") | N10: =IFERROR('Inputs'!$N$66/'Inputs'!$N$42,"") | O10: =IFERROR('Inputs'!$O$66/'Inputs'!$O$42,"") | P10: =IFERROR('Inputs'!$P$66/'Inputs'!$P$42,"") | Q10: =IF(AND(ISNUMBER($K$10),ISNUMBER($J$10)),CHOOSE(2+($K$10>$J$10)-($K$10<$J$10),"▼","►","▲"),"") | R10: =IF(ISNUMBER($K$10),CHOOSE(1+($K$10>=0.5)+($K$10>=1.5),"Low Risk","Moderate Risk","High Risk"),"")
A11: Debt / assets | B11: =IFERROR('Inputs'!$B$66/'Inputs'!$B$32,"") | C11: =IFERROR('Inputs'!$C$66/'Inputs'!$C$32,"") | D11: =IFERROR('Inputs'!$D$66/'Inputs'!$D$32,"") | E11: =IFERROR('Inputs'!$E$66/'Inputs'!$E$32,"") | F11: =IFERROR('Inputs'!$F$66/'Inputs'!$F$32,"") | G11: =IFERROR('Inputs'!$G$66/'Inputs'!$G$32,"") | H11: =IFERROR('Inputs'!$H$66/'Inputs'!$H$32,"") | I11: =IFERROR('Inputs'!$I$66/'Inputs'!$I$32,"") | J11: =IFERROR('Inputs'!$J$66/'Inputs'!$J$32,"") | K11: =IFERROR('Inputs'!$K$66/'Inputs'!$K$32,"") | L11: =IFERROR('Inputs'!$L$66/'Inputs'!$L$32,"") | M11: =IFERROR('Inputs'!$M$66/'Inputs'!$M$32,"") | N11: =IFERROR('Inputs'!$N$66/'Inputs'!$N$32,"") | O11: =IFERROR('Inputs'!$O$66/'Inputs'!$O$32,"") | P11: =IFERROR('Inputs'!$P$66/'Inputs'!$P$32,"") | Q11: =IF(AND(ISNUMBER($K$11),ISNUMBER($J$11)),CHOOSE(2+($K$11>$J$11)-($K$11<$J$11),"▼","►","▲"),"") | R11: =IF(ISNUMBER($K$11),CHOOSE(1+($K$11>=0.3)+($K$11>=0.6),"Low Risk","Moderate Risk","High Risk"),"")
A12: Debt / total capital | B12: =IFERROR('Inputs'!$B$66/('Inputs'!$B$66+'Inputs'!$B$42),"") | C12: =IFERROR('Inputs'!$C$66/('Inputs'!$C$66+'Inputs'!$C$42),"") | D12: =IFERROR('Inputs'!$D$66/('Inputs'!$D$66+'Inputs'!$D$42),"") | E12: =IFERROR('Inputs'!$E$66/('Inputs'!$E$66+'Inputs'!$E$42),"") | F12: =IFERROR('Inputs'!$F$66/('Inputs'!$F$66+'Inputs'!$F$42),"") | G12: =IFERROR('Inputs'!$G$66/('Inputs'!$G$66+'Inputs'!$G$42),"") | H12: =IFERROR('Inputs'!$H$66/('Inputs'!$H$66+'Inputs'!$H$42),"") | I12: =IFERROR('Inputs'!$I$66/('Inputs'!$I$66+'Inputs'!$I$42),"") | J12: =IFERROR('Inputs'!$J$66/('Inputs'!$J$66+'Inputs'!$J$42),"") | K12: =IFERROR('Inputs'!$K$66/('Inputs'!$K$66+'Inputs'!$K$42),"") | L12: =IFERROR('Inputs'!$L$66/('Inputs'!$L$66+'Inputs'!$L$42),"") | M12: =IFERROR('Inputs'!$M$66/('Inputs'!$M$66+'Inputs'!$M$42),"") | N12: =IFERROR('Inputs'!$N$66/('Inputs'!$N$66+'Inputs'!$N$42),"") | O12: =IFERROR('Inputs'!$O$66/('Inputs'!$O$66+'Inputs'!$O$42),"") | P12: =IFERROR('Inputs'!$P$66/('Inputs'!$P$66+'Inputs'!$P$42),"") | Q12: =IF(AND(ISNUMBER($K$12),ISNUMBER($J$12)),CHOOSE(2+($K$12>$J$12)-($K$12<$J$12),"▼","►","▲"),"") | R12: =IF(ISNUMBER($K$12),CHOOSE(1+($K$12>=0.3)+($K$12>=0.6),"Low Risk","Moderate Risk","High Risk"),"")
A13: Financial leverage (assets / equity) | B13: =IFERROR('Inputs'!$B$32/'Inputs'!$B$42,"") | C13: =IFERROR('Inputs'!$C$32/'Inputs'!$C$42,"") | D13: =IFERROR('Inputs'!$D$32/'Inputs'!$D$42,"") | E13: =IFERROR('Inputs'!$E$32/'Inputs'!$E$42,"") | F13: =IFERROR('Inputs'!$F$32/'Inputs'!$F$42,"") | G13: =IFERROR('Inputs'!$G$32/'Inputs'!$G$42,"") | H13: =IFERROR('Inputs'!$H$32/'Inputs'!$H$42,"") | I13: =IFERROR('Inputs'!$I$32/'Inputs'!$I$42,"") | J13: =IFERROR('Inputs'!$J$32/'Inputs'!$J$42,"") | K13: =IFERROR('Inputs'!$K$32/'Inputs'!$K$42,"") | L13: =IFERROR('Inputs'!$L$32/'Inputs'!$L$42,"") | M13: =IFERROR('Inputs'!$M$32/'Inputs'!$M$42,"") | N13: =IFERROR('Inputs'!$N$32/'Inputs'!$N$42,"") | O13: =IFERROR('Inputs'!$O$32/'Inputs'!$O$42,"") | P13: =IFERROR('Inputs'!$P$32/'Inputs'!$P$42,"") | Q13: =IF(AND(ISNUMBER($K$13),ISNUMBER($J$13)),CHOOSE(2+($K$13>$J$13)-($K$13<$J$13),"▼","►","▲"),"") | R13: =IF(AND(ISNUMBER($K$13),ISNUMBER(AVERAGE($B$13:$K$13))),CHOOSE(2+($K$13>AVERAGE($B$13:$K$13)*(1+0.05))-($K$13<AVERAGE($B$13:$K$13)*(1-0.05)),"Falling","Stable","Rising"),"")
A14: Equity ratio (equity / assets) | B14: =IFERROR('Inputs'!$B$42/'Inputs'!$B$32,"") | C14: =IFERROR('Inputs'!$C$42/'Inputs'!$C$32,"") | D14: =IFERROR('Inputs'!$D$42/'Inputs'!$D$32,"") | E14: =IFERROR('Inputs'!$E$42/'Inputs'!$E$32,"") | F14: =IFERROR('Inputs'!$F$42/'Inputs'!$F$32,"") | G14: =IFERROR('Inputs'!$G$42/'Inputs'!$G$32,"") | H14: =IFERROR('Inputs'!$H$42/'Inputs'!$H$32,"") | I14: =IFERROR('Inputs'!$I$42/'Inputs'!$I$32,"") | J14: =IFERROR('Inputs'!$J$42/'Inputs'!$J$32,"") | K14: =IFERROR('Inputs'!$K$42/'Inputs'!$K$32,"") | L14: =IFERROR('Inputs'!$L$42/'Inputs'!$L$32,"") | M14: =IFERROR('Inputs'!$M$42/'Inputs'!$M$32,"") | N14: =IFERROR('Inputs'!$N$42/'Inputs'!$N$32,"") | O14: =IFERROR('Inputs'!$O$42/'Inputs'!$O$32,"") | P14: =IFERROR('Inputs'!$P$42/'Inputs'!$P$32,"") | Q14: =IF(AND(ISNUMBER($K$14),ISNUMBER($J$14)),CHOOSE(2+($K$14>$J$14)-($K$14<$J$14),"▼","►","▲"),"") | R14: =IF(AND(ISNUMBER($K$14),ISNUMBER(AVERAGE($B$14:$K$14))),CHOOSE(2+($K$14>AVERAGE($B$14:$K$14)*(1+0.05))-($K$14<AVERAGE($B$14:$K$14)*(1-0.05)),"Weak","Stable","Strong"),"")
A16: Net Debt
A17: Net debt (debt − cash) | B17: ='Inputs'!$B$67 | C17: ='Inputs'!$C$67 | D17: ='Inputs'!$D$67 | E17: ='Inputs'!$E$67 | F17: ='Inputs'!$F$67 | G17: ='Inputs'!$G$67 | H17: ='Inputs'!$H$67 | I17: ='Inputs'!$I$67 | J17: ='Inputs'!$J$67 | K17: ='Inputs'!$K$67 | L17: ='Inputs'!$L$67 | M17: ='Inputs'!$M$67 | N17: ='Inputs'!$N$67 | O17: ='Inputs'!$O$67 | P17: ='Inputs'!$P$67 | Q17: =IF(AND(ISNUMBER($K$17),ISNUMBER($J$17)),CHOOSE(2+($K$17>$J$17)-($K$17<$J$17),"▼","►","▲"),"")
A18: Net debt / EBITDA | B18: =IFERROR('Inputs'!$B$67/'Inputs'!$B$14,"") | C18: =IFERROR('Inputs'!$C$67/'Inputs'!$C$14,"") | D18: =IFERROR('Inputs'!$D$67/'Inputs'!$D$14,"") | E18: =IFERROR('Inputs'!$E$67/'Inputs'!$E$14,"") | F18: =IFERROR('Inputs'!$F$67/'Inputs'!$F$14,"") | G18: =IFERROR('Inputs'!$G$67/'Inputs'!$G$14,"") | H18: =IFERROR('Inputs'!$H$67/'Inputs'!$H$14,"") | I18: =IFERROR('Inputs'!$I$67/'Inputs'!$I$14,"") | J18: =IFERROR('Inputs'!$J$67/'Inputs'!$J$14,"") | K18: =IFERROR('Inputs'!$K$67/'Inputs'!$K$14,"") | L18: =IFERROR('Inputs'!$L$67/'Inputs'!$L$14,"") | M18: =IFERROR('Inputs'!$M$67/'Inputs'!$M$14,"") | N18: =IFERROR('Inputs'!$N$67/'Inputs'!$N$14,"") | O18: =IFERROR('Inputs'!$O$67/'Inputs'!$O$14,"") | P18: =IFERROR('Inputs'!$P$67/'Inputs'!$P$14,"") | Q18: =IF(AND(ISNUMBER($K$18),ISNUMBER($J$18)),CHOOSE(2+($K$18>$J$18)-($K$18<$J$18),"▼","►","▲"),"") | R18: =IF(ISNUMBER($K$18),CHOOSE(1+($K$18>=1.0)+($K$18>=3.0),"Low Risk","Moderate Risk","High Risk"),"")
A20: Coverage
A21: Interest coverage (EBIT / interest) | B21: =IFERROR('Inputs'!$B$16/'Inputs'!$B$17,"") | C21: =IFERROR('Inputs'!$C$16/'Inputs'!$C$17,"") | D21: =IFERROR('Inputs'!$D$16/'Inputs'!$D$17,"") | E21: =IFERROR('Inputs'!$E$16/'Inputs'!$E$17,"") | F21: =IFERROR('Inputs'!$F$16/'Inputs'!$F$17,"") | G21: =IFERROR('Inputs'!$G$16/'Inputs'!$G$17,"") | H21: =IFERROR('Inputs'!$H$16/'Inputs'!$H$17,"") | I21: =IFERROR('Inputs'!$I$16/'Inputs'!$I$17,"") | J21: =IFERROR('Inputs'!$J$16/'Inputs'!$J$17,"") | K21: =IFERROR('Inputs'!$K$16/'Inputs'!$K$17,"") | L21: =IFERROR('Inputs'!$L$16/'Inputs'!$L$17,"") | M21: =IFERROR('Inputs'!$M$16/'Inputs'!$M$17,"") | N21: =IFERROR('Inputs'!$N$16/'Inputs'!$N$17,"") | O21: =IFERROR('Inputs'!$O$16/'Inputs'!$O$17,"") | P21: =IFERROR('Inputs'!$P$16/'Inputs'!$P$17,"") | Q21: =IF(AND(ISNUMBER($K$21),ISNUMBER($J$21)),CHOOSE(2+($K$21>$J$21)-($K$21<$J$21),"▼","►","▲"),"") | R21: =IF(ISNUMBER($K$21),CHOOSE(1+($K$21>=3.0)+($K$21>=6.0),"High Risk","Moderate Risk","Low Risk"),"")
A22: EBITDA / interest | B22: =IFERROR('Inputs'!$B$14/'Inputs'!$B$17,"") | C22: =IFERROR('Inputs'!$C$14/'Inputs'!$C$17,"") | D22: =IFERROR('Inputs'!$D$14/'Inputs'!$D$17,"") | E22: =IFERROR('Inputs'!$E$14/'Inputs'!$E$17,"") | F22: =IFERROR('Inputs'!$F$14/'Inputs'!$F$17,"") | G22: =IFERROR('Inputs'!$G$14/'Inputs'!$G$17,"") | H22: =IFERROR('Inputs'!$H$14/'Inputs'!$H$17,"") | I22: =IFERROR('Inputs'!$I$14/'Inputs'!$I$17,"") | J22: =IFERROR('Inputs'!$J$14/'Inputs'!$J$17,"") | K22: =IFERROR('Inputs'!$K$14/'Inputs'!$K$17,"") | L22: =IFERROR('Inputs'!$L$14/'Inputs'!$L$17,"") | M22: =IFERROR('Inputs'!$M$14/'Inputs'!$M$17,"") | N22: =IFERROR('Inputs'!$N$14/'Inputs'!$N$17,"") | O22: =IFERROR('Inputs'!$O$14/'Inputs'!$O$17,"") | P22: =IFERROR('Inputs'!$P$14/'Inputs'!$P$17,"") | Q22: =IF(AND(ISNUMBER($K$22),ISNUMBER($J$22)),CHOOSE(2+($K$22>$J$22)-($K$22<$J$22),"▼","►","▲"),"") | R22: =IF(AND(ISNUMBER($K$22),ISNUMBER(AVERAGE($B$22:$K$22))),CHOOSE(2+($K$22>AVERAGE($B$22:$K$22)*(1+0.05))-($K$22<AVERAGE($B$22:$K$22)*(1-0.05)),"Weak","Stable","Strong"),"")
A23: Debt-service coverage (EBITDA / (int + ST debt)) | B23: =IFERROR('Inputs'!$B$14/('Inputs'!$B$17+'Inputs'!$B$35),"") | C23: =IFERROR('Inputs'!$C$14/('Inputs'!$C$17+'Inputs'!$C$35),"") | D23: =IFERROR('Inputs'!$D$14/('Inputs'!$D$17+'Inputs'!$D$35),"") | E23: =IFERROR('Inputs'!$E$14/('Inputs'!$E$17+'Inputs'!$E$35),"") | F23: =IFERROR('Inputs'!$F$14/('Inputs'!$F$17+'Inputs'!$F$35),"") | G23: =IFERROR('Inputs'!$G$14/('Inputs'!$G$17+'Inputs'!$G$35),"") | H23: =IFERROR('Inputs'!$H$14/('Inputs'!$H$17+'Inputs'!$H$35),"") | I23: =IFERROR('Inputs'!$I$14/('Inputs'!$I$17+'Inputs'!$I$35),"") | J23: =IFERROR('Inputs'!$J$14/('Inputs'!$J$17+'Inputs'!$J$35),"") | K23: =IFERROR('Inputs'!$K$14/('Inputs'!$K$17+'Inputs'!$K$35),"") | L23: =IFERROR('Inputs'!$L$14/('Inputs'!$L$17+'Inputs'!$L$35),"") | M23: =IFERROR('Inputs'!$M$14/('Inputs'!$M$17+'Inputs'!$M$35),"") | N23: =IFERROR('Inputs'!$N$14/('Inputs'!$N$17+'Inputs'!$N$35),"") | O23: =IFERROR('Inputs'!$O$14/('Inputs'!$O$17+'Inputs'!$O$35),"") | P23: =IFERROR('Inputs'!$P$14/('Inputs'!$P$17+'Inputs'!$P$35),"") | Q23: =IF(AND(ISNUMBER($K$23),ISNUMBER($J$23)),CHOOSE(2+($K$23>$J$23)-($K$23<$J$23),"▼","►","▲"),"") | R23: =IF(AND(ISNUMBER($K$23),ISNUMBER(AVERAGE($B$23:$K$23))),CHOOSE(2+($K$23>AVERAGE($B$23:$K$23)*(1+0.05))-($K$23<AVERAGE($B$23:$K$23)*(1-0.05)),"Weak","Stable","Strong"),"")
A24: Fixed-charge coverage (EBIT+D&A) / interest | B24: =IFERROR(('Inputs'!$B$16+'Inputs'!$B$15)/'Inputs'!$B$17,"") | C24: =IFERROR(('Inputs'!$C$16+'Inputs'!$C$15)/'Inputs'!$C$17,"") | D24: =IFERROR(('Inputs'!$D$16+'Inputs'!$D$15)/'Inputs'!$D$17,"") | E24: =IFERROR(('Inputs'!$E$16+'Inputs'!$E$15)/'Inputs'!$E$17,"") | F24: =IFERROR(('Inputs'!$F$16+'Inputs'!$F$15)/'Inputs'!$F$17,"") | G24: =IFERROR(('Inputs'!$G$16+'Inputs'!$G$15)/'Inputs'!$G$17,"") | H24: =IFERROR(('Inputs'!$H$16+'Inputs'!$H$15)/'Inputs'!$H$17,"") | I24: =IFERROR(('Inputs'!$I$16+'Inputs'!$I$15)/'Inputs'!$I$17,"") | J24: =IFERROR(('Inputs'!$J$16+'Inputs'!$J$15)/'Inputs'!$J$17,"") | K24: =IFERROR(('Inputs'!$K$16+'Inputs'!$K$15)/'Inputs'!$K$17,"") | L24: =IFERROR(('Inputs'!$L$16+'Inputs'!$L$15)/'Inputs'!$L$17,"") | M24: =IFERROR(('Inputs'!$M$16+'Inputs'!$M$15)/'Inputs'!$M$17,"") | N24: =IFERROR(('Inputs'!$N$16+'Inputs'!$N$15)/'Inputs'!$N$17,"") | O24: =IFERROR(('Inputs'!$O$16+'Inputs'!$O$15)/'Inputs'!$O$17,"") | P24: =IFERROR(('Inputs'!$P$16+'Inputs'!$P$15)/'Inputs'!$P$17,"") | Q24: =IF(AND(ISNUMBER($K$24),ISNUMBER($J$24)),CHOOSE(2+($K$24>$J$24)-($K$24<$J$24),"▼","►","▲"),"") | R24: =IF(AND(ISNUMBER($K$24),ISNUMBER(AVERAGE($B$24:$K$24))),CHOOSE(2+($K$24>AVERAGE($B$24:$K$24)*(1+0.05))-($K$24<AVERAGE($B$24:$K$24)*(1-0.05)),"Weak","Stable","Strong"),"")
A25: Fixed-charge & debt-service coverage are proxies (no lease/principal schedule input).
A27: Automated Observations
A28: =IFERROR("» Net debt / EBITDA is "&TEXT('Solvency'!$K$18,"0.0")&"x — "&'Solvency'!$R$18&"; debt/equity is "&TEXT('Solvency'!$K$10,"0.00")&"x.","(insufficient data — populate inputs)")
A29: =IFERROR("» Interest coverage of "&TEXT('Solvency'!$K$21,"0.0")&"x indicates "&'Solvency'!$R$21&" debt-servicing capacity.","(insufficient data — populate inputs)")

Sheet Efficiency
A1: EFFICIENCY RATIOS
A2: Asset utilisation, turnover and the cash conversion cycle
A3: Institutional Financial Ratio Analysis · v1.0
A5: Dashboard | B5: Inputs | C5: Common Size | D5: Profitability | E5: Liquidity | F5: Solvency | G5: Efficiency | H5: Growth
A6: Valuation | B6: Capital Allocation | C6: Quality | D6: Benchmarking | E6: Guide | F6: Quality Control
A7: All figures in USD millions unless stated; (F) = forecast year.
A8: Efficiency ratio | B8: FY2015 | C8: FY2016 | D8: FY2017 | E8: FY2018 | F8: FY2019 | G8: FY2020 | H8: FY2021 | I8: FY2022 | J8: FY2023 | K8: FY2024 | L8: FY2025 (F) | M8: FY2026 (F) | N8: FY2027 (F) | O8: FY2028 (F) | P8: FY2029 (F) | Q8: Trend | R8: Assessment
A9: Turnover
A10: Asset turnover | C10: =IFERROR('Inputs'!$C$10/'Inputs'!$C$75,"") | D10: =IFERROR('Inputs'!$D$10/'Inputs'!$D$75,"") | E10: =IFERROR('Inputs'!$E$10/'Inputs'!$E$75,"") | F10: =IFERROR('Inputs'!$F$10/'Inputs'!$F$75,"") | G10: =IFERROR('Inputs'!$G$10/'Inputs'!$G$75,"") | H10: =IFERROR('Inputs'!$H$10/'Inputs'!$H$75,"") | I10: =IFERROR('Inputs'!$I$10/'Inputs'!$I$75,"") | J10: =IFERROR('Inputs'!$J$10/'Inputs'!$J$75,"") | K10: =IFERROR('Inputs'!$K$10/'Inputs'!$K$75,"") | L10: =IFERROR('Inputs'!$L$10/'Inputs'!$L$75,"") | M10: =IFERROR('Inputs'!$M$10/'Inputs'!$M$75,"") | N10: =IFERROR('Inputs'!$N$10/'Inputs'!$N$75,"") | O10: =IFERROR('Inputs'!$O$10/'Inputs'!$O$75,"") | P10: =IFERROR('Inputs'!$P$10/'Inputs'!$P$75,"") | Q10: =IF(AND(ISNUMBER($K$10),ISNUMBER($J$10)),CHOOSE(2+($K$10>$J$10)-($K$10<$J$10),"▼","►","▲"),"") | R10: =IF(AND(ISNUMBER($K$10),ISNUMBER(AVERAGE($B$10:$K$10))),CHOOSE(2+($K$10>AVERAGE($B$10:$K$10)*(1+0.05))-($K$10<AVERAGE($B$10:$K$10)*(1-0.05)),"Weak","Stable","Strong"),"")
A11: Fixed-asset turnover | C11: =IFERROR('Inputs'!$C$10/'Inputs'!$C$79,"") | D11: =IFERROR('Inputs'!$D$10/'Inputs'!$D$79,"") | E11: =IFERROR('Inputs'!$E$10/'Inputs'!$E$79,"") | F11: =IFERROR('Inputs'!$F$10/'Inputs'!$F$79,"") | G11: =IFERROR('Inputs'!$G$10/'Inputs'!$G$79,"") | H11: =IFERROR('Inputs'!$H$10/'Inputs'!$H$79,"") | I11: =IFERROR('Inputs'!$I$10/'Inputs'!$I$79,"") | J11: =IFERROR('Inputs'!$J$10/'Inputs'!$J$79,"") | K11: =IFERROR('Inputs'!$K$10/'Inputs'!$K$79,"") | L11: =IFERROR('Inputs'!$L$10/'Inputs'!$L$79,"") | M11: =IFERROR('Inputs'!$M$10/'Inputs'!$M$79,"") | N11: =IFERROR('Inputs'!$N$10/'Inputs'!$N$79,"") | O11: =IFERROR('Inputs'!$O$10/'Inputs'!$O$79,"") | P11: =IFERROR('Inputs'!$P$10/'Inputs'!$P$79,"") | Q11: =IF(AND(ISNUMBER($K$11),ISNUMBER($J$11)),CHOOSE(2+($K$11>$J$11)-($K$11<$J$11),"▼","►","▲"),"") | R11: =IF(AND(ISNUMBER($K$11),ISNUMBER(AVERAGE($B$11:$K$11))),CHOOSE(2+($K$11>AVERAGE($B$11:$K$11)*(1+0.05))-($K$11<AVERAGE($B$11:$K$11)*(1-0.05)),"Weak","Stable","Strong"),"")
A12: Inventory turnover | C12: =IFERROR('Inputs'!$C$11/'Inputs'!$C$77,"") | D12: =IFERROR('Inputs'!$D$11/'Inputs'!$D$77,"") | E12: =IFERROR('Inputs'!$E$11/'Inputs'!$E$77,"") | F12: =IFERROR('Inputs'!$F$11/'Inputs'!$F$77,"") | G12: =IFERROR('Inputs'!$G$11/'Inputs'!$G$77,"") | H12: =IFERROR('Inputs'!$H$11/'Inputs'!$H$77,"") | I12: =IFERROR('Inputs'!$I$11/'Inputs'!$I$77,"") | J12: =IFERROR('Inputs'!$J$11/'Inputs'!$J$77,"") | K12: =IFERROR('Inputs'!$K$11/'Inputs'!$K$77,"") | L12: =IFERROR('Inputs'!$L$11/'Inputs'!$L$77,"") | M12: =IFERROR('Inputs'!$M$11/'Inputs'!$M$77,"") | N12: =IFERROR('Inputs'!$N$11/'Inputs'!$N$77,"") | O12: =IFERROR('Inputs'!$O$11/'Inputs'!$O$77,"") | P12: =IFERROR('Inputs'!$P$11/'Inputs'!$P$77,"") | Q12: =IF(AND(ISNUMBER($K$12),ISNUMBER($J$12)),CHOOSE(2+($K$12>$J$12)-($K$12<$J$12),"▼","►","▲"),"") | R12: =IF(AND(ISNUMBER($K$12),ISNUMBER(AVERAGE($B$12:$K$12))),CHOOSE(2+($K$12>AVERAGE($B$12:$K$12)*(1+0.05))-($K$12<AVERAGE($B$12:$K$12)*(1-0.05)),"Weak","Stable","Strong"),"")
A13: Receivable turnover | C13: =IFERROR('Inputs'!$C$10/'Inputs'!$C$76,"") | D13: =IFERROR('Inputs'!$D$10/'Inputs'!$D$76,"") | E13: =IFERROR('Inputs'!$E$10/'Inputs'!$E$76,"") | F13: =IFERROR('Inputs'!$F$10/'Inputs'!$F$76,"") | G13: =IFERROR('Inputs'!$G$10/'Inputs'!$G$76,"") | H13: =IFERROR('Inputs'!$H$10/'Inputs'!$H$76,"") | I13: =IFERROR('Inputs'!$I$10/'Inputs'!$I$76,"") | J13: =IFERROR('Inputs'!$J$10/'Inputs'!$J$76,"") | K13: =IFERROR('Inputs'!$K$10/'Inputs'!$K$76,"") | L13: =IFERROR('Inputs'!$L$10/'Inputs'!$L$76,"") | M13: =IFERROR('Inputs'!$M$10/'Inputs'!$M$76,"") | N13: =IFERROR('Inputs'!$N$10/'Inputs'!$N$76,"") | O13: =IFERROR('Inputs'!$O$10/'Inputs'!$O$76,"") | P13: =IFERROR('Inputs'!$P$10/'Inputs'!$P$76,"") | Q13: =IF(AND(ISNUMBER($K$13),ISNUMBER($J$13)),CHOOSE(2+($K$13>$J$13)-($K$13<$J$13),"▼","►","▲"),"") | R13: =IF(AND(ISNUMBER($K$13),ISNUMBER(AVERAGE($B$13:$K$13))),CHOOSE(2+($K$13>AVERAGE($B$13:$K$13)*(1+0.05))-($K$13<AVERAGE($B$13:$K$13)*(1-0.05)),"Weak","Stable","Strong"),"")
A14: Payable turnover | C14: =IFERROR('Inputs'!$C$11/'Inputs'!$C$78,"") | D14: =IFERROR('Inputs'!$D$11/'Inputs'!$D$78,"") | E14: =IFERROR('Inputs'!$E$11/'Inputs'!$E$78,"") | F14: =IFERROR('Inputs'!$F$11/'Inputs'!$F$78,"") | G14: =IFERROR('Inputs'!$G$11/'Inputs'!$G$78,"") | H14: =IFERROR('Inputs'!$H$11/'Inputs'!$H$78,"") | I14: =IFERROR('Inputs'!$I$11/'Inputs'!$I$78,"") | J14: =IFERROR('Inputs'!$J$11/'Inputs'!$J$78,"") | K14: =IFERROR('Inputs'!$K$11/'Inputs'!$K$78,"") | L14: =IFERROR('Inputs'!$L$11/'Inputs'!$L$78,"") | M14: =IFERROR('Inputs'!$M$11/'Inputs'!$M$78,"") | N14: =IFERROR('Inputs'!$N$11/'Inputs'!$N$78,"") | O14: =IFERROR('Inputs'!$O$11/'Inputs'!$O$78,"") | P14: =IFERROR('Inputs'!$P$11/'Inputs'!$P$78,"") | Q14: =IF(AND(ISNUMBER($K$14),ISNUMBER($J$14)),CHOOSE(2+($K$14>$J$14)-($K$14<$J$14),"▼","►","▲"),"")
A15: Working-capital turnover | B15: =IFERROR('Inputs'!$B$10/'Inputs'!$B$68,"") | C15: =IFERROR('Inputs'!$C$10/'Inputs'!$C$68,"") | D15: =IFERROR('Inputs'!$D$10/'Inputs'!$D$68,"") | E15: =IFERROR('Inputs'!$E$10/'Inputs'!$E$68,"") | F15: =IFERROR('Inputs'!$F$10/'Inputs'!$F$68,"") | G15: =IFERROR('Inputs'!$G$10/'Inputs'!$G$68,"") | H15: =IFERROR('Inputs'!$H$10/'Inputs'!$H$68,"") | I15: =IFERROR('Inputs'!$I$10/'Inputs'!$I$68,"") | J15: =IFERROR('Inputs'!$J$10/'Inputs'!$J$68,"") | K15: =IFERROR('Inputs'!$K$10/'Inputs'!$K$68,"") | L15: =IFERROR('Inputs'!$L$10/'Inputs'!$L$68,"") | M15: =IFERROR('Inputs'!$M$10/'Inputs'!$M$68,"") | N15: =IFERROR('Inputs'!$N$10/'Inputs'!$N$68,"") | O15: =IFERROR('Inputs'!$O$10/'Inputs'!$O$68,"") | P15: =IFERROR('Inputs'!$P$10/'Inputs'!$P$68,"") | Q15: =IF(AND(ISNUMBER($K$15),ISNUMBER($J$15)),CHOOSE(2+($K$15>$J$15)-($K$15<$J$15),"▼","►","▲"),"")
A17: Cash Conversion Cycle (days)
A18: Days sales outstanding (DSO) | C18: =IFERROR('Inputs'!$C$76/'Inputs'!$C$10*365,"") | D18: =IFERROR('Inputs'!$D$76/'Inputs'!$D$10*365,"") | E18: =IFERROR('Inputs'!$E$76/'Inputs'!$E$10*365,"") | F18: =IFERROR('Inputs'!$F$76/'Inputs'!$F$10*365,"") | G18: =IFERROR('Inputs'!$G$76/'Inputs'!$G$10*365,"") | H18: =IFERROR('Inputs'!$H$76/'Inputs'!$H$10*365,"") | I18: =IFERROR('Inputs'!$I$76/'Inputs'!$I$10*365,"") | J18: =IFERROR('Inputs'!$J$76/'Inputs'!$J$10*365,"") | K18: =IFERROR('Inputs'!$K$76/'Inputs'!$K$10*365,"") | L18: =IFERROR('Inputs'!$L$76/'Inputs'!$L$10*365,"") | M18: =IFERROR('Inputs'!$M$76/'Inputs'!$M$10*365,"") | N18: =IFERROR('Inputs'!$N$76/'Inputs'!$N$10*365,"") | O18: =IFERROR('Inputs'!$O$76/'Inputs'!$O$10*365,"") | P18: =IFERROR('Inputs'!$P$76/'Inputs'!$P$10*365,"") | Q18: =IF(AND(ISNUMBER($K$18),ISNUMBER($J$18)),CHOOSE(2+($K$18>$J$18)-($K$18<$J$18),"▼","►","▲"),"")
A19: Days inventory outstanding (DIO) | C19: =IFERROR('Inputs'!$C$77/'Inputs'!$C$11*365,"") | D19: =IFERROR('Inputs'!$D$77/'Inputs'!$D$11*365,"") | E19: =IFERROR('Inputs'!$E$77/'Inputs'!$E$11*365,"") | F19: =IFERROR('Inputs'!$F$77/'Inputs'!$F$11*365,"") | G19: =IFERROR('Inputs'!$G$77/'Inputs'!$G$11*365,"") | H19: =IFERROR('Inputs'!$H$77/'Inputs'!$H$11*365,"") | I19: =IFERROR('Inputs'!$I$77/'Inputs'!$I$11*365,"") | J19: =IFERROR('Inputs'!$J$77/'Inputs'!$J$11*365,"") | K19: =IFERROR('Inputs'!$K$77/'Inputs'!$K$11*365,"") | L19: =IFERROR('Inputs'!$L$77/'Inputs'!$L$11*365,"") | M19: =IFERROR('Inputs'!$M$77/'Inputs'!$M$11*365,"") | N19: =IFERROR('Inputs'!$N$77/'Inputs'!$N$11*365,"") | O19: =IFERROR('Inputs'!$O$77/'Inputs'!$O$11*365,"") | P19: =IFERROR('Inputs'!$P$77/'Inputs'!$P$11*365,"") | Q19: =IF(AND(ISNUMBER($K$19),ISNUMBER($J$19)),CHOOSE(2+($K$19>$J$19)-($K$19<$J$19),"▼","►","▲"),"")
A20: Days payable outstanding (DPO) | C20: =IFERROR('Inputs'!$C$78/'Inputs'!$C$11*365,"") | D20: =IFERROR('Inputs'!$D$78/'Inputs'!$D$11*365,"") | E20: =IFERROR('Inputs'!$E$78/'Inputs'!$E$11*365,"") | F20: =IFERROR('Inputs'!$F$78/'Inputs'!$F$11*365,"") | G20: =IFERROR('Inputs'!$G$78/'Inputs'!$G$11*365,"") | H20: =IFERROR('Inputs'!$H$78/'Inputs'!$H$11*365,"") | I20: =IFERROR('Inputs'!$I$78/'Inputs'!$I$11*365,"") | J20: =IFERROR('Inputs'!$J$78/'Inputs'!$J$11*365,"") | K20: =IFERROR('Inputs'!$K$78/'Inputs'!$K$11*365,"") | L20: =IFERROR('Inputs'!$L$78/'Inputs'!$L$11*365,"") | M20: =IFERROR('Inputs'!$M$78/'Inputs'!$M$11*365,"") | N20: =IFERROR('Inputs'!$N$78/'Inputs'!$N$11*365,"") | O20: =IFERROR('Inputs'!$O$78/'Inputs'!$O$11*365,"") | P20: =IFERROR('Inputs'!$P$78/'Inputs'!$P$11*365,"") | Q20: =IF(AND(ISNUMBER($K$20),ISNUMBER($J$20)),CHOOSE(2+($K$20>$J$20)-($K$20<$J$20),"▼","►","▲"),"")
A21: Cash conversion cycle (DSO+DIO−DPO) | C21: =IFERROR('Efficiency'!$C$18+'Efficiency'!$C$19-'Efficiency'!$C$20,"") | D21: =IFERROR('Efficiency'!$D$18+'Efficiency'!$D$19-'Efficiency'!$D$20,"") | E21: =IFERROR('Efficiency'!$E$18+'Efficiency'!$E$19-'Efficiency'!$E$20,"") | F21: =IFERROR('Efficiency'!$F$18+'Efficiency'!$F$19-'Efficiency'!$F$20,"") | G21: =IFERROR('Efficiency'!$G$18+'Efficiency'!$G$19-'Efficiency'!$G$20,"") | H21: =IFERROR('Efficiency'!$H$18+'Efficiency'!$H$19-'Efficiency'!$H$20,"") | I21: =IFERROR('Efficiency'!$I$18+'Efficiency'!$I$19-'Efficiency'!$I$20,"") | J21: =IFERROR('Efficiency'!$J$18+'Efficiency'!$J$19-'Efficiency'!$J$20,"") | K21: =IFERROR('Efficiency'!$K$18+'Efficiency'!$K$19-'Efficiency'!$K$20,"") | L21: =IFERROR('Efficiency'!$L$18+'Efficiency'!$L$19-'Efficiency'!$L$20,"") | M21: =IFERROR('Efficiency'!$M$18+'Efficiency'!$M$19-'Efficiency'!$M$20,"") | N21: =IFERROR('Efficiency'!$N$18+'Efficiency'!$N$19-'Efficiency'!$N$20,"") | O21: =IFERROR('Efficiency'!$O$18+'Efficiency'!$O$19-'Efficiency'!$O$20,"") | P21: =IFERROR('Efficiency'!$P$18+'Efficiency'!$P$19-'Efficiency'!$P$20,"") | Q21: =IF(AND(ISNUMBER($K$21),ISNUMBER($J$21)),CHOOSE(2+($K$21>$J$21)-($K$21<$J$21),"▼","►","▲"),"") | R21: =IF(ISNUMBER($K$21),CHOOSE(1+($K$21>=30)+($K$21>=90),"Strong","Adequate","Weak"),"")
A23: Automated Observations
A24: =IFERROR("» The cash conversion cycle is "&TEXT('Efficiency'!$K$21,"0")&" days — "&'Efficiency'!$R$21&" (a negative cycle means customers fund operations).","(insufficient data — populate inputs)")
A25: =IFERROR("» Asset turnover of "&TEXT('Efficiency'!$K$10,"0.00")&"x shows revenue generated per unit of assets.","(insufficient data — populate inputs)")

Sheet Growth
A1: GROWTH ANALYSIS
A2: Year-on-year growth and compound annual growth rates
A3: Institutional Financial Ratio Analysis · v1.0
A5: Dashboard | B5: Inputs | C5: Common Size | D5: Profitability | E5: Liquidity | F5: Solvency | G5: Efficiency | H5: Growth
A6: Valuation | B6: Capital Allocation | C6: Quality | D6: Benchmarking | E6: Guide | F6: Quality Control
A7: All figures in USD millions unless stated; (F) = forecast year.
A8: Growth metric | B8: FY2015 | C8: FY2016 | D8: FY2017 | E8: FY2018 | F8: FY2019 | G8: FY2020 | H8: FY2021 | I8: FY2022 | J8: FY2023 | K8: FY2024 | L8: FY2025 (F) | M8: FY2026 (F) | N8: FY2027 (F) | O8: FY2028 (F) | P8: FY2029 (F) | Q8: Trend | R8: Assessment
A9: Year-on-Year Growth
A10: Revenue growth | C10: =IFERROR('Inputs'!$C$10/'Inputs'!$B$10-1,"") | D10: =IFERROR('Inputs'!$D$10/'Inputs'!$C$10-1,"") | E10: =IFERROR('Inputs'!$E$10/'Inputs'!$D$10-1,"") | F10: =IFERROR('Inputs'!$F$10/'Inputs'!$E$10-1,"") | G10: =IFERROR('Inputs'!$G$10/'Inputs'!$F$10-1,"") | H10: =IFERROR('Inputs'!$H$10/'Inputs'!$G$10-1,"") | I10: =IFERROR('Inputs'!$I$10/'Inputs'!$H$10-1,"") | J10: =IFERROR('Inputs'!$J$10/'Inputs'!$I$10-1,"") | K10: =IFERROR('Inputs'!$K$10/'Inputs'!$J$10-1,"") | L10: =IFERROR('Inputs'!$L$10/'Inputs'!$K$10-1,"") | M10: =IFERROR('Inputs'!$M$10/'Inputs'!$L$10-1,"") | N10: =IFERROR('Inputs'!$N$10/'Inputs'!$M$10-1,"") | O10: =IFERROR('Inputs'!$O$10/'Inputs'!$N$10-1,"") | P10: =IFERROR('Inputs'!$P$10/'Inputs'!$O$10-1,"") | Q10: =IF(AND(ISNUMBER($K$10),ISNUMBER($J$10)),CHOOSE(2+($K$10>$J$10)-($K$10<$J$10),"▼","►","▲"),"") | R10: =IF(AND(ISNUMBER($K$10),ISNUMBER(AVERAGE($B$10:$K$10))),CHOOSE(2+($K$10>AVERAGE($B$10:$K$10)*(1+0.05))-($K$10<AVERAGE($B$10:$K$10)*(1-0.05)),"Decelerating","Stable","Accelerating"),"")
A11: EBITDA growth | C11: =IFERROR('Inputs'!$C$14/'Inputs'!$B$14-1,"") | D11: =IFERROR('Inputs'!$D$14/'Inputs'!$C$14-1,"") | E11: =IFERROR('Inputs'!$E$14/'Inputs'!$D$14-1,"") | F11: =IFERROR('Inputs'!$F$14/'Inputs'!$E$14-1,"") | G11: =IFERROR('Inputs'!$G$14/'Inputs'!$F$14-1,"") | H11: =IFERROR('Inputs'!$H$14/'Inputs'!$G$14-1,"") | I11: =IFERROR('Inputs'!$I$14/'Inputs'!$H$14-1,"") | J11: =IFERROR('Inputs'!$J$14/'Inputs'!$I$14-1,"") | K11: =IFERROR('Inputs'!$K$14/'Inputs'!$J$14-1,"") | L11: =IFERROR('Inputs'!$L$14/'Inputs'!$K$14-1,"") | M11: =IFERROR('Inputs'!$M$14/'Inputs'!$L$14-1,"") | N11: =IFERROR('Inputs'!$N$14/'Inputs'!$M$14-1,"") | O11: =IFERROR('Inputs'!$O$14/'Inputs'!$N$14-1,"") | P11: =IFERROR('Inputs'!$P$14/'Inputs'!$O$14-1,"") | Q11: =IF(AND(ISNUMBER($K$11),ISNUMBER($J$11)),CHOOSE(2+($K$11>$J$11)-($K$11<$J$11),"▼","►","▲"),"") | R11: =IF(AND(ISNUMBER($K$11),ISNUMBER(AVERAGE($B$11:$K$11))),CHOOSE(2+($K$11>AVERAGE($B$11:$K$11)*(1+0.05))-($K$11<AVERAGE($B$11:$K$11)*(1-0.05)),"Decelerating","Stable","Accelerating"),"")
A12: EBIT growth | C12: =IFERROR('Inputs'!$C$16/'Inputs'!$B$16-1,"") | D12: =IFERROR('Inputs'!$D$16/'Inputs'!$C$16-1,"") | E12: =IFERROR('Inputs'!$E$16/'Inputs'!$D$16-1,"") | F12: =IFERROR('Inputs'!$F$16/'Inputs'!$E$16-1,"") | G12: =IFERROR('Inputs'!$G$16/'Inputs'!$F$16-1,"") | H12: =IFERROR('Inputs'!$H$16/'Inputs'!$G$16-1,"") | I12: =IFERROR('Inputs'!$I$16/'Inputs'!$H$16-1,"") | J12: =IFERROR('Inputs'!$J$16/'Inputs'!$I$16-1,"") | K12: =IFERROR('Inputs'!$K$16/'Inputs'!$J$16-1,"") | L12: =IFERROR('Inputs'!$L$16/'Inputs'!$K$16-1,"") | M12: =IFERROR('Inputs'!$M$16/'Inputs'!$L$16-1,"") | N12: =IFERROR('Inputs'!$N$16/'Inputs'!$M$16-1,"") | O12: =IFERROR('Inputs'!$O$16/'Inputs'!$N$16-1,"") | P12: =IFERROR('Inputs'!$P$16/'Inputs'!$O$16-1,"") | Q12: =IF(AND(ISNUMBER($K$12),ISNUMBER($J$12)),CHOOSE(2+($K$12>$J$12)-($K$12<$J$12),"▼","►","▲"),"") | R12: =IF(AND(ISNUMBER($K$12),ISNUMBER(AVERAGE($B$12:$K$12))),CHOOSE(2+($K$12>AVERAGE($B$12:$K$12)*(1+0.05))-($K$12<AVERAGE($B$12:$K$12)*(1-0.05)),"Decelerating","Stable","Accelerating"),"")
A13: Net income growth | C13: =IFERROR('Inputs'!$C$21/'Inputs'!$B$21-1,"") | D13: =IFERROR('Inputs'!$D$21/'Inputs'!$C$21-1,"") | E13: =IFERROR('Inputs'!$E$21/'Inputs'!$D$21-1,"") | F13: =IFERROR('Inputs'!$F$21/'Inputs'!$E$21-1,"") | G13: =IFERROR('Inputs'!$G$21/'Inputs'!$F$21-1,"") | H13: =IFERROR('Inputs'!$H$21/'Inputs'!$G$21-1,"") | I13: =IFERROR('Inputs'!$I$21/'Inputs'!$H$21-1,"") | J13: =IFERROR('Inputs'!$J$21/'Inputs'!$I$21-1,"") | K13: =IFERROR('Inputs'!$K$21/'Inputs'!$J$21-1,"") | L13: =IFERROR('Inputs'!$L$21/'Inputs'!$K$21-1,"") | M13: =IFERROR('Inputs'!$M$21/'Inputs'!$L$21-1,"") | N13: =IFERROR('Inputs'!$N$21/'Inputs'!$M$21-1,"") | O13: =IFERROR('Inputs'!$O$21/'Inputs'!$N$21-1,"") | P13: =IFERROR('Inputs'!$P$21/'Inputs'!$O$21-1,"") | Q13: =IF(AND(ISNUMBER($K$13),ISNUMBER($J$13)),CHOOSE(2+($K$13>$J$13)-($K$13<$J$13),"▼","►","▲"),"") | R13: =IF(AND(ISNUMBER($K$13),ISNUMBER(AVERAGE($B$13:$K$13))),CHOOSE(2+($K$13>AVERAGE($B$13:$K$13)*(1+0.05))-($K$13<AVERAGE($B$13:$K$13)*(1-0.05)),"Decelerating","Stable","Accelerating"),"")
A14: Free cash flow growth | C14: =IFERROR('Inputs'!$C$48/'Inputs'!$B$48-1,"") | D14: =IFERROR('Inputs'!$D$48/'Inputs'!$C$48-1,"") | E14: =IFERROR('Inputs'!$E$48/'Inputs'!$D$48-1,"") | F14: =IFERROR('Inputs'!$F$48/'Inputs'!$E$48-1,"") | G14: =IFERROR('Inputs'!$G$48/'Inputs'!$F$48-1,"") | H14: =IFERROR('Inputs'!$H$48/'Inputs'!$G$48-1,"") | I14: =IFERROR('Inputs'!$I$48/'Inputs'!$H$48-1,"") | J14: =IFERROR('Inputs'!$J$48/'Inputs'!$I$48-1,"") | K14: =IFERROR('Inputs'!$K$48/'Inputs'!$J$48-1,"") | L14: =IFERROR('Inputs'!$L$48/'Inputs'!$K$48-1,"") | M14: =IFERROR('Inputs'!$M$48/'Inputs'!$L$48-1,"") | N14: =IFERROR('Inputs'!$N$48/'Inputs'!$M$48-1,"") | O14: =IFERROR('Inputs'!$O$48/'Inputs'!$N$48-1,"") | P14: =IFERROR('Inputs'!$P$48/'Inputs'!$O$48-1,"") | Q14: =IF(AND(ISNUMBER($K$14),ISNUMBER($J$14)),CHOOSE(2+($K$14>$J$14)-($K$14<$J$14),"▼","►","▲"),"") | R14: =IF(AND(ISNUMBER($K$14),ISNUMBER(AVERAGE($B$14:$K$14))),CHOOSE(2+($K$14>AVERAGE($B$14:$K$14)*(1+0.05))-($K$14<AVERAGE($B$14:$K$14)*(1-0.05)),"Decelerating","Stable","Accelerating"),"")
A15: Asset growth | C15: =IFERROR('Inputs'!$C$32/'Inputs'!$B$32-1,"") | D15: =IFERROR('Inputs'!$D$32/'Inputs'!$C$32-1,"") | E15: =IFERROR('Inputs'!$E$32/'Inputs'!$D$32-1,"") | F15: =IFERROR('Inputs'!$F$32/'Inputs'!$E$32-1,"") | G15: =IFERROR('Inputs'!$G$32/'Inputs'!$F$32-1,"") | H15: =IFERROR('Inputs'!$H$32/'Inputs'!$G$32-1,"") | I15: =IFERROR('Inputs'!$I$32/'Inputs'!$H$32-1,"") | J15: =IFERROR('Inputs'!$J$32/'Inputs'!$I$32-1,"") | K15: =IFERROR('Inputs'!$K$32/'Inputs'!$J$32-1,"") | L15: =IFERROR('Inputs'!$L$32/'Inputs'!$K$32-1,"") | M15: =IFERROR('Inputs'!$M$32/'Inputs'!$L$32-1,"") | N15: =IFERROR('Inputs'!$N$32/'Inputs'!$M$32-1,"") | O15: =IFERROR('Inputs'!$O$32/'Inputs'!$N$32-1,"") | P15: =IFERROR('Inputs'!$P$32/'Inputs'!$O$32-1,"") | Q15: =IF(AND(ISNUMBER($K$15),ISNUMBER($J$15)),CHOOSE(2+($K$15>$J$15)-($K$15<$J$15),"▼","►","▲"),"") | R15: =IF(AND(ISNUMBER($K$15),ISNUMBER(AVERAGE($B$15:$K$15))),CHOOSE(2+($K$15>AVERAGE($B$15:$K$15)*(1+0.05))-($K$15<AVERAGE($B$15:$K$15)*(1-0.05)),"Decelerating","Stable","Accelerating"),"")
A16: Equity growth | C16: =IFERROR('Inputs'!$C$42/'Inputs'!$B$42-1,"") | D16: =IFERROR('Inputs'!$D$42/'Inputs'!$C$42-1,"") | E16: =IFERROR('Inputs'!$E$42/'Inputs'!$D$42-1,"") | F16: =IFERROR('Inputs'!$F$42/'Inputs'!$E$42-1,"") | G16: =IFERROR('Inputs'!$G$42/'Inputs'!$F$42-1,"") | H16: =IFERROR('Inputs'!$H$42/'Inputs'!$G$42-1,"") | I16: =IFERROR('Inputs'!$I$42/'Inputs'!$H$42-1,"") | J16: =IFERROR('Inputs'!$J$42/'Inputs'!$I$42-1,"") | K16: =IFERROR('Inputs'!$K$42/'Inputs'!$J$42-1,"") | L16: =IFERROR('Inputs'!$L$42/'Inputs'!$K$42-1,"") | M16: =IFERROR('Inputs'!$M$42/'Inputs'!$L$42-1,"") | N16: =IFERROR('Inputs'!$N$42/'Inputs'!$M$42-1,"") | O16: =IFERROR('Inputs'!$O$42/'Inputs'!$N$42-1,"") | P16: =IFERROR('Inputs'!$P$42/'Inputs'!$O$42-1,"") | Q16: =IF(AND(ISNUMBER($K$16),ISNUMBER($J$16)),CHOOSE(2+($K$16>$J$16)-($K$16<$J$16),"▼","►","▲"),"") | R16: =IF(AND(ISNUMBER($K$16),ISNUMBER(AVERAGE($B$16:$K$16))),CHOOSE(2+($K$16>AVERAGE($B$16:$K$16)*(1+0.05))-($K$16<AVERAGE($B$16:$K$16)*(1-0.05)),"Decelerating","Stable","Accelerating"),"")
A18: Compound Annual Growth (CAGR)
A19: Metric | B19: 3-Year | C19: 5-Year | D19: 10-Year (FY2015–FY2024)
A20: Revenue | B20: =IFERROR(('Inputs'!$K$10/'Inputs'!$H$10)^(1/3)-1,"") | C20: =IFERROR(('Inputs'!$K$10/'Inputs'!$F$10)^(1/5)-1,"") | D20: =IFERROR(('Inputs'!$K$10/'Inputs'!$B$10)^(1/9)-1,"")
A21: EBITDA | B21: =IFERROR(('Inputs'!$K$14/'Inputs'!$H$14)^(1/3)-1,"") | C21: =IFERROR(('Inputs'!$K$14/'Inputs'!$F$14)^(1/5)-1,"") | D21: =IFERROR(('Inputs'!$K$14/'Inputs'!$B$14)^(1/9)-1,"")
A22: EBIT | B22: =IFERROR(('Inputs'!$K$16/'Inputs'!$H$16)^(1/3)-1,"") | C22: =IFERROR(('Inputs'!$K$16/'Inputs'!$F$16)^(1/5)-1,"") | D22: =IFERROR(('Inputs'!$K$16/'Inputs'!$B$16)^(1/9)-1,"")
A23: Net income | B23: =IFERROR(('Inputs'!$K$21/'Inputs'!$H$21)^(1/3)-1,"") | C23: =IFERROR(('Inputs'!$K$21/'Inputs'!$F$21)^(1/5)-1,"") | D23: =IFERROR(('Inputs'!$K$21/'Inputs'!$B$21)^(1/9)-1,"")
A24: Free cash flow | B24: =IFERROR(('Inputs'!$K$48/'Inputs'!$H$48)^(1/3)-1,"") | C24: =IFERROR(('Inputs'!$K$48/'Inputs'!$F$48)^(1/5)-1,"") | D24: =IFERROR(('Inputs'!$K$48/'Inputs'!$B$48)^(1/9)-1,"")
A25: Total assets | B25: =IFERROR(('Inputs'!$K$32/'Inputs'!$H$32)^(1/3)-1,"") | C25: =IFERROR(('Inputs'!$K$32/'Inputs'!$F$32)^(1/5)-1,"") | D25: =IFERROR(('Inputs'!$K$32/'Inputs'!$B$32)^(1/9)-1,"")
A26: Equity | B26: =IFERROR(('Inputs'!$K$42/'Inputs'!$H$42)^(1/3)-1,"") | C26: =IFERROR(('Inputs'!$K$42/'Inputs'!$F$42)^(1/5)-1,"") | D26: =IFERROR(('Inputs'!$K$42/'Inputs'!$B$42)^(1/9)-1,"")
A28: Automated Observations
A29: =IFERROR("» Revenue compounded at "&TEXT('Growth'!$C$20,"0.0%")&" over 5 years and "&TEXT('Growth'!$D$20,"0.0%")&" over the full window; latest-year growth is "&TEXT('Growth'!$K$10,"0.0%")&".","(insufficient data — populate inputs)")
A30: =IFERROR("» Net income grew "&TEXT('Growth'!$C$23,"0.0%")&" (5y CAGR) vs revenue "&TEXT('Growth'!$C$20,"0.0%")&" — profit "&IF('Growth'!$C$23>'Growth'!$C$20,"outgrew","lagged")&" the top line.","(insufficient data — populate inputs)")

Sheet Valuation
A1: VALUATION RATIOS
A2: Multiples and yields with a transparent EV bridge
A3: Institutional Financial Ratio Analysis · v1.0
A5: Dashboard | B5: Inputs | C5: Common Size | D5: Profitability | E5: Liquidity | F5: Solvency | G5: Efficiency | H5: Growth
A6: Valuation | B6: Capital Allocation | C6: Quality | D6: Benchmarking | E6: Guide | F6: Quality Control
A7: All figures in USD millions unless stated; (F) = forecast year.
A8: Valuation metric | B8: FY2015 | C8: FY2016 | D8: FY2017 | E8: FY2018 | F8: FY2019 | G8: FY2020 | H8: FY2021 | I8: FY2022 | J8: FY2023 | K8: FY2024 | L8: FY2025 (F) | M8: FY2026 (F) | N8: FY2027 (F) | O8: FY2028 (F) | P8: FY2029 (F) | Q8: Trend | R8: Assessment
A9: Enterprise Value Build (every step shown)
A10: Market capitalisation | B10: ='Inputs'!$B$54 | C10: ='Inputs'!$C$54 | D10: ='Inputs'!$D$54 | E10: ='Inputs'!$E$54 | F10: ='Inputs'!$F$54 | G10: ='Inputs'!$G$54 | H10: ='Inputs'!$H$54 | I10: ='Inputs'!$I$54 | J10: ='Inputs'!$J$54 | K10: ='Inputs'!$K$54 | L10: ='Inputs'!$L$54 | M10: ='Inputs'!$M$54 | N10: ='Inputs'!$N$54 | O10: ='Inputs'!$O$54 | P10: ='Inputs'!$P$54
A11: (+) Total debt | B11: ='Inputs'!$B$66 | C11: ='Inputs'!$C$66 | D11: ='Inputs'!$D$66 | E11: ='Inputs'!$E$66 | F11: ='Inputs'!$F$66 | G11: ='Inputs'!$G$66 | H11: ='Inputs'!$H$66 | I11: ='Inputs'!$I$66 | J11: ='Inputs'!$J$66 | K11: ='Inputs'!$K$66 | L11: ='Inputs'!$L$66 | M11: ='Inputs'!$M$66 | N11: ='Inputs'!$N$66 | O11: ='Inputs'!$O$66 | P11: ='Inputs'!$P$66
A12: (−) Cash & equivalents | B12: =-'Inputs'!$B$23 | C12: =-'Inputs'!$C$23 | D12: =-'Inputs'!$D$23 | E12: =-'Inputs'!$E$23 | F12: =-'Inputs'!$F$23 | G12: =-'Inputs'!$G$23 | H12: =-'Inputs'!$H$23 | I12: =-'Inputs'!$I$23 | J12: =-'Inputs'!$J$23 | K12: =-'Inputs'!$K$23 | L12: =-'Inputs'!$L$23 | M12: =-'Inputs'!$M$23 | N12: =-'Inputs'!$N$23 | O12: =-'Inputs'!$O$23 | P12: =-'Inputs'!$P$23
A13: (=) Enterprise value | B13: ='Inputs'!$B$73 | C13: ='Inputs'!$C$73 | D13: ='Inputs'!$D$73 | E13: ='Inputs'!$E$73 | F13: ='Inputs'!$F$73 | G13: ='Inputs'!$G$73 | H13: ='Inputs'!$H$73 | I13: ='Inputs'!$I$73 | J13: ='Inputs'!$J$73 | K13: ='Inputs'!$K$73 | L13: ='Inputs'!$L$73 | M13: ='Inputs'!$M$73 | N13: ='Inputs'!$N$73 | O13: ='Inputs'!$O$73 | P13: ='Inputs'!$P$73
A15: Earnings Multiples
A16: P / E | B16: =IFERROR('Inputs'!$B$54/'Inputs'!$B$21,"") | C16: =IFERROR('Inputs'!$C$54/'Inputs'!$C$21,"") | D16: =IFERROR('Inputs'!$D$54/'Inputs'!$D$21,"") | E16: =IFERROR('Inputs'!$E$54/'Inputs'!$E$21,"") | F16: =IFERROR('Inputs'!$F$54/'Inputs'!$F$21,"") | G16: =IFERROR('Inputs'!$G$54/'Inputs'!$G$21,"") | H16: =IFERROR('Inputs'!$H$54/'Inputs'!$H$21,"") | I16: =IFERROR('Inputs'!$I$54/'Inputs'!$I$21,"") | J16: =IFERROR('Inputs'!$J$54/'Inputs'!$J$21,"") | K16: =IFERROR('Inputs'!$K$54/'Inputs'!$K$21,"") | L16: =IFERROR('Inputs'!$L$54/'Inputs'!$L$21,"") | M16: =IFERROR('Inputs'!$M$54/'Inputs'!$M$21,"") | N16: =IFERROR('Inputs'!$N$54/'Inputs'!$N$21,"") | O16: =IFERROR('Inputs'!$O$54/'Inputs'!$O$21,"") | P16: =IFERROR('Inputs'!$P$54/'Inputs'!$P$21,"") | Q16: =IF(AND(ISNUMBER($K$16),ISNUMBER($J$16)),CHOOSE(2+($K$16>$J$16)-($K$16<$J$16),"▼","►","▲"),"") | R16: =IF(AND(ISNUMBER($K$16),ISNUMBER(AVERAGE($B$16:$K$16))),CHOOSE(2+($K$16>AVERAGE($B$16:$K$16)*(1+0.05))-($K$16<AVERAGE($B$16:$K$16)*(1-0.05)),"Below avg","In-line","Above avg"),"")
A17: Forward P / E | B17: =IFERROR('Inputs'!$B$54/'Inputs'!$C$21,"") | C17: =IFERROR('Inputs'!$C$54/'Inputs'!$D$21,"") | D17: =IFERROR('Inputs'!$D$54/'Inputs'!$E$21,"") | E17: =IFERROR('Inputs'!$E$54/'Inputs'!$F$21,"") | F17: =IFERROR('Inputs'!$F$54/'Inputs'!$G$21,"") | G17: =IFERROR('Inputs'!$G$54/'Inputs'!$H$21,"") | H17: =IFERROR('Inputs'!$H$54/'Inputs'!$I$21,"") | I17: =IFERROR('Inputs'!$I$54/'Inputs'!$J$21,"") | J17: =IFERROR('Inputs'!$J$54/'Inputs'!$K$21,"") | K17: =IFERROR('Inputs'!$K$54/'Inputs'!$L$21,"") | L17: =IFERROR('Inputs'!$L$54/'Inputs'!$M$21,"") | M17: =IFERROR('Inputs'!$M$54/'Inputs'!$N$21,"") | N17: =IFERROR('Inputs'!$N$54/'Inputs'!$O$21,"") | O17: =IFERROR('Inputs'!$O$54/'Inputs'!$P$21,"") | P17: ="" | Q17: =IF(AND(ISNUMBER($K$17),ISNUMBER($J$17)),CHOOSE(2+($K$17>$J$17)-($K$17<$J$17),"▼","►","▲"),"") | R17: =IF(AND(ISNUMBER($K$17),ISNUMBER(AVERAGE($B$17:$K$17))),CHOOSE(2+($K$17>AVERAGE($B$17:$K$17)*(1+0.05))-($K$17<AVERAGE($B$17:$K$17)*(1-0.05)),"Below avg","In-line","Above avg"),"")
A18: PEG (P/E ÷ earnings growth) | C18: =IFERROR(('Inputs'!$C$54/'Inputs'!$C$21)/(('Inputs'!$C$21/'Inputs'!$B$21-1)*100),"") | D18: =IFERROR(('Inputs'!$D$54/'Inputs'!$D$21)/(('Inputs'!$D$21/'Inputs'!$C$21-1)*100),"") | E18: =IFERROR(('Inputs'!$E$54/'Inputs'!$E$21)/(('Inputs'!$E$21/'Inputs'!$D$21-1)*100),"") | F18: =IFERROR(('Inputs'!$F$54/'Inputs'!$F$21)/(('Inputs'!$F$21/'Inputs'!$E$21-1)*100),"") | G18: =IFERROR(('Inputs'!$G$54/'Inputs'!$G$21)/(('Inputs'!$G$21/'Inputs'!$F$21-1)*100),"") | H18: =IFERROR(('Inputs'!$H$54/'Inputs'!$H$21)/(('Inputs'!$H$21/'Inputs'!$G$21-1)*100),"") | I18: =IFERROR(('Inputs'!$I$54/'Inputs'!$I$21)/(('Inputs'!$I$21/'Inputs'!$H$21-1)*100),"") | J18: =IFERROR(('Inputs'!$J$54/'Inputs'!$J$21)/(('Inputs'!$J$21/'Inputs'!$I$21-1)*100),"") | K18: =IFERROR(('Inputs'!$K$54/'Inputs'!$K$21)/(('Inputs'!$K$21/'Inputs'!$J$21-1)*100),"") | L18: =IFERROR(('Inputs'!$L$54/'Inputs'!$L$21)/(('Inputs'!$L$21/'Inputs'!$K$21-1)*100),"") | M18: =IFERROR(('Inputs'!$M$54/'Inputs'!$M$21)/(('Inputs'!$M$21/'Inputs'!$L$21-1)*100),"") | N18: =IFERROR(('Inputs'!$N$54/'Inputs'!$N$21)/(('Inputs'!$N$21/'Inputs'!$M$21-1)*100),"") | O18: =IFERROR(('Inputs'!$O$54/'Inputs'!$O$21)/(('Inputs'!$O$21/'Inputs'!$N$21-1)*100),"") | P18: =IFERROR(('Inputs'!$P$54/'Inputs'!$P$21)/(('Inputs'!$P$21/'Inputs'!$O$21-1)*100),"") | Q18: =IF(AND(ISNUMBER($K$18),ISNUMBER($J$18)),CHOOSE(2+($K$18>$J$18)-($K$18<$J$18),"▼","►","▲"),"")
A19: Earnings yield | B19: =IFERROR('Inputs'!$B$21/'Inputs'!$B$54,"") | C19: =IFERROR('Inputs'!$C$21/'Inputs'!$C$54,"") | D19: =IFERROR('Inputs'!$D$21/'Inputs'!$D$54,"") | E19: =IFERROR('Inputs'!$E$21/'Inputs'!$E$54,"") | F19: =IFERROR('Inputs'!$F$21/'Inputs'!$F$54,"") | G19: =IFERROR('Inputs'!$G$21/'Inputs'!$G$54,"") | H19: =IFERROR('Inputs'!$H$21/'Inputs'!$H$54,"") | I19: =IFERROR('Inputs'!$I$21/'Inputs'!$I$54,"") | J19: =IFERROR('Inputs'!$J$21/'Inputs'!$J$54,"") | K19: =IFERROR('Inputs'!$K$21/'Inputs'!$K$54,"") | L19: =IFERROR('Inputs'!$L$21/'Inputs'!$L$54,"") | M19: =IFERROR('Inputs'!$M$21/'Inputs'!$M$54,"") | N19: =IFERROR('Inputs'!$N$21/'Inputs'!$N$54,"") | O19: =IFERROR('Inputs'!$O$21/'Inputs'!$O$54,"") | P19: =IFERROR('Inputs'!$P$21/'Inputs'!$P$54,"") | Q19: =IF(AND(ISNUMBER($K$19),ISNUMBER($J$19)),CHOOSE(2+($K$19>$J$19)-($K$19<$J$19),"▼","►","▲"),"") | R19: =IF(AND(ISNUMBER($K$19),ISNUMBER(AVERAGE($B$19:$K$19))),CHOOSE(2+($K$19>AVERAGE($B$19:$K$19)*(1+0.05))-($K$19<AVERAGE($B$19:$K$19)*(1-0.05)),"Low","Average","High"),"")
A21: Enterprise-Value Multiples
A22: EV / Revenue | B22: =IFERROR('Inputs'!$B$73/'Inputs'!$B$10,"") | C22: =IFERROR('Inputs'!$C$73/'Inputs'!$C$10,"") | D22: =IFERROR('Inputs'!$D$73/'Inputs'!$D$10,"") | E22: =IFERROR('Inputs'!$E$73/'Inputs'!$E$10,"") | F22: =IFERROR('Inputs'!$F$73/'Inputs'!$F$10,"") | G22: =IFERROR('Inputs'!$G$73/'Inputs'!$G$10,"") | H22: =IFERROR('Inputs'!$H$73/'Inputs'!$H$10,"") | I22: =IFERROR('Inputs'!$I$73/'Inputs'!$I$10,"") | J22: =IFERROR('Inputs'!$J$73/'Inputs'!$J$10,"") | K22: =IFERROR('Inputs'!$K$73/'Inputs'!$K$10,"") | L22: =IFERROR('Inputs'!$L$73/'Inputs'!$L$10,"") | M22: =IFERROR('Inputs'!$M$73/'Inputs'!$M$10,"") | N22: =IFERROR('Inputs'!$N$73/'Inputs'!$N$10,"") | O22: =IFERROR('Inputs'!$O$73/'Inputs'!$O$10,"") | P22: =IFERROR('Inputs'!$P$73/'Inputs'!$P$10,"") | Q22: =IF(AND(ISNUMBER($K$22),ISNUMBER($J$22)),CHOOSE(2+($K$22>$J$22)-($K$22<$J$22),"▼","►","▲"),"") | R22: =IF(AND(ISNUMBER($K$22),ISNUMBER(AVERAGE($B$22:$K$22))),CHOOSE(2+($K$22>AVERAGE($B$22:$K$22)*(1+0.05))-($K$22<AVERAGE($B$22:$K$22)*(1-0.05)),"Below avg","In-line","Above avg"),"")
A23: EV / EBITDA | B23: =IFERROR('Inputs'!$B$73/'Inputs'!$B$14,"") | C23: =IFERROR('Inputs'!$C$73/'Inputs'!$C$14,"") | D23: =IFERROR('Inputs'!$D$73/'Inputs'!$D$14,"") | E23: =IFERROR('Inputs'!$E$73/'Inputs'!$E$14,"") | F23: =IFERROR('Inputs'!$F$73/'Inputs'!$F$14,"") | G23: =IFERROR('Inputs'!$G$73/'Inputs'!$G$14,"") | H23: =IFERROR('Inputs'!$H$73/'Inputs'!$H$14,"") | I23: =IFERROR('Inputs'!$I$73/'Inputs'!$I$14,"") | J23: =IFERROR('Inputs'!$J$73/'Inputs'!$J$14,"") | K23: =IFERROR('Inputs'!$K$73/'Inputs'!$K$14,"") | L23: =IFERROR('Inputs'!$L$73/'Inputs'!$L$14,"") | M23: =IFERROR('Inputs'!$M$73/'Inputs'!$M$14,"") | N23: =IFERROR('Inputs'!$N$73/'Inputs'!$N$14,"") | O23: =IFERROR('Inputs'!$O$73/'Inputs'!$O$14,"") | P23: =IFERROR('Inputs'!$P$73/'Inputs'!$P$14,"") | Q23: =IF(AND(ISNUMBER($K$23),ISNUMBER($J$23)),CHOOSE(2+($K$23>$J$23)-($K$23<$J$23),"▼","►","▲"),"") | R23: =IF(AND(ISNUMBER($K$23),ISNUMBER(AVERAGE($B$23:$K$23))),CHOOSE(2+($K$23>AVERAGE($B$23:$K$23)*(1+0.05))-($K$23<AVERAGE($B$23:$K$23)*(1-0.05)),"Below avg","In-line","Above avg"),"")
A24: EV / EBIT | B24: =IFERROR('Inputs'!$B$73/'Inputs'!$B$16,"") | C24: =IFERROR('Inputs'!$C$73/'Inputs'!$C$16,"") | D24: =IFERROR('Inputs'!$D$73/'Inputs'!$D$16,"") | E24: =IFERROR('Inputs'!$E$73/'Inputs'!$E$16,"") | F24: =IFERROR('Inputs'!$F$73/'Inputs'!$F$16,"") | G24: =IFERROR('Inputs'!$G$73/'Inputs'!$G$16,"") | H24: =IFERROR('Inputs'!$H$73/'Inputs'!$H$16,"") | I24: =IFERROR('Inputs'!$I$73/'Inputs'!$I$16,"") | J24: =IFERROR('Inputs'!$J$73/'Inputs'!$J$16,"") | K24: =IFERROR('Inputs'!$K$73/'Inputs'!$K$16,"") | L24: =IFERROR('Inputs'!$L$73/'Inputs'!$L$16,"") | M24: =IFERROR('Inputs'!$M$73/'Inputs'!$M$16,"") | N24: =IFERROR('Inputs'!$N$73/'Inputs'!$N$16,"") | O24: =IFERROR('Inputs'!$O$73/'Inputs'!$O$16,"") | P24: =IFERROR('Inputs'!$P$73/'Inputs'!$P$16,"") | Q24: =IF(AND(ISNUMBER($K$24),ISNUMBER($J$24)),CHOOSE(2+($K$24>$J$24)-($K$24<$J$24),"▼","►","▲"),"") | R24: =IF(AND(ISNUMBER($K$24),ISNUMBER(AVERAGE($B$24:$K$24))),CHOOSE(2+($K$24>AVERAGE($B$24:$K$24)*(1+0.05))-($K$24<AVERAGE($B$24:$K$24)*(1-0.05)),"Below avg","In-line","Above avg"),"")
A25: EV / FCF | B25: =IFERROR('Inputs'!$B$73/'Inputs'!$B$48,"") | C25: =IFERROR('Inputs'!$C$73/'Inputs'!$C$48,"") | D25: =IFERROR('Inputs'!$D$73/'Inputs'!$D$48,"") | E25: =IFERROR('Inputs'!$E$73/'Inputs'!$E$48,"") | F25: =IFERROR('Inputs'!$F$73/'Inputs'!$F$48,"") | G25: =IFERROR('Inputs'!$G$73/'Inputs'!$G$48,"") | H25: =IFERROR('Inputs'!$H$73/'Inputs'!$H$48,"") | I25: =IFERROR('Inputs'!$I$73/'Inputs'!$I$48,"") | J25: =IFERROR('Inputs'!$J$73/'Inputs'!$J$48,"") | K25: =IFERROR('Inputs'!$K$73/'Inputs'!$K$48,"") | L25: =IFERROR('Inputs'!$L$73/'Inputs'!$L$48,"") | M25: =IFERROR('Inputs'!$M$73/'Inputs'!$M$48,"") | N25: =IFERROR('Inputs'!$N$73/'Inputs'!$N$48,"") | O25: =IFERROR('Inputs'!$O$73/'Inputs'!$O$48,"") | P25: =IFERROR('Inputs'!$P$73/'Inputs'!$P$48,"") | Q25: =IF(AND(ISNUMBER($K$25),ISNUMBER($J$25)),CHOOSE(2+($K$25>$J$25)-($K$25<$J$25),"▼","►","▲"),"") | R25: =IF(AND(ISNUMBER($K$25),ISNUMBER(AVERAGE($B$25:$K$25))),CHOOSE(2+($K$25>AVERAGE($B$25:$K$25)*(1+0.05))-($K$25<AVERAGE($B$25:$K$25)*(1-0.05)),"Below avg","In-line","Above avg"),"")
A27: Book & Cash-Flow Multiples / Yields
A28: P / B | B28: =IFERROR('Inputs'!$B$54/'Inputs'!$B$42,"") | C28: =IFERROR('Inputs'!$C$54/'Inputs'!$C$42,"") | D28: =IFERROR('Inputs'!$D$54/'Inputs'!$D$42,"") | E28: =IFERROR('Inputs'!$E$54/'Inputs'!$E$42,"") | F28: =IFERROR('Inputs'!$F$54/'Inputs'!$F$42,"") | G28: =IFERROR('Inputs'!$G$54/'Inputs'!$G$42,"") | H28: =IFERROR('Inputs'!$H$54/'Inputs'!$H$42,"") | I28: =IFERROR('Inputs'!$I$54/'Inputs'!$I$42,"") | J28: =IFERROR('Inputs'!$J$54/'Inputs'!$J$42,"") | K28: =IFERROR('Inputs'!$K$54/'Inputs'!$K$42,"") | L28: =IFERROR('Inputs'!$L$54/'Inputs'!$L$42,"") | M28: =IFERROR('Inputs'!$M$54/'Inputs'!$M$42,"") | N28: =IFERROR('Inputs'!$N$54/'Inputs'!$N$42,"") | O28: =IFERROR('Inputs'!$O$54/'Inputs'!$O$42,"") | P28: =IFERROR('Inputs'!$P$54/'Inputs'!$P$42,"") | Q28: =IF(AND(ISNUMBER($K$28),ISNUMBER($J$28)),CHOOSE(2+($K$28>$J$28)-($K$28<$J$28),"▼","►","▲"),"") | R28: =IF(AND(ISNUMBER($K$28),ISNUMBER(AVERAGE($B$28:$K$28))),CHOOSE(2+($K$28>AVERAGE($B$28:$K$28)*(1+0.05))-($K$28<AVERAGE($B$28:$K$28)*(1-0.05)),"Below avg","In-line","Above avg"),"")
A29: P / Tangible book | B29: =IFERROR('Inputs'!$B$54/'Inputs'!$B$72,"") | C29: =IFERROR('Inputs'!$C$54/'Inputs'!$C$72,"") | D29: =IFERROR('Inputs'!$D$54/'Inputs'!$D$72,"") | E29: =IFERROR('Inputs'!$E$54/'Inputs'!$E$72,"") | F29: =IFERROR('Inputs'!$F$54/'Inputs'!$F$72,"") | G29: =IFERROR('Inputs'!$G$54/'Inputs'!$G$72,"") | H29: =IFERROR('Inputs'!$H$54/'Inputs'!$H$72,"") | I29: =IFERROR('Inputs'!$I$54/'Inputs'!$I$72,"") | J29: =IFERROR('Inputs'!$J$54/'Inputs'!$J$72,"") | K29: =IFERROR('Inputs'!$K$54/'Inputs'!$K$72,"") | L29: =IFERROR('Inputs'!$L$54/'Inputs'!$L$72,"") | M29: =IFERROR('Inputs'!$M$54/'Inputs'!$M$72,"") | N29: =IFERROR('Inputs'!$N$54/'Inputs'!$N$72,"") | O29: =IFERROR('Inputs'!$O$54/'Inputs'!$O$72,"") | P29: =IFERROR('Inputs'!$P$54/'Inputs'!$P$72,"") | Q29: =IF(AND(ISNUMBER($K$29),ISNUMBER($J$29)),CHOOSE(2+($K$29>$J$29)-($K$29<$J$29),"▼","►","▲"),"") | R29: =IF(AND(ISNUMBER($K$29),ISNUMBER(AVERAGE($B$29:$K$29))),CHOOSE(2+($K$29>AVERAGE($B$29:$K$29)*(1+0.05))-($K$29<AVERAGE($B$29:$K$29)*(1-0.05)),"Below avg","In-line","Above avg"),"")
A30: P / FCF | B30: =IFERROR('Inputs'!$B$54/'Inputs'!$B$48,"") | C30: =IFERROR('Inputs'!$C$54/'Inputs'!$C$48,"") | D30: =IFERROR('Inputs'!$D$54/'Inputs'!$D$48,"") | E30: =IFERROR('Inputs'!$E$54/'Inputs'!$E$48,"") | F30: =IFERROR('Inputs'!$F$54/'Inputs'!$F$48,"") | G30: =IFERROR('Inputs'!$G$54/'Inputs'!$G$48,"") | H30: =IFERROR('Inputs'!$H$54/'Inputs'!$H$48,"") | I30: =IFERROR('Inputs'!$I$54/'Inputs'!$I$48,"") | J30: =IFERROR('Inputs'!$J$54/'Inputs'!$J$48,"") | K30: =IFERROR('Inputs'!$K$54/'Inputs'!$K$48,"") | L30: =IFERROR('Inputs'!$L$54/'Inputs'!$L$48,"") | M30: =IFERROR('Inputs'!$M$54/'Inputs'!$M$48,"") | N30: =IFERROR('Inputs'!$N$54/'Inputs'!$N$48,"") | O30: =IFERROR('Inputs'!$O$54/'Inputs'!$O$48,"") | P30: =IFERROR('Inputs'!$P$54/'Inputs'!$P$48,"") | Q30: =IF(AND(ISNUMBER($K$30),ISNUMBER($J$30)),CHOOSE(2+($K$30>$J$30)-($K$30<$J$30),"▼","►","▲"),"") | R30: =IF(AND(ISNUMBER($K$30),ISNUMBER(AVERAGE($B$30:$K$30))),CHOOSE(2+($K$30>AVERAGE($B$30:$K$30)*(1+0.05))-($K$30<AVERAGE($B$30:$K$30)*(1-0.05)),"Below avg","In-line","Above avg"),"")
A31: FCF yield | B31: =IFERROR('Inputs'!$B$48/'Inputs'!$B$54,"") | C31: =IFERROR('Inputs'!$C$48/'Inputs'!$C$54,"") | D31: =IFERROR('Inputs'!$D$48/'Inputs'!$D$54,"") | E31: =IFERROR('Inputs'!$E$48/'Inputs'!$E$54,"") | F31: =IFERROR('Inputs'!$F$48/'Inputs'!$F$54,"") | G31: =IFERROR('Inputs'!$G$48/'Inputs'!$G$54,"") | H31: =IFERROR('Inputs'!$H$48/'Inputs'!$H$54,"") | I31: =IFERROR('Inputs'!$I$48/'Inputs'!$I$54,"") | J31: =IFERROR('Inputs'!$J$48/'Inputs'!$J$54,"") | K31: =IFERROR('Inputs'!$K$48/'Inputs'!$K$54,"") | L31: =IFERROR('Inputs'!$L$48/'Inputs'!$L$54,"") | M31: =IFERROR('Inputs'!$M$48/'Inputs'!$M$54,"") | N31: =IFERROR('Inputs'!$N$48/'Inputs'!$N$54,"") | O31: =IFERROR('Inputs'!$O$48/'Inputs'!$O$54,"") | P31: =IFERROR('Inputs'!$P$48/'Inputs'!$P$54,"") | Q31: =IF(AND(ISNUMBER($K$31),ISNUMBER($J$31)),CHOOSE(2+($K$31>$J$31)-($K$31<$J$31),"▼","►","▲"),"") | R31: =IF(AND(ISNUMBER($K$31),ISNUMBER(AVERAGE($B$31:$K$31))),CHOOSE(2+($K$31>AVERAGE($B$31:$K$31)*(1+0.05))-($K$31<AVERAGE($B$31:$K$31)*(1-0.05)),"Low","Average","High"),"")
A32: Dividend yield | B32: =IFERROR('Inputs'!$B$56/'Inputs'!$B$52,"") | C32: =IFERROR('Inputs'!$C$56/'Inputs'!$C$52,"") | D32: =IFERROR('Inputs'!$D$56/'Inputs'!$D$52,"") | E32: =IFERROR('Inputs'!$E$56/'Inputs'!$E$52,"") | F32: =IFERROR('Inputs'!$F$56/'Inputs'!$F$52,"") | G32: =IFERROR('Inputs'!$G$56/'Inputs'!$G$52,"") | H32: =IFERROR('Inputs'!$H$56/'Inputs'!$H$52,"") | I32: =IFERROR('Inputs'!$I$56/'Inputs'!$I$52,"") | J32: =IFERROR('Inputs'!$J$56/'Inputs'!$J$52,"") | K32: =IFERROR('Inputs'!$K$56/'Inputs'!$K$52,"") | L32: =IFERROR('Inputs'!$L$56/'Inputs'!$L$52,"") | M32: =IFERROR('Inputs'!$M$56/'Inputs'!$M$52,"") | N32: =IFERROR('Inputs'!$N$56/'Inputs'!$N$52,"") | O32: =IFERROR('Inputs'!$O$56/'Inputs'!$O$52,"") | P32: =IFERROR('Inputs'!$P$56/'Inputs'!$P$52,"") | Q32: =IF(AND(ISNUMBER($K$32),ISNUMBER($J$32)),CHOOSE(2+($K$32>$J$32)-($K$32<$J$32),"▼","►","▲"),"") | R32: =IF(AND(ISNUMBER($K$32),ISNUMBER(AVERAGE($B$32:$K$32))),CHOOSE(2+($K$32>AVERAGE($B$32:$K$32)*(1+0.05))-($K$32<AVERAGE($B$32:$K$32)*(1-0.05)),"Low","Average","High"),"")
A34: Automated Observations
A35: =IFERROR("» Shares trade on "&TEXT('Valuation'!$K$23,"0.0")&"x EV/EBITDA and "&TEXT('Valuation'!$K$16,"0.0")&"x P/E — "&'Valuation'!$R$23&" versus the company's own history.","(insufficient data — populate inputs)")
A36: =IFERROR("» FCF yield is "&TEXT('Valuation'!$K$31,"0.0%")&" and earnings yield "&TEXT('Valuation'!$K$19,"0.0%")&", the inverse of the P/E.","(insufficient data — populate inputs)")

Sheet Capital Allocation
A1: CAPITAL ALLOCATION ANALYSIS
A2: Distributions, buybacks, reinvestment and discipline
A3: Institutional Financial Ratio Analysis · v1.0
A5: Dashboard | B5: Inputs | C5: Common Size | D5: Profitability | E5: Liquidity | F5: Solvency | G5: Efficiency | H5: Growth
A6: Valuation | B6: Capital Allocation | C6: Quality | D6: Benchmarking | E6: Guide | F6: Quality Control
A7: All figures in USD millions unless stated; (F) = forecast year.
A8: Capital-allocation metric | B8: FY2015 | C8: FY2016 | D8: FY2017 | E8: FY2018 | F8: FY2019 | G8: FY2020 | H8: FY2021 | I8: FY2022 | J8: FY2023 | K8: FY2024 | L8: FY2025 (F) | M8: FY2026 (F) | N8: FY2027 (F) | O8: FY2028 (F) | P8: FY2029 (F) | Q8: Trend | R8: Assessment
A9: Distributions
A10: Dividend payout ratio | B10: =IFERROR('Inputs'!$B$49/'Inputs'!$B$21,"") | C10: =IFERROR('Inputs'!$C$49/'Inputs'!$C$21,"") | D10: =IFERROR('Inputs'!$D$49/'Inputs'!$D$21,"") | E10: =IFERROR('Inputs'!$E$49/'Inputs'!$E$21,"") | F10: =IFERROR('Inputs'!$F$49/'Inputs'!$F$21,"") | G10: =IFERROR('Inputs'!$G$49/'Inputs'!$G$21,"") | H10: =IFERROR('Inputs'!$H$49/'Inputs'!$H$21,"") | I10: =IFERROR('Inputs'!$I$49/'Inputs'!$I$21,"") | J10: =IFERROR('Inputs'!$J$49/'Inputs'!$J$21,"") | K10: =IFERROR('Inputs'!$K$49/'Inputs'!$K$21,"") | L10: =IFERROR('Inputs'!$L$49/'Inputs'!$L$21,"") | M10: =IFERROR('Inputs'!$M$49/'Inputs'!$M$21,"") | N10: =IFERROR('Inputs'!$N$49/'Inputs'!$N$21,"") | O10: =IFERROR('Inputs'!$O$49/'Inputs'!$O$21,"") | P10: =IFERROR('Inputs'!$P$49/'Inputs'!$P$21,"") | Q10: =IF(AND(ISNUMBER($K$10),ISNUMBER($J$10)),CHOOSE(2+($K$10>$J$10)-($K$10<$J$10),"▼","►","▲"),"") | R10: =IF(AND(ISNUMBER($K$10),ISNUMBER(AVERAGE($B$10:$K$10))),CHOOSE(2+($K$10>AVERAGE($B$10:$K$10)*(1+0.05))-($K$10<AVERAGE($B$10:$K$10)*(1-0.05)),"Falling","Stable","Rising"),"")
A11: Dividend per share growth | C11: =IFERROR('Inputs'!$C$56/'Inputs'!$B$56-1,"") | D11: =IFERROR('Inputs'!$D$56/'Inputs'!$C$56-1,"") | E11: =IFERROR('Inputs'!$E$56/'Inputs'!$D$56-1,"") | F11: =IFERROR('Inputs'!$F$56/'Inputs'!$E$56-1,"") | G11: =IFERROR('Inputs'!$G$56/'Inputs'!$F$56-1,"") | H11: =IFERROR('Inputs'!$H$56/'Inputs'!$G$56-1,"") | I11: =IFERROR('Inputs'!$I$56/'Inputs'!$H$56-1,"") | J11: =IFERROR('Inputs'!$J$56/'Inputs'!$I$56-1,"") | K11: =IFERROR('Inputs'!$K$56/'Inputs'!$J$56-1,"") | L11: =IFERROR('Inputs'!$L$56/'Inputs'!$K$56-1,"") | M11: =IFERROR('Inputs'!$M$56/'Inputs'!$L$56-1,"") | N11: =IFERROR('Inputs'!$N$56/'Inputs'!$M$56-1,"") | O11: =IFERROR('Inputs'!$O$56/'Inputs'!$N$56-1,"") | P11: =IFERROR('Inputs'!$P$56/'Inputs'!$O$56-1,"") | Q11: =IF(AND(ISNUMBER($K$11),ISNUMBER($J$11)),CHOOSE(2+($K$11>$J$11)-($K$11<$J$11),"▼","►","▲"),"") | R11: =IF(AND(ISNUMBER($K$11),ISNUMBER(AVERAGE($B$11:$K$11))),CHOOSE(2+($K$11>AVERAGE($B$11:$K$11)*(1+0.05))-($K$11<AVERAGE($B$11:$K$11)*(1-0.05)),"Falling","Stable","Rising"),"")
A12: Share buybacks | B12: ='Inputs'!$B$50 | C12: ='Inputs'!$C$50 | D12: ='Inputs'!$D$50 | E12: ='Inputs'!$E$50 | F12: ='Inputs'!$F$50 | G12: ='Inputs'!$G$50 | H12: ='Inputs'!$H$50 | I12: ='Inputs'!$I$50 | J12: ='Inputs'!$J$50 | K12: ='Inputs'!$K$50 | L12: ='Inputs'!$L$50 | M12: ='Inputs'!$M$50 | N12: ='Inputs'!$N$50 | O12: ='Inputs'!$O$50 | P12: ='Inputs'!$P$50 | Q12: =IF(AND(ISNUMBER($K$12),ISNUMBER($J$12)),CHOOSE(2+($K$12>$J$12)-($K$12<$J$12),"▼","►","▲"),"") | R12: =IF(AND(ISNUMBER($K$12),ISNUMBER(AVERAGE($B$12:$K$12))),CHOOSE(2+($K$12>AVERAGE($B$12:$K$12)*(1+0.05))-($K$12<AVERAGE($B$12:$K$12)*(1-0.05)),"Falling","Stable","Rising"),"")
A13: Share count change (− = buyback) | C13: =IFERROR('Inputs'!$C$53/'Inputs'!$B$53-1,"") | D13: =IFERROR('Inputs'!$D$53/'Inputs'!$C$53-1,"") | E13: =IFERROR('Inputs'!$E$53/'Inputs'!$D$53-1,"") | F13: =IFERROR('Inputs'!$F$53/'Inputs'!$E$53-1,"") | G13: =IFERROR('Inputs'!$G$53/'Inputs'!$F$53-1,"") | H13: =IFERROR('Inputs'!$H$53/'Inputs'!$G$53-1,"") | I13: =IFERROR('Inputs'!$I$53/'Inputs'!$H$53-1,"") | J13: =IFERROR('Inputs'!$J$53/'Inputs'!$I$53-1,"") | K13: =IFERROR('Inputs'!$K$53/'Inputs'!$J$53-1,"") | L13: =IFERROR('Inputs'!$L$53/'Inputs'!$K$53-1,"") | M13: =IFERROR('Inputs'!$M$53/'Inputs'!$L$53-1,"") | N13: =IFERROR('Inputs'!$N$53/'Inputs'!$M$53-1,"") | O13: =IFERROR('Inputs'!$O$53/'Inputs'!$N$53-1,"") | P13: =IFERROR('Inputs'!$P$53/'Inputs'!$O$53-1,"") | Q13: =IF(AND(ISNUMBER($K$13),ISNUMBER($J$13)),CHOOSE(2+($K$13>$J$13)-($K$13<$J$13),"▼","►","▲"),"") | R13: =IF(ISNUMBER($K$13),CHOOSE(1+($K$13>=0)+($K$13>=1e-06),"Reducing","Flat","Diluting"),"")
A14: Total payout (div + buyback) / NI | B14: =IFERROR(('Inputs'!$B$49+'Inputs'!$B$50)/'Inputs'!$B$21,"") | C14: =IFERROR(('Inputs'!$C$49+'Inputs'!$C$50)/'Inputs'!$C$21,"") | D14: =IFERROR(('Inputs'!$D$49+'Inputs'!$D$50)/'Inputs'!$D$21,"") | E14: =IFERROR(('Inputs'!$E$49+'Inputs'!$E$50)/'Inputs'!$E$21,"") | F14: =IFERROR(('Inputs'!$F$49+'Inputs'!$F$50)/'Inputs'!$F$21,"") | G14: =IFERROR(('Inputs'!$G$49+'Inputs'!$G$50)/'Inputs'!$G$21,"") | H14: =IFERROR(('Inputs'!$H$49+'Inputs'!$H$50)/'Inputs'!$H$21,"") | I14: =IFERROR(('Inputs'!$I$49+'Inputs'!$I$50)/'Inputs'!$I$21,"") | J14: =IFERROR(('Inputs'!$J$49+'Inputs'!$J$50)/'Inputs'!$J$21,"") | K14: =IFERROR(('Inputs'!$K$49+'Inputs'!$K$50)/'Inputs'!$K$21,"") | L14: =IFERROR(('Inputs'!$L$49+'Inputs'!$L$50)/'Inputs'!$L$21,"") | M14: =IFERROR(('Inputs'!$M$49+'Inputs'!$M$50)/'Inputs'!$M$21,"") | N14: =IFERROR(('Inputs'!$N$49+'Inputs'!$N$50)/'Inputs'!$N$21,"") | O14: =IFERROR(('Inputs'!$O$49+'Inputs'!$O$50)/'Inputs'!$O$21,"") | P14: =IFERROR(('Inputs'!$P$49+'Inputs'!$P$50)/'Inputs'!$P$21,"") | Q14: =IF(AND(ISNUMBER($K$14),ISNUMBER($J$14)),CHOOSE(2+($K$14>$J$14)-($K$14<$J$14),"▼","►","▲"),"") | R14: =IF(AND(ISNUMBER($K$14),ISNUMBER(AVERAGE($B$14:$K$14))),CHOOSE(2+($K$14>AVERAGE($B$14:$K$14)*(1+0.05))-($K$14<AVERAGE($B$14:$K$14)*(1-0.05)),"Falling","Stable","Rising"),"")
A16: Reinvestment & Conversion
A17: Retention ratio (1 − payout) | B17: =IFERROR(1-'Inputs'!$B$49/'Inputs'!$B$21,"") | C17: =IFERROR(1-'Inputs'!$C$49/'Inputs'!$C$21,"") | D17: =IFERROR(1-'Inputs'!$D$49/'Inputs'!$D$21,"") | E17: =IFERROR(1-'Inputs'!$E$49/'Inputs'!$E$21,"") | F17: =IFERROR(1-'Inputs'!$F$49/'Inputs'!$F$21,"") | G17: =IFERROR(1-'Inputs'!$G$49/'Inputs'!$G$21,"") | H17: =IFERROR(1-'Inputs'!$H$49/'Inputs'!$H$21,"") | I17: =IFERROR(1-'Inputs'!$I$49/'Inputs'!$I$21,"") | J17: =IFERROR(1-'Inputs'!$J$49/'Inputs'!$J$21,"") | K17: =IFERROR(1-'Inputs'!$K$49/'Inputs'!$K$21,"") | L17: =IFERROR(1-'Inputs'!$L$49/'Inputs'!$L$21,"") | M17: =IFERROR(1-'Inputs'!$M$49/'Inputs'!$M$21,"") | N17: =IFERROR(1-'Inputs'!$N$49/'Inputs'!$N$21,"") | O17: =IFERROR(1-'Inputs'!$O$49/'Inputs'!$O$21,"") | P17: =IFERROR(1-'Inputs'!$P$49/'Inputs'!$P$21,"") | Q17: =IF(AND(ISNUMBER($K$17),ISNUMBER($J$17)),CHOOSE(2+($K$17>$J$17)-($K$17<$J$17),"▼","►","▲"),"")
A18: FCF conversion (FCF / net income) | B18: =IFERROR('Inputs'!$B$48/'Inputs'!$B$21,"") | C18: =IFERROR('Inputs'!$C$48/'Inputs'!$C$21,"") | D18: =IFERROR('Inputs'!$D$48/'Inputs'!$D$21,"") | E18: =IFERROR('Inputs'!$E$48/'Inputs'!$E$21,"") | F18: =IFERROR('Inputs'!$F$48/'Inputs'!$F$21,"") | G18: =IFERROR('Inputs'!$G$48/'Inputs'!$G$21,"") | H18: =IFERROR('Inputs'!$H$48/'Inputs'!$H$21,"") | I18: =IFERROR('Inputs'!$I$48/'Inputs'!$I$21,"") | J18: =IFERROR('Inputs'!$J$48/'Inputs'!$J$21,"") | K18: =IFERROR('Inputs'!$K$48/'Inputs'!$K$21,"") | L18: =IFERROR('Inputs'!$L$48/'Inputs'!$L$21,"") | M18: =IFERROR('Inputs'!$M$48/'Inputs'!$M$21,"") | N18: =IFERROR('Inputs'!$N$48/'Inputs'!$N$21,"") | O18: =IFERROR('Inputs'!$O$48/'Inputs'!$O$21,"") | P18: =IFERROR('Inputs'!$P$48/'Inputs'!$P$21,"") | Q18: =IF(AND(ISNUMBER($K$18),ISNUMBER($J$18)),CHOOSE(2+($K$18>$J$18)-($K$18<$J$18),"▼","►","▲"),"") | R18: =IF(AND(ISNUMBER($K$18),ISNUMBER(AVERAGE($B$18:$K$18))),CHOOSE(2+($K$18>AVERAGE($B$18:$K$18)*(1+0.05))-($K$18<AVERAGE($B$18:$K$18)*(1-0.05)),"Weak","Stable","Strong"),"")
A20: Capital Allocation Score (latest year, 0–5)
A21: Converts ≥80% of profit to FCF | B21: =('Capital Allocation'!$K$18>=0.8)*1
A22: Reducing share count | B22: =('Inputs'!$K$53<'Inputs'!$J$53)*1
A23: ROIC above WACC | B23: =('Profitability'!$K$20>'Inputs'!$B$82)*1
A24: Dividend per share rising | B24: =('Inputs'!$K$56>'Inputs'!$J$56)*1
A25: Disciplined payout (20–100%) | B25: =AND('Capital Allocation'!$K$14>=0.2,'Capital Allocation'!$K$14<=1)*1
A26: Capital Allocation Score (/5) | B26: =SUM(B21:B25) | C26: =IF(ISNUMBER($B$26),CHOOSE(1+($B$26>=2)+($B$26>=4),"Weak","Adequate","Strong"),"")
A28: Automated Observations
A29: =IFERROR("» Capital allocation scores "&TEXT('Capital Allocation'!$B$26,"0")&"/5 — "&'Capital Allocation'!$C$26&". Total payout is "&TEXT('Capital Allocation'!$K$14,"0%")&" of net income.","(insufficient data — populate inputs)")
A30: =IFERROR("» Share count "&IF('Inputs'!$K$53<'Inputs'!$B$53,"fell from ","rose from ")&TEXT('Inputs'!$B$53,"#,##0")&" to "&TEXT('Inputs'!$K$53,"#,##0")&"m over the period.","(insufficient data — populate inputs)")

Sheet Quality
A1: QUALITY ANALYSIS
A2: Piotroski F · Altman Z · Beneish M · economic profit
A3: Institutional Financial Ratio Analysis · v1.0
A5: Dashboard | B5: Inputs | C5: Common Size | D5: Profitability | E5: Liquidity | F5: Solvency | G5: Efficiency | H5: Growth
A6: Valuation | B6: Capital Allocation | C6: Quality | D6: Benchmarking | E6: Guide | F6: Quality Control
A7: All figures in USD millions unless stated; (F) = forecast year.
A8: Quality metric | B8: FY2015 | C8: FY2016 | D8: FY2017 | E8: FY2018 | F8: FY2019 | G8: FY2020 | H8: FY2021 | I8: FY2022 | J8: FY2023 | K8: FY2024 | L8: FY2025 (F) | M8: FY2026 (F) | N8: FY2027 (F) | O8: FY2028 (F) | P8: FY2029 (F) | Q8: Trend | R8: Assessment
A9: Altman Z-Score (bankruptcy/distress risk)
A10: X1 = working capital / assets | B10: =IFERROR('Inputs'!$B$68/'Inputs'!$B$32,"") | C10: =IFERROR('Inputs'!$C$68/'Inputs'!$C$32,"") | D10: =IFERROR('Inputs'!$D$68/'Inputs'!$D$32,"") | E10: =IFERROR('Inputs'!$E$68/'Inputs'!$E$32,"") | F10: =IFERROR('Inputs'!$F$68/'Inputs'!$F$32,"") | G10: =IFERROR('Inputs'!$G$68/'Inputs'!$G$32,"") | H10: =IFERROR('Inputs'!$H$68/'Inputs'!$H$32,"") | I10: =IFERROR('Inputs'!$I$68/'Inputs'!$I$32,"") | J10: =IFERROR('Inputs'!$J$68/'Inputs'!$J$32,"") | K10: =IFERROR('Inputs'!$K$68/'Inputs'!$K$32,"") | L10: =IFERROR('Inputs'!$L$68/'Inputs'!$L$32,"") | M10: =IFERROR('Inputs'!$M$68/'Inputs'!$M$32,"") | N10: =IFERROR('Inputs'!$N$68/'Inputs'!$N$32,"") | O10: =IFERROR('Inputs'!$O$68/'Inputs'!$O$32,"") | P10: =IFERROR('Inputs'!$P$68/'Inputs'!$P$32,"")
A11: X2 = retained earnings / assets | B11: =IFERROR('Inputs'!$B$43/'Inputs'!$B$32,"") | C11: =IFERROR('Inputs'!$C$43/'Inputs'!$C$32,"") | D11: =IFERROR('Inputs'!$D$43/'Inputs'!$D$32,"") | E11: =IFERROR('Inputs'!$E$43/'Inputs'!$E$32,"") | F11: =IFERROR('Inputs'!$F$43/'Inputs'!$F$32,"") | G11: =IFERROR('Inputs'!$G$43/'Inputs'!$G$32,"") | H11: =IFERROR('Inputs'!$H$43/'Inputs'!$H$32,"") | I11: =IFERROR('Inputs'!$I$43/'Inputs'!$I$32,"") | J11: =IFERROR('Inputs'!$J$43/'Inputs'!$J$32,"") | K11: =IFERROR('Inputs'!$K$43/'Inputs'!$K$32,"") | L11: =IFERROR('Inputs'!$L$43/'Inputs'!$L$32,"") | M11: =IFERROR('Inputs'!$M$43/'Inputs'!$M$32,"") | N11: =IFERROR('Inputs'!$N$43/'Inputs'!$N$32,"") | O11: =IFERROR('Inputs'!$O$43/'Inputs'!$O$32,"") | P11: =IFERROR('Inputs'!$P$43/'Inputs'!$P$32,"")
A12: X3 = EBIT / assets | B12: =IFERROR('Inputs'!$B$16/'Inputs'!$B$32,"") | C12: =IFERROR('Inputs'!$C$16/'Inputs'!$C$32,"") | D12: =IFERROR('Inputs'!$D$16/'Inputs'!$D$32,"") | E12: =IFERROR('Inputs'!$E$16/'Inputs'!$E$32,"") | F12: =IFERROR('Inputs'!$F$16/'Inputs'!$F$32,"") | G12: =IFERROR('Inputs'!$G$16/'Inputs'!$G$32,"") | H12: =IFERROR('Inputs'!$H$16/'Inputs'!$H$32,"") | I12: =IFERROR('Inputs'!$I$16/'Inputs'!$I$32,"") | J12: =IFERROR('Inputs'!$J$16/'Inputs'!$J$32,"") | K12: =IFERROR('Inputs'!$K$16/'Inputs'!$K$32,"") | L12: =IFERROR('Inputs'!$L$16/'Inputs'!$L$32,"") | M12: =IFERROR('Inputs'!$M$16/'Inputs'!$M$32,"") | N12: =IFERROR('Inputs'!$N$16/'Inputs'!$N$32,"") | O12: =IFERROR('Inputs'!$O$16/'Inputs'!$O$32,"") | P12: =IFERROR('Inputs'!$P$16/'Inputs'!$P$32,"")
A13: X4 = market cap / total liabilities | B13: =IFERROR('Inputs'!$B$54/'Inputs'!$B$41,"") | C13: =IFERROR('Inputs'!$C$54/'Inputs'!$C$41,"") | D13: =IFERROR('Inputs'!$D$54/'Inputs'!$D$41,"") | E13: =IFERROR('Inputs'!$E$54/'Inputs'!$E$41,"") | F13: =IFERROR('Inputs'!$F$54/'Inputs'!$F$41,"") | G13: =IFERROR('Inputs'!$G$54/'Inputs'!$G$41,"") | H13: =IFERROR('Inputs'!$H$54/'Inputs'!$H$41,"") | I13: =IFERROR('Inputs'!$I$54/'Inputs'!$I$41,"") | J13: =IFERROR('Inputs'!$J$54/'Inputs'!$J$41,"") | K13: =IFERROR('Inputs'!$K$54/'Inputs'!$K$41,"") | L13: =IFERROR('Inputs'!$L$54/'Inputs'!$L$41,"") | M13: =IFERROR('Inputs'!$M$54/'Inputs'!$M$41,"") | N13: =IFERROR('Inputs'!$N$54/'Inputs'!$N$41,"") | O13: =IFERROR('Inputs'!$O$54/'Inputs'!$O$41,"") | P13: =IFERROR('Inputs'!$P$54/'Inputs'!$P$41,"")
A14: X5 = revenue / assets | B14: =IFERROR('Inputs'!$B$10/'Inputs'!$B$32,"") | C14: =IFERROR('Inputs'!$C$10/'Inputs'!$C$32,"") | D14: =IFERROR('Inputs'!$D$10/'Inputs'!$D$32,"") | E14: =IFERROR('Inputs'!$E$10/'Inputs'!$E$32,"") | F14: =IFERROR('Inputs'!$F$10/'Inputs'!$F$32,"") | G14: =IFERROR('Inputs'!$G$10/'Inputs'!$G$32,"") | H14: =IFERROR('Inputs'!$H$10/'Inputs'!$H$32,"") | I14: =IFERROR('Inputs'!$I$10/'Inputs'!$I$32,"") | J14: =IFERROR('Inputs'!$J$10/'Inputs'!$J$32,"") | K14: =IFERROR('Inputs'!$K$10/'Inputs'!$K$32,"") | L14: =IFERROR('Inputs'!$L$10/'Inputs'!$L$32,"") | M14: =IFERROR('Inputs'!$M$10/'Inputs'!$M$32,"") | N14: =IFERROR('Inputs'!$N$10/'Inputs'!$N$32,"") | O14: =IFERROR('Inputs'!$O$10/'Inputs'!$O$32,"") | P14: =IFERROR('Inputs'!$P$10/'Inputs'!$P$32,"")
A15: Altman Z-Score | B15: =IFERROR(1.2*'Quality'!$B$10+1.4*'Quality'!$B$11+3.3*'Quality'!$B$12+0.6*'Quality'!$B$13+1.0*'Quality'!$B$14,"") | C15: =IFERROR(1.2*'Quality'!$C$10+1.4*'Quality'!$C$11+3.3*'Quality'!$C$12+0.6*'Quality'!$C$13+1.0*'Quality'!$C$14,"") | D15: =IFERROR(1.2*'Quality'!$D$10+1.4*'Quality'!$D$11+3.3*'Quality'!$D$12+0.6*'Quality'!$D$13+1.0*'Quality'!$D$14,"") | E15: =IFERROR(1.2*'Quality'!$E$10+1.4*'Quality'!$E$11+3.3*'Quality'!$E$12+0.6*'Quality'!$E$13+1.0*'Quality'!$E$14,"") | F15: =IFERROR(1.2*'Quality'!$F$10+1.4*'Quality'!$F$11+3.3*'Quality'!$F$12+0.6*'Quality'!$F$13+1.0*'Quality'!$F$14,"") | G15: =IFERROR(1.2*'Quality'!$G$10+1.4*'Quality'!$G$11+3.3*'Quality'!$G$12+0.6*'Quality'!$G$13+1.0*'Quality'!$G$14,"") | H15: =IFERROR(1.2*'Quality'!$H$10+1.4*'Quality'!$H$11+3.3*'Quality'!$H$12+0.6*'Quality'!$H$13+1.0*'Quality'!$H$14,"") | I15: =IFERROR(1.2*'Quality'!$I$10+1.4*'Quality'!$I$11+3.3*'Quality'!$I$12+0.6*'Quality'!$I$13+1.0*'Quality'!$I$14,"") | J15: =IFERROR(1.2*'Quality'!$J$10+1.4*'Quality'!$J$11+3.3*'Quality'!$J$12+0.6*'Quality'!$J$13+1.0*'Quality'!$J$14,"") | K15: =IFERROR(1.2*'Quality'!$K$10+1.4*'Quality'!$K$11+3.3*'Quality'!$K$12+0.6*'Quality'!$K$13+1.0*'Quality'!$K$14,"") | L15: =IFERROR(1.2*'Quality'!$L$10+1.4*'Quality'!$L$11+3.3*'Quality'!$L$12+0.6*'Quality'!$L$13+1.0*'Quality'!$L$14,"") | M15: =IFERROR(1.2*'Quality'!$M$10+1.4*'Quality'!$M$11+3.3*'Quality'!$M$12+0.6*'Quality'!$M$13+1.0*'Quality'!$M$14,"") | N15: =IFERROR(1.2*'Quality'!$N$10+1.4*'Quality'!$N$11+3.3*'Quality'!$N$12+0.6*'Quality'!$N$13+1.0*'Quality'!$N$14,"") | O15: =IFERROR(1.2*'Quality'!$O$10+1.4*'Quality'!$O$11+3.3*'Quality'!$O$12+0.6*'Quality'!$O$13+1.0*'Quality'!$O$14,"") | P15: =IFERROR(1.2*'Quality'!$P$10+1.4*'Quality'!$P$11+3.3*'Quality'!$P$12+0.6*'Quality'!$P$13+1.0*'Quality'!$P$14,"") | Q15: =IF(AND(ISNUMBER($K$15),ISNUMBER($J$15)),CHOOSE(2+($K$15>$J$15)-($K$15<$J$15),"▼","►","▲"),"") | R15: =IF(ISNUMBER($K$15),CHOOSE(1+($K$15>=1.81)+($K$15>=2.99),"Distress","Grey","Safe"),"")
A16: Z > 2.99 = safe zone · 1.81–2.99 = grey zone · < 1.81 = distress zone.
A18: Piotroski F-Score (fundamental strength, 0–9)
A19: ROA = net income / assets | B19: =IFERROR('Inputs'!$B$21/'Inputs'!$B$32,"") | C19: =IFERROR('Inputs'!$C$21/'Inputs'!$C$32,"") | D19: =IFERROR('Inputs'!$D$21/'Inputs'!$D$32,"") | E19: =IFERROR('Inputs'!$E$21/'Inputs'!$E$32,"") | F19: =IFERROR('Inputs'!$F$21/'Inputs'!$F$32,"") | G19: =IFERROR('Inputs'!$G$21/'Inputs'!$G$32,"") | H19: =IFERROR('Inputs'!$H$21/'Inputs'!$H$32,"") | I19: =IFERROR('Inputs'!$I$21/'Inputs'!$I$32,"") | J19: =IFERROR('Inputs'!$J$21/'Inputs'!$J$32,"") | K19: =IFERROR('Inputs'!$K$21/'Inputs'!$K$32,"") | L19: =IFERROR('Inputs'!$L$21/'Inputs'!$L$32,"") | M19: =IFERROR('Inputs'!$M$21/'Inputs'!$M$32,"") | N19: =IFERROR('Inputs'!$N$21/'Inputs'!$N$32,"") | O19: =IFERROR('Inputs'!$O$21/'Inputs'!$O$32,"") | P19: =IFERROR('Inputs'!$P$21/'Inputs'!$P$32,"")
A20: Current ratio | B20: =IFERROR('Inputs'!$B$27/'Inputs'!$B$37,"") | C20: =IFERROR('Inputs'!$C$27/'Inputs'!$C$37,"") | D20: =IFERROR('Inputs'!$D$27/'Inputs'!$D$37,"") | E20: =IFERROR('Inputs'!$E$27/'Inputs'!$E$37,"") | F20: =IFERROR('Inputs'!$F$27/'Inputs'!$F$37,"") | G20: =IFERROR('Inputs'!$G$27/'Inputs'!$G$37,"") | H20: =IFERROR('Inputs'!$H$27/'Inputs'!$H$37,"") | I20: =IFERROR('Inputs'!$I$27/'Inputs'!$I$37,"") | J20: =IFERROR('Inputs'!$J$27/'Inputs'!$J$37,"") | K20: =IFERROR('Inputs'!$K$27/'Inputs'!$K$37,"") | L20: =IFERROR('Inputs'!$L$27/'Inputs'!$L$37,"") | M20: =IFERROR('Inputs'!$M$27/'Inputs'!$M$37,"") | N20: =IFERROR('Inputs'!$N$27/'Inputs'!$N$37,"") | O20: =IFERROR('Inputs'!$O$27/'Inputs'!$O$37,"") | P20: =IFERROR('Inputs'!$P$27/'Inputs'!$P$37,"")
A21: Gross margin | B21: =IFERROR('Inputs'!$B$12/'Inputs'!$B$10,"") | C21: =IFERROR('Inputs'!$C$12/'Inputs'!$C$10,"") | D21: =IFERROR('Inputs'!$D$12/'Inputs'!$D$10,"") | E21: =IFERROR('Inputs'!$E$12/'Inputs'!$E$10,"") | F21: =IFERROR('Inputs'!$F$12/'Inputs'!$F$10,"") | G21: =IFERROR('Inputs'!$G$12/'Inputs'!$G$10,"") | H21: =IFERROR('Inputs'!$H$12/'Inputs'!$H$10,"") | I21: =IFERROR('Inputs'!$I$12/'Inputs'!$I$10,"") | J21: =IFERROR('Inputs'!$J$12/'Inputs'!$J$10,"") | K21: =IFERROR('Inputs'!$K$12/'Inputs'!$K$10,"") | L21: =IFERROR('Inputs'!$L$12/'Inputs'!$L$10,"") | M21: =IFERROR('Inputs'!$M$12/'Inputs'!$M$10,"") | N21: =IFERROR('Inputs'!$N$12/'Inputs'!$N$10,"") | O21: =IFERROR('Inputs'!$O$12/'Inputs'!$O$10,"") | P21: =IFERROR('Inputs'!$P$12/'Inputs'!$P$10,"")
A22: Asset turnover | B22: =IFERROR('Inputs'!$B$10/'Inputs'!$B$32,"") | C22: =IFERROR('Inputs'!$C$10/'Inputs'!$C$32,"") | D22: =IFERROR('Inputs'!$D$10/'Inputs'!$D$32,"") | E22: =IFERROR('Inputs'!$E$10/'Inputs'!$E$32,"") | F22: =IFERROR('Inputs'!$F$10/'Inputs'!$F$32,"") | G22: =IFERROR('Inputs'!$G$10/'Inputs'!$G$32,"") | H22: =IFERROR('Inputs'!$H$10/'Inputs'!$H$32,"") | I22: =IFERROR('Inputs'!$I$10/'Inputs'!$I$32,"") | J22: =IFERROR('Inputs'!$J$10/'Inputs'!$J$32,"") | K22: =IFERROR('Inputs'!$K$10/'Inputs'!$K$32,"") | L22: =IFERROR('Inputs'!$L$10/'Inputs'!$L$32,"") | M22: =IFERROR('Inputs'!$M$10/'Inputs'!$M$32,"") | N22: =IFERROR('Inputs'!$N$10/'Inputs'!$N$32,"") | O22: =IFERROR('Inputs'!$O$10/'Inputs'!$O$32,"") | P22: =IFERROR('Inputs'!$P$10/'Inputs'!$P$32,"")
A23: LT debt / assets | B23: =IFERROR('Inputs'!$B$38/'Inputs'!$B$32,"") | C23: =IFERROR('Inputs'!$C$38/'Inputs'!$C$32,"") | D23: =IFERROR('Inputs'!$D$38/'Inputs'!$D$32,"") | E23: =IFERROR('Inputs'!$E$38/'Inputs'!$E$32,"") | F23: =IFERROR('Inputs'!$F$38/'Inputs'!$F$32,"") | G23: =IFERROR('Inputs'!$G$38/'Inputs'!$G$32,"") | H23: =IFERROR('Inputs'!$H$38/'Inputs'!$H$32,"") | I23: =IFERROR('Inputs'!$I$38/'Inputs'!$I$32,"") | J23: =IFERROR('Inputs'!$J$38/'Inputs'!$J$32,"") | K23: =IFERROR('Inputs'!$K$38/'Inputs'!$K$32,"") | L23: =IFERROR('Inputs'!$L$38/'Inputs'!$L$32,"") | M23: =IFERROR('Inputs'!$M$38/'Inputs'!$M$32,"") | N23: =IFERROR('Inputs'!$N$38/'Inputs'!$N$32,"") | O23: =IFERROR('Inputs'!$O$38/'Inputs'!$O$32,"") | P23: =IFERROR('Inputs'!$P$38/'Inputs'!$P$32,"")
A24: 1. ROA > 0 | C24: =('Inputs'!$C$21>0)*1 | D24: =('Inputs'!$D$21>0)*1 | E24: =('Inputs'!$E$21>0)*1 | F24: =('Inputs'!$F$21>0)*1 | G24: =('Inputs'!$G$21>0)*1 | H24: =('Inputs'!$H$21>0)*1 | I24: =('Inputs'!$I$21>0)*1 | J24: =('Inputs'!$J$21>0)*1 | K24: =('Inputs'!$K$21>0)*1 | L24: =('Inputs'!$L$21>0)*1 | M24: =('Inputs'!$M$21>0)*1 | N24: =('Inputs'!$N$21>0)*1 | O24: =('Inputs'!$O$21>0)*1 | P24: =('Inputs'!$P$21>0)*1
A25: 2. Operating cash flow > 0 | C25: =('Inputs'!$C$46>0)*1 | D25: =('Inputs'!$D$46>0)*1 | E25: =('Inputs'!$E$46>0)*1 | F25: =('Inputs'!$F$46>0)*1 | G25: =('Inputs'!$G$46>0)*1 | H25: =('Inputs'!$H$46>0)*1 | I25: =('Inputs'!$I$46>0)*1 | J25: =('Inputs'!$J$46>0)*1 | K25: =('Inputs'!$K$46>0)*1 | L25: =('Inputs'!$L$46>0)*1 | M25: =('Inputs'!$M$46>0)*1 | N25: =('Inputs'!$N$46>0)*1 | O25: =('Inputs'!$O$46>0)*1 | P25: =('Inputs'!$P$46>0)*1
A26: 3. ROA improved | C26: =('Quality'!$C$19>'Quality'!$B$19)*1 | D26: =('Quality'!$D$19>'Quality'!$C$19)*1 | E26: =('Quality'!$E$19>'Quality'!$D$19)*1 | F26: =('Quality'!$F$19>'Quality'!$E$19)*1 | G26: =('Quality'!$G$19>'Quality'!$F$19)*1 | H26: =('Quality'!$H$19>'Quality'!$G$19)*1 | I26: =('Quality'!$I$19>'Quality'!$H$19)*1 | J26: =('Quality'!$J$19>'Quality'!$I$19)*1 | K26: =('Quality'!$K$19>'Quality'!$J$19)*1 | L26: =('Quality'!$L$19>'Quality'!$K$19)*1 | M26: =('Quality'!$M$19>'Quality'!$L$19)*1 | N26: =('Quality'!$N$19>'Quality'!$M$19)*1 | O26: =('Quality'!$O$19>'Quality'!$N$19)*1 | P26: =('Quality'!$P$19>'Quality'!$O$19)*1
A27: 4. CFO > net income (accruals) | C27: =('Inputs'!$C$46>'Inputs'!$C$21)*1 | D27: =('Inputs'!$D$46>'Inputs'!$D$21)*1 | E27: =('Inputs'!$E$46>'Inputs'!$E$21)*1 | F27: =('Inputs'!$F$46>'Inputs'!$F$21)*1 | G27: =('Inputs'!$G$46>'Inputs'!$G$21)*1 | H27: =('Inputs'!$H$46>'Inputs'!$H$21)*1 | I27: =('Inputs'!$I$46>'Inputs'!$I$21)*1 | J27: =('Inputs'!$J$46>'Inputs'!$J$21)*1 | K27: =('Inputs'!$K$46>'Inputs'!$K$21)*1 | L27: =('Inputs'!$L$46>'Inputs'!$L$21)*1 | M27: =('Inputs'!$M$46>'Inputs'!$M$21)*1 | N27: =('Inputs'!$N$46>'Inputs'!$N$21)*1 | O27: =('Inputs'!$O$46>'Inputs'!$O$21)*1 | P27: =('Inputs'!$P$46>'Inputs'!$P$21)*1
A28: 5. Lower leverage | C28: =('Quality'!$C$23<'Quality'!$B$23)*1 | D28: =('Quality'!$D$23<'Quality'!$C$23)*1 | E28: =('Quality'!$E$23<'Quality'!$D$23)*1 | F28: =('Quality'!$F$23<'Quality'!$E$23)*1 | G28: =('Quality'!$G$23<'Quality'!$F$23)*1 | H28: =('Quality'!$H$23<'Quality'!$G$23)*1 | I28: =('Quality'!$I$23<'Quality'!$H$23)*1 | J28: =('Quality'!$J$23<'Quality'!$I$23)*1 | K28: =('Quality'!$K$23<'Quality'!$J$23)*1 | L28: =('Quality'!$L$23<'Quality'!$K$23)*1 | M28: =('Quality'!$M$23<'Quality'!$L$23)*1 | N28: =('Quality'!$N$23<'Quality'!$M$23)*1 | O28: =('Quality'!$O$23<'Quality'!$N$23)*1 | P28: =('Quality'!$P$23<'Quality'!$O$23)*1
A29: 6. Higher current ratio | C29: =('Quality'!$C$20>'Quality'!$B$20)*1 | D29: =('Quality'!$D$20>'Quality'!$C$20)*1 | E29: =('Quality'!$E$20>'Quality'!$D$20)*1 | F29: =('Quality'!$F$20>'Quality'!$E$20)*1 | G29: =('Quality'!$G$20>'Quality'!$F$20)*1 | H29: =('Quality'!$H$20>'Quality'!$G$20)*1 | I29: =('Quality'!$I$20>'Quality'!$H$20)*1 | J29: =('Quality'!$J$20>'Quality'!$I$20)*1 | K29: =('Quality'!$K$20>'Quality'!$J$20)*1 | L29: =('Quality'!$L$20>'Quality'!$K$20)*1 | M29: =('Quality'!$M$20>'Quality'!$L$20)*1 | N29: =('Quality'!$N$20>'Quality'!$M$20)*1 | O29: =('Quality'!$O$20>'Quality'!$N$20)*1 | P29: =('Quality'!$P$20>'Quality'!$O$20)*1
A30: 7. No new shares | C30: =('Inputs'!$C$53<='Inputs'!$B$53)*1 | D30: =('Inputs'!$D$53<='Inputs'!$C$53)*1 | E30: =('Inputs'!$E$53<='Inputs'!$D$53)*1 | F30: =('Inputs'!$F$53<='Inputs'!$E$53)*1 | G30: =('Inputs'!$G$53<='Inputs'!$F$53)*1 | H30: =('Inputs'!$H$53<='Inputs'!$G$53)*1 | I30: =('Inputs'!$I$53<='Inputs'!$H$53)*1 | J30: =('Inputs'!$J$53<='Inputs'!$I$53)*1 | K30: =('Inputs'!$K$53<='Inputs'!$J$53)*1 | L30: =('Inputs'!$L$53<='Inputs'!$K$53)*1 | M30: =('Inputs'!$M$53<='Inputs'!$L$53)*1 | N30: =('Inputs'!$N$53<='Inputs'!$M$53)*1 | O30: =('Inputs'!$O$53<='Inputs'!$N$53)*1 | P30: =('Inputs'!$P$53<='Inputs'!$O$53)*1
A31: 8. Higher gross margin | C31: =('Quality'!$C$21>'Quality'!$B$21)*1 | D31: =('Quality'!$D$21>'Quality'!$C$21)*1 | E31: =('Quality'!$E$21>'Quality'!$D$21)*1 | F31: =('Quality'!$F$21>'Quality'!$E$21)*1 | G31: =('Quality'!$G$21>'Quality'!$F$21)*1 | H31: =('Quality'!$H$21>'Quality'!$G$21)*1 | I31: =('Quality'!$I$21>'Quality'!$H$21)*1 | J31: =('Quality'!$J$21>'Quality'!$I$21)*1 | K31: =('Quality'!$K$21>'Quality'!$J$21)*1 | L31: =('Quality'!$L$21>'Quality'!$K$21)*1 | M31: =('Quality'!$M$21>'Quality'!$L$21)*1 | N31: =('Quality'!$N$21>'Quality'!$M$21)*1 | O31: =('Quality'!$O$21>'Quality'!$N$21)*1 | P31: =('Quality'!$P$21>'Quality'!$O$21)*1
A32: 9. Higher asset turnover | C32: =('Quality'!$C$22>'Quality'!$B$22)*1 | D32: =('Quality'!$D$22>'Quality'!$C$22)*1 | E32: =('Quality'!$E$22>'Quality'!$D$22)*1 | F32: =('Quality'!$F$22>'Quality'!$E$22)*1 | G32: =('Quality'!$G$22>'Quality'!$F$22)*1 | H32: =('Quality'!$H$22>'Quality'!$G$22)*1 | I32: =('Quality'!$I$22>'Quality'!$H$22)*1 | J32: =('Quality'!$J$22>'Quality'!$I$22)*1 | K32: =('Quality'!$K$22>'Quality'!$J$22)*1 | L32: =('Quality'!$L$22>'Quality'!$K$22)*1 | M32: =('Quality'!$M$22>'Quality'!$L$22)*1 | N32: =('Quality'!$N$22>'Quality'!$M$22)*1 | O32: =('Quality'!$O$22>'Quality'!$N$22)*1 | P32: =('Quality'!$P$22>'Quality'!$O$22)*1
A33: Piotroski F-Score (/9) | C33: =SUM('Quality'!$C$24,'Quality'!$C$25,'Quality'!$C$26,'Quality'!$C$27,'Quality'!$C$28,'Quality'!$C$29,'Quality'!$C$30,'Quality'!$C$31,'Quality'!$C$32) | D33: =SUM('Quality'!$D$24,'Quality'!$D$25,'Quality'!$D$26,'Quality'!$D$27,'Quality'!$D$28,'Quality'!$D$29,'Quality'!$D$30,'Quality'!$D$31,'Quality'!$D$32) | E33: =SUM('Quality'!$E$24,'Quality'!$E$25,'Quality'!$E$26,'Quality'!$E$27,'Quality'!$E$28,'Quality'!$E$29,'Quality'!$E$30,'Quality'!$E$31,'Quality'!$E$32) | F33: =SUM('Quality'!$F$24,'Quality'!$F$25,'Quality'!$F$26,'Quality'!$F$27,'Quality'!$F$28,'Quality'!$F$29,'Quality'!$F$30,'Quality'!$F$31,'Quality'!$F$32) | G33: =SUM('Quality'!$G$24,'Quality'!$G$25,'Quality'!$G$26,'Quality'!$G$27,'Quality'!$G$28,'Quality'!$G$29,'Quality'!$G$30,'Quality'!$G$31,'Quality'!$G$32) | H33: =SUM('Quality'!$H$24,'Quality'!$H$25,'Quality'!$H$26,'Quality'!$H$27,'Quality'!$H$28,'Quality'!$H$29,'Quality'!$H$30,'Quality'!$H$31,'Quality'!$H$32) | I33: =SUM('Quality'!$I$24,'Quality'!$I$25,'Quality'!$I$26,'Quality'!$I$27,'Quality'!$I$28,'Quality'!$I$29,'Quality'!$I$30,'Quality'!$I$31,'Quality'!$I$32) | J33: =SUM('Quality'!$J$24,'Quality'!$J$25,'Quality'!$J$26,'Quality'!$J$27,'Quality'!$J$28,'Quality'!$J$29,'Quality'!$J$30,'Quality'!$J$31,'Quality'!$J$32) | K33: =SUM('Quality'!$K$24,'Quality'!$K$25,'Quality'!$K$26,'Quality'!$K$27,'Quality'!$K$28,'Quality'!$K$29,'Quality'!$K$30,'Quality'!$K$31,'Quality'!$K$32) | L33: =SUM('Quality'!$L$24,'Quality'!$L$25,'Quality'!$L$26,'Quality'!$L$27,'Quality'!$L$28,'Quality'!$L$29,'Quality'!$L$30,'Quality'!$L$31,'Quality'!$L$32) | M33: =SUM('Quality'!$M$24,'Quality'!$M$25,'Quality'!$M$26,'Quality'!$M$27,'Quality'!$M$28,'Quality'!$M$29,'Quality'!$M$30,'Quality'!$M$31,'Quality'!$M$32) | N33: =SUM('Quality'!$N$24,'Quality'!$N$25,'Quality'!$N$26,'Quality'!$N$27,'Quality'!$N$28,'Quality'!$N$29,'Quality'!$N$30,'Quality'!$N$31,'Quality'!$N$32) | O33: =SUM('Quality'!$O$24,'Quality'!$O$25,'Quality'!$O$26,'Quality'!$O$27,'Quality'!$O$28,'Quality'!$O$29,'Quality'!$O$30,'Quality'!$O$31,'Quality'!$O$32) | P33: =SUM('Quality'!$P$24,'Quality'!$P$25,'Quality'!$P$26,'Quality'!$P$27,'Quality'!$P$28,'Quality'!$P$29,'Quality'!$P$30,'Quality'!$P$31,'Quality'!$P$32) | Q33: =IF(AND(ISNUMBER($K$33),ISNUMBER($J$33)),CHOOSE(2+($K$33>$J$33)-($K$33<$J$33),"▼","►","▲"),"") | R33: =IF(ISNUMBER($K$33),CHOOSE(1+($K$33>=3)+($K$33>=7),"Weak","Average","Strong"),"")
A35: Beneish M-Score (earnings-manipulation risk)
A36: DSRI (receivables/sales index) | C36: =IFERROR(('Inputs'!$C$24/'Inputs'!$C$10)/('Inputs'!$B$24/'Inputs'!$B$10),"") | D36: =IFERROR(('Inputs'!$D$24/'Inputs'!$D$10)/('Inputs'!$C$24/'Inputs'!$C$10),"") | E36: =IFERROR(('Inputs'!$E$24/'Inputs'!$E$10)/('Inputs'!$D$24/'Inputs'!$D$10),"") | F36: =IFERROR(('Inputs'!$F$24/'Inputs'!$F$10)/('Inputs'!$E$24/'Inputs'!$E$10),"") | G36: =IFERROR(('Inputs'!$G$24/'Inputs'!$G$10)/('Inputs'!$F$24/'Inputs'!$F$10),"") | H36: =IFERROR(('Inputs'!$H$24/'Inputs'!$H$10)/('Inputs'!$G$24/'Inputs'!$G$10),"") | I36: =IFERROR(('Inputs'!$I$24/'Inputs'!$I$10)/('Inputs'!$H$24/'Inputs'!$H$10),"") | J36: =IFERROR(('Inputs'!$J$24/'Inputs'!$J$10)/('Inputs'!$I$24/'Inputs'!$I$10),"") | K36: =IFERROR(('Inputs'!$K$24/'Inputs'!$K$10)/('Inputs'!$J$24/'Inputs'!$J$10),"") | L36: =IFERROR(('Inputs'!$L$24/'Inputs'!$L$10)/('Inputs'!$K$24/'Inputs'!$K$10),"") | M36: =IFERROR(('Inputs'!$M$24/'Inputs'!$M$10)/('Inputs'!$L$24/'Inputs'!$L$10),"") | N36: =IFERROR(('Inputs'!$N$24/'Inputs'!$N$10)/('Inputs'!$M$24/'Inputs'!$M$10),"") | O36: =IFERROR(('Inputs'!$O$24/'Inputs'!$O$10)/('Inputs'!$N$24/'Inputs'!$N$10),"") | P36: =IFERROR(('Inputs'!$P$24/'Inputs'!$P$10)/('Inputs'!$O$24/'Inputs'!$O$10),"")
A37: GMI (gross-margin index) | C37: =IFERROR(('Inputs'!$B$12/'Inputs'!$B$10)/('Inputs'!$C$12/'Inputs'!$C$10),"") | D37: =IFERROR(('Inputs'!$C$12/'Inputs'!$C$10)/('Inputs'!$D$12/'Inputs'!$D$10),"") | E37: =IFERROR(('Inputs'!$D$12/'Inputs'!$D$10)/('Inputs'!$E$12/'Inputs'!$E$10),"") | F37: =IFERROR(('Inputs'!$E$12/'Inputs'!$E$10)/('Inputs'!$F$12/'Inputs'!$F$10),"") | G37: =IFERROR(('Inputs'!$F$12/'Inputs'!$F$10)/('Inputs'!$G$12/'Inputs'!$G$10),"") | H37: =IFERROR(('Inputs'!$G$12/'Inputs'!$G$10)/('Inputs'!$H$12/'Inputs'!$H$10),"") | I37: =IFERROR(('Inputs'!$H$12/'Inputs'!$H$10)/('Inputs'!$I$12/'Inputs'!$I$10),"") | J37: =IFERROR(('Inputs'!$I$12/'Inputs'!$I$10)/('Inputs'!$J$12/'Inputs'!$J$10),"") | K37: =IFERROR(('Inputs'!$J$12/'Inputs'!$J$10)/('Inputs'!$K$12/'Inputs'!$K$10),"") | L37: =IFERROR(('Inputs'!$K$12/'Inputs'!$K$10)/('Inputs'!$L$12/'Inputs'!$L$10),"") | M37: =IFERROR(('Inputs'!$L$12/'Inputs'!$L$10)/('Inputs'!$M$12/'Inputs'!$M$10),"") | N37: =IFERROR(('Inputs'!$M$12/'Inputs'!$M$10)/('Inputs'!$N$12/'Inputs'!$N$10),"") | O37: =IFERROR(('Inputs'!$N$12/'Inputs'!$N$10)/('Inputs'!$O$12/'Inputs'!$O$10),"") | P37: =IFERROR(('Inputs'!$O$12/'Inputs'!$O$10)/('Inputs'!$P$12/'Inputs'!$P$10),"")
A38: AQI (asset-quality index) | C38: =IFERROR((1-('Inputs'!$C$27+'Inputs'!$C$28)/'Inputs'!$C$32)/(1-('Inputs'!$B$27+'Inputs'!$B$28)/'Inputs'!$B$32),"") | D38: =IFERROR((1-('Inputs'!$D$27+'Inputs'!$D$28)/'Inputs'!$D$32)/(1-('Inputs'!$C$27+'Inputs'!$C$28)/'Inputs'!$C$32),"") | E38: =IFERROR((1-('Inputs'!$E$27+'Inputs'!$E$28)/'Inputs'!$E$32)/(1-('Inputs'!$D$27+'Inputs'!$D$28)/'Inputs'!$D$32),"") | F38: =IFERROR((1-('Inputs'!$F$27+'Inputs'!$F$28)/'Inputs'!$F$32)/(1-('Inputs'!$E$27+'Inputs'!$E$28)/'Inputs'!$E$32),"") | G38: =IFERROR((1-('Inputs'!$G$27+'Inputs'!$G$28)/'Inputs'!$G$32)/(1-('Inputs'!$F$27+'Inputs'!$F$28)/'Inputs'!$F$32),"") | H38: =IFERROR((1-('Inputs'!$H$27+'Inputs'!$H$28)/'Inputs'!$H$32)/(1-('Inputs'!$G$27+'Inputs'!$G$28)/'Inputs'!$G$32),"") | I38: =IFERROR((1-('Inputs'!$I$27+'Inputs'!$I$28)/'Inputs'!$I$32)/(1-('Inputs'!$H$27+'Inputs'!$H$28)/'Inputs'!$H$32),"") | J38: =IFERROR((1-('Inputs'!$J$27+'Inputs'!$J$28)/'Inputs'!$J$32)/(1-('Inputs'!$I$27+'Inputs'!$I$28)/'Inputs'!$I$32),"") | K38: =IFERROR((1-('Inputs'!$K$27+'Inputs'!$K$28)/'Inputs'!$K$32)/(1-('Inputs'!$J$27+'Inputs'!$J$28)/'Inputs'!$J$32),"") | L38: =IFERROR((1-('Inputs'!$L$27+'Inputs'!$L$28)/'Inputs'!$L$32)/(1-('Inputs'!$K$27+'Inputs'!$K$28)/'Inputs'!$K$32),"") | M38: =IFERROR((1-('Inputs'!$M$27+'Inputs'!$M$28)/'Inputs'!$M$32)/(1-('Inputs'!$L$27+'Inputs'!$L$28)/'Inputs'!$L$32),"") | N38: =IFERROR((1-('Inputs'!$N$27+'Inputs'!$N$28)/'Inputs'!$N$32)/(1-('Inputs'!$M$27+'Inputs'!$M$28)/'Inputs'!$M$32),"") | O38: =IFERROR((1-('Inputs'!$O$27+'Inputs'!$O$28)/'Inputs'!$O$32)/(1-('Inputs'!$N$27+'Inputs'!$N$28)/'Inputs'!$N$32),"") | P38: =IFERROR((1-('Inputs'!$P$27+'Inputs'!$P$28)/'Inputs'!$P$32)/(1-('Inputs'!$O$27+'Inputs'!$O$28)/'Inputs'!$O$32),"")
A39: SGI (sales-growth index) | C39: =IFERROR('Inputs'!$C$10/'Inputs'!$B$10,"") | D39: =IFERROR('Inputs'!$D$10/'Inputs'!$C$10,"") | E39: =IFERROR('Inputs'!$E$10/'Inputs'!$D$10,"") | F39: =IFERROR('Inputs'!$F$10/'Inputs'!$E$10,"") | G39: =IFERROR('Inputs'!$G$10/'Inputs'!$F$10,"") | H39: =IFERROR('Inputs'!$H$10/'Inputs'!$G$10,"") | I39: =IFERROR('Inputs'!$I$10/'Inputs'!$H$10,"") | J39: =IFERROR('Inputs'!$J$10/'Inputs'!$I$10,"") | K39: =IFERROR('Inputs'!$K$10/'Inputs'!$J$10,"") | L39: =IFERROR('Inputs'!$L$10/'Inputs'!$K$10,"") | M39: =IFERROR('Inputs'!$M$10/'Inputs'!$L$10,"") | N39: =IFERROR('Inputs'!$N$10/'Inputs'!$M$10,"") | O39: =IFERROR('Inputs'!$O$10/'Inputs'!$N$10,"") | P39: =IFERROR('Inputs'!$P$10/'Inputs'!$O$10,"")
A40: DEPI (depreciation index) | C40: =IFERROR(('Inputs'!$B$15/('Inputs'!$B$15+'Inputs'!$B$28))/('Inputs'!$C$15/('Inputs'!$C$15+'Inputs'!$C$28)),"") | D40: =IFERROR(('Inputs'!$C$15/('Inputs'!$C$15+'Inputs'!$C$28))/('Inputs'!$D$15/('Inputs'!$D$15+'Inputs'!$D$28)),"") | E40: =IFERROR(('Inputs'!$D$15/('Inputs'!$D$15+'Inputs'!$D$28))/('Inputs'!$E$15/('Inputs'!$E$15+'Inputs'!$E$28)),"") | F40: =IFERROR(('Inputs'!$E$15/('Inputs'!$E$15+'Inputs'!$E$28))/('Inputs'!$F$15/('Inputs'!$F$15+'Inputs'!$F$28)),"") | G40: =IFERROR(('Inputs'!$F$15/('Inputs'!$F$15+'Inputs'!$F$28))/('Inputs'!$G$15/('Inputs'!$G$15+'Inputs'!$G$28)),"") | H40: =IFERROR(('Inputs'!$G$15/('Inputs'!$G$15+'Inputs'!$G$28))/('Inputs'!$H$15/('Inputs'!$H$15+'Inputs'!$H$28)),"") | I40: =IFERROR(('Inputs'!$H$15/('Inputs'!$H$15+'Inputs'!$H$28))/('Inputs'!$I$15/('Inputs'!$I$15+'Inputs'!$I$28)),"") | J40: =IFERROR(('Inputs'!$I$15/('Inputs'!$I$15+'Inputs'!$I$28))/('Inputs'!$J$15/('Inputs'!$J$15+'Inputs'!$J$28)),"") | K40: =IFERROR(('Inputs'!$J$15/('Inputs'!$J$15+'Inputs'!$J$28))/('Inputs'!$K$15/('Inputs'!$K$15+'Inputs'!$K$28)),"") | L40: =IFERROR(('Inputs'!$K$15/('Inputs'!$K$15+'Inputs'!$K$28))/('Inputs'!$L$15/('Inputs'!$L$15+'Inputs'!$L$28)),"") | M40: =IFERROR(('Inputs'!$L$15/('Inputs'!$L$15+'Inputs'!$L$28))/('Inputs'!$M$15/('Inputs'!$M$15+'Inputs'!$M$28)),"") | N40: =IFERROR(('Inputs'!$M$15/('Inputs'!$M$15+'Inputs'!$M$28))/('Inputs'!$N$15/('Inputs'!$N$15+'Inputs'!$N$28)),"") | O40: =IFERROR(('Inputs'!$N$15/('Inputs'!$N$15+'Inputs'!$N$28))/('Inputs'!$O$15/('Inputs'!$O$15+'Inputs'!$O$28)),"") | P40: =IFERROR(('Inputs'!$O$15/('Inputs'!$O$15+'Inputs'!$O$28))/('Inputs'!$P$15/('Inputs'!$P$15+'Inputs'!$P$28)),"")
A41: SGAI (SG&A index) | C41: =IFERROR(('Inputs'!$C$13/'Inputs'!$C$10)/('Inputs'!$B$13/'Inputs'!$B$10),"") | D41: =IFERROR(('Inputs'!$D$13/'Inputs'!$D$10)/('Inputs'!$C$13/'Inputs'!$C$10),"") | E41: =IFERROR(('Inputs'!$E$13/'Inputs'!$E$10)/('Inputs'!$D$13/'Inputs'!$D$10),"") | F41: =IFERROR(('Inputs'!$F$13/'Inputs'!$F$10)/('Inputs'!$E$13/'Inputs'!$E$10),"") | G41: =IFERROR(('Inputs'!$G$13/'Inputs'!$G$10)/('Inputs'!$F$13/'Inputs'!$F$10),"") | H41: =IFERROR(('Inputs'!$H$13/'Inputs'!$H$10)/('Inputs'!$G$13/'Inputs'!$G$10),"") | I41: =IFERROR(('Inputs'!$I$13/'Inputs'!$I$10)/('Inputs'!$H$13/'Inputs'!$H$10),"") | J41: =IFERROR(('Inputs'!$J$13/'Inputs'!$J$10)/('Inputs'!$I$13/'Inputs'!$I$10),"") | K41: =IFERROR(('Inputs'!$K$13/'Inputs'!$K$10)/('Inputs'!$J$13/'Inputs'!$J$10),"") | L41: =IFERROR(('Inputs'!$L$13/'Inputs'!$L$10)/('Inputs'!$K$13/'Inputs'!$K$10),"") | M41: =IFERROR(('Inputs'!$M$13/'Inputs'!$M$10)/('Inputs'!$L$13/'Inputs'!$L$10),"") | N41: =IFERROR(('Inputs'!$N$13/'Inputs'!$N$10)/('Inputs'!$M$13/'Inputs'!$M$10),"") | O41: =IFERROR(('Inputs'!$O$13/'Inputs'!$O$10)/('Inputs'!$N$13/'Inputs'!$N$10),"") | P41: =IFERROR(('Inputs'!$P$13/'Inputs'!$P$10)/('Inputs'!$O$13/'Inputs'!$O$10),"")
A42: LVGI (leverage index) | C42: =IFERROR(('Inputs'!$C$41/'Inputs'!$C$32)/('Inputs'!$B$41/'Inputs'!$B$32),"") | D42: =IFERROR(('Inputs'!$D$41/'Inputs'!$D$32)/('Inputs'!$C$41/'Inputs'!$C$32),"") | E42: =IFERROR(('Inputs'!$E$41/'Inputs'!$E$32)/('Inputs'!$D$41/'Inputs'!$D$32),"") | F42: =IFERROR(('Inputs'!$F$41/'Inputs'!$F$32)/('Inputs'!$E$41/'Inputs'!$E$32),"") | G42: =IFERROR(('Inputs'!$G$41/'Inputs'!$G$32)/('Inputs'!$F$41/'Inputs'!$F$32),"") | H42: =IFERROR(('Inputs'!$H$41/'Inputs'!$H$32)/('Inputs'!$G$41/'Inputs'!$G$32),"") | I42: =IFERROR(('Inputs'!$I$41/'Inputs'!$I$32)/('Inputs'!$H$41/'Inputs'!$H$32),"") | J42: =IFERROR(('Inputs'!$J$41/'Inputs'!$J$32)/('Inputs'!$I$41/'Inputs'!$I$32),"") | K42: =IFERROR(('Inputs'!$K$41/'Inputs'!$K$32)/('Inputs'!$J$41/'Inputs'!$J$32),"") | L42: =IFERROR(('Inputs'!$L$41/'Inputs'!$L$32)/('Inputs'!$K$41/'Inputs'!$K$32),"") | M42: =IFERROR(('Inputs'!$M$41/'Inputs'!$M$32)/('Inputs'!$L$41/'Inputs'!$L$32),"") | N42: =IFERROR(('Inputs'!$N$41/'Inputs'!$N$32)/('Inputs'!$M$41/'Inputs'!$M$32),"") | O42: =IFERROR(('Inputs'!$O$41/'Inputs'!$O$32)/('Inputs'!$N$41/'Inputs'!$N$32),"") | P42: =IFERROR(('Inputs'!$P$41/'Inputs'!$P$32)/('Inputs'!$O$41/'Inputs'!$O$32),"")
A43: TATA (total accruals / assets) | C43: =IFERROR(('Inputs'!$C$21-'Inputs'!$C$46)/'Inputs'!$C$32,"") | D43: =IFERROR(('Inputs'!$D$21-'Inputs'!$D$46)/'Inputs'!$D$32,"") | E43: =IFERROR(('Inputs'!$E$21-'Inputs'!$E$46)/'Inputs'!$E$32,"") | F43: =IFERROR(('Inputs'!$F$21-'Inputs'!$F$46)/'Inputs'!$F$32,"") | G43: =IFERROR(('Inputs'!$G$21-'Inputs'!$G$46)/'Inputs'!$G$32,"") | H43: =IFERROR(('Inputs'!$H$21-'Inputs'!$H$46)/'Inputs'!$H$32,"") | I43: =IFERROR(('Inputs'!$I$21-'Inputs'!$I$46)/'Inputs'!$I$32,"") | J43: =IFERROR(('Inputs'!$J$21-'Inputs'!$J$46)/'Inputs'!$J$32,"") | K43: =IFERROR(('Inputs'!$K$21-'Inputs'!$K$46)/'Inputs'!$K$32,"") | L43: =IFERROR(('Inputs'!$L$21-'Inputs'!$L$46)/'Inputs'!$L$32,"") | M43: =IFERROR(('Inputs'!$M$21-'Inputs'!$M$46)/'Inputs'!$M$32,"") | N43: =IFERROR(('Inputs'!$N$21-'Inputs'!$N$46)/'Inputs'!$N$32,"") | O43: =IFERROR(('Inputs'!$O$21-'Inputs'!$O$46)/'Inputs'!$O$32,"") | P43: =IFERROR(('Inputs'!$P$21-'Inputs'!$P$46)/'Inputs'!$P$32,"")
A44: Beneish M-Score | C44: =IFERROR(-4.84+0.92*'Quality'!$C$36+0.528*'Quality'!$C$37+0.404*'Quality'!$C$38+0.892*'Quality'!$C$39+0.115*'Quality'!$C$40-0.172*'Quality'!$C$41+4.679*'Quality'!$C$43-0.327*'Quality'!$C$42,"") | D44: =IFERROR(-4.84+0.92*'Quality'!$D$36+0.528*'Quality'!$D$37+0.404*'Quality'!$D$38+0.892*'Quality'!$D$39+0.115*'Quality'!$D$40-0.172*'Quality'!$D$41+4.679*'Quality'!$D$43-0.327*'Quality'!$D$42,"") | E44: =IFERROR(-4.84+0.92*'Quality'!$E$36+0.528*'Quality'!$E$37+0.404*'Quality'!$E$38+0.892*'Quality'!$E$39+0.115*'Quality'!$E$40-0.172*'Quality'!$E$41+4.679*'Quality'!$E$43-0.327*'Quality'!$E$42,"") | F44: =IFERROR(-4.84+0.92*'Quality'!$F$36+0.528*'Quality'!$F$37+0.404*'Quality'!$F$38+0.892*'Quality'!$F$39+0.115*'Quality'!$F$40-0.172*'Quality'!$F$41+4.679*'Quality'!$F$43-0.327*'Quality'!$F$42,"") | G44: =IFERROR(-4.84+0.92*'Quality'!$G$36+0.528*'Quality'!$G$37+0.404*'Quality'!$G$38+0.892*'Quality'!$G$39+0.115*'Quality'!$G$40-0.172*'Quality'!$G$41+4.679*'Quality'!$G$43-0.327*'Quality'!$G$42,"") | H44: =IFERROR(-4.84+0.92*'Quality'!$H$36+0.528*'Quality'!$H$37+0.404*'Quality'!$H$38+0.892*'Quality'!$H$39+0.115*'Quality'!$H$40-0.172*'Quality'!$H$41+4.679*'Quality'!$H$43-0.327*'Quality'!$H$42,"") | I44: =IFERROR(-4.84+0.92*'Quality'!$I$36+0.528*'Quality'!$I$37+0.404*'Quality'!$I$38+0.892*'Quality'!$I$39+0.115*'Quality'!$I$40-0.172*'Quality'!$I$41+4.679*'Quality'!$I$43-0.327*'Quality'!$I$42,"") | J44: =IFERROR(-4.84+0.92*'Quality'!$J$36+0.528*'Quality'!$J$37+0.404*'Quality'!$J$38+0.892*'Quality'!$J$39+0.115*'Quality'!$J$40-0.172*'Quality'!$J$41+4.679*'Quality'!$J$43-0.327*'Quality'!$J$42,"") | K44: =IFERROR(-4.84+0.92*'Quality'!$K$36+0.528*'Quality'!$K$37+0.404*'Quality'!$K$38+0.892*'Quality'!$K$39+0.115*'Quality'!$K$40-0.172*'Quality'!$K$41+4.679*'Quality'!$K$43-0.327*'Quality'!$K$42,"") | L44: =IFERROR(-4.84+0.92*'Quality'!$L$36+0.528*'Quality'!$L$37+0.404*'Quality'!$L$38+0.892*'Quality'!$L$39+0.115*'Quality'!$L$40-0.172*'Quality'!$L$41+4.679*'Quality'!$L$43-0.327*'Quality'!$L$42,"") | M44: =IFERROR(-4.84+0.92*'Quality'!$M$36+0.528*'Quality'!$M$37+0.404*'Quality'!$M$38+0.892*'Quality'!$M$39+0.115*'Quality'!$M$40-0.172*'Quality'!$M$41+4.679*'Quality'!$M$43-0.327*'Quality'!$M$42,"") | N44: =IFERROR(-4.84+0.92*'Quality'!$N$36+0.528*'Quality'!$N$37+0.404*'Quality'!$N$38+0.892*'Quality'!$N$39+0.115*'Quality'!$N$40-0.172*'Quality'!$N$41+4.679*'Quality'!$N$43-0.327*'Quality'!$N$42,"") | O44: =IFERROR(-4.84+0.92*'Quality'!$O$36+0.528*'Quality'!$O$37+0.404*'Quality'!$O$38+0.892*'Quality'!$O$39+0.115*'Quality'!$O$40-0.172*'Quality'!$O$41+4.679*'Quality'!$O$43-0.327*'Quality'!$O$42,"") | P44: =IFERROR(-4.84+0.92*'Quality'!$P$36+0.528*'Quality'!$P$37+0.404*'Quality'!$P$38+0.892*'Quality'!$P$39+0.115*'Quality'!$P$40-0.172*'Quality'!$P$41+4.679*'Quality'!$P$43-0.327*'Quality'!$P$42,"") | Q44: =IF(AND(ISNUMBER($K$44),ISNUMBER($J$44)),CHOOSE(2+($K$44>$J$44)-($K$44<$J$44),"▼","►","▲"),"") | R44: =IF(ISNUMBER($K$44),CHOOSE(1+($K$44>=-2.22)+($K$44>=-1.78),"Low Risk","Watch","Manipulation"),"")
A45: M < −2.22 = unlikely manipulator · −2.22 to −1.78 = watch · > −1.78 = elevated risk.
A47: Value Creation (ROIC vs WACC)
A48: ROIC | C48: =IFERROR('Inputs'!$C$71/'Inputs'!$C$80,"") | D48: =IFERROR('Inputs'!$D$71/'Inputs'!$D$80,"") | E48: =IFERROR('Inputs'!$E$71/'Inputs'!$E$80,"") | F48: =IFERROR('Inputs'!$F$71/'Inputs'!$F$80,"") | G48: =IFERROR('Inputs'!$G$71/'Inputs'!$G$80,"") | H48: =IFERROR('Inputs'!$H$71/'Inputs'!$H$80,"") | I48: =IFERROR('Inputs'!$I$71/'Inputs'!$I$80,"") | J48: =IFERROR('Inputs'!$J$71/'Inputs'!$J$80,"") | K48: =IFERROR('Inputs'!$K$71/'Inputs'!$K$80,"") | L48: =IFERROR('Inputs'!$L$71/'Inputs'!$L$80,"") | M48: =IFERROR('Inputs'!$M$71/'Inputs'!$M$80,"") | N48: =IFERROR('Inputs'!$N$71/'Inputs'!$N$80,"") | O48: =IFERROR('Inputs'!$O$71/'Inputs'!$O$80,"") | P48: =IFERROR('Inputs'!$P$71/'Inputs'!$P$80,"") | Q48: =IF(AND(ISNUMBER($K$48),ISNUMBER($J$48)),CHOOSE(2+($K$48>$J$48)-($K$48<$J$48),"▼","►","▲"),"")
A49: WACC | B49: ='Inputs'!$B$82 | C49: ='Inputs'!$B$82 | D49: ='Inputs'!$B$82 | E49: ='Inputs'!$B$82 | F49: ='Inputs'!$B$82 | G49: ='Inputs'!$B$82 | H49: ='Inputs'!$B$82 | I49: ='Inputs'!$B$82 | ... P49: ='Inputs'!$B$82
A50: ROIC − WACC spread | C50: =IFERROR('Quality'!$C$48-'Inputs'!$B$82,"") | D50: =IFERROR('Quality'!$D$48-'Inputs'!$B$82,"") | E50: =IFERROR('Quality'!$E$48-'Inputs'!$B$82,"") | F50: =IFERROR('Quality'!$F$48-'Inputs'!$B$82,"") | G50: =IFERROR('Quality'!$G$48-'Inputs'!$B$82,"") | H50: =IFERROR('Quality'!$H$48-'Inputs'!$B$82,"") | I50: =IFERROR('Quality'!$I$48-'Inputs'!$B$82,"") | J50: =IFERROR('Quality'!$J$48-'Inputs'!$B$82,"") | K50: =IFERROR('Quality'!$K$48-'Inputs'!$B$82,"") | L50: =IFERROR('Quality'!$L$48-'Inputs'!$B$82,"") | M50: =IFERROR('Quality'!$M$48-'Inputs'!$B$82,"") | N50: =IFERROR('Quality'!$N$48-'Inputs'!$B$82,"") | O50: =IFERROR('Quality'!$O$48-'Inputs'!$B$82,"") | P50: =IFERROR('Quality'!$P$48-'Inputs'!$B$82,"") | Q50: =IF(AND(ISNUMBER($K$50),ISNUMBER($J$50)),CHOOSE(2+($K$50>$J$50)-($K$50<$J$50),"▼","►","▲"),"") | R50: =IF(ISNUMBER($K$50),CHOOSE(1+($K$50>=0)+($K$50>=0.03),"Value-destroying","Roughly neutral","Value-creating"),"")
A51: Economic profit = spread × invested capital | C51: =IFERROR(('Quality'!$C$48-'Inputs'!$B$82)*'Inputs'!$C$80,"") | D51: =IFERROR(('Quality'!$D$48-'Inputs'!$B$82)*'Inputs'!$D$80,"") | E51: =IFERROR(('Quality'!$E$48-'Inputs'!$B$82)*'Inputs'!$E$80,"") | F51: =IFERROR(('Quality'!$F$48-'Inputs'!$B$82)*'Inputs'!$F$80,"") | G51: =IFERROR(('Quality'!$G$48-'Inputs'!$B$82)*'Inputs'!$G$80,"") | H51: =IFERROR(('Quality'!$H$48-'Inputs'!$B$82)*'Inputs'!$H$80,"") | I51: =IFERROR(('Quality'!$I$48-'Inputs'!$B$82)*'Inputs'!$I$80,"") | J51: =IFERROR(('Quality'!$J$48-'Inputs'!$B$82)*'Inputs'!$J$80,"") | K51: =IFERROR(('Quality'!$K$48-'Inputs'!$B$82)*'Inputs'!$K$80,"") | L51: =IFERROR(('Quality'!$L$48-'Inputs'!$B$82)*'Inputs'!$L$80,"") | M51: =IFERROR(('Quality'!$M$48-'Inputs'!$B$82)*'Inputs'!$M$80,"") | N51: =IFERROR(('Quality'!$N$48-'Inputs'!$B$82)*'Inputs'!$N$80,"") | O51: =IFERROR(('Quality'!$O$48-'Inputs'!$B$82)*'Inputs'!$O$80,"") | P51: =IFERROR(('Quality'!$P$48-'Inputs'!$B$82)*'Inputs'!$P$80,"") | Q51: =IF(AND(ISNUMBER($K$51),ISNUMBER($J$51)),CHOOSE(2+($K$51>$J$51)-($K$51<$J$51),"▼","►","▲"),"")
A53: Automated Observations
A54: =IFERROR("» Altman Z of "&TEXT('Quality'!$K$15,"0.0")&" places the company in the "&'Quality'!$R$15&" zone; Piotroski F is "&TEXT('Quality'!$K$33,"0")&"/9 ("&'Quality'!$R$33&").","(insufficient data — populate inputs)")
A55: =IFERROR("» Beneish M of "&TEXT('Quality'!$K$44,"0.00")&" implies "&'Quality'!$R$44&" for earnings manipulation.","(insufficient data — populate inputs)")
A56: =IFERROR("» ROIC exceeds WACC by "&TEXT('Quality'!$K$50,"0.0%")&", generating "&TEXT('Quality'!$K$51,"#,##0")&" of economic profit — "&'Quality'!$R$50&".","(insufficient data — populate inputs)")

Sheet Benchmarking
A1: INDUSTRY BENCHMARKING
A2: Company vs peers — ranking, percentile and best-in-class
A3: Institutional Financial Ratio Analysis · v1.0
A5: Dashboard | B5: Inputs | C5: Common Size | D5: Profitability | E5: Liquidity | F5: Solvency | G5: Efficiency | H5: Growth
A6: Valuation | B6: Capital Allocation | C6: Quality | D6: Benchmarking | E6: Guide | F6: Quality Control
A7: Company figures link to the latest reported year; peer cells are inputs.
A8: Ratio (latest year) | B8: Company | C8: Peer A | D8: Peer B | E8: Peer C | F8: Peer D | G8: Peer E | H8: Median | I8: Rank | J8: Pct'ile | K8: Flag
A9: Gross margin | B9: ='Profitability'!$K$10 | H9: =IFERROR(MEDIAN(B9:G9),"") | I9: =IFERROR(RANK($B$9,B9:G9,0),"") | J9: =IFERROR((6-$I$9)/5,"") | K9: =IFERROR(IF($I$9=1,"Best-in-Class",""),"")
A10: Operating margin | B10: ='Profitability'!$K$12 | H10: =IFERROR(MEDIAN(B10:G10),"") | I10: =IFERROR(RANK($B$10,B10:G10,0),"") | J10: =IFERROR((6-$I$10)/5,"") | K10: =IFERROR(IF($I$10=1,"Best-in-Class",""),"")
A11: Net margin | B11: ='Profitability'!$K$14 | H11: =IFERROR(MEDIAN(B11:G11),"") | I11: =IFERROR(RANK($B$11,B11:G11,0),"") | J11: =IFERROR((6-$I$11)/5,"") | K11: =IFERROR(IF($I$11=1,"Best-in-Class",""),"")
A12: ROE | B12: ='Profitability'!$K$18 | H12: =IFERROR(MEDIAN(B12:G12),"") | I12: =IFERROR(RANK($B$12,B12:G12,0),"") | J12: =IFERROR((6-$I$12)/5,"") | K12: =IFERROR(IF($I$12=1,"Best-in-Class",""),"")
A13: ROIC | B13: ='Profitability'!$K$20 | H13: =IFERROR(MEDIAN(B13:G13),"") | I13: =IFERROR(RANK($B$13,B13:G13,0),"") | J13: =IFERROR((6-$I$13)/5,"") | K13: =IFERROR(IF($I$13=1,"Best-in-Class",""),"")
A14: Current ratio | B14: ='Liquidity'!$K$10 | H14: =IFERROR(MEDIAN(B14:G14),"") | I14: =IFERROR(RANK($B$14,B14:G14,0),"") | J14: =IFERROR((6-$I$14)/5,"") | K14: =IFERROR(IF($I$14=1,"Best-in-Class",""),"")
A15: Net debt / EBITDA | B15: ='Solvency'!$K$18 | H15: =IFERROR(MEDIAN(B15:G15),"") | I15: =IFERROR(RANK($B$15,B15:G15,1),"") | J15: =IFERROR((6-$I$15)/5,"") | K15: =IFERROR(IF($I$15=1,"Best-in-Class",""),"")
A16: Revenue 5y CAGR | B16: ='Growth'!$C$20 | H16: =IFERROR(MEDIAN(B16:G16),"") | I16: =IFERROR(RANK($B$16,B16:G16,0),"") | J16: =IFERROR((6-$I$16)/5,"") | K16: =IFERROR(IF($I$16=1,"Best-in-Class",""),"")
A17: FCF margin | B17: ='Profitability'!$K$15 | H17: =IFERROR(MEDIAN(B17:G17),"") | I17: =IFERROR(RANK($B$17,B17:G17,0),"") | J17: =IFERROR((6-$I$17)/5,"") | K17: =IFERROR(IF($I$17=1,"Best-in-Class",""),"")
A18: EV / EBITDA | B18: ='Valuation'!$K$23 | H18: =IFERROR(MEDIAN(B18:G18),"") | I18: =IFERROR(RANK($B$18,B18:G18,1),"") | J18: =IFERROR((6-$I$18)/5,"") | K18: =IFERROR(IF($I$18=1,"Best-in-Class",""),"")
A20: Competitive Profile (vs peer median)
A21: Entity | B21: Gross | C21: Operating | D21: Net | E21: ROE | F21: ROIC | G21: FCF mgn
A22: Company | B22: =$B$9 | C22: =$B$10 | D22: =$B$11 | E22: =$B$12 | F22: =$B$13 | G22: =$B$17
A23: Peer median | B23: =$H$9 | C23: =$H$10 | D23: =$H$11 | E23: =$H$12 | F23: =$H$13 | G23: =$H$17
A44: Automated Observations
A45: =IFERROR("» The company ranks best-in-class on "&TEXT(COUNTIF(K9:K18,"Best-in-Class"),"0")&" of "&"10"&" benchmarked metrics versus its peer set.","(insufficient data — populate inputs)")

Sheet Guide
A1: RATIO INTERPRETATION GUIDE
A2: Definition, formula, ranges and investment meaning for every ratio
A3: Institutional Financial Ratio Analysis · v1.0
A5: Dashboard | B5: Inputs | C5: Common Size | D5: Profitability | E5: Liquidity | F5: Solvency | G5: Efficiency | H5: Growth
A6: Valuation | B6: Capital Allocation | C6: Quality | D6: Benchmarking | E6: Guide | F6: Quality Control
A7: Ratio | B7: Formula | C7: What it measures | D7: Strong | E7: Average | F7: Weak | G7: Investment meaning
A8: Gross Margin | B8: Gross Profit / Revenue | C8: Pricing power and production efficiency. | D8: >40% | E8: 20–40% | F8: <20% | G8: High, stable gross margins signal a durable competitive advantage.
A9: Operating Margin | B9: EBIT / Revenue | C9: Core profitability after operating costs. | D9: >18% | E9: 8–18% | F9: <8% | G9: Expanding operating margin shows operating leverage and cost control.
A10: Net Margin | B10: Net Income / Revenue | C10: Bottom-line profitability. | D10: >12% | E10: 5–12% | F10: <5% | G10: Persistent net margins indicate quality earnings.
A11: ROE | B11: Net Income / Average Equity | C11: Return generated on shareholders' capital. | D11: >15% | E11: 8–15% | F11: <8% | G11: High ROE not driven by leverage is a hallmark of quality.
A12: ROA | B12: Net Income / Average Assets | C12: Efficiency of the asset base. | D12: >7% | E12: 3–7% | F12: <3% | G12: Rising ROA shows assets are deployed more productively.
A13: ROIC | B13: NOPAT / Invested Capital | C13: Return on all invested capital. | D13: >12% | E13: 8–12% | F13: <8% | G13: ROIC above WACC is the clearest sign of value creation.
A14: ROCE | B14: EBIT / Capital Employed | C14: Pre-tax return on long-term capital. | D14: >12% | E14: 8–12% | F14: <8% | G14: Consistent ROCE indicates a capital-efficient business.
A15: Current Ratio | B15: Current Assets / Current Liabilities | C15: Short-term liquidity. | D15: >2.0x | E15: 1.0–2.0x | F15: <1.0x | G15: Below 1.0x can signal liquidity stress; very high may be inefficient.
A16: Quick Ratio | B16: (Current Assets − Inventory) / Current Liabilities | C16: Liquidity excluding inventory. | D16: >1.2x | E16: 0.8–1.2x | F16: <0.8x | G16: A stricter liquidity test for inventory-heavy firms.
A17: Cash Ratio | B17: (Cash + Equivalents) / Current Liabilities | C17: Most conservative liquidity test. | D17: >0.5x | E17: 0.2–0.5x | F17: <0.2x | G17: Shows ability to cover current liabilities from cash alone.
A18: Debt-to-Equity | B18: Total Debt / Equity | C18: Reliance on debt vs equity. | D18: <0.5x | E18: 0.5–1.5x | F18: >1.5x | G18: Higher leverage raises returns but also financial risk.
... A35: ROIC − WACC Spread | B35: ROIC − WACC | C35: Economic value creation. | D35: >3% | E35: 0–3% | F35: <0% | G35: A positive spread means the firm earns above its cost of capital.

Sheet Quality Control
A1: QUALITY CONTROL
A2: Automated validation, integrity and data-gap checks
A3: Institutional Financial Ratio Analysis · v1.0
A5: Dashboard | B5: Inputs | C5: Common Size | D5: Profitability | E5: Liquidity | F5: Solvency | G5: Efficiency | H5: Growth
A6: Valuation | B6: Capital Allocation | C6: Quality | D6: Benchmarking | E6: Guide | F6: Quality Control
A7: Overall Data Health
A8: Overall verdict | B8: =IF('Quality Control'!$B$9>0,"FAIL — fix flagged items",IF('Quality Control'!$B$10>0,"REVIEW — some items to check","PASS — all checks clear"))
A9: Checks failed | B9: =COUNTIF(C13:C24,"FAIL")
A10: Checks to review | B10: =COUNTIF(C13:C24,"REVIEW")
A12: Statement Integrity
A13: Balance sheet balances (max |A−(L+E)|) | B13: =MAX(ABS('Inputs'!$B$32-'Inputs'!$B$44),ABS('Inputs'!$C$32-'Inputs'!$C$44),ABS('Inputs'!$D$32-'Inputs'!$D$44),ABS('Inputs'!$E$32-'Inputs'!$E$44),ABS('Inputs'!$F$32-'Inputs'!$F$44),ABS('Inputs'!$G$32-'Inputs'!$G$44),ABS('Inputs'!$H$32-'Inputs'!$H$44),ABS('Inputs'!$I$32-'Inputs'!$I$44),ABS('Inputs'!$J$32-'Inputs'!$J$44),ABS('Inputs'!$K$32-'Inputs'!$K$44),ABS('Inputs'!$L$32-'Inputs'!$L$44),ABS('Inputs'!$M$32-'Inputs'!$M$44),ABS('Inputs'!$N$32-'Inputs'!$N$44),ABS('Inputs'!$O$32-'Inputs'!$O$44),ABS('Inputs'!$P$32-'Inputs'!$P$44)) | C13: =IF($B$13<=1,"PASS",IF($B$13<=0.01*'Inputs'!$K$32,"REVIEW","FAIL")) | D13: Total assets must equal liabilities + equity every year.
A14: DuPont ROE ties to ROE | B14: =IFERROR(ABS('Profitability'!$K$28-'Profitability'!$K$18),"") | C14: =IF(ISNUMBER($B$14),IF($B$14<=0.0001,"PASS","FAIL"),"REVIEW") | D14: DuPont decomposition (margin×turnover×leverage) must reproduce ROE.
A15: Common-size revenue = 100% | B15: =IFERROR(ABS('Common Size'!$K$10-1),"") | C15: =IF(ISNUMBER($B$15),IF($B$15<=0.0001,"PASS","FAIL"),"REVIEW") | D15: The common-size revenue row must equal 100%.
A17: Data Presence & Sanity
A18: Key inputs present (latest year) | B18: =IF(NOT(ISNUMBER('Inputs'!$K$10)),1,0)+IF(NOT(ISNUMBER('Inputs'!$K$11)),1,0)+IF(NOT(ISNUMBER('Inputs'!$K$42)),1,0)+IF(NOT(ISNUMBER('Inputs'!$K$32)),1,0)+IF(NOT(ISNUMBER('Inputs'!$K$46)),1,0)+IF(NOT(ISNUMBER('Inputs'!$K$53)),1,0)+IF(NOT(ISNUMBER('Inputs'!$K$52)),1,0) | C18: =IF($B$18=0,"PASS",IF($B$18<=2,"REVIEW","FAIL")) | D18: Count of essential latest-year inputs that are blank/missing.
A19: Revenue positive every year (no zero denominators) | B19: =MIN('Inputs'!$B$10,'Inputs'!$C$10,'Inputs'!$D$10,'Inputs'!$E$10,'Inputs'!$F$10,'Inputs'!$G$10,'Inputs'!$H$10,'Inputs'!$I$10,'Inputs'!$J$10,'Inputs'!$K$10,'Inputs'!$L$10,'Inputs'!$M$10,'Inputs'!$N$10,'Inputs'!$O$10,'Inputs'!$P$10) | C19: =IF(AND(ISNUMBER($B$19),$B$19>0),"PASS","FAIL") | D19: Zero/negative revenue would break margin and turnover ratios.
A20: Equity positive every year | B20: =MIN('Inputs'!$B$42,'Inputs'!$C$42,'Inputs'!$D$42,'Inputs'!$E$42,'Inputs'!$F$42,'Inputs'!$G$42,'Inputs'!$H$42,'Inputs'!$I$42,'Inputs'!$J$42,'Inputs'!$K$42,'Inputs'!$L$42,'Inputs'!$M$42,'Inputs'!$N$42,'Inputs'!$O$42,'Inputs'!$P$42) | C20: =IF(AND(ISNUMBER($B$20),$B$20>0),"PASS","REVIEW") | D20: Negative equity makes ROE and leverage ratios hard to interpret.
A21: Revenue-growth outliers (max |YoY|) | B21: =MAX(ABS(IFERROR('Inputs'!$C$10/'Inputs'!$B$10-1,0)),ABS(IFERROR('Inputs'!$D$10/'Inputs'!$C$10-1,0)),ABS(IFERROR('Inputs'!$E$10/'Inputs'!$D$10-1,0)),ABS(IFERROR('Inputs'!$F$10/'Inputs'!$E$10-1,0)),ABS(IFERROR('Inputs'!$G$10/'Inputs'!$F$10-1,0)),ABS(IFERROR('Inputs'!$H$10/'Inputs'!$G$10-1,0)),ABS(IFERROR('Inputs'!$I$10/'Inputs'!$H$10-1,0)),ABS(IFERROR('Inputs'!$J$10/'Inputs'!$I$10-1,0)),ABS(IFERROR('Inputs'!$K$10/'Inputs'!$J$10-1,0)),ABS(IFERROR('Inputs'!$L$10/'Inputs'!$K$10-1,0)),ABS(IFERROR('Inputs'!$M$10/'Inputs'!$L$10-1,0)),ABS(IFERROR('Inputs'!$N$10/'Inputs'!$M$10-1,0)),ABS(IFERROR('Inputs'!$O$10/'Inputs'!$N$10-1,0)),ABS(IFERROR('Inputs'!$P$10/'Inputs'!$O$10-1,0))) | C21: =IF($B$21<=1,"PASS","REVIEW") | D21: A year-on-year move above 100% may be a data-entry error.
A22: WACC within plausible range | B22: ='Inputs'!$B$82 | C22: =IF(AND($B$22>=0.04,$B$22<=0.18),"PASS","REVIEW") | D22: Cost of capital should sit roughly within 4–18%.
A23: Currency & units specified | C23: =IF(AND(ISTEXT('Home'!$B$8),ISTEXT('Home'!$B$9)),"PASS","REVIEW") | D23: Currency and units should be stated so figures are unambiguous.
A24: Model integrity (no circular references) | C24: ="PASS" | D24: The workbook is acyclic by construction — outputs trace one way to inputs.
